Workbook
Name AddressOfSite: 'General Information'!$D$404:$D$503
Name AmountOfEmissionsTable: 'Environmental Disclosures'!$D$80:$K$179
Name AmountOfEmissionToAir: 'Environmental Disclosures'!$G$80:$I$179
Name AmountOfEmissionToAir_unit: 'Environmental Disclosures'!$C$78
Name AmountOfEmissionToSoil: 'Environmental Disclosures'!$K$80:$K$179
Name AmountOfEmissionToSoil_unit: 'Environmental Disclosures'!$C$78
Name AmountOfEmissionToWater: 'Environmental Disclosures'!$J$80:$J$179
Name AmountOfEmissionToWater_unit: 'Environmental Disclosures'!$C$78
Name AmountOfWaterWithdrawnAtSitesLocatedInAreasOfHighWaterStress: 'Environmental Disclosures'!$D$304
Name AreaOfSiteInBiodiversitySensitiveArea: 'Environmental Disclosures'!$G$188:$I$287
Name AreaOfSiteInBiodiversitySensitiveArea_unit: 'Environmental Disclosures'!$C$186
Name Assets: 'General Information'!$E$280
Name AverageNumberOfAnnualTrainingHoursPerFemaleEmployee: 'Social Disclosures'!$D$158
Name AverageNumberOfAnnualTrainingHoursPerMaleEmployee: 'Social Disclosures'!$D$157
Name AverageNumberOfAnnualTrainingHoursPerNonReportedGenderEmployee: 'Social Disclosures'!$D$160
Name AverageNumberOfAnnualTrainingHoursPerOtherGenderEmployee: 'Social Disclosures'!$D$159
Name BaselineYearMember: 'Environmental Disclosures'!$G$21
Name BasisForPreparation: 'General Information'!$E$122
Name BasisForReporting: 'General Information'!$E$177
Name BreakdownOfAnnualMassFlowOfRelevantMaterialsUsedByTheUndertakingHypercube: 'Environmental Disclosures'!$C$435:$I$534
Name BreakdownOfEnergyConsumptionAxis: 'Environmental Disclosures'!$C$12:$F$14
Name BreakdownOfEnergyConsumptionTable: 'Environmental Disclosures'!$G$12:$K$14
Name CityOfSite: 'General Information'!$F$404:$F$503
Name CountryOfEmploymentContractAxis: 'Social Disclosures'!$C$29:$D$128
Name CountryOfPrimaryOperationsAndLocationOfSignificantAssets: 'General Information'!$E$285
Name CountryOfSite: 'General Information'!$G$404:$G$503
Name DateOfAdoptionOfTransitionPlanForUndertakingNotHavingAdoptedTransitionPlanYet: 'Environmental Disclosures'!$D$62
Name DescriptionOfActionsTakeToAddressTheConfirmedIncidents: 'Social Disclosures'!$D$192
Name DescriptionOfATargetRelatedToAPolicy: 'General Information'!$E$520
Name DescriptionOfATransitionPlanForClimateChangeMitigationIncludingAnExplanationOfHowItIsContributingToReduceGhgEmissions: 'Environmental Disclosures'!$D$58
Name DescriptionOfClimateRelatedHazardsAndClimateRelatedTransitionEvents: 'Environmental Disclosures'!$E$540
Name DescriptionOfHowCircularEconomyPrinciplesAreApplied: 'Environmental Disclosures'!$D$317
Name DescriptionOfKeyElementsOfStrategyThatRelatesToOrAffectsSustainabilityIssues: 'General Information'!$E$529
Name DescriptionOfLimitsToTheDistributionOfProfitsConnectedToTheMutualisticNatureOrToTheNatureOfTheActivitiesConsistingInServicesOfGeneralEconomicInterestSGEI: 'General Information'!$D$516
Name DescriptionOfMainBusinessRelationships: 'General Information'!$E$527
Name DescriptionOfPracticesPoliciesAndOrFutureInitiatives: 'General Information'!$E$519
Name DescriptionOfSignificantGroupsOfProductsAndOrServicesOffered: 'General Information'!$E$525
Name DescriptionOfSignificantMarketsTheUndertakingOperatesIn: 'General Information'!$E$526
Name DescriptionOfSustainabilityRelatedCertificationsOrLabels: 'General Information'!$E$395
Name DescriptionOfTheEffectiveParticipationOfWorkersUsersOrOtherInterestedPartiesOrCommunitiesInGovernance: 'General Information'!$D$514
Name DisclosureOfAnyOtherEnvironmentalAndOrEntitySpecificEnvironmentalDisclosures: 'Environmental Disclosures'!$C$548
Name DisclosureOfAnyOtherGeneralAndOrEntitySpecificInformation: 'General Information'!$C$533
Name DisclosureOfAnyOtherGovernanceAndOrEntitySpecificGovernanceDisclosures: 'Governance Disclosures'!$C$38
Name DisclosureOfAnyOtherSocialAndOrEntitySpecificSocialDisclosures: 'Social Disclosures'!$C$200
Name DisclosureOfHowItHasAssessedTheExposureAndSensitivityOfItsAssetsActivitiesAndValueChainToTheseHazardsAndTransitionEvents: 'Environmental Disclosures'!$E$541
Name DisclosureOfListOfMainActionsTheEntitySeeksInOrderToAchieveItsTargets: 'Environmental Disclosures'!$C$52
Name DisclosureOfWhetherItHasUndertakenClimateChangeAdaptationActionsForAnyClimateRelatedHazardsAndTransitionEvents: 'Environmental Disclosures'!$E$543
Name EmployeeCountingMethodology: 'General Information'!$E$283
Name EmployeesReceivePayEqualOrAboveMinimumWageDeterminedByNationalLawOrCollectiveAgreement: 'Social Disclosures'!$D$147
Name EmployeeTurnoverRate: 'Social Disclosures'!$D$137
Name EnergyConsumptionFromElectricity_NonRenewableEnergyMember: 'Environmental Disclosures'!$J$12
Name EnergyConsumptionFromElectricity_RenewableEnergyMember: 'Environmental Disclosures'!$G$12
Name EnergyConsumptionFromElectricity_TotalRenewableAndNonRenewableEnergyMember: 'Environmental Disclosures'!$K$12
Name EnergyConsumptionFromFuels_NonRenewableEnergyMember: 'Environmental Disclosures'!$J$14
Name EnergyConsumptionFromFuels_RenewableEnergyMember: 'Environmental Disclosures'!$G$14
Name EnergyConsumptionFromFuels_TotalRenewableAndNonRenewableEnergyMember: 'Environmental Disclosures'!$K$14
Name EnergyConsumptionFromSelfGeneratedElectricity_NonRenewableEnergyMember: 'Environmental Disclosures'!$J$13
Name EnergyConsumptionFromSelfGeneratedElectricity_RenewableEnergyMember: 'Environmental Disclosures'!$G$13
Name EnergyConsumptionFromSelfGeneratedElectricity_TotalRenewableAndNonRenewableEnergyMember: 'Environmental Disclosures'!$K$13
Name enum_B2: 'Enumeration Lists'!$P$2:$P$4

Sheet Introduction
B1: =template_label_version | C1: 1.2.0
B2: =template_label_publication_date | C2: 46077
B3: {=IF(ISERROR(CELL("filename",A1)),"Warning: The Digital Template was developed and tested using Microsoft Excel 365. Functionality may be limited or incorrect when using other spreadsheet applications or older versions of Excel.","")}
B10: =template_label_taxonomy_entry_point | C10: https://xbrl.efrag.org/taxonomy/vsme/2026-02-01/vsme-all.xsd
B11: =template_label_select_template_display_language | C11: English - Official [en]
B12: =template_label_title_of_report | C12: =template_label_main_title_of_report_text
B13: =template_label_subtitle_of_report | C13: =template_label_subtitle_of_report_text
B14: =template_label_vsme_digital_template
B15: =template_label_the_purpose_of_this_digital_template_is_to_illustrate_how_vsme_reporting_can_be_implemented_in_a_digital_template
B18: =template_label_how_to_use_it
B19: =template_label_0_provide_information_that_is_mandatory_in_order_to_generate_the_vsme_and_xbrl_report
B20: =template_label_1_fill_in_the_disclosures_on_the_four_worksheets
B21: =template_label_2_find_more_information_on_the_actual_disclosure_requirements_in_the_vsme_standard
B22: =template_label_3_for_open_tables_like_the_list_of_subsidizers_sites_please_expand_the_groups_by_clicking_the_plus
B23: =template_label_4_validate_the_data_entered_by_checking_the_validation_status
B24: =template_label_5_convert_this_template_to_an_inline_xbrl_report
B25: =template_label_6_the_undertaking_may_also_upload_the_report_to_public_repositories_or_a_webpage
B27: =template_label_cell_background_color_index
B28: =template_label_general_principles | C28: =template_label_indicates_that_the_disclosure_is_from_the_general_principles_of_the_vsme
B29: =template_label_basic_module | C29: =template_label_indicates_that_the_disclosure_is_from_the_vsme_basic_module
B30: =template_label_comprehensive_module | C30: =template_label_indicates_that_the_disclosure_is_from_the_vsme_comprehensive_module
C31: =template_label_indicates_that_the_cell_is_automatically_calculated_and_that_no_data_entry_is_required
C32: =template_label_indicates_that_the_datapoint_often_a_condition_will_not_be_included_in_the_vsme_and_digital_xbrl_report
C33: =template_label_indicates_that_no_data_entry_is_required_unless_certain_logics_are_selected_in_the_disclosure_itself
B34: =template_label_validation_missing_value_error_velue_inconsistency_invalid_url | C34: =template_label_indicates_that_either_data_entry_is_incorrect_in_terms_of_format_or_that_certain_information
B35: Validation OK | C35: =template_label_indicates_that_data_entry_is_ok_and_the_undertaking_can_proceed_to_the_next_disclosure
B36: =template_label_validation_classified_or_sensitive_information | C36: =template_label_indicates_that_the_undertaking_has_omitted_the_data_entry_as_it_is_deemed_to_be_classified_or_sensitive_information
C37: =template_label_no_value_can_be_entered_in_the_cell
B38: [+] | C38: =template_label_lists_can_be_expanded_using_the_plus_button_on_the_left
B44: =template_label_efrag_is_funded_by_the_european_union_through_the_single_market_programme
B45: =template_label_reproduction_and_use_rights_are_strictly_limited

Sheet Table of Contents & Validation
B2: =template_label_table_of_contents_validation | C2: =template_label_overall_validation_status_validation | D2: =template_classified_or_sensitive_information
B3: =template_label_contents_grouping_follows_templates_framework | C3: {=IF(SUMPRODUCT(--((C5:C71<>template_label_ok)*(C5:C71<>"-")*(C5:C71<>"")*(C5:C71<>template_label_classified_or_sensitive_information))) > 0, template_label_incomplete, template_label_complete)} | D3: =template_filling_sensitive_checkboxes
C4: =template_label_specific_content_validation_status_validation
B5: =template_label_general_information_validation
B6: =template_label_information_on_the_report_necessary_for_xbrl_validation | C6: =IF( AND( COUNTIF('General Information'!F3:F12, template_label_missing_value) > 0, COUNTIF('General Information'!F3:F12, template_label_error) = 0 ), template_label_missing_value, IF( AND( COUNTIF('General Information'!F3:F12, template_label_error) > 0, COUNTIF('General Information'!F3:F12, template_label_missing_value) = 0 ), template_label_value_inconsistency, IF( AND( COUNTIF('General Information'!F3:F12, template_label_error) > 0, COUNTIF('General Information'!F3:F12, template_label_missing_value) > 0 ), template_label_error_plus_value_inconsistency, template_label_ok ) ) )
B7: =template_label_information_on_previous_reporting_period_validation | C7: =IF(COUNTIF('General Information'!F18:F119, template_label_missing_value) > 0, template_label_missing_value, IF(COUNTIF('General Information'!F18:F119, template_label_invalid_url ) > 0, template_label_invalid_url, IF(COUNTIF('General Information'!F18:F119, template_label_value_inconsistency ) > 0, template_label_value_inconsistency, IF(COUNTIF('General Information'!F18:F119, template_label_ok) > 0, template_label_ok, "-"))))
B8: =template_label_basic_module_validation
B9: =template_label_general_information_validation
B10: =template_label_b1_basis_for_preparation_validation | C10: =IF(D10=TRUE,template_label_classified_or_sensitive_information, IF(COUNTIF(C11:C15,template_label_error_plus_missing_value_plus_value_inconsistency)>0,template_label_error_plus_missing_value_plus_value_inconsistency, IF(COUNTIF(C11:C15,template_label_error_plus_value_inconsistency)>0,template_label_error_plus_value_inconsistency, IF(COUNTIF(C11:C15,template_label_error_plus_missing_value)>0,template_label_error_plus_missing_value, IF(COUNTIF(C11:C15,template_label_error)>0,template_label_error, IF(COUNTIF(C11:C15,template_label_missing_value_plus_value_inconsistency)>0,template_label_missing_value_plus_value_inconsistency, IF(COUNTIF(C11:C15,template_label_value_inconsistency)>0,template_label_value_inconsistency, IF(COUNTIF(C11:C15,template_label_missing_value)>0,template_label_missing_value, IF(COUNTIF(C11:C15,template_label_ok)=ROWS(C11:C15),template_label_ok, IF(COUNTIF(C11:C15,"-")=ROWS(C11:C15),"-", IF(AND(COUNTIF(C11:C15,template_label_ok)>0, COUNTIF(C11:C15,template_label_error_plus_missing_value_plus_value_inconsistency)=0, COUNTIF(C11:C15,template_label_error_plus_value_inconsistency)=0, COUNTIF(C11:C15,template_label_error_plus_missing_value)=0, COUNTIF(C11:C15,template_label_error)=0, COUNTIF(C11:C15,template_label_missing_value_plus_value_inconsistency)=0, COUNTIF(C11:C15,template_label_value_inconsistency)=0, COUNTIF(C11:C15,template_label_missing_value)=0, OR(COUNTIF(C11:C15,template_label_missing_value)=0, COUNTIF(C11:C15,template_label_missing_value)>0)), template_label_ok, "-"))))))))) )) | D10: =IF(COUNTIF(D12:D15,TRUE)=ROWS(D12:D15),TRUE,FALSE)
B11: =template_label_b1_basis_for_preparation | C11: =IF(COUNTIF('General Information'!F122,template_label_missing_value)>0,template_label_missing_value, IF(COUNTIF('General Information'!F122,template_label_ok)>0,template_label_ok,"-"))
B12: =template_label_b1_other_undertakings_general_information | C12: =IF(D12=TRUE, template_label_classified_or_sensitive_information,IF( AND( COUNTIF('General Information'!F177:F285,template_label_missing_value)>0, COUNTIF('General Information'!F177:F285,template_label_value_inconsistency)=0, COUNTIF('General Information'!F177:F285,template_label_error)=0 ), template_label_missing_value, IF( AND( COUNTIF('General Information'!F177:F285,template_label_value_inconsistency)>0, COUNTIF('General Information'!F177:F285,template_label_missing_value)=0, COUNTIF('General Information'!F177:F285,template_label_error)=0 ), template_label_value_inconsistency, IF( AND( COUNTIF('General Information'!F177:F285,template_label_value_inconsistency)=0, COUNTIF('General Information'!F177:F285,template_label_missing_value)=0, COUNTIF('General Information'!F177:F285,template_label_error)>0 ), template_label_error, IF( AND( COUNTIF('General Information'!F177:F285,template_label_value_inconsistency)>0, COUNTIF('General Information'!F177:F285,template_label_missing_value)>0, COUNTIF('General Information'!F177:F285,template_label_error)=0 ), template_label_missing_value_plus_value_inconsistency, IF( AND( COUNTIF('General Information'!F177:F285,template_label_value_inconsistency)=0, COUNTIF('General Information'!F177:F285,template_label_missing_value)>0, COUNTIF('General Information'!F177:F285,template_label_error)>0 ), template_label_error_plus_missing_value, IF( AND( COUNTIF('General Information'!F177:F285,template_label_value_inconsistency)>0, COUNTIF('General Information'!F177:F285,template_label_missing_value)=0, COUNTIF('General Information'!F177:F285,template_label_error)>0 ), template_label_error_plus_value_inconsistency, IF( AND( COUNTIF('General Information'!F177:F285,template_label_value_inconsistency)>0, COUNTIF('General Information'!F177:F285,template_label_missing_value)>0, COUNTIF('General Information'!F177:F285,template_label_error)>0 ), template_label_error_plus_missing_value_plus_value_inconsistency, IF( AND( COUNTIF('General Information'!F177:F285,template_label_value_inconsistency)=0, COUNTIF('General Information'!F177:F285,template_label_missing_value)=0, COUNTIF('General Information'!F177:F285,template_label_error)=0, COUNTIF('General Information'!F177:F285,template_label_ok)>0 ), template_label_ok, "-" ))))))))) | D12: FALSE
B13: =template_label_b1_list_of_subsidiaries | C13: =IF(D13=TRUE, template_label_classified_or_sensitive_information, IF( COUNTIF('General Information'!F290:F389, template_label_missing_value) > 0, template_label_missing_value, IF( COUNTIF('General Information'!F290:F389, template_label_ok) > 0, template_label_ok, "-" ) ) ) | D13: FALSE
B14: =template_label_b1_disclosure_of_sustainability_related_certification_or_label | C14: =IF(D14=TRUE, template_label_classified_or_sensitive_information, IF( COUNTIF('General Information'!I395, template_label_missing_value) > 0, template_label_missing_value, IF( COUNTIF('General Information'!I395, template_label_ok) > 0, template_label_ok, "-" ) ) ) | D14: FALSE
B15: =template_label_b1_list_of_site | C15: =IF(D15=TRUE, template_label_classified_or_sensitive_information, IF( COUNTIF('General Information'!I404:I503, template_label_missing_value) > 0, template_label_missing_value, IF( COUNTIF('General Information'!I404:I503, template_label_ok) > 0, template_label_ok, "-" ) ) ) | D15: FALSE
B16: =template_label_b2_practices_policies_and_future_initiatives_for_transitioning_towards_a_more_sustainable_economy_validation | C16: =IF(D16=TRUE,template_label_classified_or_sensitive_information, IF(COUNTIF(C17:C18,template_label_error_plus_missing_value_plus_value_inconsistency)>0,template_label_error_plus_missing_value_plus_value_inconsistency, IF(COUNTIF(C17:C18,template_label_error_plus_value_inconsistency)>0,template_label_error_plus_value_inconsistency, IF(COUNTIF(C17:C18,template_label_error_plus_missing_value)>0,template_label_error_plus_missing_value, IF(COUNTIF(C17:C18,template_label_error)>0,template_label_error, IF(COUNTIF(C17:C18,template_label_missing_value_plus_value_inconsistency)>0,template_label_missing_value_plus_value_inconsistency, IF(COUNTIF(C17:C18,template_label_value_inconsistency)>0,template_label_value_inconsistency, IF(COUNTIF(C17:C18,template_label_missing_value)>0,template_label_missing_value, IF(COUNTIF(C17:C18,template_label_ok)=ROWS(C17:C18),template_label_ok, IF(COUNTIF(C17:C18,"-")=ROWS(C17:C18),"-", IF(AND(COUNTIF(C17:C18,template_label_ok)>0, COUNTIF(C17:C18,template_label_error_plus_missing_value_plus_value_inconsistency)=0, COUNTIF(C17:C18,template_label_error_plus_value_inconsistency)=0, COUNTIF(C17:C18,template_label_error_plus_missing_value)=0, COUNTIF(C17:C18,template_label_error)=0, COUNTIF(C17:C18,template_label_missing_value_plus_value_inconsistency)=0, COUNTIF(C17:C18,template_label_value_inconsistency)=0, COUNTIF(C17:C18,template_label_missing_value)=0,OR(COUNTIF(C17:C18,template_label_missing_value)=0, COUNTIF(C17:C18,template_label_missing_value)>0)), template_label_ok, "-"))))))))) )) | D16: =IF(COUNTIF(D17:D18,TRUE)=ROWS(D17:D18),TRUE,FALSE)
B17: =template_label_b2_practices_policies_and_future_initiatives_for_transitioning_towards_a_more_sustainable_economy | C17: =IF(D17=TRUE, template_label_classified_or_sensitive_information, IF( COUNTIF('General Information'!P510, template_label_missing_value) > 0, template_label_missing_value, IF( COUNTIF('General Information'!P510, template_label_ok) > 0, template_label_ok, "-" ) ) ) | D17: FALSE
B18: =template_label_b2_cooperative_specific_disclosures | C18: {=IF(D18=TRUE, template_label_classified_or_sensitive_information, IF(OR('General Information'!E514:E516=template_label_ok),template_label_ok,"-") )} | D18: FALSE
B19: =template_label_environmental_disclosures_validation
B20: =template_label_b3_energy_and_greenhouse_gas_emissions_validation | C20: =IF(D20=TRUE,template_label_classified_or_sensitive_information, IF(COUNTIF(C21:C24,template_label_error_plus_missing_value_plus_value_inconsistency)>0,template_label_error_plus_missing_value_plus_value_inconsistency, IF(COUNTIF(C21:C24,template_label_error_plus_value_inconsistency)>0,template_label_error_plus_value_inconsistency, IF(COUNTIF(C21:C24,template_label_error_plus_missing_value)>0,template_label_error_plus_missing_value, IF(COUNTIF(C21:C24,template_label_error)>0,template_label_error, IF(COUNTIF(C21:C24,template_label_missing_value_plus_value_inconsistency)>0,template_label_missing_value_plus_value_inconsistency, IF(COUNTIF(C21:C24,template_label_value_inconsistency)>0,template_label_value_inconsistency, IF(COUNTIF(C21:C24,template_label_missing_value)>0,template_label_missing_value, IF(COUNTIF(C21:C24,template_label_ok)=ROWS(C21:C24),template_label_ok, IF(COUNTIF(C21:C24,"-")=ROWS(C21:C24),"-", IF(AND(COUNTIF(C21:C24,template_label_ok)>0, COUNTIF(C21:C24,template_label_error_plus_missing_value_plus_value_inconsistency)=0, COUNTIF(C21:C24,template_label_error_plus_value_inconsistency)=0, COUNTIF(C21:C24,template_label_error_plus_missing_value)=0, COUNTIF(C21:C24,template_label_error)=0, COUNTIF(C21:C24,template_label_missing_value_plus_value_inconsistency)=0, COUNTIF(C21:C24,template_label_value_inconsistency)=0, COUNTIF(C21:C24,template_label_missing_value)=0,OR(COUNTIF(C21:C24,template_label_missing_value)=0, COUNTIF(C21:C24,template_label_missing_value)>0)), template_label_ok, "-"))))))))) )) | D20: =IF(COUNTIF(D21:D24,TRUE)=ROWS(D21:D24),TRUE,FALSE)
B21: =template_label_b3_total_energy_consumption | C21: =IF(D21=TRUE, template_label_classified_or_sensitive_information, IF(COUNTIF('Environmental Disclosures'!L5,template_label_missing_value)>0,template_label_missing_value, IF(COUNTIF('Environmental Disclosures'!L5,template_label_ok)>0,template_label_ok,"-")) ) | D21: FALSE
B22: =template_label_b3_breakdown_of_energy_consumption | C22: =IF(D22=TRUE,template_label_classified_or_sensitive_information, IF( AND( COUNTIF('Environmental Disclosures'!L12:L14,template_label_missing_value)>0, COUNTIF('Environmental Disclosures'!L12:L14,template_label_value_inconsistency)=0 ), template_label_missing_value, IF( AND( COUNTIF('Environmental Disclosures'!L12:L14,template_label_value_inconsistency)>0, COUNTIF('Environmental Disclosures'!L12:L14,template_label_missing_value)=0 ), template_label_value_inconsistency, IF( AND( COUNTIF('Environmental Disclosures'!L12:L14,template_label_value_inconsistency)>0, COUNTIF('Environmental Disclosures'!L12:L14,template_label_missing_value)>0 ), template_label_error_plus_value_inconsistency, IF( COUNTIF('Environmental Disclosures'!L12:L14,"-")=3, "-", IF( COUNTIF('Environmental Disclosures'!L12:L14,template_label_ok)>0, template_label_ok, "-" ) )) )) ) | D22: FALSE
B23: =template_label_b3_estimated_greenhouse_gas_emissions | C23: =IF(D23=TRUE, template_label_classified_or_sensitive_information, IF(COUNTIF('Environmental Disclosures'!L21:L44,template_label_missing_value)>0,template_label_missing_value, IF(COUNTIF('Environmental Disclosures'!L21:L44,template_label_ok)>0,template_label_ok,"-")) ) | D23: FALSE
B24: =template_label_b3_greenhouse_gas_emission_intensity_per_turnover | C24: =IF(D24=TRUE, template_label_classified_or_sensitive_information, IF(C23=template_label_ok,template_label_ok,"-") ) | D24: FALSE
B25: =template_label_b4_pollution_of_air_water_and_soil_validation | C25: =IF(D25=TRUE, template_label_classified_or_sensitive_information, IF(COUNTIF('Environmental Disclosures'!L75:L179,template_label_invalid_url)>0, template_label_invalid_url, IF(AND(COUNTIF('Environmental Disclosures'!L75:L179,template_label_missing_value)>0, COUNTIF('Environmental Disclosures'!L75:L179,template_label_value_inconsistency)>0), template_label_missing_value_plus_value_inconsistency, IF(COUNTIF('Environmental Disclosures'!L75:L179,template_label_missing_value)>0, template_label_missing_value, IF(COUNTIF('Environmental Disclosures'!L75:L179,template_label_value_inconsistency)>0, template_label_value_inconsistency, IF(COUNTIF('Environmental Disclosures'!L75:L179,template_label_ok)>0, template_label_ok, "-"))))) ) | D25: FALSE
B26: =template_label_b5_biodiversity_validation | C26: =IF(D26=TRUE, template_label_classified_or_sensitive_information, IF(COUNTIF(C27:C28,template_label_error_plus_missing_value_plus_value_inconsistency)>0,template_label_error_plus_missing_value_plus_value_inconsistency, IF(COUNTIF(C27:C28,template_label_error_plus_value_inconsistency)>0,template_label_error_plus_value_inconsistency, IF(COUNTIF(C27:C28,template_label_error_plus_missing_value)>0,template_label_error_plus_missing_value, IF(COUNTIF(C27:C28,template_label_error)>0,template_label_error, IF(COUNTIF(C27:C28,template_label_missing_value_plus_value_inconsistency)>0,template_label_missing_value_plus_value_inconsistency, IF(COUNTIF(C27:C28,template_label_value_inconsistency)>0,template_label_value_inconsistency, IF(COUNTIF(C27:C28,template_label_missing_value)>0,template_label_missing_value, IF(COUNTIF(C27:C28,template_label_ok)=ROWS(C27:C28),template_label_ok, IF(COUNTIF(C27:C28,"-")=ROWS(C27:C28),"-", IF(AND(COUNTIF(C27:C28,template_label_ok)>0, COUNTIF(C27:C28,template_label_error_plus_missing_value_plus_value_inconsistency)=0, COUNTIF(C27:C28,template_label_error_plus_value_inconsistency)=0, COUNTIF(C27:C28,template_label_error_plus_missing_value)=0, COUNTIF(C27:C28,template_label_error)=0, COUNTIF(C27:C28,template_label_missing_value_plus_value_inconsistency)=0, COUNTIF(C27:C28,template_label_value_inconsistency)=0, COUNTIF(C27:C28,template_label_missing_value)=0,OR(COUNTIF(C27:C28,template_label_missing_value)=0, COUNTIF(C27:C28,template_label_missing_value)>0)), template_label_ok, "-"))))))))) )) | D26: =IF(COUNTIF(D27:D28,TRUE)=ROWS(D27:D28),TRUE,FALSE)
B27: =template_label_b5_sites_in_biodiversity_sensitive_areas | C27: =IF(D27=TRUE, template_label_classified_or_sensitive_information, IF(AND( COUNTIF('Environmental Disclosures'!D188:D287,template_label_ok) + COUNTIF('Environmental Disclosures'!L186:L287,template_label_ok) > 0, COUNTIF('Environmental Disclosures'!D188:D287,template_label_missing_value) + COUNTIF('Environmental Disclosures'!L186:L287,template_label_missing_value) = 0, COUNTIF('Environmental Disclosures'!D188:D287,template_label_value_inconsistency) + COUNTIF('Environmental Disclosures'!L186:L287,template_label_value_inconsistency) = 0), template_label_ok, IF(AND( COUNTIF('Environmental Disclosures'!D188:D287,template_label_missing_value) + COUNTIF('Environmental Disclosures'!L186:L287,template_label_missing_value) > 0, COUNTIF('Environmental Disclosures'!D188:D287,template_label_value_inconsistency) + COUNTIF('Environmental Disclosures'!L186:L287,template_label_value_inconsistency) = 0), template_label_missing_value, IF(AND( COUNTIF('Environmental Disclosures'!D188:D287,template_label_value_inconsistency) + COUNTIF('Environmental Disclosures'!L186:L287,template_label_value_inconsistency) > 0, COUNTIF('Environmental Disclosures'!D188:D287,template_label_missing_value) + COUNTIF('Environmental Disclosures'!L186:L287,template_label_missing_value) = 0), template_label_value_inconsistency, IF(AND( COUNTIF('Environmental Disclosures'!D188:D287,template_label_value_inconsistency) + COUNTIF('Environmental Disclosures'!L186:L287,template_label_value_inconsistency) > 0, COUNTIF('Environmental Disclosures'!D188:D287,template_label_missing_value) + COUNTIF('Environmental Disclosures'!L186:L287,template_label_missing_value) > 0), template_label_missing_value_plus_value_inconsistency, "-" ) ) ) ) ) | D27: FALSE
B28: =template_label_b5_biodiversity_land_use | C28: =IF(D28=TRUE, template_label_classified_or_sensitive_information, IF( AND( COUNTIF('Environmental Disclosures'!G293:G298,template_label_missing_value)>0, COUNTIF('Environmental Disclosures'!G293:G298,template_label_value_inconsistency)=0, COUNTIF('Environmental Disclosures'!G293:G298,template_label_ok)>=0 ), template_label_missing_value, IF( AND( COUNTIF('Environmental Disclosures'!G293:G298,template_label_value_inconsistency)>0, COUNTIF('Environmental Disclosures'!G293:G298,template_label_missing_value)=0, COUNTIF('Environmental Disclosures'!G293:G298,template_label_ok)>=0 ), template_label_value_inconsistency, IF( AND( COUNTIF('Environmental Disclosures'!G293:G298,template_label_value_inconsistency)>0, COUNTIF('Environmental Disclosures'!G293:G298,template_label_missing_value)>0, COUNTIF('Environmental Disclosures'!G293:G298,template_label_ok)>=0 ), template_label_missing_value_plus_value_inconsistency, IF( AND( COUNTIF('Environmental Disclosures'!G293:G298,template_label_value_inconsistency)=0, COUNTIF('Environmental Disclosures'!G293:G298,template_label_missing_value)=0, COUNTIF('Environmental Disclosures'!G293:G298,template_label_ok)>0 ), template_label_ok, "-" ) ) )) ) | D28: FALSE
B29: =template_label_b6_water_validation | C29: =IF(D29=TRUE, template_label_classified_or_sensitive_information, IF(COUNTIF(C30:C31,template_label_error_plus_missing_value_plus_value_inconsistency)>0,template_label_error_plus_missing_value_plus_value_inconsistency, IF(COUNTIF(C30:C31,template_label_error_plus_value_inconsistency)>0,template_label_error_plus_value_inconsistency, IF(COUNTIF(C30:C31,template_label_error_plus_missing_value)>0,template_label_error_plus_missing_value, IF(COUNTIF(C30:C31,template_label_error)>0,template_label_error, IF(COUNTIF(C30:C31,template_label_missing_value_plus_value_inconsistency)>0,template_label_missing_value_plus_value_inconsistency, IF(COUNTIF(C30:C31,template_label_value_inconsistency)>0,template_label_value_inconsistency, IF(COUNTIF(C30:C31,template_label_missing_value)>0,template_label_missing_value, IF(COUNTIF(C30:C31,template_label_ok)=ROWS(C30:C31),template_label_ok, IF(COUNTIF(C30:C31,"-")=ROWS(C30:C31),"-", IF(AND(COUNTIF(C30:C31,template_label_ok)>0, COUNTIF(C27:C28,template_label_error_plus_missing_value_plus_value_inconsistency)=0, COUNTIF(C30:C31,template_label_error_plus_value_inconsistency)=0, COUNTIF(C30:C31,template_label_error_plus_missing_value)=0, COUNTIF(C30:C31,template_label_error)=0, COUNTIF(C30:C31,template_label_missing_value_plus_value_inconsistency)=0, COUNTIF(C30:C31,template_label_value_inconsistency)=0, COUNTIF(C30:C31,template_label_missing_value)=0,OR(COUNTIF(C30:C31,template_label_missing_value)=0, COUNTIF(C30:C31,template_label_missing_value)>0)), template_label_ok, "-"))))))))) )) | D29: =IF(COUNTIF(D30:D31,TRUE)=ROWS(D30:D31),TRUE,FALSE)
B30: =template_label_b6_water_withdrawal | C30: =IF(D30=TRUE, template_label_classified_or_sensitive_information, IF(COUNTIF('Environmental Disclosures'!E303:F304, template_label_missing_value) > 0, template_label_missing_value, IF(COUNTIF('Environmental Disclosures'!E303:F304, template_label_ok) > 0, template_label_ok, "-")) ) | D30: FALSE
B31: =template_label_b6_water_consumption | C31: =IF(D31=TRUE, template_label_classified_or_sensitive_information, IF(COUNTIF('Environmental Disclosures'!E310:F310, template_label_missing_value) > 0, template_label_missing_value, IF(COUNTIF('Environmental Disclosures'!E310:F310, template_label_ok) > 0, template_label_ok, "-")) ) | D31: FALSE
B32: =template_label_b7_resource_use_circular_economy_and_waste_management_validation | C32: =IF(D32=TRUE, template_label_classified_or_sensitive_information, IF(COUNTIF(C33:C35, template_label_error_plus_missing_value_plus_value_inconsistency) > 0, template_label_error_plus_missing_value_plus_value_inconsistency, IF(COUNTIF(C33:C35, template_label_error_plus_value_inconsistency) > 0, template_label_error_plus_value_inconsistency, IF(COUNTIF(C33:C35, template_label_error_plus_missing_value) > 0, template_label_error_plus_missing_value, IF(COUNTIF(C33:C35, template_label_error) > 0, template_label_error, IF(COUNTIF(C33:C35, template_label_missing_value_plus_value_inconsistency) > 0, template_label_missing_value_plus_value_inconsistency, IF(COUNTIF(C33:C35, template_label_value_inconsistency) > 0, template_label_value_inconsistency, IF(COUNTIF(C33:C35, template_label_missing_value) > 0, template_label_missing_value, IF(COUNTIF(C33:C35, template_label_ok) = ROWS(C33:C35), template_label_ok, IF(COUNTIF(C33:C35, "-") = ROWS(C33:C35), "-", IF(AND(COUNTIF(C33:C35,template_label_ok)>0, COUNTIF(C33:C35,template_label_error_plus_missing_value_plus_value_inconsistency)=0, COUNTIF(C33:C35,template_label_error_plus_value_inconsistency)=0, COUNTIF(C33:C35,template_label_error_plus_missing_value)=0, COUNTIF(C33:C35,template_label_error)=0, COUNTIF(C33:C35,template_label_missing_value_plus_value_inconsistency)=0, COUNTIF(C33:C35,template_label_value_inconsistency)=0, COUNTIF(C33:C35,template_label_missing_value)=0,OR(COUNTIF(C33:C35,template_label_missing_value)=0, COUNTIF(C33:C35,template_label_missing_value)>0)), template_label_ok, "-"))))))))) )) | D32: =IF(COUNTIF(D34:D35,TRUE)=ROWS(D34:D35),TRUE,FALSE)
B33: =template_label_b7_description_of_circular_economy_principles | C33: =IF(D33=TRUE, template_label_classified_or_sensitive_information, IF( AND( COUNTIF('Environmental Disclosures'!H316:I317, template_label_missing_value) > 0, COUNTIF('Environmental Disclosures'!H316:I317, template_label_value_inconsistency) = 0, COUNTIF('Environmental Disclosures'!H316:I317, template_label_ok) >= 0 ), template_label_missing_value, IF( AND( COUNTIF('Environmental Disclosures'!H316:I317, template_label_value_inconsistency) > 0, COUNTIF('Environmental Disclosures'!H316:I317, template_label_missing_value) = 0, COUNTIF('Environmental Disclosures'!H316:I317, template_label_ok) >= 0 ), template_label_value_inconsistency, IF( AND( COUNTIF('Environmental Disclosures'!H316:I317, template_label_value_inconsistency) > 0, COUNTIF('Environmental Disclosures'!H316:I317, template_label_missing_value) > 0, COUNTIF('Environmental Disclosures'!H316:I317, template_label_ok) >= 0 ), template_label_missing_value_plus_value_inconsistency, IF( AND( COUNTIF('Environmental Disclosures'!H316:I317, template_label_value_inconsistency) = 0, COUNTIF('Environmental Disclosures'!H316:I317, template_label_missing_value) = 0, COUNTIF('Environmental Disclosures'!H316:I317, template_label_ok) > 0 ), template_label_ok, "-" ) ) )) ) | D33: FALSE
B34: =template_label_b7_waste_generated | C34: =IF(D34=TRUE, template_label_classified_or_sensitive_information, IF( AND( COUNTIF('Environmental Disclosures'!M323:M423, template_label_error) > 0, COUNTIF('Environmental Disclosures'!M323:M423, template_label_missing_value) > 0, COUNTIF('Environmental Disclosures'!M323:M423, template_label_value_inconsistency) > 0 ), template_label_error_plus_missing_value_plus_value_inconsistency, IF( AND( COUNTIF('Environmental Disclosures'!M323:M423, template_label_error) > 0, COUNTIF('Environmental Disclosures'!M323:M423, template_label_value_inconsistency) > 0, COUNTIF('Environmental Disclosures'!M323:M423, template_label_missing_value) = 0 ), template_label_error_plus_value_inconsistency, IF( AND( COUNTIF('Environmental Disclosures'!M323:M423, template_label_error) > 0, COUNTIF('Environmental Disclosures'!M323:M423, template_label_missing_value) > 0, COUNTIF('Environmental Disclosures'!M323:M423, template_label_value_inconsistency) = 0 ), template_label_error_plus_missing_value, IF( AND( COUNTIF('Environmental Disclosures'!M323:M423, template_label_missing_value) > 0, COUNTIF('Environmental Disclosures'!M323:M423, template_label_value_inconsistency) > 0, COUNTIF('Environmental Disclosures'!M323:M423, template_label_error) = 0 ), template_label_missing_value_plus_value_inconsistency, IF( AND( COUNTIF('Environmental Disclosures'!M323:M423, template_label_error) > 0, COUNTIF('Environmental Disclosures'!M323:M423, template_label_missing_value) = 0, COUNTIF('Environmental Disclosures'!M323:M423, template_label_value_inconsistency) = 0 ), template_label_error, IF( AND( COUNTIF('Environmental Disclosures'!M323:M423, template_label_missing_value) > 0, COUNTIF('Environmental Disclosures'!M323:M423, template_label_error) = 0, COUNTIF('Environmental Disclosures'!M323:M423, template_label_value_inconsistency) = 0 ), template_label_missing_value, IF( AND( COUNTIF('Environmental Disclosures'!M323:M423, template_label_value_inconsistency) > 0, COUNTIF('Environmental Disclosures'!M323:M423, template_label_error) = 0, COUNTIF('Environmental Disclosures'!M323:M423, template_label_missing_value) = 0 ), template_label_value_inconsistency, IF( AND( COUNTIF('Environmental Disclosures'!M323:M423, template_label_error) = 0, COUNTIF('Environmental Disclosures'!M323:M423, template_label_missing_value) = 0, COUNTIF('Environmental Disclosures'!M323:M423, template_label_value_inconsistency) = 0, COUNTIF('Environmental Disclosures'!M323:M423, template_label_ok) > 0 ), template_label_ok, "-" )))))))) ) | D34: FALSE
B35: =template_label_b7_annual_mass_flow_of_relevant_materials_used | C35: =IF(D35=TRUE, template_label_classified_or_sensitive_information, IF(COUNTIF('Environmental Disclosures'!K435:K534, template_label_missing_value) > 0, template_label_missing_value, IF(COUNTIF('Environmental Disclosures'!K435:K534, template_label_ok) > 0, template_label_ok, "-")) ) | D35: FALSE
B36: =template_label_social_disclosures_validation
B37: =template_label_b8_workforce_general_characteristics_validation | C37: =IF(D37=TRUE, template_label_classified_or_sensitive_information, IF(COUNTIF(C38:C41, template_label_error_plus_missing_value_plus_value_inconsistency) > 0, template_label_error_plus_missing_value_plus_value_inconsistency, IF(COUNTIF(C38:C41, template_label_error_plus_value_inconsistency) > 0, template_label_error_plus_value_inconsistency, IF(COUNTIF(C38:C41, template_label_error_plus_missing_value) > 0, template_label_error_plus_missing_value, IF(COUNTIF(C38:C41, template_label_error) > 0, template_label_error, IF(COUNTIF(C38:C41, template_label_missing_value_plus_value_inconsistency) > 0, template_label_missing_value_plus_value_inconsistency, IF(COUNTIF(C38:C41, template_label_value_inconsistency) > 0, template_label_value_inconsistency, IF(COUNTIF(C38:C41, template_label_missing_value) > 0, template_label_missing_value, IF(COUNTIF(C38:C41, template_label_ok) = ROWS(C38:C41), template_label_ok, IF(COUNTIF(C38:C41, "-") = ROWS(C38:C41), "-", IF(AND(COUNTIF(C38:C41,template_label_ok)>0, COUNTIF(C38:C41,template_label_error_plus_missing_value_plus_value_inconsistency)=0, COUNTIF(C38:C41,template_label_error_plus_value_inconsistency)=0, COUNTIF(C38:C41,template_label_error_plus_missing_value)=0, COUNTIF(C38:C41,template_label_error)=0, COUNTIF(C38:C41,template_label_missing_value_plus_value_inconsistency)=0, COUNTIF(C38:C41,template_label_value_inconsistency)=0, COUNTIF(C38:C41,template_label_missing_value)=0,OR(COUNTIF(C38:C41,template_label_missing_value)=0, COUNTIF(C38:C41,template_label_missing_value)>0)), template_label_ok, "-"))))))))) )) | D37: =IF(COUNTIF(D38:D41,TRUE)=ROWS(D38:D41),TRUE,FALSE)
B38: =template_label_b8_workforce_general_characteristics_type_of_contract | C38: =IF(D38=TRUE, template_label_classified_or_sensitive_information, IF(COUNTIF('Social Disclosures'!H10, template_label_missing_value) > 0, template_label_missing_value, IF(COUNTIF('Social Disclosures'!H10, template_label_ok) > 0, template_label_ok, "-")) ) | D38: FALSE
B39: =template_label_b8_workforce_general_characteristics_gender | C39: =IF(D39=TRUE,template_label_classified_or_sensitive_information, IF(COUNTIF('Social Disclosures'!H18,template_label_missing_value)>0, template_label_missing_value,IF(COUNTIF('Social Disclosures'!H18,template_label_value_inconsistency)>0, template_label_value_inconsistency, IF(COUNTIF('Social Disclosures'!H18,template_label_ok)>0, template_label_ok, "-")) )) | D39: FALSE
B40: =template_label_b8_workforce_general_characteristics_country_of_employment | C40: =IF(D40=TRUE, template_label_classified_or_sensitive_information, IF(COUNTIF('Social Disclosures'!I29:I128, template_label_missing_value) > 0, template_label_missing_value, IF(COUNTIF('Social Disclosures'!I29:I128, template_label_ok) > 0, template_label_ok, "-")) ) | D40: FALSE
B41: =template_label_b8_workforce_general_characteristics_turnover_rate | C41: =IF(D41=TRUE, template_label_classified_or_sensitive_information, IF(COUNTIF('Social Disclosures'!I134:I136, template_label_missing_value) > 0, template_label_missing_value, IF(COUNTIF('Social Disclosures'!I134:I136, template_label_ok) > 0, template_label_ok, "-")) ) | D41: FALSE
B42: =template_label_b9_workforce_health_and_safety_validation | C42: =IF(D42=TRUE, template_label_classified_or_sensitive_information, IF(COUNTIF('Social Disclosures'!I140:I144, template_label_missing_value) > 0, template_label_missing_value, IF(COUNTIF('Social Disclosures'!I140:I144, template_label_ok) > 0, template_label_ok, "-")) ) | D42: FALSE
B43: =template_label_b10_workforce_remuneration_collective_bargaining_and_training_validation | C43: =IF(D43=TRUE,template_label_classified_or_sensitive_information, IF(COUNTIF(C44:C45,template_label_error_plus_missing_value_plus_value_inconsistency)>0,template_label_error_plus_missing_value_plus_value_inconsistency, IF(COUNTIF(C44:C45,template_label_error_plus_value_inconsistency)>0,template_label_error_plus_value_inconsistency, IF(COUNTIF(C44:C45,template_label_error_plus_missing_value)>0,template_label_error_plus_missing_value, IF(COUNTIF(C44:C45,template_label_error)>0,template_label_error, IF(COUNTIF(C44:C45,template_label_missing_value_plus_value_inconsistency)>0,template_label_missing_value_plus_value_inconsistency, IF(COUNTIF(C44:C45,template_label_value_inconsistency)>0,template_label_value_inconsistency, IF(COUNTIF(C44:C45,template_label_missing_value)>0,template_label_missing_value, IF(COUNTIF(C44:C45,template_label_ok)=ROWS(C44:C45),template_label_ok, IF(COUNTIF(C44:C45,"-")=ROWS(C44:C45),"-", IF(AND(COUNTIF(C44:C45,template_label_ok)>0,COUNTIF(C44:C45,template_label_error_plus_missing_value_plus_value_inconsistency)=0,COUNTIF(C44:C45,template_label_error_plus_value_inconsistency)=0,COUNTIF(C44:C45,template_label_error_plus_missing_value)=0,COUNTIF(C44:C45,template_label_error)=0,COUNTIF(C44:C45,template_label_missing_value_plus_value_inconsistency)=0,COUNTIF(C44:C45,template_label_value_inconsistency)=0,COUNTIF(C44:C45,template_label_missing_value)=0,OR(COUNTIF(C44:C45,template_label_missing_value)=0, COUNTIF(C44:C45,template_label_missing_value)>0)),template_label_ok, "-"))))))))))) | D43: =IF(COUNTIF(D44:D45,TRUE)=ROWS(D44:D45),TRUE,FALSE)
B44: =template_label_b10_workforce_remuneration_collective_bargaining | C44: =IF(D44=TRUE, template_label_classified_or_sensitive_information, IF(COUNTIF('Social Disclosures'!I147:I151, template_label_missing_value) > 0, template_label_missing_value, IF(COUNTIF('Social Disclosures'!I147:I151, template_label_ok) > 0, template_label_ok, "-")) ) | D44: FALSE
B45: =template_label_number_of_annual_training_hours_per_employee_during_the_reporting_period | C45: =IF(D45=TRUE, template_label_classified_or_sensitive_information, IF(COUNTIF('Social Disclosures'!I157:I160, template_label_missing_value) > 0, template_label_missing_value, IF(COUNTIF('Social Disclosures'!I157:I160, template_label_ok) > 0, template_label_ok, "-")) ) | D45: FALSE
B46: =template_label_governance_disclosures_validation
B47: =template_label_b11_convictions_and_fines_for_corruption_and_bribery_validation | C47: =IF(D47=TRUE, template_label_classified_or_sensitive_information, IF(COUNTIF('Governance Disclosures'!I6:I7, template_label_missing_value) > 0, template_label_missing_value, IF(COUNTIF('Governance Disclosures'!I6:I7, template_label_ok) > 0, template_label_ok, "-")) ) | D47: FALSE
B48: =template_label_comprehensive_module_validation
B49: =template_label_general_information_validation
B50: =template_label_c1_strategy_business_model_and_sustainability_related_initiatives_validation | C50: =IF(D50=TRUE, template_label_classified_or_sensitive_information, IF(COUNTIF('General Information'!H525:H529, template_label_missing_value) > 0, template_label_missing_value, IF(COUNTIF('General Information'!H525:H529, template_label_ok) > 0, template_label_ok, "-")) ) | D50: FALSE
B51: =template_label_c2_description_of_practices_policies_and_future_initiatives_for_transitioning_towards_a_more_sustainable_economy_validation | C51: =IF(D51=TRUE, template_label_classified_or_sensitive_information, IF(COUNTIF('General Information'!H519:H521, template_label_missing_value) > 0, template_label_missing_value, IF(COUNTIF('General Information'!H519:H521, template_label_ok) > 0, template_label_ok, "-")) ) | D51: FALSE
B52: =template_label_environmental_disclosures_validation
B53: =template_label_c3_ghg_reduction_targets_and_climate_transition_validation | C53: =IF(D53=TRUE,template_label_classified_or_sensitive_information, IF(COUNTIF(C54:C56,template_label_error_plus_missing_value_plus_value_inconsistency)>0,template_label_error_plus_missing_value_plus_value_inconsistency, IF(COUNTIF(C54:C56,template_label_error_plus_value_inconsistency)>0,template_label_error_plus_value_inconsistency, IF(COUNTIF(C54:C56,template_label_error_plus_missing_value)>0,template_label_error_plus_missing_value, IF(COUNTIF(C54:C56,template_label_error)>0,template_label_error, IF(COUNTIF(C54:C56,template_label_missing_value_plus_value_inconsistency)>0,template_label_missing_value_plus_value_inconsistency, IF(COUNTIF(C54:C56,template_label_value_inconsistency)>0,template_label_value_inconsistency, IF(COUNTIF(C54:C56,template_label_missing_value)>0,template_label_missing_value, IF(COUNTIF(C54:C56,template_label_ok)=ROWS(C54:C56),template_label_ok, IF(COUNTIF(C54:C56,"-")=ROWS(C54:C56),"-", IF(AND(COUNTIF(C54:C56,template_label_ok)>0, COUNTIF(C54:C56,template_label_error_plus_missing_value_plus_value_inconsistency)=0, COUNTIF(C54:C56,template_label_error_plus_value_inconsistency)=0, COUNTIF(C54:C56,template_label_error_plus_missing_value)=0, COUNTIF(C54:C56,template_label_error)=0, COUNTIF(C54:C56,template_label_missing_value_plus_value_inconsistency)=0, COUNTIF(C54:C56,template_label_value_inconsistency)=0, COUNTIF(C54:C56,template_label_missing_value)=0), template_label_ok, "-"))))))))))) | D53: =IF(COUNTIF(D54:D56,TRUE)=ROWS(D54:D56),TRUE,FALSE)
B54: =template_label_c3_ghg_reduction_targets | C54: =IF(D54=TRUE, template_label_classified_or_sensitive_information, IF(AND('General Information'!E122 = "Option A (Basic Module only)", COUNTA('Environmental Disclosures'!G21:G24) = 0), "-", IF(COUNTIF('Environmental Disclosures'!L52, template_label_missing_value) > 0, template_label_missing_value, IF(COUNTIF('Environmental Disclosures'!L52, template_label_ok) > 0, template_label_ok, "-"))) ) | D54: FALSE
B55: =template_label_c3_disclosure_of_list_of_main_actions_the_entity_seeks_in_order_to_achieve_its_targets | C55: =IF(D55=TRUE, template_label_classified_or_sensitive_information, IF(COUNTIF('Environmental Disclosures'!L52, template_label_missing_value) > 0, template_label_missing_value, IF(COUNTIF('Environmental Disclosures'!L52, template_label_ok) > 0, template_label_ok, "-")) ) | D55: FALSE
B56: =template_label_c3_transition_plan_for_undertakings_operating_in_high_climate_impact_sectors | C56: =IF(D56=TRUE, template_label_classified_or_sensitive_information, IF( AND( COUNTIF('Environmental Disclosures'!L57:L59, template_label_missing_value) > 0, COUNTIF('Environmental Disclosures'!L57:L59, template_label_error) = 0, COUNTIF('Environmental Disclosures'!L57:L59, template_label_ok) >= 0 ), template_label_missing_value, IF( AND( COUNTIF('Environmental Disclosures'!L57:L59, template_label_error) > 0, COUNTIF('Environmental Disclosures'!L57:L59, template_label_missing_value) = 0, COUNTIF('Environmental Disclosures'!L57:L59, template_label_ok) >= 0 ), template_label_error, IF( AND( COUNTIF('Environmental Disclosures'!L57:L59, template_label_error) > 0, COUNTIF('Environmental Disclosures'!L57:L59, template_label_missing_value) > 0, COUNTIF('Environmental Disclosures'!L57:L59, template_label_ok) >= 0 ), template_label_error_plus_missing_value, IF( AND( COUNTIF('Environmental Disclosures'!L57:L59, template_label_error) = 0, COUNTIF('Environmental Disclosures'!L57:L59, template_label_missing_value) = 0, COUNTIF('Environmental Disclosures'!L57:L59, template_label_ok) > 0 ), template_label_ok, "-" ) ) )) ) | D56: FALSE
B57: =template_label_c4_climate_risks_validation | C57: =IF(D57=TRUE, template_label_classified_or_sensitive_information, IF(COUNTIF('Environmental Disclosures'!L540:L544, template_label_missing_value) > 0, template_label_missing_value, IF(COUNTIF('Environmental Disclosures'!L540:L544, template_label_ok) > 0, template_label_ok, "-")) ) | D57: FALSE
B58: =template_label_social_disclosures_validation
B59: =template_label_c5_additional_general_workforce_characteristics_validation | C59: =IF(D59=TRUE, template_label_classified_or_sensitive_information, IF(COUNTIF('Social Disclosures'!I165:I169, template_label_ok) > 0, template_label_ok, "-") ) | D59: FALSE
B60: =template_label_c6_additional_own_workforce_information_human_rights_policies_and_processes_validation | C60: =IF(D60=TRUE, template_label_classified_or_sensitive_information, IF( AND( COUNTIF('Social Disclosures'!I172:I181, template_label_missing_value) > 0, COUNTIF('Social Disclosures'!I172:I181, template_label_value_inconsistency) = 0, COUNTIF('Social Disclosures'!I172:I181, template_label_ok) >= 0 ), template_label_missing_value, IF( AND( COUNTIF('Social Disclosures'!I172:I181, template_label_value_inconsistency) > 0, COUNTIF('Social Disclosures'!I172:I181, template_label_missing_value) = 0, COUNTIF('Social Disclosures'!I172:I181, template_label_ok) >= 0 ), template_label_value_inconsistency, IF( AND( COUNTIF('Social Disclosures'!I172:I181, template_label_value_inconsistency) > 0, COUNTIF('Social Disclosures'!I172:I181, template_label_missing_value) > 0, COUNTIF('Social Disclosures'!I172:I181, template_label_ok) >= 0 ), template_label_missing_value_plus_value_inconsistency, IF( AND( COUNTIF('Social Disclosures'!I172:I181, template_label_value_inconsistency) = 0, COUNTIF('Social Disclosures'!I172:I181, template_label_missing_value) = 0, COUNTIF('Social Disclosures'!I172:I181, template_label_ok) > 0 ), template_label_ok, "-" ) ) )) ) | D60: FALSE
B61: =template_label_c7_severe_negative_human_rights_incidents_validation | C61: =IF(D61=TRUE, template_label_classified_or_sensitive_information, IF( AND( COUNTIF('Social Disclosures'!I184:I194, template_label_missing_value) > 0, COUNTIF('Social Disclosures'!I184:I194, template_label_value_inconsistency) = 0, COUNTIF('Social Disclosures'!I184:I194, template_label_ok) >= 0 ), template_label_missing_value, IF( AND( COUNTIF('Social Disclosures'!I184:I194, template_label_value_inconsistency) > 0, COUNTIF('Social Disclosures'!I184:I194, template_label_missing_value) = 0, COUNTIF('Social Disclosures'!I184:I194, template_label_ok) >= 0 ), template_label_value_inconsistency, IF( AND( COUNTIF('Social Disclosures'!I184:I194, template_label_value_inconsistency) > 0, COUNTIF('Social Disclosures'!I184:I194, template_label_missing_value) > 0, COUNTIF('Social Disclosures'!I184:I194, template_label_ok) >= 0 ), template_label_missing_value_plus_value_inconsistency, IF( AND( COUNTIF('Social Disclosures'!I184:I194, template_label_value_inconsistency) = 0, COUNTIF('Social Disclosures'!I184:I194, template_label_missing_value) = 0, COUNTIF('Social Disclosures'!I184:I194, template_label_ok) > 0 ), template_label_ok, "-" ) ) )) ) | D61: FALSE
B62: =template_label_governance_disclosures_validation
B63: =template_label_c8_revenues_from_certain_sectors_and_exclusion_from_eu_reference_benchmarks_validation | C63: =IF(D63=TRUE,template_label_classified_or_sensitive_information, IF(COUNTIF(C64:C65,template_label_error_plus_missing_value_plus_value_inconsistency)>0,template_label_error_plus_missing_value_plus_value_inconsistency, IF(COUNTIF(C64:C65,template_label_error_plus_value_inconsistency)>0,template_label_error_plus_value_inconsistency, IF(COUNTIF(C64:C65,template_label_error_plus_missing_value)>0,template_label_error_plus_missing_value, IF(COUNTIF(C64:C65,template_label_error)>0,template_label_error, IF(COUNTIF(C64:C65,template_label_missing_value_plus_value_inconsistency)>0,template_label_missing_value_plus_value_inconsistency, IF(COUNTIF(C64:C65,template_label_value_inconsistency)>0,template_label_value_inconsistency, IF(COUNTIF(C64:C65,template_label_missing_value)>0,template_label_missing_value, IF(COUNTIF(C64:C65,template_label_ok)=ROWS(C64:C65),template_label_ok, IF(COUNTIF(C64:C65,"-")=ROWS(C64:C65),"-", IF(AND(COUNTIF(C64:C65,template_label_ok)>0, COUNTIF(C64:C65,template_label_error_plus_missing_value_plus_value_inconsistency)=0, COUNTIF(C64:C65,template_label_error_plus_value_inconsistency)=0, COUNTIF(C64:C65,template_label_error_plus_missing_value)=0, COUNTIF(C64:C65,template_label_error)=0, COUNTIF(C64:C65,template_label_missing_value_plus_value_inconsistency)=0, COUNTIF(C64:C65,template_label_value_inconsistency)=0, COUNTIF(C64:C65,template_label_missing_value)=0), template_label_ok, "-"))))))))))) | D63: =IF(COUNTIF(D64:D65,TRUE)=ROWS(D64:D65),TRUE,FALSE)
B64: =template_label_c8_revenues_from_certain_sectors | C64: =IF(D64=TRUE, template_label_classified_or_sensitive_information, IF(COUNTIF('Governance Disclosures'!I12:I18, template_label_value_inconsistency) > 0, template_label_value_inconsistency, IF(COUNTIF('Governance Disclosures'!I12:I18, template_label_ok) > 0, template_label_ok, "-")) ) | D64: FALSE
B65: =template_label_c8_exclusion_from_eu_reference_benchmarks | C65: =IF(D65=TRUE, template_label_classified_or_sensitive_information, IF(COUNTIF('Governance Disclosures'!I22:I26, template_label_missing_value) > 0, template_label_missing_value, IF(COUNTIF('Governance Disclosures'!I22:I26, template_label_ok) > 0, template_label_ok, "-")) ) | D65: FALSE
B66: =template_label_c9_gender_diversity_ratio_in_the_governance_body_validation | C66: =IF(D66=TRUE, template_label_classified_or_sensitive_information, IF(COUNTIF('Governance Disclosures'!I31:I32, template_label_missing_value) > 0, template_label_missing_value, IF(COUNTIF('Governance Disclosures'!I31:I32, template_label_ok) > 0, template_label_ok, "-")) ) | D66: FALSE
B67: =template_label_additional_disclosures_validation
B68: =template_label_disclosure_of_any_other_general_and_or_entity_specific_information_on_the_reporting_period | C68: =IF(D68=TRUE, template_label_classified_or_sensitive_information, IF('General Information'!I533 = template_label_ok, template_label_ok, "-") ) | D68: FALSE
B69: =template_label_disclosure_of_any_other_environmental_and_or_entity_specific_environmental_disclosures | C69: =IF(D69=TRUE, template_label_classified_or_sensitive_information, IF('Environmental Disclosures'!M548 = template_label_ok, template_label_ok, "-") ) | D69: FALSE
B70: =template_label_disclosure_of_any_other_social_and_or_entity_specific_social_disclosures | C70: =IF(D70=TRUE, template_label_classified_or_sensitive_information, IF('Social Disclosures'!I200 = template_label_ok, template_label_ok, "-") ) | D70: FALSE
B71: =template_label_disclosure_of_any_other_governance_and_or_entity_specific_governance_disclosures | C71: =IF(D71=TRUE, template_label_classified_or_sensitive_information, IF('Governance Disclosures'!I38 = template_label_ok, template_label_ok, "-") ) | D71: FALSE

Sheet General Information
A1: =template_label_paragraph_reference | B1: =template_label_paragraph_guidance_reference
C2: =template_label_information_on_the_report_necessary_for_xbrl & " " & template_label_always_to_be_reported
C3: =template_label_name_of_the_reporting_entity | D3: Company XYZ | F3: =IF(D3 = "", template_label_missing_value, template_label_ok)
C4: =template_label_identifier_of_the_reporting_entity | D4: LEI | E4: TestCode1234 | F4: =IF(OR(D4 = "", E4 = ""), template_label_missing_value, template_label_ok) | G4: =template_label_identifier_warning
C5: =template_label_currency_of_the_monetary_values_in_the_report | D5: EUR | F5: =IF(D5 = "", template_label_missing_value, template_label_ok)
C6: =template_label_starting_year | D6: 2024 | F6: =IF(OR(D6 = "", D7 = "", D8 = ""), template_label_missing_value, IF(OR( AND(D7 = 2, D8 > 29), AND(D7 = 2, D8 = 29, NOT(AND(MOD(D6, 4) = 0, OR(MOD(D6, 100) <> 0, MOD(D6, 400) = 0)))), AND(OR(D7 = 4, D7 = 6, D7 = 9, D7 = 11), D8 = 31) ), template_label_error, IF(F10 = template_label_value_inconsistency, template_label_value_inconsistency, template_label_ok) ) ) | G6: =template_label_date_warning
C7: =template_label_starting_month | D7: 1
C8: =template_label_starting_day | D8: 1
C9: =template_label_reporting_period_start_date | D9: =IF(OR(ISBLANK(D6), ISBLANK(D7), ISBLANK(D8)), "-", D6 & "-" & TEXT(D7, "00") & "-" & TEXT(D8, "00"))
C10: =template_label_ending_year | D10: 2024 | F10: =IF(OR(D10 = "", D11 = "", D12 = ""), template_label_missing_value, IF(OR( AND(D11 = 2, D12 > 29), AND(D11 = 2, D12 = 29, NOT(AND(MOD(D10, 4) = 0, OR(MOD(D10, 100) <> 0, MOD(D10, 400) = 0)))), AND(OR(D11 = 4, D11 = 6, D11 = 9, D11 = 11), D12 = 31) ), template_label_error, IF(D10 < D6, template_label_value_inconsistency, IF(D10 > D6, template_label_ok, IF(AND(D10 = D6, MATCH(D11, {1;2;3;4;5;6;7;8;9;10;11;12}, 0) < MATCH(D7, {1;2;3;4;5;6;7;8;9;10;11;12}, 0)), template_label_value_inconsistency, IF(AND(D10 = D6, MATCH(D11, {1;2;3;4;5;6;7;8;9;10;11;12}, 0) > MATCH(D7, {1;2;3;4;5;6;7;8;9;10;11;12}, 0)), template_label_ok, IF(AND(D10 = D6, MATCH(D11, {1;2;3;4;5;6;7;8;9;10;11;12}, 0) = MATCH(D7, {1;2;3;4;5;6;7;8;9;10;11;12}, 0), D12 < D8), template_label_value_inconsistency, template_label_ok ))))))) | G10: =template_label_date_warning
C11: =template_label_ending_month | D11: 12
C12: Ending day | D12: 31
C13: =template_label_reporting_period_end_date | D13: =IF(OR(ISBLANK(D10), ISBLANK(D11), ISBLANK(D12)), "-", D10 & "-" & TEXT(D11, "00") & "-" & TEXT(D12, "00"))
C16: =template_label_information_on_previous_reporting_period
C17: 16
C18: =template_label_disclosures_from_the_previous_reporting_period_that_remain_unchanged | E18: TRUE | F18: =IF(E18 = FALSE, "", template_label_ok)
C19: =template_label_disclosures_for_which_no_changes_are_reported_compared_to_the_previous_period_reporting | E19: B2 – Practices, policies and future initiatives for transitioning towards a more sustainable economy | F19: =IF(AND(E18 = FALSE, E19 = ""), "", IF(AND(E18 = FALSE, E19 <> ""), "", IF(AND(E18 = TRUE, E19 = ""), template_label_missing_value, IF(AND(E18 = TRUE, E19 <> "", COUNTIF(E19:E118, E19) = COUNTA(E19:E118), COUNTA(E19:E118) > 1), template_label_value_inconsistency, template_label_ok)))) | G19: =template_label_additional_rows_warning
E20: B3 – Energy and greenhouse gas emissions | F20: =IF($E$18 = FALSE, "", IF(E20 = "", "", IF(COUNTIF($E$19:$E$118, E20) > 1, template_label_value_inconsistency, template_label_ok)))
F21: =IF($E$18 = FALSE, "", IF(E21 = "", "", IF(COUNTIF($E$19:$E$118, E21) > 1, template_label_value_inconsistency, template_label_ok)))
F22: =IF($E$18 = FALSE, "", IF(E22 = "", "", IF(COUNTIF($E$19:$E$118, E22) > 1, template_label_value_inconsistency, template_label_ok)))
F23: =IF($E$18 = FALSE, "", IF(E23 = "", "", IF(COUNTIF($E$19:$E$118, E23) > 1, template_label_value_inconsistency, template_label_ok)))
F24: =IF($E$18 = FALSE, "", IF(E24 = "", "", IF(COUNTIF($E$19:$E$118, E24) > 1, template_label_value_inconsistency, template_label_ok)))
F25: =IF($E$18 = FALSE, "", IF(E25 = "", "", IF(COUNTIF($E$19:$E$118, E25) > 1, template_label_value_inconsistency, template_label_ok)))
F26: =IF($E$18 = FALSE, "", IF(E26 = "", "", IF(COUNTIF($E$19:$E$118, E26) > 1, template_label_value_inconsistency, template_label_ok)))
F27: =IF($E$18 = FALSE, "", IF(E27 = "", "", IF(COUNTIF($E$19:$E$118, E27) > 1, template_label_value_inconsistency, template_label_ok)))
C119: =template_label_link_to_previous_report_containing_disclosures_that_remain_unchanged | E119: www.Test.Report.com | F119: =IF(AND(E18 = FALSE, E119 = ""), "", IF(AND(E18 = TRUE, E119 = ""), template_label_missing_value, IF(AND(E18 = FALSE, E119 <> ""), "", IF(AND(E18 = TRUE, E119 <> "", OR(LEFT(E119, 7) = "http://", LEFT(E119, 8) = "https://", LEFT(E119, 4) = "www.")), template_label_ok, IF(E18 = TRUE, template_label_invalid_url, template_label_missing_value)))))
C121: =template_label_b1_basis_for_preparation & " " & template_label_from & " " & template_starting_date_display & " " & template_label_to & " " & template_ending_date_display & " " & template_label_always_to_be_reported
A122: 24(a) | B122: N/A | C122: =template_label_basis_for_preparation | E122: Option B (Basic Module and Comprehensive Module) | F122: =IF( 'Table of Contents & Validation'!D11=TRUE, IF(E122 = "", "", template_label_ok), IF(E122 = "", template_label_missing_value, template_label_ok) )
A123: 24(b) | B123: N/A | C123: =template_label_list_of_omitted_disclosures_deemed_to_be_classified_or_sensitive_information | E123: =_xlfn.XLOOKUP('Technical Sheet'!A28, 'Technical Sheet'!E106:E167, 'Table of Contents & Validation'!B10:B71, "") | F123: =template_label_bold_omitted_information
E124: =_xlfn.XLOOKUP('Technical Sheet'!A29, 'Technical Sheet'!E107:E168, 'Table of Contents & Validation'!B11:B72, "")
E125: =_xlfn.XLOOKUP('Technical Sheet'!A30, 'Technical Sheet'!E108:E169, 'Table of Contents & Validation'!B12:B73, "")
E126: =_xlfn.XLOOKUP('Technical Sheet'!A31, 'Technical Sheet'!E109:E170, 'Table of Contents & Validation'!B13:B74, "")
E127: =_xlfn.XLOOKUP('Technical Sheet'!A32, 'Technical Sheet'!E110:E171, 'Table of Contents & Validation'!B14:B75, "")
E128: =_xlfn.XLOOKUP('Technical Sheet'!A33, 'Technical Sheet'!E111:E172, 'Table of Contents & Validation'!B15:B76, "")
E129: =_xlfn.XLOOKUP('Technical Sheet'!A34, 'Technical Sheet'!E112:E173, 'Table of Contents & Validation'!B16:B77, "")
E130: =_xlfn.XLOOKUP('Technical Sheet'!A35, 'Technical Sheet'!E113:E174, 'Table of Contents & Validation'!B17:B78, "")
E131: =_xlfn.XLOOKUP('Technical Sheet'!A36, 'Technical Sheet'!E114:E175, 'Table of Contents & Validation'!B18:B79, "")
E132: =_xlfn.XLOOKUP('Technical Sheet'!A37, 'Technical Sheet'!E115:E176, 'Table of Contents & Validation'!B19:B80, "")
E133: =_xlfn.XLOOKUP('Technical Sheet'!A38, 'Technical Sheet'!E116:E177, 'Table of Contents & Validation'!B20:B81, "")
E134: =_xlfn.XLOOKUP('Technical Sheet'!A39, 'Technical Sheet'!E117:E178, 'Table of Contents & Validation'!B21:B82, "")
E135: =_xlfn.XLOOKUP('Technical Sheet'!A40, 'Technical Sheet'!E118:E179, 'Table of Contents & Validation'!B22:B83, "")
... E174: =_xlfn.XLOOKUP('Technical Sheet'!A79, 'Technical Sheet'!E157:E218, 'Table of Contents & Validation'!B61:B122, "")
C176: =template_label_b1_other_undertakings_general_information & " " & template_label_from & " " & template_starting_date_display & " " & template_label_to & " " & template_ending_date_display & " " & template_label_always_to_be_reported
A177: 24(c) | B177: N/A | C177: =template_label_basis_for_reporting | E177: Sustainability report prepared on a consolidated basis | F177: =IF( OR( 'Table of Contents & Validation'!D12=TRUE, 'Table of Contents & Validation'!D10=TRUE ), IF( AND( OR( E122="Option A (Basic Module only)", E122="Option B (Basic Module and Comprehensive Module)" ), E177="" ), "", IF( AND(E122<>"", E177<>""), template_label_ok, "" ) ), IF( AND( OR( E122="Option A (Basic Module only)", E122="Option B (Basic Module and Comprehensive Module)" ), E177="" ), template_label_missing_value, IF( AND(E122<>"", E177<>""), template_label_ok, "" ) ) )
A178: 24(e)(i) | B178: 4 | C178: =template_label_undertakings_legal_form | E178: private limited liability undertaking | F178: =IF(OR( 'Table of Contents & Validation'!D12=TRUE, 'Table of Contents & Validation'!D10=TRUE),IF(AND(OR(E122="Option A (Basic Module only)",E122="Option B (Basic Module and Comprehensive Module)"),E178=""), "", IF(E122="","",template_label_ok)), IF(AND(OR(E122="Option A (Basic Module only)",E122="Option B (Basic Module and Comprehensive Module)"),E178=""), template_label_missing_value, IF(E122="","",template_label_ok)) ) | G178: =template_label_other_warning
C179: =template_label_other_undertakings_legal_form_specification | F179: =IF( 'Table of Contents & Validation'!D11=TRUE, IF(AND(E178 = "other (please specify the legal form in the row below)", E179 <> ""), template_label_ok, IF(AND(E178 = "other (please specify the legal form in the row below)", E179 = ""), template_label_missing_value, IF(AND(E178 = "", E179 = ""), "", IF(AND(E178 <> "other (please specify the legal form in the row below)", E179 = ""), "", "")))), IF(AND(E178 = "other (please specify the legal form in the row below)", E179 <> ""), template_label_ok, IF(AND(E178 = "other (please specify the legal form in the row below)", E179 = ""), template_label_missing_value, IF(AND(E178 = "", E179 = ""), "", IF(AND(E178 <> "other (please specify the legal form in the row below)", E179 = ""), "", "")))) )
A180: 24(e)(ii) | B180: 5-6 | C180: =template_label_nace_sector_classification_code | E180: NACE G - 47.22 Retail sale of meat and meat products | F180: =IF(OR( 'Table of Contents & Validation'!D12=TRUE,'Table of Contents & Validation'!D10=TRUE),IF(OR(E122="Option A (Basic Module only)",E122="Option B (Basic Module and Comprehensive Module)"), IF(COUNTIF(enum_ListNACECategories,E180)>0,template_label_error, IF(E180="","", IF(COUNTIF($E$180:$E$279,E180)>1,template_label_value_inconsistency,template_label_ok) ) ), "" ), IF(OR(E122="Option A (Basic Module only)",E122="Option B (Basic Module and Comprehensive Module)"), IF(COUNTIF(enum_ListNACECategories,E180)>0,template_label_error, IF(E180="",template_label_missing_value, IF(COUNTIF($E$180:$E$279,E180)>1,template_label_value_inconsistency,template_label_ok) ) ), "" ) ) | G180: =template_label_NACE_warning
E181: NACE G - 47.21 Retail sale of fruit and vegetables | F181: =IF(COUNTIF(enum_ListNACECategories, E181) > 0, template_label_error, IF(E181 = "", "", IF(COUNTIF($E$180:$E$279, E181) > 1, template_label_value_inconsistency, template_label_ok)))
F182: =IF(COUNTIF(enum_ListNACECategories, E182) > 0, template_label_error, IF(E182 = "", "", IF(COUNTIF($E$180:$E$279, E182) > 1, template_label_value_inconsistency, template_label_ok)))
F183: =IF(COUNTIF(enum_ListNACECategories, E183) > 0, template_label_error, IF(E183 = "", "", IF(COUNTIF($E$180:$E$279, E183) > 1, template_label_value_inconsistency, template_label_ok)))
F184: =IF(COUNTIF(enum_ListNACECategories, E184) > 0, template_label_error, IF(E184 = "", "", IF(COUNTIF($E$180:$E$279, E184) > 1, template_label_value_inconsistency, template_label_ok)))
F185: =IF(COUNTIF(enum_ListNACECategories, E185) > 0, template_label_error, IF(E185 = "", "", IF(COUNTIF($E$180:$E$279, E185) > 1, template_label_value_inconsistency, template_label_ok)))
F186: =IF(COUNTIF(enum_ListNACECategories, E186) > 0, template_label_error, IF(E186 = "", "", IF(COUNTIF($E$180:$E$279, E186) > 1, template_label_value_inconsistency, template_label_ok)))
F187: =IF(COUNTIF(enum_ListNACECategories, E187) > 0, template_label_error, IF(E187 = "", "", IF(COUNTIF($E$180:$E$279, E187) > 1, template_label_value_inconsistency, template_label_ok)))
F188: =IF(COUNTIF(enum_ListNACECategories, E188) > 0, template_label_error, IF(E188 = "", "", IF(COUNTIF($E$180:$E$279, E188) > 1, template_label_value_inconsistency, template_label_ok)))
F189: =IF(COUNTIF(enum_ListNACECategories, E189) > 0, template_label_error, IF(E189 = "", "", IF(COUNTIF($E$180:$E$279, E189) > 1, template_label_value_inconsistency, template_label_ok)))
F190: =IF(COUNTIF(enum_ListNACECategories, E190) > 0, template_label_error, IF(E190 = "", "", IF(COUNTIF($E$180:$E$279, E190) > 1, template_label_value_inconsistency, template_label_ok)))
F191: =IF(COUNTIF(enum_ListNACECategories, E191) > 0, template_label_error, IF(E191 = "", "", IF(COUNTIF($E$180:$E$279, E191) > 1, template_label_value_inconsistency, template_label_ok)))
F192: =IF(COUNTIF(enum_ListNACECategories, E192) > 0, template_label_error, IF(E192 = "", "", IF(COUNTIF($E$180:$E$279, E192) > 1, template_label_value_inconsistency, template_label_ok)))
F193: =IF(COUNTIF(enum_ListNACECategories, E193) > 0, template_label_error, IF(E193 = "", "", IF(COUNTIF($E$180:$E$279, E193) > 1, template_label_value_inconsistency, template_label_ok)))
... F279: =IF(COUNTIF(enum_ListNACECategories, E279) > 0, template_label_error, IF(E279 = "", "", IF(COUNTIF($E$180:$E$279, E279) > 1, template_label_value_inconsistency, template_label_ok)))
A280: 24(e)(iii) | B280: N/A | C280: =template_label_size_of_balance_sheet_in & " " & template_currency | E280: 600000 | F280: =IF(OR( 'Table of Contents & Validation'!D12=TRUE,'Table of Contents & Validation'!D10=TRUE),IF(AND(OR(E122="Option A (Basic Module only)",E122="Option B (Basic Module and Comprehensive Module)"),E280=""), "", IF(E122="","",template_label_ok)), IF(AND(OR(E122="Option A (Basic Module only)",E122="Option B (Basic Module and Comprehensive Module)"),E280=""), template_label_missing_value, IF(E122="","",template_label_ok)) )
A281: 24(e)(iv) | B281: N/A | C281: =template_label_turnover_in & " " & template_currency | E281: 235000 | F281: =IF(OR( 'Table of Contents & Validation'!D12=TRUE,'Table of Contents & Validation'!D10=TRUE), IF(AND(OR(E122 = "Option A (Basic Module only)", E122 = "Option B (Basic Module and Comprehensive Module)"), E281 = ""), "", IF(E122 = "", "", template_label_ok)), IF(AND(OR(E122 = "Option A (Basic Module only)", E122 = "Option B (Basic Module and Comprehensive Module)"), E281 = ""), template_label_missing_value, IF(E122 = "", "", template_label_ok)) )
A282: 24(e)(v) | B282: 7-8 | C282: =+template_label_number_of_employees | E282: 151 | F282: =IF(OR( 'Table of Contents & Validation'!D12=TRUE, 'Table of Contents & Validation'!D10=TRUE), IF(AND(OR(E122 = "Option A (Basic Module only)", E122 = "Option B (Basic Module and Comprehensive Module)"), E282 = ""), "", IF(E122 = "", "", template_label_ok)), IF(AND(OR(E122 = "Option A (Basic Module only)", E122 = "Option B (Basic Module and Comprehensive Module)"), E282 = ""), template_label_missing_value, IF(E122 = "", "", template_label_ok)) )
A283: 24(e)(v) | B283: 7-8 | C283: =template_label_employee_counting_methodology_end_of_reporting_period_or_average_during_the_reporting_period | E283: As an average across the reporting period | F283: =IF(OR( 'Table of Contents & Validation'!D12=TRUE, 'Table of Contents & Validation'!D10=TRUE), IF(AND(OR(E122 = "Option A (Basic Module only)", E122 = "Option B (Basic Module and Comprehensive Module)"), E283 = ""), "", IF(E122 = "", "", template_label_ok)), IF(AND(OR(E122 = "Option A (Basic Module only)", E122 = "Option B (Basic Module and Comprehensive Module)"), E283 = ""), template_label_missing_value, IF(E122 = "", "", template_label_ok)) )
A284: 24(e)(v) | B284: 7-8 | C284: =template_label_employee_counting_methodology_headcount_or_fulltime_equivalent | E284: Full-time equivalent (FTE) | F284: =IF(OR( 'Table of Contents & Validation'!D12=TRUE, 'Table of Contents & Validation'!D10=TRUE), IF(AND(OR(E122 = "Option A (Basic Module only)", E122 = "Option B (Basic Module and Comprehensive Module)"), E284 = ""), "", IF(E122 = "", "", template_label_ok)), IF(AND(OR(E122 = "Option A (Basic Module only)", E122 = "Option B (Basic Module and Comprehensive Module)"), E284 = ""), template_label_missing_value, IF(E122 = "", "", template_label_ok)) )
A285: 24(e)(vi) | B285: 9-12 | C285: =template_label_country_of_primary_operations_and_location_of_significant_asset | E285: Italy | F285: =IF(OR( 'Table of Contents & Validation'!D12=TRUE, 'Table of Contents & Validation'!D10=TRUE), IF(AND(OR(E122 = "Option A (Basic Module only)", E122 = "Option B (Basic Module and Comprehensive Module)"), E285 = ""), "", IF(E122 = "", "", template_label_ok)), IF(AND(OR(E122 = "Option A (Basic Module only)", E122 = "Option B (Basic Module and Comprehensive Module)"), E285 = ""), template_label_missing_value, IF(E122 = "", "", template_label_ok)) )
C287: =template_label_b1_list_of_subsidiaries & " " & template_label_from & " " & template_starting_date_display & " " & template_label_to & " " & template_ending_date_display & " " & template_label_if_applicable
C288: 24(d)
C289: =template_label_id | D289: =template_label_name | E289: =template_label_registered_address
C290: 1 | D290: Company XYZ Subsidiary 1 | E290: Street XYZ, Country | F290: =IF(AND(BasisForReporting="Sustainability report prepared on a consolidated basis", D290<>"", E290=""), template_label_missing_value, IF(AND(BasisForReporting="Sustainability report prepared on a consolidated basis", D290<>"", E290<>""), template_label_ok, IF(AND(BasisForReporting="Sustainability report prepared on a consolidated basis", D290="", E290=""), template_label_missing_value, ""))) | G290: =template_label_additional_rows_warning
C291: 2 | F291: =IF(AND(D291<>"",E291=""), template_label_missing_value, IF(AND(D291<>"",E291<>""), template_label_ok, IF(AND(D291="",E291=""), "", template_label_missing_value)))
C292: 3 | F292: =IF(AND(D292<>"",E292=""), template_label_missing_value, IF(AND(D292<>"",E292<>""), template_label_ok, IF(AND(D292="",E292=""), "", template_label_missing_value)))
C293: 4 | F293: =IF(AND(D293<>"",E293=""), template_label_missing_value, IF(AND(D293<>"",E293<>""), template_label_ok, IF(AND(D293="",E293=""), "", template_label_missing_value)))
C294: 5 | F294: =IF(AND(D294<>"",E294=""), template_label_missing_value, IF(AND(D294<>"",E294<>""), template_label_ok, IF(AND(D294="",E294=""), "", template_label_missing_value)))
C295: 6 | F295: =IF(AND(D295<>"",E295=""), template_label_missing_value, IF(AND(D295<>"",E295<>""), template_label_ok, IF(AND(D295="",E295=""), "", template_label_missing_value)))
C296: 7 | F296: =IF(AND(D296<>"",E296=""), template_label_missing_value, IF(AND(D296<>"",E296<>""), template_label_ok, IF(AND(D296="",E296=""), "", template_label_missing_value)))
C297: 8 | F297: =IF(AND(D297<>"",E297=""), template_label_missing_value, IF(AND(D297<>"",E297<>""), template_label_ok, IF(AND(D297="",E297=""), "", template_label_missing_value)))
C298: 9 | F298: =IF(AND(D298<>"",E298=""), template_label_missing_value, IF(AND(D298<>"",E298<>""), template_label_ok, IF(AND(D298="",E298=""), "", template_label_missing_value)))
C299: 10 | F299: =IF(AND(D299<>"",E299=""), template_label_missing_value, IF(AND(D299<>"",E299<>""), template_label_ok, IF(AND(D299="",E299=""), "", template_label_missing_value)))
C300: 11 | F300: =IF(AND(D300<>"",E300=""), template_label_missing_value, IF(AND(D300<>"",E300<>""), template_label_ok, IF(AND(D300="",E300=""), "", template_label_missing_value)))
C301: 12 | F301: =IF(AND(D301<>"",E301=""), template_label_missing_value, IF(AND(D301<>"",E301<>""), template_label_ok, IF(AND(D301="",E301=""), "", template_label_missing_value)))
C302: 13 | F302: =IF(AND(D302<>"",E302=""), template_label_missing_value, IF(AND(D302<>"",E302<>""), template_label_ok, IF(AND(D302="",E302=""), "", template_label_missing_value)))
... C314: 25 | F314: =IF(AND(D314<>"",E314=""), template_label_missing_value, IF(AND(D314<>"",E314<>""), template_label_ok, IF(AND(D314="",E314=""), "", template_label_missing_value)))
F315: =IF(AND(D315<>"",E315=""), template_label_missing_value, IF(AND(D315<>"",E315<>""), template_label_ok, IF(AND(D315="",E315=""), "", template_label_missing_value)))
F316: =IF(AND(D316<>"",E316=""), template_label_missing_value, IF(AND(D316<>"",E316<>""), template_label_ok, IF(AND(D316="",E316=""), "", template_label_missing_value)))
F317: =IF(AND(D317<>"",E317=""), template_label_missing_value, IF(AND(D317<>"",E317<>""), template_label_ok, IF(AND(D317="",E317=""), "", template_label_missing_value)))
F318: =IF(AND(D318<>"",E318=""), template_label_missing_value, IF(AND(D318<>"",E318<>""), template_label_ok, IF(AND(D318="",E318=""), "", template_label_missing_value)))
F319: =IF(AND(D319<>"",E319=""), template_label_missing_value, IF(AND(D319<>"",E319<>""), template_label_ok, IF(AND(D319="",E319=""), "", template_label_missing_value)))
F320: =IF(AND(D320<>"",E320=""), template_label_missing_value, IF(AND(D320<>"",E320<>""), template_label_ok, IF(AND(D320="",E320=""), "", template_label_missing_value)))
F321: =IF(AND(D321<>"",E321=""), template_label_missing_value, IF(AND(D321<>"",E321<>""), template_label_ok, IF(AND(D321="",E321=""), "", template_label_missing_value)))
F322: =IF(AND(D322<>"",E322=""), template_label_missing_value, IF(AND(D322<>"",E322<>""), template_label_ok, IF(AND(D322="",E322=""), "", template_label_missing_value)))
F323: =IF(AND(D323<>"",E323=""), template_label_missing_value, IF(AND(D323<>"",E323<>""), template_label_ok, IF(AND(D323="",E323=""), "", template_label_missing_value)))
F324: =IF(AND(D324<>"",E324=""), template_label_missing_value, IF(AND(D324<>"",E324<>""), template_label_ok, IF(AND(D324="",E324=""), "", template_label_missing_value)))
F325: =IF(AND(D325<>"",E325=""), template_label_missing_value, IF(AND(D325<>"",E325<>""), template_label_ok, IF(AND(D325="",E325=""), "", template_label_missing_value)))
F326: =IF(AND(D326<>"",E326=""), template_label_missing_value, IF(AND(D326<>"",E326<>""), template_label_ok, IF(AND(D326="",E326=""), "", template_label_missing_value)))
... F389: =IF(AND(D389<>"",E389=""), template_label_missing_value, IF(AND(D389<>"",E389<>""), template_label_ok, IF(AND(D389="",E389=""), "", template_label_missing_value)))
C391: =template_label_b1_disclosure_of_sustainability_related_certification_or_label & " " & template_label_from & " " & template_starting_date_display & " " & template_label_to & " " & template_ending_date_display & " " & template_label_if_applicable
C392: 25
C393: 13
...

Sheet Environmental Disclosures
A1: =template_label_paragraph_reference | B1: =template_label_paragraph_guidance_reference
C2: =template_label_b3_total_energy_consumption&" "&template_label_from&" "&template_starting_date_display&" "&template_label_to&" "&template_ending_date_display&" "&template_label_always_to_be_reported
C3: 29
C4: 18-25
C5: =template_label_total_energy_consumption | G5: 250 | L5: =IF(OR( 'Table of Contents & Validation'!D21=TRUE, 'Table of Contents & Validation'!D20=TRUE), IF(AND(OR('General Information'!E122="Option A (Basic Module only)", 'General Information'!E122="Option B (Basic Module and Comprehensive Module)"), G5=""), "", IF('General Information'!E122="", "", template_label_ok)), IF(AND(OR('General Information'!E122="Option A (Basic Module only)", 'General Information'!E122="Option B (Basic Module and Comprehensive Module)"), G5=""), template_label_missing_value, IF('General Information'!E122="", "", template_label_ok)) )
C7: =template_label_b3_breakdown_of_energy_consumption&" "&template_label_from&" "&template_starting_date_display&" "&template_label_to&" "&template_ending_date_display&" "&template_label_if_applicable
C8: 29
C9: 18-25
C10: =template_label_has_the_undertaking_obtained_the_necessary_information_to_provide_an_energy_consumption_breakdown | G10: TRUE
G11: =template_label_renewable | J11: =template_label_non_renewable | K11: =template_label_total_renewable_and_nonrenewable
C12: =template_label_electricity | G12: 10 | J12: 100 | L12: {=IF(G10=TRUE, IF(SUMPRODUCT(--(G12:J14<>"-"), --(G12:J14<>""))>0, IF(SUM(G12:J14) > TotalEnergyConsumption, template_label_value_inconsistency, template_label_ok), template_label_missing_value), "")}
C13: =template_label_selfgenerated_electricity | G13: 23 | J13: 20
C14: =template_label_fuels | M14: =template_label_energy_consumption_warning
C16: =template_label_b3_estimated_greenhouse_gas_emissions& " "&template_label_always_to_be_reported | G16: =template_label_c3_ghg_reduction_targets&" "&template_label_if_applicable
C17: 30 | G17: 54(b) | J17: 54(a) | K17: 54(d)
C18: N/A | D18: 26-45 | G18: 152-158 | J18: 152-158 | K18: 152-158
G19: =template_label_has_the_undertaking_has_established_ghg_emission_reduction_targets | J19: TRUE
D20: =template_label_current_reporting_period | G20: =template_label_base_year | J20: =template_label_target_year | K20: =template_label_percentage_reduction_from_base_year
A21: =template_label_GHG_calculator | C21: =template_label_year_date | D21: =IF('General Information'!$D$9="", "-", 'General Information'!$D$9) & " - " & IF('General Information'!$D$13="", "-", 'General Information'!$D$13) | G21: 2020 | J21: 2030 | L21: =IF(AND(J19=TRUE, G21<>"", J21<>""), template_label_ok, IF(AND(J19=TRUE, G21="", J21=""), template_label_missing_value, IF(AND(J19=FALSE, G21="", J21=""), "", IF(AND(J19=TRUE, OR(G21="", J21="")), template_label_missing_value, ""))))
C22: =template_label_gross_scope_1_ghg_emissions | D22: 100 | G22: 150 | J22: 75 | K22: =IF(AND(G22="", J22=""), "-", IFERROR(-(1 - (J22 / G22)), "-")) | L22: =IF(OR( 'Table of Contents & Validation'!D23=TRUE,'Table of Contents & Validation'!D20=TRUE), IF(AND(OR(BasisForPreparation="Option A (Basic Module Only)", BasisForPreparation="Option B (Basic Module and Comprehensive Module)"), D22="", J19=FALSE), "", IF(AND(OR(BasisForPreparation="Option A (Basic Module Only)", BasisForPreparation="Option B (Basic Module and Comprehensive Module)"), D22<>"", G22<>"", J22<>"", J19=TRUE), template_label_ok, IF(AND(BasisForPreparation="Option A (Basic Module Only)", D22<>"", OR(G22="", J22=""), J19=FALSE), template_label_ok, IF(AND(BasisForPreparation="Option A (Basic Module Only)", D22<>"", OR(G22="", J22=""), J19=TRUE), template_label_missing_value, IF(AND(BasisForPreparation="Option B (Basic Module and Comprehensive Module)", D22<>"", OR(G22="", J22=""), J19=TRUE), template_label_missing_value, IF(AND(BasisForPreparation="Option B (Basic Module and Comprehensive Module)", D22="", OR(G22="", J22=""), J19=TRUE), template_label_missing_value, IF(AND(BasisForPreparation="Option A (Basic Module Only)", D22<>"", G22="", J22="", J19=FALSE), template_label_ok, IF(AND(BasisForPreparation="Option B (Basic Module and Comprehensive Module)", D22<>"", G22="", J22="", J19=FALSE), template_label_ok, IF(OR(BasisForPreparation="", D22="", G22="", J22="", J19=FALSE), "", template_label_missing_value))))))))), IF(AND(OR(BasisForPreparation="Option A (Basic Module Only)", BasisForPreparation="Option B (Basic Module and Comprehensive Module)"), D22="", J19=FALSE), template_label_missing_value, IF(AND(OR(BasisForPreparation="Option A (Basic Module Only)", BasisForPreparation="Option B (Basic Module and Comprehensive Module)"), D22<>"", G22<>"", J22<>"", J19=TRUE), template_label_ok, IF(AND(BasisForPreparation="Option A (Basic Module Only)", D22<>"", OR(G22="", J22=""), J19=FALSE), template_label_ok, IF(AND(BasisForPreparation="Option A (Basic Module Only)", D22<>"", OR(G22="", J22=""), J19=TRUE), template_label_missing_value, IF(AND(BasisForPreparation="Option B (Basic Module and Comprehensive Module)", D22<>"", OR(G22="", J22=""), J19=TRUE), template_label_missing_value, IF(AND(BasisForPreparation="Option B (Basic Module and Comprehensive Module)", D22="", OR(G22="", J22=""), J19=TRUE), template_label_missing_value, IF(AND(BasisForPreparation="Option A (Basic Module Only)", D22<>"", G22="", J22="", J19=FALSE), template_label_ok, IF(AND(BasisForPreparation="Option B (Basic Module and Comprehensive Module)", D22<>"", G22="", J22="", J19=FALSE), template_label_ok, IF(OR(BasisForPreparation="", D22="", G22="", J22="", J19=FALSE), "", template_label_missing_value))))))))) )
C23: =template_label_gross_scope_2_location_based_ghg_emissions | D23: 50 | G23: 75 | J23: 15 | K23: =IF(AND(G23="", J23=""), "-", IFERROR(-(1 - (J23 / G23)), "-")) | L23: =IF(OR( 'Table of Contents & Validation'!D23=TRUE,'Table of Contents & Validation'!D20=TRUE), IF(AND(OR(BasisForPreparation="Option A (Basic Module Only)", BasisForPreparation="Option B (Basic Module and Comprehensive Module)"), D23="", J19=FALSE), "", IF(AND(OR(BasisForPreparation="Option A (Basic Module Only)", BasisForPreparation="Option B (Basic Module and Comprehensive Module)"), D23<>"", G23<>"", J23<>"", J19=TRUE), template_label_ok, IF(AND(BasisForPreparation="Option A (Basic Module Only)", D23<>"", OR(G23="", J23=""), J19=FALSE), template_label_ok, IF(AND(BasisForPreparation="Option A (Basic Module Only)", D23<>"", OR(G23="", J23=""), J19=TRUE), template_label_missing_value, IF(AND(BasisForPreparation="Option B (Basic Module and Comprehensive Module)", D23<>"", OR(G23="", J23=""), J19=TRUE), template_label_missing_value, IF(AND(BasisForPreparation="Option B (Basic Module and Comprehensive Module)", D23="", OR(G23="", J23=""), J19=TRUE), template_label_missing_value, IF(AND(BasisForPreparation="Option A (Basic Module Only)", D23<>"", G23="", J23="", J19=FALSE), template_label_ok, IF(AND(BasisForPreparation="Option B (Basic Module and Comprehensive Module)", D23<>"", G23="", J23="", J19=FALSE), template_label_ok, IF(OR(BasisForPreparation="", D23="", G23="", J23="", J19=FALSE), "", template_label_missing_value))))))))), IF(AND(OR(BasisForPreparation="Option A (Basic Module Only)", BasisForPreparation="Option B (Basic Module and Comprehensive Module)"), D23="", J19=FALSE), template_label_missing_value, IF(AND(OR(BasisForPreparation="Option A (Basic Module Only)", BasisForPreparation="Option B (Basic Module and Comprehensive Module)"), D23<>"", G23<>"", J23<>"", J19=TRUE), template_label_ok, IF(AND(BasisForPreparation="Option A (Basic Module Only)", D23<>"", OR(G23="", J23=""), J19=FALSE), template_label_ok, IF(AND(BasisForPreparation="Option A (Basic Module Only)", D23<>"", OR(G23="", J23=""), J19=TRUE), template_label_missing_value, IF(AND(BasisForPreparation="Option B (Basic Module and Comprehensive Module)", D23<>"", OR(G23="", J23=""), J19=TRUE), template_label_missing_value, IF(AND(BasisForPreparation="Option B (Basic Module and Comprehensive Module)", D23="", OR(G23="", J23=""), J19=TRUE), template_label_missing_value, IF(AND(BasisForPreparation="Option A (Basic Module Only)", D23<>"", G23="", J23="", J19=FALSE), template_label_ok, IF(AND(BasisForPreparation="Option B (Basic Module and Comprehensive Module)", D23<>"", G23="", J23="", J19=FALSE), template_label_ok, IF(OR(BasisForPreparation="", D23="", G23="", J23="", J19=FALSE), "", template_label_missing_value))))))))) )
C24: =template_label_gross_scope_2_market_based_ghg_emissions & " - " & template_label_may_not_headline | K24: =IF(AND(G24="", J24=""), "-", IFERROR(-(1 - (J24 / G24)), "-")) | L24: =IF(D24<>"", IF(AND(G24="", J24=""), template_label_ok, IF(AND(G24<>"", J24=""), template_label_missing_value, template_label_ok) ), "")
C25: =template_label_total_scope_1_and_scope_2_ghg_emissions_location_based | K25: =IF(AND(G25="", J25=""), "-", IFERROR(-(1 - (J25 / G25)), "-"))
C26: =template_label_total_scope_1_and_scope_2_ghg_emissions_market_based & " - " & template_label_may_not_headline | K26: =IF(AND(G26="", J26=""), "-", IFERROR(-(1 - (J26 / G26)), "-"))
C27: 50-53 | G27: 54
C28: N/A | D28: 150-151 | G28: N/A | J28: N/A
C29: =template_label_is_the_undertaking_disclosing_entity_specific_information_on_scope_3_emissions | G29: TRUE
C30: =template_label_1_purchased_goods_and_services | D30: 200 | G30: 300 | J30: 100 | K30: =IF(OR(G30="", J30=""), "-", IFERROR(-(1 - (J30 / G30)), "-")) | L30: {=IF( OR( SUMPRODUCT((G30:G44<>"")*(J30:J44="")) > 0, SUMPRODUCT((J30:J44<>"")*(G30:G44="")) > 0 ), template_label_missing_value, IF( AND(G29=TRUE, COUNTA(D30:F44)=0), template_label_missing_value, IF(G29=FALSE, "", template_label_ok) ) )} | M30: =template_label_scope_3_categories_warning
C31: =template_label_2_capital_goods | K31: =IF(OR(G31="", J31=""), "-", IFERROR(-(1 - (J31 / G31)), "-"))
C32: =template_label_3_fuel__and_energy_related_activities | K32: =IF(OR(G32="", J32=""), "-", IFERROR(-(1 - (J32 / G32)), "-"))
C33: =template_label_4_upstream_transportation_and_distribution | K33: =IF(OR(G33="", J33=""), "-", IFERROR(-(1 - (J33 / G33)), "-"))
C34: =template_label_5_waste_generated_in_operations | K34: =IF(OR(G34="", J34=""), "-", IFERROR(-(1 - (J34 / G34)), "-"))
C35: =template_label_6_business_travel | K35: =IF(OR(G35="", J35=""), "-", IFERROR(-(1 - (J35 / G35)), "-"))
C36: =template_label_7_employee_commuting | K36: =IF(OR(G36="", J36=""), "-", IFERROR(-(1 - (J36 / G36)), "-"))
C37: =template_label_8_upstream_leased_assets | K37: =IF(OR(G37="", J37=""), "-", IFERROR(-(1 - (J37 / G37)), "-"))
C38: =template_label_9_downstream_transportation_and_distribution | D38: 500 | G38: 400 | J38: 200 | K38: =IF(OR(G38="", J38=""), "-", IFERROR(-(1 - (J38 / G38)), "-"))
C39: =template_label_10_processing_of_sold_products | K39: =IF(OR(G39="", J39=""), "-", IFERROR(-(1 - (J39 / G39)), "-"))
C40: =template_label_11_use_of_sold_products | K40: =IF(OR(G40="", J40=""), "-", IFERROR(-(1 - (J40 / G40)), "-"))
C41: =template_label_12_end_of_life_treatment_of_sold_products | K41: =IF(OR(G41="", J41=""), "-", IFERROR(-(1 - (J41 / G41)), "-"))
C42: =template_label_13_downstream_leased_assets | K42: =IF(OR(G42="", J42=""), "-", IFERROR(-(1 - (J42 / G42)), "-"))
C43: =template_label_14_franchises | K43: =IF(OR(G43="", J43=""), "-", IFERROR(-(1 - (J43 / G43)), "-"))
C44: =template_label_15_investments | K44: =IF(OR(G44="", J44=""), "-", IFERROR(-(1 - (J44 / G44)), "-"))
C45: =template_label_total_scope_3_ghg_emissions | K45: =IF(AND(G45="", J45=""), "-", IFERROR(-(1 - (J45 / G45)), "-"))
C46: =template_label_total_scope_1_scope_2_and_scope_3_ghg_emissions_location_based | K46: =IF(AND(G46="", J46=""), "-", IFERROR(-(1 - (J46 / G46)), "-"))
C47: =template_label_total_scope_1_scope_2_and_scope_3_ghg_emissions_market_based & " - " & template_label_may_not_headline | K47: =IF(AND(G47="", J47=""), "-", IFERROR(-(1 - (J47 / G47)), "-"))
C49: =template_label_c3_disclosure_of_list_of_main_actions_the_entity_seeks_in_order_to_achieve_its_targets&" "&template_label_from&" "&template_starting_date_display&" "&template_label_to&" "&template_ending_date_display&" "&template_label_if_applicable
C50: 54(e)
C51: 159
C52: Lorem ipsum dolor sit amet, consectetur adipiscing elit, sed do eiusmod tempor incididunt ut labore et dolore magna aliqua. Ut enim ad minim veniam, quis nostrud exercitation ullamco laboris nisi ut aliquip ex ea commodo consequat. | L52: =IF(AND(J19=TRUE, C52<>""), template_label_ok, IF(AND(J19=TRUE, C52=""), template_label_missing_value, ""))
A55: =template_label_supporting_guidance_c3 | C55: =template_label_c3_transition_plan_for_undertakings_operating_in_high_climate_impact_sectors&" "&template_label_from&" "&template_starting_date_display&" "&template_label_to&" "&template_ending_date_display&" "& template_label_if_applicable
A56: 55 | B56: 160-163 | C56: =template_label_is_the_undertaking_operating_in_high_impact_sectors | D56: =OR( ISNUMBER(MATCH('General Information'!E180, 'Enumeration Lists'!A3:A677, 0)), ISNUMBER(MATCH('General Information'!E181, 'Enumeration Lists'!A3:A677, 0)), ISNUMBER(MATCH('General Information'!E182, 'Enumeration Lists'!A3:A677, 0)), ISNUMBER(MATCH('General Information'!E183, 'Enumeration Lists'!A3:A677, 0)), ISNUMBER(MATCH('General Information'!E184, 'Enumeration Lists'!A3:A677, 0)), ISNUMBER(MATCH('General Information'!E180, 'Enumeration Lists'!A782:A791, 0)), ISNUMBER(MATCH('General Information'!E181, 'Enumeration Lists'!A782:A791, 0)), ISNUMBER(MATCH('General Information'!E182, 'Enumeration Lists'!A782:A791, 0)), ISNUMBER(MATCH('General Information'!E183, 'Enumeration Lists'!A782:A791, 0)), ISNUMBER(MATCH('General Information'!E184, 'Enumeration Lists'!A782:A791, 0)) )
A57: 55 | B57: 160-163 | C57: =template_label_status_of_implementation_of_a_transition_plan_in_relation_to_climate_change_mitigation | D57: Adoption of a transition plan is planned in the future | L57: =IF(AND(OR(D57="A transition plan has already been adopted", D57="Adoption of a transition plan is planned in the future"), D56=TRUE), template_label_ok, IF(AND(BasisForPreparation="Option B (Basic Module and Comprehensive Module)", D57="", D56=TRUE), template_label_missing_value, "" ) )
A58: 55 | B58: 160-163 | C58: =template_label_description_of_a_transition_plan_for_climate_change_mitigation & " - " & template_label_may_not_headline | L58: =IF(AND(D57="A transition plan has already been adopted", DescriptionOfATransitionPlanForClimateChangeMitigationIncludingAnExplanationOfHowItIsContributingToReduceGhgEmissions<>""), template_label_ok, "")
A59: 56 | B59: 160-163 | C59: =template_label_date_of_foreseen_adoption_of_transition_plan_for_undertaking_not_having_adopted_transition_plan_yet | D59: =template_label_year | I59: 2028 | L59: =IF(AND(D57="A transition plan has already been adopted", OR(I59="", I60="", I61="")), "", IF(AND(D57="Adoption of a transition plan is planned in the future", OR(I59="", I60="", I61="")), template_label_missing_value, IF(AND(D57="", OR(I59="", I60="", I61="")), "", IF(OR( AND(I60=2, I61>29), AND(I60=2, I61=29, NOT(AND(MOD(I59,4)=0, OR(MOD(I59,100)<>0, MOD(I59,400)=0)))), AND(OR(I60=4, I60=6, I60=9, I60=11), I61=31) ), template_label_error, template_label_ok ) ) ) )
D60: =template_label_month | I60: 1
D61: =template_label_day | I61: 1
C64: =template_label_b3_greenhouse_gas_emission_intensity_per_turnover&" "&template_label_from&" "&template_starting_date_display&" "&template_label_to&" "&template_ending_date_display&" "&template_label_always_to_be_reported
C65: 31
C66: =template_label_scope_1_and_scope_2_ghg_emissions_intensity_location_based
C67: =template_label_scope_1_and_scope_2_ghg_emissions_intensity_market_based & " - " & template_label_may_not_headline
C68: =template_label_total_scope_1_scope_2_and_scope_3_ghg_emissions_intensity_location_based
C69: =template_label_total_scope_1_scope_2_and_scope_3_ghg_emissions_intensity_market_based & " - " & template_label_may_not_headline
C71: =template_label_b4_pollution_of_air_water_and_soil&" "&template_label_from&" "&template_starting_date_display&" "&template_label_to&" "&template_ending_date_display&" "&template_label_if_applicable
C72: 32
C73: 46-69
C74: =template_label_required_by_law_or_other_national_regulations_to_report_to_competent_authorities_its_emissions_of_pollutants | G74: TRUE
C75: =template_label_is_this_disclosure_already_publicly_available | G75: FALSE | L75: {=IF(AND(G75=TRUE, D80:K179=""), template_label_ok, IF(AND(OR(D80:K179<>""), G75=TRUE), template_label_value_inconsistency, "" ) )}
C76: =template_label_please_provide_the_relevant_url_link_or_hyperlink_of_where_this_information_is_reported | L76: =IF(G75=TRUE, IF(G76="", template_label_missing_value, IF(OR(LEFT(G76,7)="http://", LEFT(G76,8)="https://", LEFT(G76,4)="www."), template_label_ok, template_label_invalid_url ) ), "")
C77: =template_label_please_select_the_unit_used_for_reporting_the_amount
C78: metric tonnes (t) | L78: {=IF(AND(OR(D80:F179<>"", G80:I179<>"", J80:J179<>"", G296<>"", K80:K179<>""), C78<>"", G74=TRUE, G75=FALSE), template_label_ok, IF(AND(OR(D80:F179<>"", G80:I179<>"", J80:J179<>"", G296<>"", K80:K179<>""), C78<>"", G74=TRUE, G75=TRUE), template_label_value_inconsistency, IF(AND(OR(D80:D179="", G80:G179="", J80:J179="", K80:K179=""), C78<>"", G74=TRUE, G75=FALSE), template_label_ok, IF(AND(OR(D80:D179="", G80:G179="", J80:J179="", K80:K179=""), C78<>"", G74=TRUE, G75=TRUE), template_label_value_inconsistency, IF(AND(C78="", G74=TRUE, G75=FALSE), template_label_missing_value, "" ) ) ) ) )}
C79: =template_label_row_id | D79: =template_label_pollutant | G79: =template_label_emission_to_air | J79: =template_label_emission_to_water | K79: =template_label_emission_to_soil
C80: 1 | D80: Alachlor | G80: 567 | L80: =IF(AND($G$74=TRUE,$G$75=TRUE,OR(D80<>"",G80<>"",J80<>"",K80<>"")), template_label_value_inconsistency, IF($G$74<>TRUE,"", IF(AND(D80="",G80="",J80="",K80="",G74=TRUE,G75=FALSE),template_label_missing_value, IF(AND(D80="",G80="",J80="",K80="",G74=TRUE,G75=TRUE),"", IF(AND(D80="",G80="",J80="",K80="",G74=FALSE),"", IF(AND(D80<>"",G80="",J80="",K80=""),template_label_missing_value, IF(AND(D80<>"",OR(G80<>"",J80<>"",K80<>"")), IF(COUNTIF($D$80:$D$179,D80)>1,template_label_value_inconsistency,template_label_ok), template_label_missing_value)))))))
C81: 2 | D81: Anthracene | K81: 67 | L81: =IF(AND($G$74=TRUE,$G$75=TRUE,OR(D81<>"",G81<>"",J81<>"",K81<>"")), template_label_value_inconsistency, IF($G$74<>TRUE, "", IF(AND(D81="", G81="", J81="", K81=""), "", IF(AND(D81<>"", G81="", J81="", K81=""), template_label_missing_value, IF(AND(D81<>"", OR(G81<>"", J81<>"", K81<>"")), IF(COUNTIF($D$80:$D$179, D81)>1, template_label_value_inconsistency, template_label_ok), template_label_missing_value)))))
C82: 3 | D82: Carbon dioxide (CO2) | J82: 567 | L82: =IF(AND($G$74=TRUE,$G$75=TRUE,OR(D82<>"",G82<>"",J82<>"",K82<>"")), template_label_value_inconsistency, IF($G$74<>TRUE, "", IF(AND(D82="", G82="", J82="", K82=""), "", IF(AND(D82<>"", G82="", J82="", K82=""), template_label_missing_value, IF(AND(D82<>"", OR(G82<>"", J82<>"", K82<>"")), IF(COUNTIF($D$80:$D$179, D82)>1, template_label_value_inconsistency, template_label_ok), template_label_missing_value))))) | M82: =template_label_additional_rows_warning
C83: 4 | L83: =IF(AND($G$74=TRUE,$G$75=TRUE,OR(D83<>"",G83<>"",J83<>"",K83<>"")), template_label_value_inconsistency, IF($G$74<>TRUE, "", IF(AND(D83="", G83="", J83="", K83=""), "", IF(AND(D83<>"", G83="", J83="", K83=""), template_label_missing_value, IF(AND(D83<>"", OR(G83<>"", J83<>"", K83<>"")), IF(COUNTIF($D$80:$D$179, D83)>1, template_label_value_inconsistency, template_label_ok), template_label_missing_value)))))
C84: 5 | L84: =IF(AND($G$74=TRUE,$G$75=TRUE,OR(D84<>"",G84<>"",J84<>"",K84<>"")), template_label_value_inconsistency, IF($G$74<>TRUE, "", IF(AND(D84="", G84="", J84="", K84=""), "", IF(AND(D84<>"", G84="", J84="", K84=""), template_label_missing_value, IF(AND(D84<>"", OR(G84<>"", J84<>"", K84<>"")), IF(COUNTIF($D$80:$D$179, D84)>1, template_label_value_inconsistency, template_label_ok), template_label_missing_value)))))
C85: 6 | L85: =IF(AND($G$74=TRUE,$G$75=TRUE,OR(D85<>"",G85<>"",J85<>"",K85<>"")), template_label_value_inconsistency, IF($G$74<>TRUE, "", IF(AND(D85="", G85="", J85="", K85=""), "", IF(AND(D85<>"", G85="", J85="", K85=""), template_label_missing_value, IF(AND(D85<>"", OR(G85<>"", J85<>"", K85<>"")), IF(COUNTIF($D$80:$D$179, D85)>1, template_label_value_inconsistency, template_label_ok), template_label_missing_value)))))
C86: 7 | L86: =IF(AND($G$74=TRUE,$G$75=TRUE,OR(D86<>"",G86<>"",J86<>"",K86<>"")), template_label_value_inconsistency, IF($G$74<>TRUE, "", IF(AND(D86="", G86="", J86="", K86=""), "", IF(AND(D86<>"", G86="", J86="", K86=""), template_label_missing_value, IF(AND(D86<>"", OR(G86<>"", J86<>"", K86<>"")), IF(COUNTIF($D$80:$D$179, D86)>1, template_label_value_inconsistency, template_label_ok), template_label_missing_value)))))
C87: 8 | L87: =IF(AND($G$74=TRUE,$G$75=TRUE,OR(D87<>"",G87<>"",J87<>"",K87<>"")), template_label_value_inconsistency, IF($G$74<>TRUE, "", IF(AND(D87="", G87="", J87="", K87=""), "", IF(AND(D87<>"", G87="", J87="", K87=""), template_label_missing_value, IF(AND(D87<>"", OR(G87<>"", J87<>"", K87<>"")), IF(COUNTIF($D$80:$D$179, D87)>1, template_label_value_inconsistency, template_label_ok), template_label_missing_value)))))
C88: 9 | L88: =IF(AND($G$74=TRUE,$G$75=TRUE,OR(D88<>"",G88<>"",J88<>"",K88<>"")), template_label_value_inconsistency, IF($G$74<>TRUE, "", IF(AND(D88="", G88="", J88="", K88=""), "", IF(AND(D88<>"", G88="", J88="", K88=""), template_label_missing_value, IF(AND(D88<>"", OR(G88<>"", J88<>"", K88<>"")), IF(COUNTIF($D$80:$D$179, D88)>1, template_label_value_inconsistency, template_label_ok), template_label_missing_value)))))
C89: 10 | L89: =IF(AND($G$74=TRUE,$G$75=TRUE,OR(D89<>"",G89<>"",J89<>"",K89<>"")), template_label_value_inconsistency, IF($G$74<>TRUE, "", IF(AND(D89="", G89="", J89="", K89=""), "", IF(AND(D89<>"", G89="", J89="", K89=""), template_label_missing_value, IF(AND(D89<>"", OR(G89<>"", J89<>"", K89<>"")), IF(COUNTIF($D$80:$D$179, D89)>1, template_label_value_inconsistency, template_label_ok), template_label_missing_value)))))
C90: 11 | L90: =IF(AND($G$74=TRUE,$G$75=TRUE,OR(D90<>"",G90<>"",J90<>"",K90<>"")), template_label_value_inconsistency, IF($G$74<>TRUE, "", IF(AND(D90="", G90="", J90="", K90=""), "", IF(AND(D90<>"", G90="", J90="", K90=""), template_label_missing_value, IF(AND(D90<>"", OR(G90<>"", J90<>"", K90<>"")), IF(COUNTIF($D$80:$D$179, D90)>1, template_label_value_inconsistency, template_label_ok), template_label_missing_value)))))
C91: 12 | L91: =IF(AND($G$74=TRUE,$G$75=TRUE,OR(D91<>"",G91<>"",J91<>"",K91<>"")), template_label_value_inconsistency, IF($G$74<>TRUE, "", IF(AND(D91="", G91="", J91="", K91=""), "", IF(AND(D91<>"", G91="", J91="", K91=""), template_label_missing_value, IF(AND(D91<>"", OR(G91<>"", J91<>"", K91<>"")), IF(COUNTIF($D$80:$D$179, D91)>1, template_label_value_inconsistency, template_label_ok), template_label_missing_value)))))
C92: 13 | L92: =IF(AND($G$74=TRUE,$G$75=TRUE,OR(D92<>"",G92<>"",J92<>"",K92<>"")), template_label_value_inconsistency, IF($G$74<>TRUE, "", IF(AND(D92="", G92="", J92="", K92=""), "", IF(AND(D92<>"", G92="", J92="", K92=""), template_label_missing_value, IF(AND(D92<>"", OR(G92<>"", J92<>"", K92<>"")), IF(COUNTIF($D$80:$D$179, D92)>1, template_label_value_inconsistency, template_label_ok), template_label_missing_value)))))
C93: 14 | L93: =IF(AND($G$74=TRUE,$G$75=TRUE,OR(D93<>"",G93<>"",J93<>"",K93<>"")), template_label_value_inconsistency, IF($G$74<>TRUE, "", IF(AND(D93="", G93="", J93="", K93=""), "", IF(AND(D93<>"", G93="", J93="", K93=""), template_label_missing_value, IF(AND(D93<>"", OR(G93<>"", J93<>"", K93<>"")), IF(COUNTIF($D$80:$D$179, D93)>1, template_label_value_inconsistency, template_label_ok), template_label_missing_value)))))
C94: 15 | L94: =IF(AND($G$74=TRUE,$G$75=TRUE,OR(D94<>"",G94<>"",J94<>"",K94<>"")), template_label_value_inconsistency, IF($G$74<>TRUE, "", IF(AND(D94="", G94="", J94="", K94=""), "", IF(AND(D94<>"", G94="", J94="", K94=""), template_label_missing_value, IF(AND(D94<>"", OR(G94<>"", J94<>"", K94<>"")), IF(COUNTIF($D$80:$D$179, D94)>1, template_label_value_inconsistency, template_label_ok), template_label_missing_value)))))
... C179: 100 | L179: =IF(AND($G$74=TRUE,$G$75=TRUE,OR(D179<>"",G179<>"",J179<>"",K179<>"")), template_label_value_inconsistency, IF($G$74<>TRUE, "", IF(AND(D179="", G179="", J179="", K179=""), "", IF(AND(D179<>"", G179="", J179="", K179=""), template_label_missing_value, IF(AND(D179<>"", OR(G179<>"", J179<>"", K179<>"")), IF(COUNTIF($D$80:$D$179, D179)>1, template_label_value_inconsistency, template_label_ok), template_label_missing_value)))))
C181: =template_label_b5_sites_in_biodiversity_sensitive_areas&" "&template_label_from&" "&template_starting_date_display&" "&template_label_to&" "&template_ending_date_display&" "&template_label_if_applicable
C182: 33
C183: 70-73
C184: =template_label_does_the_undertaking_have_sites_that_are_located_in_or_near_biodiversity_sensitive_areas | G184: TRUE
C185: =template_label_please_select_the_unit_used_for_the_area
C186: squared meters (m2) | L186: =IF(AND(G184=TRUE,C186=""), template_label_missing_value, IF(AND(G184=TRUE,C186<>""), template_label_ok, ""))
C187: =template_label_related_site_id | D187: =template_label_site_location_in_near_a_biodiversity_area | G187: =template_label_area_hectares_or_m2 | J187: =template_label_site_located_in_a_biodiversity_sensitive_area | K187: =template_label_site_located_near_a_biodiversity_sensitive_area
C188: 1 | D188: =IF(C188 = "", "", IF(AND(COUNTIF('General Information'!C404:C503, C188), INDEX('General Information'!D404:D503, MATCH(C188, 'General Information'!C404:C503, 0)) = ""), "VALUE INCONSISTENCY", IFERROR(VLOOKUP(C188, ListOfSitesTable, 5, FALSE),"") & " " & IFERROR(VLOOKUP(C188, ListOfSitesTable, 4, FALSE),"") & " " & IFERROR(VLOOKUP(C188, ListOfSitesTable, 2, FALSE),""))) | G188: 1200 | J188: TRUE | K188: FALSE | L188: =IF($G$184=FALSE, "", IF(AND($G$184=TRUE, TRIM(D188)<>"", TRIM(G188)<>"", OR(J188=TRUE, K188=TRUE)), template_label_ok, IF(AND($G$184=TRUE, TRIM(D188)<>"", TRIM(G188)<>"", J188=FALSE, K188=FALSE), template_label_missing_value, IF(AND($G$184=TRUE, TRIM(D188)<>"", TRIM(G188)="", J188=FALSE, K188=FALSE), template_label_missing_value, IF(AND($G$184=TRUE, TRIM(D188)<>"", TRIM(G188)="", OR(J188=TRUE, K188=TRUE)), template_label_missing_value, IF(AND($G$184=TRUE, TRIM(D188)="", TRIM(G188)<>"", J188=FALSE, K188=FALSE), template_label_missing_value, IF(AND($G$184=TRUE, TRIM(D188)="", TRIM(G188)="", OR(J188=TRUE, K188=TRUE)), template_label_missing_value, IF(AND($G$184=TRUE, TRIM(D188)="", TRIM(G188)<>"", OR(J188=TRUE, K188=TRUE)), template_label_missing_value, "" ) ) ) ) ) ) ) ) | M188: =template_label_site_ID_value_inconsistency_warning
D189: =IF(C189 = "", "", IF(COUNTIF($C$188:C188, C189), "VALUE INCONSISTENCY", IF(AND(COUNTIF('General Information'!$C$404:$C$503, C189), INDEX('General Information'!$D$404:$D$503, MATCH(C189, 'General Information'!$C$404:$C$503, 0)) = ""), "VALUE INCONSISTENCY", IFERROR(VLOOKUP(C189, ListOfSitesTable, 5, FALSE), "") & " " & IFERROR(VLOOKUP(C189, ListOfSitesTable, 4, FALSE), "") & " " & IFERROR(VLOOKUP(C189, ListOfSitesTable, 2, FALSE), "")))) | J189: FALSE | K189: FALSE | L189: =IF($G$184=FALSE, "", IF(AND($G$184=TRUE, TRIM(D189)<>"", TRIM(G189)<>"", OR(J189=TRUE, K189=TRUE)), template_label_ok, IF(AND($G$184=TRUE, TRIM(D189)<>"", TRIM(G189)<>"", J189=FALSE, K189=FALSE), template_label_missing_value, IF(AND($G$184=TRUE, TRIM(D189)<>"", TRIM(G189)="", J189=FALSE, K189=FALSE), template_label_missing_value, IF(AND($G$184=TRUE, TRIM(D189)<>"", TRIM(G189)="", OR(J189=TRUE, K189=TRUE)), template_label_missing_value, IF(AND($G$184=TRUE, TRIM(D189)="", TRIM(G189)<>"", J189=FALSE, K189=FALSE), template_label_missing_value, IF(AND($G$184=TRUE, TRIM(D189)="", TRIM(G189)="", OR(J189=TRUE, K189=TRUE)), template_label_missing_value, IF(AND($G$184=TRUE, TRIM(D189)="", TRIM(G189)<>"", OR(J189=TRUE, K189=TRUE)), template_label_missing_value, "" ) ) ) ) ) ) ) )
D190: =IF(C190 = "", "", IF(COUNTIF($C$188:C189, C190), "VALUE INCONSISTENCY", IF(AND(COUNTIF('General Information'!$C$404:$C$503, C190), INDEX('General Information'!$D$404:$D$503, MATCH(C190, 'General Information'!$C$404:$C$503, 0)) = ""), "VALUE INCONSISTENCY", IFERROR(VLOOKUP(C190, ListOfSitesTable, 5, FALSE), "") & " " & IFERROR(VLOOKUP(C190, ListOfSitesTable, 4, FALSE), "") & " " & IFERROR(VLOOKUP(C190, ListOfSitesTable, 2, FALSE), "")))) | J190: FALSE | K190: FALSE | L190: =IF($G$184=FALSE, "", IF(AND($G$184=TRUE, TRIM(D190)<>"", TRIM(G190)<>"", OR(J190=TRUE, K190=TRUE)), template_label_ok, IF(AND($G$184=TRUE, TRIM(D190)<>"", TRIM(G190)<>"", J190=FALSE, K190=FALSE), template_label_missing_value, IF(AND($G$184=TRUE, TRIM(D190)<>"", TRIM(G190)="", J190=FALSE, K190=FALSE), template_label_missing_value, IF(AND($G$184=TRUE, TRIM(D190)<>"", TRIM(G190)="", OR(J190=TRUE, K190=TRUE)), template_label_missing_value, IF(AND($G$184=TRUE, TRIM(D190)="", TRIM(G190)<>"", J190=FALSE, K190=FALSE), template_label_missing_value, IF(AND($G$184=TRUE, TRIM(D190)="", TRIM(G190)="", OR(J190=TRUE, K190=TRUE)), template_label_missing_value, IF(AND($G$184=TRUE, TRIM(D190)="", TRIM(G190)<>"", OR(J190=TRUE, K190=TRUE)), template_label_missing_value, "" ) ) ) ) ) ) ) ) | M190: =template_label_additional_rows_warning
D191: =IF(C191 = "", "", IF(COUNTIF($C$188:C190, C191), "VALUE INCONSISTENCY", IF(AND(COUNTIF('General Information'!$C$404:$C$503, C191), INDEX('General Information'!$D$404:$D$503, MATCH(C191, 'General Information'!$C$404:$C$503, 0)) = ""), "VALUE INCONSISTENCY", IFERROR(VLOOKUP(C191, ListOfSitesTable, 5, FALSE), "") & " " & IFERROR(VLOOKUP(C191, ListOfSitesTable, 4, FALSE), "") & " " & IFERROR(VLOOKUP(C191, ListOfSitesTable, 2, FALSE), "")))) | J191: FALSE | K191: FALSE | L191: =IF($G$184=FALSE, "", IF(AND($G$184=TRUE, TRIM(D191)<>"", TRIM(G191)<>"", OR(J191=TRUE, K191=TRUE)), template_label_ok, IF(AND($G$184=TRUE, TRIM(D191)<>"", TRIM(G191)<>"", J191=FALSE, K191=FALSE), template_label_missing_value, IF(AND($G$184=TRUE, TRIM(D191)<>"", TRIM(G191)="", J191=FALSE, K191=FALSE), template_label_missing_value, IF(AND($G$184=TRUE, TRIM(D191)<>"", TRIM(G191)="", OR(J191=TRUE, K191=TRUE)), template_label_missing_value, IF(AND($G$184=TRUE, TRIM(D191)="", TRIM(G191)<>"", J191=FALSE, K191=FALSE), template_label_missing_value, IF(AND($G$184=TRUE, TRIM(D191)="", TRIM(G191)="", OR(J191=TRUE, K191=TRUE)), template_label_missing_value, IF(AND($G$184=TRUE, TRIM(D191)="", TRIM(G191)<>"", OR(J191=TRUE, K191=TRUE)), template_label_missing_value, "" ) ) ) ) ) ) ) )
D192: =IF(C192 = "", "", IF(COUNTIF($C$188:C191, C192), "VALUE INCONSISTENCY", IF(AND(COUNTIF('General Information'!$C$404:$C$503, C192), INDEX('General Information'!$D$404:$D$503, MATCH(C192, 'General Information'!$C$404:$C$503, 0)) = ""), "VALUE INCONSISTENCY", IFERROR(VLOOKUP(C192, ListOfSitesTable, 5, FALSE), "") & " " & IFERROR(VLOOKUP(C192, ListOfSitesTable, 4, FALSE), "") & " " & IFERROR(VLOOKUP(C192, ListOfSitesTable, 2, FALSE), "")))) | J192: FALSE | K192: FALSE | L192: =IF($G$184=FALSE, "", IF(AND($G$184=TRUE, TRIM(D192)<>"", TRIM(G192)<>"", OR(J192=TRUE, K192=TRUE)), template_label_ok, IF(AND($G$184=TRUE, TRIM(D192)<>"", TRIM(G192)<>"", J192=FALSE, K192=FALSE), template_label_missing_value, IF(AND($G$184=TRUE, TRIM(D192)<>"", TRIM(G192)="", J192=FALSE, K192=FALSE), template_label_missing_value, IF(AND($G$184=TRUE, TRIM(D192)<>"", TRIM(G192)="", OR(J192=TRUE, K192=TRUE)), template_label_missing_value, IF(AND($G$184=TRUE, TRIM(D192)="", TRIM(G192)<>"", J192=FALSE, K192=FALSE), template_label_missing_value, IF(AND($G$184=TRUE, TRIM(D192)="", TRIM(G192)="", OR(J192=TRUE, K192=TRUE)), template_label_missing_value, IF(AND($G$184=TRUE, TRIM(D192)="", TRIM(G192)<>"", OR(J192=TRUE, K192=TRUE)), template_label_missing_value, "" ) ) ) ) ) ) ) )
D193: =IF(C193 = "", "", IF(COUNTIF($C$188:C192, C193), "VALUE INCONSISTENCY", IF(AND(COUNTIF('General Information'!$C$404:$C$503, C193), INDEX('General Information'!$D$404:$D$503, MATCH(C193, 'General Information'!$C$404:$C$503, 0)) = ""), "VALUE INCONSISTENCY", IFERROR(VLOOKUP(C193, ListOfSitesTable, 5, FALSE), "") & " " & IFERROR(VLOOKUP(C193, ListOfSitesTable, 4, FALSE), "") & " " & IFERROR(VLOOKUP(C193, ListOfSitesTable, 2, FALSE), "")))) | J193: FALSE | K193: FALSE | L193: =IF($G$184=FALSE, "", IF(AND($G$184=TRUE, TRIM(D193)<>"", TRIM(G193)<>"", OR(J193=TRUE, K193=TRUE)), template_label_ok, IF(AND($G$184=TRUE, TRIM(D193)<>"", TRIM(G193)<>"", J193=FALSE, K193=FALSE), template_label_missing_value, IF(AND($G$184=TRUE, TRIM(D193)<>"", TRIM(G193)="", J193=FALSE, K193=FALSE), template_label_missing_value, IF(AND($G$184=TRUE, TRIM(D193)<>"", TRIM(G193)="", OR(J193=TRUE, K193=TRUE)), template_label_missing_value, IF(AND($G$184=TRUE, TRIM(D193)="", TRIM(G193)<>"", J193=FALSE, K193=FALSE), template_label_missing_value, IF(AND($G$184=TRUE, TRIM(D193)="", TRIM(G193)="", OR(J193=TRUE, K193=TRUE)), template_label_missing_value, IF(AND($G$184=TRUE, TRIM(D193)="", TRIM(G193)<>"", OR(J193=TRUE, K193=TRUE)), template_label_missing_value, "" ) ) ) ) ) ) ) )
...

Sheet Social Disclosures
A1: =template_label_paragraph_reference | B1: =template_label_paragraph_guidance_reference
C2: =template_label_employee_counting_methodology_for_the_disclosures_below_headcount_full_time_equivalent | F2: =IF('General Information'!$E$284="","-",'General Information'!$E$284)
C3: =template_label_employee_counting_methodology_for_the_disclosures_below_period | F3: =IF('General Information'!$E$283="","-",'General Information'!$E$283)
C6: =template_label_b8_workforce_general_characteristics_type_of_contract&" "&template_label_always_to_be_reported
C7: 39(a)
C8: 110-117
C9: =template_label_type_of_contract | D9: =template_label_number_of_employees
C10: =template_label_permanent_contract | D10: 110 | H10: =IF(OR( 'Table of Contents & Validation'!D38=TRUE,'Table of Contents & Validation'!D37=TRUE), IF( AND( OR( 'General Information'!E122="Option A (Basic Module only)", 'General Information'!E122="Option B (Basic Module and Comprehensive Module)" ), D10="" ), "", IF('General Information'!E122="", "", template_label_ok ) ), IF( AND( OR( 'General Information'!E122="Option A (Basic Module only)", 'General Information'!E122="Option B (Basic Module and Comprehensive Module)" ), D10="" ), template_label_missing_value, IF('General Information'!E122="", "", template_label_ok ) ) )
C11: =template_label_temporary_contract
C12: =template_label_total_employees | D12: =IF('General Information'!$E$282="", "-", VALUE(SUBSTITUTE('General Information'!$E$282, "-", "0")))
C14: =template_label_b8_workforce_general_characteristics_gender&" "&template_label_always_to_be_reported
C15: 39(b)
C16: 110-117
C17: =template_label_gender | D17: =template_label_number_of_employees
C18: =template_label_male | D18: 55 | H18: =IF(OR( 'Table of Contents & Validation'!D39=TRUE,'Table of Contents & Validation'!D37=TRUE), IF( 'General Information'!E282="", IF( OR( 'General Information'!E122="Option A (Basic Module only)", 'General Information'!E122="Option B (Basic Module and Comprehensive Module)" ), IF( NumberOfMaleEmployees +NumberOfFemaleEmployees +NumberOfOtherGenderEmployees +NumberOfNonReportedGenderEmployees =D22, template_label_ok, "" ), "" ), IF( OR( 'General Information'!E122="Option A (Basic Module only)", 'General Information'!E122="Option B (Basic Module and Comprehensive Module)" ), IF( NumberOfMaleEmployees +NumberOfFemaleEmployees +NumberOfOtherGenderEmployees +NumberOfNonReportedGenderEmployees =D22, template_label_ok, "" ), "" ) ), IF( 'General Information'!E282="", IF( OR( 'General Information'!E122="Option A (Basic Module only)", 'General Information'!E122="Option B (Basic Module and Comprehensive Module)" ), IF( NumberOfMaleEmployees +NumberOfFemaleEmployees +NumberOfOtherGenderEmployees +NumberOfNonReportedGenderEmployees =D22, template_label_ok, template_label_missing_value ), "" ), IF( OR( 'General Information'!E122="Option A (Basic Module only)", 'General Information'!E122="Option B (Basic Module and Comprehensive Module)" ), IF( NumberOfMaleEmployees +NumberOfFemaleEmployees +NumberOfOtherGenderEmployees +NumberOfNonReportedGenderEmployees =D22, template_label_ok, template_label_value_inconsistency ), "" ) ) ) | I18: =template_label_number_of_employees_warning
C19: =template_label_female | D19: 40
C20: =template_label_other | D20: 5
C21: =template_label_not_reported | D21: 51
C22: =template_label_total_employees | D22: =IF('General Information'!$E$282="","-",'General Information'!$E$282)
C24: =template_label_b8_workforce_general_characteristics_country_of_employment&" "&template_label_if_applicable
C25: 39(c)
C26: 110-117
C27: =template_label_undertaking_operating_in_more_than_one_country | E27: TRUE
C28: =template_label_country_of_employment_contract | E28: =template_label_number_of_employees
C29: Italy | E29: 140 | I29: =IF( AND(C29="", E29=""), "", IF( AND(C29<>"", E29=""), template_label_missing_value, IF( AND(C29<>"", E29<>""), IF( SUM($E$29:$E$128)<$E$129, template_label_missing_value, IF( COUNTIF($C$29:$C$128, C29) > 1, template_label_value_inconsistency, template_label_ok ) ), template_label_missing_value ) ) ) | J29: =template_label_number_of_employees_warning
C30: Belgium | E30: 1 | I30: =IF( AND(C30="", E30=""), "", IF( AND(C30<>"", E30=""), template_label_missing_value, IF( AND(C30<>"", E30<>""), IF( SUM($E$29:$E$128)<$E$129, template_label_missing_value, IF( COUNTIF($C$29:$C$128, C30) > 1, template_label_value_inconsistency, template_label_ok) ), template_label_missing_value) ) )
C31: Albania | E31: 10 | I31: =IF( AND(C31="", E31=""), "", IF( AND(C31<>"", E31=""), template_label_missing_value, IF( AND(C31<>"", E31<>""), IF( SUM($E$29:$E$128)<$E$129, template_label_missing_value, IF( COUNTIF($C$29:$C$128, C31) > 1, template_label_value_inconsistency, template_label_ok) ), template_label_missing_value) ) ) | J31: =template_label_additional_rows_warning
I32: =IF( AND(C32="", E32=""), "", IF( AND(C32<>"", E32=""), template_label_missing_value, IF( AND(C32<>"", E32<>""), IF( SUM($E$29:$E$128)<$E$129, template_label_missing_value, IF( COUNTIF($C$29:$C$128, C32) > 1, template_label_value_inconsistency, template_label_ok) ), template_label_missing_value) ) )
I33: =IF( AND(C33="", E33=""), "", IF( AND(C33<>"", E33=""), template_label_missing_value, IF( AND(C33<>"", E33<>""), IF( SUM($E$29:$E$128)<$E$129, template_label_missing_value, IF( COUNTIF($C$29:$C$128, C33) > 1, template_label_value_inconsistency, template_label_ok) ), template_label_missing_value) ) )
I34: =IF( AND(C34="", E34=""), "", IF( AND(C34<>"", E34=""), template_label_missing_value, IF( AND(C34<>"", E34<>""), IF( SUM($E$29:$E$128)<$E$129, template_label_missing_value, IF( COUNTIF($C$29:$C$128, C34) > 1, template_label_value_inconsistency, template_label_ok) ), template_label_missing_value) ) )
I35: =IF( AND(C35="", E35=""), "", IF( AND(C35<>"", E35=""), template_label_missing_value, IF( AND(C35<>"", E35<>""), IF( SUM($E$29:$E$128)<$E$129, template_label_missing_value, IF( COUNTIF($C$29:$C$128, C35) > 1, template_label_value_inconsistency, template_label_ok) ), template_label_missing_value) ) )
I36: =IF( AND(C36="", E36=""), "", IF( AND(C36<>"", E36=""), template_label_missing_value, IF( AND(C36<>"", E36<>""), IF( SUM($E$29:$E$128)<$E$129, template_label_missing_value, IF( COUNTIF($C$29:$C$128, C36) > 1, template_label_value_inconsistency, template_label_ok) ), template_label_missing_value) ) )
I37: =IF( AND(C37="", E37=""), "", IF( AND(C37<>"", E37=""), template_label_missing_value, IF( AND(C37<>"", E37<>""), IF( SUM($E$29:$E$128)<$E$129, template_label_missing_value, IF( COUNTIF($C$29:$C$128, C37) > 1, template_label_value_inconsistency, template_label_ok) ), template_label_missing_value) ) )
I38: =IF( AND(C38="", E38=""), "", IF( AND(C38<>"", E38=""), template_label_missing_value, IF( AND(C38<>"", E38<>""), IF( SUM($E$29:$E$128)<$E$129, template_label_missing_value, IF( COUNTIF($C$29:$C$128, C38) > 1, template_label_value_inconsistency, template_label_ok) ), template_label_missing_value) ) )
I39: =IF( AND(C39="", E39=""), "", IF( AND(C39<>"", E39=""), template_label_missing_value, IF( AND(C39<>"", E39<>""), IF( SUM($E$29:$E$128)<$E$129, template_label_missing_value, IF( COUNTIF($C$29:$C$128, C39) > 1, template_label_value_inconsistency, template_label_ok) ), template_label_missing_value) ) )
I40: =IF( AND(C40="", E40=""), "", IF( AND(C40<>"", E40=""), template_label_missing_value, IF( AND(C40<>"", E40<>""), IF( SUM($E$29:$E$128)<$E$129, template_label_missing_value, IF( COUNTIF($C$29:$C$128, C40) > 1, template_label_value_inconsistency, template_label_ok) ), template_label_missing_value) ) )
I41: =IF( AND(C41="", E41=""), "", IF( AND(C41<>"", E41=""), template_label_missing_value, IF( AND(C41<>"", E41<>""), IF( SUM($E$29:$E$128)<$E$129, template_label_missing_value, IF( COUNTIF($C$29:$C$128, C41) > 1, template_label_value_inconsistency, template_label_ok) ), template_label_missing_value) ) )
I42: =IF( AND(C42="", E42=""), "", IF( AND(C42<>"", E42=""), template_label_missing_value, IF( AND(C42<>"", E42<>""), IF( SUM($E$29:$E$128)<$E$129, template_label_missing_value, IF( COUNTIF($C$29:$C$128, C42) > 1, template_label_value_inconsistency, template_label_ok) ), template_label_missing_value) ) )
I43: =IF( AND(C43="", E43=""), "", IF( AND(C43<>"", E43=""), template_label_missing_value, IF( AND(C43<>"", E43<>""), IF( SUM($E$29:$E$128)<$E$129, template_label_missing_value, IF( COUNTIF($C$29:$C$128, C43) > 1, template_label_value_inconsistency, template_label_ok) ), template_label_missing_value) ) )
... I60: =IF( AND(C60="", E60=""), "", IF( AND(C60<>"", E60=""), template_label_missing_value, IF( AND(C60<>"", E60<>""), IF( SUM($E$29:$E$128)<$E$129, template_label_missing_value, IF( COUNTIF($C$29:$C$128, C60) > 1, template_label_value_inconsistency, template_label_ok) ), template_label_missing_value) ) )
I61: =IF( AND(C61="", E61=""), "", IF( AND(C61<>"", E61=""), template_label_missing_value, IF( AND(C61<>"", E61<>""), IF( SUM($E$29:$E$128)<$E$129, template_label_missing_value, IF( COUNTIF($C$29:$C$128, C61) > 1, template_label_value_inconsistency, template_label_ok ) ), template_label_missing_value ) ) )
I62: =IF( AND(C62="", E62=""), "", IF( AND(C62<>"", E62=""), template_label_missing_value, IF( AND(C62<>"", E62<>""), IF( SUM($E$29:$E$128)<$E$129, template_label_missing_value, IF( COUNTIF($C$29:$C$128, C62) > 1, template_label_value_inconsistency, template_label_ok) ), template_label_missing_value) ) )
I63: =IF( AND(C63="", E63=""), "", IF( AND(C63<>"", E63=""), template_label_missing_value, IF( AND(C63<>"", E63<>""), IF( SUM($E$29:$E$128)<$E$129, template_label_missing_value, IF( COUNTIF($C$29:$C$128, C63) > 1, template_label_value_inconsistency, template_label_ok) ), template_label_missing_value) ) )
I64: =IF( AND(C64="", E64=""), "", IF( AND(C64<>"", E64=""), template_label_missing_value, IF( AND(C64<>"", E64<>""), IF( SUM($E$29:$E$128)<$E$129, template_label_missing_value, IF( COUNTIF($C$29:$C$128, C64) > 1, template_label_value_inconsistency, template_label_ok) ), template_label_missing_value) ) )
I65: =IF( AND(C65="", E65=""), "", IF( AND(C65<>"", E65=""), template_label_missing_value, IF( AND(C65<>"", E65<>""), IF( SUM($E$29:$E$128)<$E$129, template_label_missing_value, IF( COUNTIF($C$29:$C$128, C65) > 1, template_label_value_inconsistency, template_label_ok) ), template_label_missing_value) ) )
I66: =IF( AND(C66="", E66=""), "", IF( AND(C66<>"", E66=""), template_label_missing_value, IF( AND(C66<>"", E66<>""), IF( SUM($E$29:$E$128)<$E$129, template_label_missing_value, IF( COUNTIF($C$29:$C$128, C66) > 1, template_label_value_inconsistency, template_label_ok) ), template_label_missing_value) ) )
I67: =IF( AND(C67="", E67=""), "", IF( AND(C67<>"", E67=""), template_label_missing_value, IF( AND(C67<>"", E67<>""), IF( SUM($E$29:$E$128)<$E$129, template_label_missing_value, IF( COUNTIF($C$29:$C$128, C67) > 1, template_label_value_inconsistency, template_label_ok) ), template_label_missing_value) ) )
I68: =IF( AND(C68="", E68=""), "", IF( AND(C68<>"", E68=""), template_label_missing_value, IF( AND(C68<>"", E68<>""), IF( SUM($E$29:$E$128)<$E$129, template_label_missing_value, IF( COUNTIF($C$29:$C$128, C68) > 1, template_label_value_inconsistency, template_label_ok) ), template_label_missing_value) ) )
I69: =IF( AND(C69="", E69=""), "", IF( AND(C69<>"", E69=""), template_label_missing_value, IF( AND(C69<>"", E69<>""), IF( SUM($E$29:$E$128)<$E$129, template_label_missing_value, IF( COUNTIF($C$29:$C$128, C69) > 1, template_label_value_inconsistency, template_label_ok) ), template_label_missing_value) ) )
I70: =IF( AND(C70="", E70=""), "", IF( AND(C70<>"", E70=""), template_label_missing_value, IF( AND(C70<>"", E70<>""), IF( SUM($E$29:$E$128)<$E$129, template_label_missing_value, IF( COUNTIF($C$29:$C$128, C70) > 1, template_label_value_inconsistency, template_label_ok) ), template_label_missing_value) ) )
I71: =IF( AND(C71="", E71=""), "", IF( AND(C71<>"", E71=""), template_label_missing_value, IF( AND(C71<>"", E71<>""), IF( SUM($E$29:$E$128)<$E$129, template_label_missing_value, IF( COUNTIF($C$29:$C$128, C71) > 1, template_label_value_inconsistency, template_label_ok) ), template_label_missing_value) ) )
I72: =IF( AND(C72="", E72=""), "", IF( AND(C72<>"", E72=""), template_label_missing_value, IF( AND(C72<>"", E72<>""), IF( SUM($E$29:$E$128)<$E$129, template_label_missing_value, IF( COUNTIF($C$29:$C$128, C72) > 1, template_label_value_inconsistency, template_label_ok) ), template_label_missing_value) ) )
I73: =IF( AND(C73="", E73=""), "", IF( AND(C73<>"", E73=""), template_label_missing_value, IF( AND(C73<>"", E73<>""), IF( SUM($E$29:$E$128)<$E$129, template_label_missing_value, IF( COUNTIF($C$29:$C$128, C73) > 1, template_label_value_inconsistency, template_label_ok) ), template_label_missing_value) ) )
... I92: =IF( AND(C92="", E92=""), "", IF( AND(C92<>"", E92=""), template_label_missing_value, IF( AND(C92<>"", E92<>""), IF( SUM($E$29:$E$128)<$E$129, template_label_missing_value, IF( COUNTIF($C$29:$C$128, C92) > 1, template_label_value_inconsistency, template_label_ok) ), template_label_missing_value) ) )
I93: =IF( AND(C93="", E93=""), "", IF( AND(C93<>"", E93=""), template_label_missing_value, IF( AND(C93<>"", E93<>""), IF( SUM($E$29:$E$128)<$E$129, template_label_missing_value, IF( COUNTIF($C$29:$C$128, C93) > 1, template_label_value_inconsistency, template_label_ok ) ), template_label_missing_value ) ) )
I94: =IF( AND(C94="", E94=""), "", IF( AND(C94<>"", E94=""), template_label_missing_value, IF( AND(C94<>"", E94<>""), IF( SUM($E$29:$E$128)<$E$129, template_label_missing_value, IF( COUNTIF($C$29:$C$128, C94) > 1, template_label_value_inconsistency, template_label_ok) ), template_label_missing_value) ) )
I95: =IF( AND(C95="", E95=""), "", IF( AND(C95<>"", E95=""), template_label_missing_value, IF( AND(C95<>"", E95<>""), IF( SUM($E$29:$E$128)<$E$129, template_label_missing_value, IF( COUNTIF($C$29:$C$128, C95) > 1, template_label_value_inconsistency, template_label_ok) ), template_label_missing_value) ) )
I96: =IF( AND(C96="", E96=""), "", IF( AND(C96<>"", E96=""), template_label_missing_value, IF( AND(C96<>"", E96<>""), IF( SUM($E$29:$E$128)<$E$129, template_label_missing_value, IF( COUNTIF($C$29:$C$128, C96) > 1, template_label_value_inconsistency, template_label_ok) ), template_label_missing_value) ) )
I97: =IF( AND(C97="", E97=""), "", IF( AND(C97<>"", E97=""), template_label_missing_value, IF( AND(C97<>"", E97<>""), IF( SUM($E$29:$E$128)<$E$129, template_label_missing_value, IF( COUNTIF($C$29:$C$128, C97) > 1, template_label_value_inconsistency, template_label_ok) ), template_label_missing_value) ) )
I98: =IF( AND(C98="", E98=""), "", IF( AND(C98<>"", E98=""), template_label_missing_value, IF( AND(C98<>"", E98<>""), IF( SUM($E$29:$E$128)<$E$129, template_label_missing_value, IF( COUNTIF($C$29:$C$128, C98) > 1, template_label_value_inconsistency, template_label_ok) ), template_label_missing_value) ) )
I99: =IF( AND(C99="", E99=""), "", IF( AND(C99<>"", E99=""), template_label_missing_value, IF( AND(C99<>"", E99<>""), IF( SUM($E$29:$E$128)<$E$129, template_label_missing_value, IF( COUNTIF($C$29:$C$128, C99) > 1, template_label_value_inconsistency, template_label_ok) ), template_label_missing_value) ) )
I100: =IF( AND(C100="", E100=""), "", IF( AND(C100<>"", E100=""), template_label_missing_value, IF( AND(C100<>"", E100<>""), IF( SUM($E$29:$E$128)<$E$129, template_label_missing_value, IF( COUNTIF($C$29:$C$128, C100) > 1, template_label_value_inconsistency, template_label_ok) ), template_label_missing_value) ) )
I101: =IF( AND(C101="", E101=""), "", IF( AND(C101<>"", E101=""), template_label_missing_value, IF( AND(C101<>"", E101<>""), IF( SUM($E$29:$E$128)<$E$129, template_label_missing_value, IF( COUNTIF($C$29:$C$128, C101) > 1, template_label_value_inconsistency, template_label_ok) ), template_label_missing_value) ) )
I102: =IF( AND(C102="", E102=""), "", IF( AND(C102<>"", E102=""), template_label_missing_value, IF( AND(C102<>"", E102<>""), IF( SUM($E$29:$E$128)<$E$129, template_label_missing_value, IF( COUNTIF($C$29:$C$128, C102) > 1, template_label_value_inconsistency, template_label_ok) ), template_label_missing_value) ) )
I103: =IF( AND(C103="", E103=""), "", IF( AND(C103<>"", E103=""), template_label_missing_value, IF( AND(C103<>"", E103<>""), IF( SUM($E$29:$E$128)<$E$129, template_label_missing_value, IF( COUNTIF($C$29:$C$128, C103) > 1, template_label_value_inconsistency, template_label_ok) ), template_label_missing_value) ) )
I104: =IF( AND(C104="", E104=""), "", IF( AND(C104<>"", E104=""), template_label_missing_value, IF( AND(C104<>"", E104<>""), IF( SUM($E$29:$E$128)<$E$129, template_label_missing_value, IF( COUNTIF($C$29:$C$128, C104) > 1, template_label_value_inconsistency, template_label_ok) ), template_label_missing_value) ) )
I105: =IF( AND(C105="", E105=""), "", IF( AND(C105<>"", E105=""), template_label_missing_value, IF( AND(C105<>"", E105<>""), IF( SUM($E$29:$E$128)<$E$129, template_label_missing_value, IF( COUNTIF($C$29:$C$128, C105) > 1, template_label_value_inconsistency, template_label_ok) ), template_label_missing_value) ) )
... I128: =IF( AND(C128="", E128=""), "", IF( AND(C128<>"", E128=""), template_label_missing_value, IF( AND(C128<>"", E128<>""), IF( SUM($E$29:$E$128)<$E$129, template_label_missing_value, IF( COUNTIF($C$29:$C$128, C128) > 1, template_label_value_inconsistency, template_label_ok) ), template_label_missing_value) ) )
C129: =template_label_total_employees | E129: =IF('General Information'!$E$282="","-",'General Information'!$E$282)
C131: =template_label_b8_workforce_general_characteristics_turnover_rate&" "&template_label_from&" "&template_starting_date_display&" "&template_label_to&" "&template_ending_date_display&" "&template_label_if_applicable
C132: 40
C133: 118
C134: =template_label_number_of_employees_who_left_during_the_reporting_period | D134: 50 | I134: =IF( AND('General Information'!$E$282<50, D134=""), "", IF( AND('General Information'!$E$282<50, D134<>""), template_label_ok, IF( AND('General Information'!$E$282>=50, D134<>""), template_label_ok, template_label_missing_value ) ) )
C135: =template_label_number_of_employees_at_the_beginning_of_the_reporting_period | D135: 201 | I135: =IF( AND('General Information'!$E$282<50, D135=""), "", IF( AND('General Information'!$E$282<50, D135<>""), template_label_ok, IF( AND('General Information'!$E$282>=50, D135<>""), template_label_ok, template_label_missing_value ) ) )
C136: =template_label_number_of_employees_at_the_end_of_the_reporting_period | D136: 151 | I136: =IF( AND('General Information'!$E$282<50, D136=""), "", IF( AND('General Information'!$E$282<50, D136<>""), template_label_ok, IF( AND('General Information'!$E$282>=50, D136<>""), template_label_ok, template_label_missing_value ) ) )
C137: =template_label_employee_turnover_rate_in_the_reporting_period
C139: =template_label_b9_workforce_health_and_safety&" "&template_label_from&" "&template_starting_date_display&" "&template_label_to&" "&template_ending_date_display&" "&template_label_always_to_be_reported
A140: 41(a) | B140: 119-126 | C140: =template_label_number_of_recordable_work_related_accidents_in_the_reporting_period | D140: 0 | I140: =IF( 'Table of Contents & Validation'!D42=TRUE, IF( AND( OR('General Information'!E122="Option A (Basic Module only)", 'General Information'!E122="Option B (Basic Module and Comprehensive Module)"), NumberOfRecordableWorkRelatedAccidentsInTheReportingPeriod="" ), "", IF('General Information'!E122="", "", template_label_ok) ), IF( AND( OR('General Information'!E122="Option A (Basic Module only)", 'General Information'!E122="Option B (Basic Module and Comprehensive Module)"), NumberOfRecordableWorkRelatedAccidentsInTheReportingPeriod="" ), template_label_missing_value, IF('General Information'!E122="", "", template_label_ok) ) )
A141: 41(a) | B141: 119-126 | C141: =template_label_number_of_hours_worked_by_one_fulltime_employee_in_the_reporting_period | D141: 2000 | I141: =IF(D141="", "MISSING VALUE", IF(D141<>2000, "OK", "")) | J141: =template_label_health_and_safety_formula_warning
A142: 41(a) | B142: 119-126 | C142: =template_label_total_number_of_hours_worked_in_a_year_by_all_employees_in_the_reporting_period | D142: =IF('General Information'!E282="","-",D141*'General Information'!E282)
A143: 41(a) | B143: 119-126 | C143: =template_label_rate_of_recordable_work_related_accidents_in_the_reporting_period
A144: 41(b) | B144: 119-126 | C144: =template_label_number_of_fatalities_as_a_result_of_work_related_injuries_and_work_related_ill_health | D144: 0 | I144: =IF( 'Table of Contents & Validation'!D42=TRUE, IF( AND( OR('General Information'!E122="Option A (Basic Module only)", 'General Information'!E122="Option B (Basic Module and Comprehensive Module)"), NumberOfFatalitiesAsAResultOfWorkRelatedInjuriesAndWorkRelatedIllHealth="" ), "", IF('General Information'!E122="", "", template_label_ok) ), IF( AND( OR('General Information'!E122="Option A (Basic Module only)", 'General Information'!E122="Option B (Basic Module and Comprehensive Module)"), NumberOfFatalitiesAsAResultOfWorkRelatedInjuriesAndWorkRelatedIllHealth="" ), template_label_missing_value, IF('General Information'!E122="", "", template_label_ok) ) )
C146: =template_label_b10_workforce_remuneration_collective_bargaining&" "&template_label_from&" "&template_starting_date_display&" "&template_label_to&" "&template_ending_date_display&" "&template_label_always_to_be_reported_if_applicable
A147: 42(a) | B147: 127-128 | C147: =template_label_employees_receive_pay_that_is_equal_or_above_applicable_minimum_wage | D147: YES | I147: =IF(OR( 'Table of Contents & Validation'!D44=TRUE,'Table of Contents & Validation'!D43=TRUE), IF( AND( OR('General Information'!E122="Option A (Basic Module only)", 'General Information'!E122="Option B (Basic Module and Comprehensive Module)"), EmployeesReceivePayEqualOrAboveMinimumWageDeterminedByNationalLawOrCollectiveAgreement="" ), "", IF('General Information'!E122="", "", template_label_ok) ), IF( AND( OR('General Information'!E122="Option A (Basic Module only)", 'General Information'!E122="Option B (Basic Module and Comprehensive Module)"), EmployeesReceivePayEqualOrAboveMinimumWageDeterminedByNationalLawOrCollectiveAgreement="" ), template_label_missing_value, IF('General Information'!E122="", "", template_label_ok) ) )
A148: 42(b) | B148: 129-136 | C148: =template_label_average_gross_hourly_pay_level_of_male_employees & " " & "(" & template_label_amount_in & " " & template_currency & ")" | D148: 20 | I148: =IF( AND('General Information'!$E$282<150, D148=""), "", IF( AND('General Information'!$E$282<150, D148<>""), template_label_ok, IF( AND('General Information'!$E$282>=150, D148<>""), template_label_ok, template_label_missing_value ) ) )
A149: 42(b) | B149: 129-136 | C149: =template_label_average_gross_hourly_pay_level_of_female_employees & " " & "(" & template_label_amount_in & " " & template_currency & ")" | D149: 18 | I149: =IF( AND('General Information'!$E$282<150, D149=""), "", IF( AND('General Information'!$E$282<150, D149<>""), template_label_ok, IF( AND('General Information'!$E$282>=150, D149<>""), template_label_ok, template_label_missing_value ) ) )
A150: 42(b) | B150: 129-136 | C150: =template_label_percentage_gap_in_pay_between_the__undertakings_female_and_male_employees
A151: 42(c) | B151: 137-140 | C151: =template_label_number_of_employees_covered_by_collective_bargaining_agreements | D151: 140 | I151: =IF(OR( 'Table of Contents & Validation'!D44=TRUE,'Table of Contents & Validation'!D43=TRUE), IF( AND( OR('General Information'!E122="Option A (Basic Module only)",'General Information'!E122="Option B (Basic Module and Comprehensive Module)"), D151="" ), "", IF('General Information'!E122="","",template_label_ok) ), IF( AND( OR('General Information'!E122="Option A (Basic Module only)",'General Information'!E122="Option B (Basic Module and Comprehensive Module)"), D151="" ), template_label_missing_value, IF('General Information'!E122="","",template_label_ok) ) )
C152: =template_label_percentage_of_employees_covered_by_collective_bargaining_agreements
C154: =template_label_number_of_annual_training_hours_per_employee_during_the_reporting_period&" "&template_label_from&" "&template_starting_date_display&" "&template_label_to&" "&template_ending_date_display&" "&template_label_always_to_be_reported
C155: 42(d)
C156: =template_label_gender | D156: =template_label_number_of_annual_training_hours_per_employee_during_the_reporting_period
C157: =template_label_male | D157: 100 | I157: =IF(OR( 'Table of Contents & Validation'!D45=TRUE,'Table of Contents & Validation'!D43=TRUE), IF( OR('General Information'!E122="Option A (Basic Module only)", 'General Information'!E122="Option B (Basic Module and Comprehensive Module)"), IF(OR(D157<>"", D158<>"", D159<>"", D160<>""), template_label_ok, ""), "" ), IF( OR('General Information'!E122="Option A (Basic Module only)", 'General Information'!E122="Option B (Basic Module and Comprehensive Module)"), IF(OR(D157<>"", D158<>"", D159<>"", D160<>""), template_label_ok, template_label_missing_value), "" ) )
C158: =template_label_female | D158: 150
C159: =template_label_other | D159: 140
C160: =template_label_not_reported | D160: 120
C161: =template_label_average_number_of_annual_training_hours_per_employee
C162: =IFERROR( IF( AND(D18<>"",D18<>0,D19<>"",D19<>0,D20<>"",D20<>0,D21<>"",D21<>0), AVERAGE(D157:D160), IF(OR(D18="", D18=0), AVERAGE(D158:D160), IF(OR(D19="", D19=0), AVERAGE(D157,D159,D160), IF(OR(D20="", D20=0), AVERAGE(D157,D158,D160), IF(OR(D21="", D21=0), AVERAGE(D157,D158,D159), "-")))) ), "-")
C164: =template_label_c5_additional_workforce_characteristics&" "&template_label_from&" "&template_starting_date_display&" "&template_label_to&" "&template_ending_date_display&" " & template_label_may
A165: 59 | B165: 167-169 | C165: =template_label_number_of_male_employees_at_management_level | D165: 5 | I165: =IF(D165<>"", template_label_ok, "")
...

Sheet Governance Disclosures
A1: Paragraph Reference | B1: Paragraph Guidance Reference
C2: =template_label_b11_convictions_and_fines_for_corruption_and_bribery&" "&template_label_from&" "&template_starting_date_display&" "&template_label_to&" "&template_ending_date_display&" "&template_label_if_applicable
C3: 43
C4: 141-144
C5: =template_label_has_the_undertaking_incurred_in_convictions_and_fines_in_the_reporting_period | H5: TRUE
C6: =template_label_total_number_of_convictions_for_the_violation_of_anti_corruption_and_anti_bribery_laws | H6: 1 | I6: =IF(AND($H$5=TRUE,H6<>""), template_label_ok, IF(AND($H$5=TRUE,H6=""), template_label_missing_value, ""))
C7: =template_label_total_amount_of_fines_for_the_violation_of_anti_corruption_and_anti_bribery_laws & " " & "(" & template_label_amount_in & " " & template_currency & ")" | H7: 5000 | I7: =IF(AND($H$5=TRUE,H7<>""), template_label_ok, IF(AND($H$5=TRUE,H7=""), template_label_missing_value, ""))
C9: =template_label_c8_revenues_from_certain_sectors&" "&template_label_from&" "&template_starting_date_display&" "&template_label_to&" "&template_ending_date_display&" "&template_label_if_applicable
C10: =template_label_is_the_undertaking_deriving_revenues_from_one_of_the_activities_listed_below | H10: FALSE
H11: =template_label_monetary_amount_in & " " & template_currency
A12: 63(a) | B12: 175-176 | C12: =template_label_revenue_derived_from_controversial_weapons | I12: =IF(AND(H10=FALSE,COUNTA(H12:H16)=0, H18=""), "", IF(AND(OR(COUNTA(H12:H16)>0, H18<>""), SUM(H12:H16, H18)<='General Information'!E281), template_label_ok, IF(AND(H10=TRUE, COUNTA(H12:H16)=0, H18=""), template_label_missing_value, template_label_value_inconsistency ) ) )
A13: 63(b) | B13: 175-176 | C13: =template_label_revenue_derived_from_cultivation_and_production_of_tobacco
A14: 63(c) | B14: 175-176 | C14: =template_label_revenue_derived_from_coal
A15: 63(c) | B15: 175-176 | C15: =template_label_revenue_derived_from_oil
A16: 63(c) | B16: 175-176 | C16: =template_label_revenue_derived_from_gas
A17: 63(c) | B17: 175-176 | C17: =template_label_total_revenues_derived_from_fossil_fuel_sector
A18: 63(d) | B18: 175-176 | C18: =template_label_revenue_derived_from_chemicals_production
C20: =template_label_c8_exclusion_from_eu_reference_benchmarks&" "&template_label_from&" "&template_starting_date_display&" "&template_label_to&" "&template_ending_date_display&" "&template_label_always_to_be_reported
C21: =template_label_undertakings_are_excluded_from_the_eu_paris_aligned_benchmarks_if_they_derive
A22: 64 | B22: 177(a) | C22: =template_label_1_percent_or_more_of_their_revenues_from_exploration_mining_extraction_distribution_or_refining_of_hard_coal_and_lignite | H22: FALSE | I22: =IF(OR( 'Table of Contents & Validation'!D65=TRUE,'Table of Contents & Validation'!D63=TRUE), IF(AND(OR(H22=TRUE, H23=TRUE, H24=TRUE, H25=TRUE), 'General Information'!E122="Option B (Basic Module and Comprehensive Module)"), template_label_ok, IF(AND(H22=FALSE, H23=FALSE, H24=FALSE, H25=FALSE, H26=FALSE, 'General Information'!E122="Option B (Basic Module and Comprehensive Module)"), "", IF('General Information'!E122="Option A (Basic Module only)", "", IF(AND('General Information'!E122="Option B (Basic Module and Comprehensive Module)", H26=TRUE), template_label_ok, "")))), IF(AND(OR(H22=TRUE, H23=TRUE, H24=TRUE, H25=TRUE), 'General Information'!E122="Option B (Basic Module and Comprehensive Module)"), template_label_ok, IF(AND(H22=FALSE, H23=FALSE, H24=FALSE, H25=FALSE, H26=FALSE, 'General Information'!E122="Option B (Basic Module and Comprehensive Module)"), template_label_missing_value, IF('General Information'!E122="Option A (Basic Module only)", "", IF(AND('General Information'!E122="Option B (Basic Module and Comprehensive Module)", H26=TRUE), template_label_ok, "")))) )
A23: 64 | B23: 177(b) | C23: =template_label_10_percent_or_more_of_their_revenues_from_the_exploration_extraction_distribution_or_refining_of_oil_fuels | H23: FALSE
A24: 64 | B24: 177(c) | C24: =template_label_50_percent_or_more_of_their_revenues_from_the_exploration_extraction_manufacturing_or_distribution_of_gaseous_fuels | H24: FALSE
A25: 64 | B25: 177(d) | C25: =template_label_50_percent_or_more_of_their_revenues_from_electricity_generation | H25: FALSE
C26: =template_label_none_of_the_above | H26: TRUE
A27: 64 | B27: 177 | C27: =template_label_undertakings_are_excluded_from_any_eu_reference_benchmarks_that_are_aligned_with_the_paris_agreement | I27: =IF(H27=TRUE, template_label_ok, "")
C29: =template_label_c9_gender_diversity_ratio_in_the_governance_body&" "&template_label_at&" "&template_ending_date_display&" "&template_label_if_applicable
C30: =template_label_does_the_undertaking_have_a_governance_body_in_place | H30: TRUE
A31: 65 | B31: 178-180 | C31: =template_label_number_of_female_board_members_at_the_end_of_the_reporting_period | H31: 5 | I31: =IF(AND($H$30=TRUE, H31<>""), template_label_ok, IF(AND($H$30=TRUE, H31=""), template_label_missing_value, ""))
C32: =template_label_number_of_male_board_members_at_the_end_of_the_reporting_period | H32: 2 | I32: =IF(AND($H$30=TRUE, H32<>""), template_label_ok, IF(AND($H$30=TRUE, H32=""), template_label_missing_value, ""))
C33: =template_label_gender_diversity_ratio_in_governance_body
C36: =template_label_disclosure_of_any_other_governance_and_or_entity_specific_governance_disclosures&" "&template_label_from&" "&template_starting_date_display&" "&template_label_to&" "&template_ending_date_display&" " & template_label_may
C37: 10
I38: =IF(C38<>"",template_label_ok, "")

Sheet Fuel Converter
A1: =template_label_fuel_converter
A2: =template_label_disclaimer
A3: =template_label_this_converter_is_intended_solely_to_illustrate_how_energy_consumption_in_mwh
A4: =template_label_please_note_that_the_typical_values_for_net_calorific_value_and_density_are_provided_for_each_fuel_type
A5: =template_label_additionally_users_are_encouraged_to_determine_the_renewability_status_of_each_fuel_based_on_guarantees_of_origin
B6: =template_label_indicates_that_the_cell_should_be_filled_either_by_selecting_a_value_from_the_dropdown
A7: - | B7: =template_label_indicates_that_the_cell_is_automatically_calculated_and_that_no_data_entry_is_required
A9: =template_label_fuel_type | B9: =template_label_unit_of_measurement | C9: =template_label_amount | D9: =template_label_state_of_matter | E9: =template_label_typical_renewable_state | F9: =template_label_calculated_energy_in_mwh | G9: =template_label_overall_validation_status_validation&":" | H9: {=_xlfn.IFS( OR( COUNTIF(G10:G19,template_label_liquid_warning)>0, COUNTIF(G10:G19,template_label_gaseous_warning)>0, COUNTIF(G10:G19,template_label_solid_warning)>0 ), template_label_incomplete, COUNTBLANK(A10:A19)=10, "-", AND( COUNTIF(G10:G19,template_label_liquid_warning)=0, COUNTIF(G10:G19,template_label_gaseous_warning)=0, COUNTIF(G10:G19,template_label_solid_warning)=0, COUNTBLANK(A10:A19)<>10, COUNTIF(F10:F19,"-")=10 ), "-", AND( COUNTIF(G10:G19,template_label_liquid_warning)=0, COUNTIF(G10:G19,template_label_gaseous_warning)=0, COUNTIF(G10:G19,template_label_solid_warning)=0, COUNTIF(F10:F19,"-")<>10 ), template_label_complete )} | J9: =template_label_usage_of_fuel_converter
A10: Biodiesel | B10: m³ - cubic meters | C10: 12 | D10: =P11 | E10: =P12 | F10: =IF(C10="","-",O23) | G10: =IF(AND(B10="",D10="Liquid"), template_label_liquid_warning, IF(AND(A10<>"",B10<>"",C10<>"",D10<>"",E10<>"",F10<>"",OR(AND(OR(B10="L - Liter",B10="m³ - cubic meters"),OR(D10="Liquid",D10="Gaseous")),AND(OR(B10="Kg - Kilogram",B10="t - tonne",B10="g - gram"),D10="Solid"))),"OK", IF(AND(OR(B10="m³ - cubic meters",B10="L - Liter"),D10="Liquid",C10=""), "", IF(AND(OR(B10="Gg - Gigagram",B10="t - tonne",B10="Kg - Kilogram",B10="g - gram"),D10="Liquid"), template_label_liquid_warning, IF(AND(B10="",D10="Gaseous"), template_label_gaseous_warning, IF(AND(A10<>"",B10<>"",C10<>"",D10<>"",E10<>"",F10<>"",OR(AND(OR(B10="L - Liter",B10="m³ - cubic meters"),OR(D10="Liquid",D10="Gaseous")),AND(OR(B10="Kg - Kilogram",B10="t - tonne",B10="g - gram"),D10="Solid"))),"OK",IF(AND(OR(B10="m³ - cubic meters",B10="L - Liter"),D10="Gaseous",C10=""), "", IF(AND(OR(B10="Gg - Gigagram",B10="t - tonne",B10="Kg - Kilogram",B10="g - gram"),D10="Gaseous"), template_label_gaseous_warning, IF(AND(B10="",D10="Solid"), template_label_solid_warning, IF(AND(A10<>"",B10<>"",C10<>"",D10<>"",E10<>"",F10<>"",OR(AND(OR(B10="L - Liter",B10="m³ - cubic meters"),OR(D10="Liquid",D10="Gaseous")),AND(OR(B10="Kg - Kilogram",B10="t - tonne",B10="g - gram"),D10="Solid"))),"OK",IF(AND(OR(B10="Gg - Gigagram",B10="t - tonne",B10="Kg - Kilogram",B10="g - gram"),D10="Solid"), "", IF(AND(OR(B10="m³ - cubic meters",B10="L - Liter"),D10="Solid"), template_label_solid_warning, "")))))))))))) | J10: =template_label_1_in_cell_a9_select_the_fuel_used_searching_for_it_or_scrolling_down_the_list_displayed_clicking_the_cell | O10: What is your fuel? | P10: =IF(A10="","-",A10) | S10: What is your fuel? | T10: =IF(A11="","-",A11) | W10: What is your fuel? | X10: =IF(A12="","-",A12) | AA10: What is your fuel? | AB10: =IF(A13="","-",A13) | AE10: What is your fuel? | AF10: =IF(A14="","-",A14) | AI10: What is your fuel? | AJ10: =IF(A15="","-",A15) | AM10: What is your fuel? | AN10: =IF(A16="","-",A16) | AQ10: What is your fuel? | AR10: =IF(A17="","-",A17) | AU10: What is your fuel? | AV10: =IF(A18="","-",A18) | AY10: What is your fuel? | AZ10: =IF(A19="","-",A19)
A11: Methane | B11: L - Liter | C11: 23 | D11: =T11 | E11: =T12 | F11: =IF(C11="","-",S23) | G11: =IF(AND(B11="",D11="Liquid"), template_label_liquid_warning, IF(AND(A11<>"",B11<>"",C11<>"",D11<>"",E11<>"",F11<>"",OR(AND(OR(B11="L - Liter",B11="m³ - cubic meters"),OR(D11="Liquid",D11="Gaseous")),AND(OR(B11="Kg - Kilogram",B11="t - tonne",B11="g - gram"),D11="Solid"))),"OK", IF(AND(OR(B11="m³ - cubic meters",B11="L - Liter"),D11="Liquid",C11=""), "", IF(AND(OR(B11="Gg - Gigagram",B11="t - tonne",B11="Kg - Kilogram",B11="g - gram"),D11="Liquid"), template_label_liquid_warning, IF(AND(B11="",D11="Gaseous"), template_label_gaseous_warning, IF(AND(A11<>"",B11<>"",C11<>"",D11<>"",E11<>"",F11<>"",OR(AND(OR(B11="L - Liter",B11="m³ - cubic meters"),OR(D11="Liquid",D11="Gaseous")),AND(OR(B11="Kg - Kilogram",B11="t - tonne",B11="g - gram"),D11="Solid"))),"OK",IF(AND(OR(B11="m³ - cubic meters",B11="L - Liter"),D11="Gaseous",C11=""), "", IF(AND(OR(B11="Gg - Gigagram",B11="t - tonne",B11="Kg - Kilogram",B11="g - gram"),D11="Gaseous"), template_label_gaseous_warning, IF(AND(B11="",D11="Solid"), template_label_solid_warning, IF(AND(A11<>"",B11<>"",C11<>"",D11<>"",E11<>"",F11<>"",OR(AND(OR(B11="L - Liter",B11="m³ - cubic meters"),OR(D11="Liquid",D11="Gaseous")),AND(OR(B11="Kg - Kilogram",B11="t - tonne",B11="g - gram"),D11="Solid"))),"OK",IF(AND(OR(B11="Gg - Gigagram",B11="t - tonne",B11="Kg - Kilogram",B11="g - gram"),D11="Solid"), "", IF(AND(OR(B11="m³ - cubic meters",B11="L - Liter"),D11="Solid"), template_label_solid_warning, "")))))))))))) | J11: =template_label_2_in_cell_b9_select_the_unit_of_measurement_used | O11: State of matter | P11: =IF(OR(P10="", P10="-"), "-", IFERROR(IF(INDEX('Fuel Conversion Parameters'!$B$2:$B$61, MATCH(P10, 'Fuel Conversion Parameters'!$A$2:$A$61, 0))="", "MISSING VALUE", INDEX('Fuel Conversion Parameters'!$B$2:$B$61, MATCH(P10, 'Fuel Conversion Parameters'!$A$2:$A$61, 0))), "MISSING VALUE")) | S11: State of matter | T11: =IF(OR(T10="", T10="-"), "-", IFERROR(IF(INDEX('Fuel Conversion Parameters'!$B$2:$B$61, MATCH(T10, 'Fuel Conversion Parameters'!$A$2:$A$61, 0))="", "MISSING VALUE", INDEX('Fuel Conversion Parameters'!$B$2:$B$61, MATCH(T10, 'Fuel Conversion Parameters'!$A$2:$A$61, 0))), "MISSING VALUE")) | W11: State of matter | X11: =IF(OR(X10="", X10="-"), "-", IFERROR(IF(INDEX('Fuel Conversion Parameters'!$B$2:$B$61, MATCH(X10, 'Fuel Conversion Parameters'!$A$2:$A$61, 0))="", "MISSING VALUE", INDEX('Fuel Conversion Parameters'!$B$2:$B$61, MATCH(X10, 'Fuel Conversion Parameters'!$A$2:$A$61, 0))), "MISSING VALUE")) | AA11: State of matter | AB11: =IF(OR(AB10="", AB10="-"), "-", IFERROR(IF(INDEX('Fuel Conversion Parameters'!$B$2:$B$61, MATCH(AB10, 'Fuel Conversion Parameters'!$A$2:$A$61, 0))="", "MISSING VALUE", INDEX('Fuel Conversion Parameters'!$B$2:$B$61, MATCH(AB10, 'Fuel Conversion Parameters'!$A$2:$A$61, 0))), "MISSING VALUE")) | AE11: State of matter | AF11: =IF(OR(AF10="", AF10="-"), "-", IFERROR(IF(INDEX('Fuel Conversion Parameters'!$B$2:$B$61, MATCH(AF10, 'Fuel Conversion Parameters'!$A$2:$A$61, 0))="", "MISSING VALUE", INDEX('Fuel Conversion Parameters'!$B$2:$B$61, MATCH(AF10, 'Fuel Conversion Parameters'!$A$2:$A$61, 0))), "MISSING VALUE")) | AI11: State of matter | AJ11: =IF(OR(AJ10="", AJ10="-"), "-", IFERROR(IF(INDEX('Fuel Conversion Parameters'!$B$2:$B$61, MATCH(AJ10, 'Fuel Conversion Parameters'!$A$2:$A$61, 0))="", "MISSING VALUE", INDEX('Fuel Conversion Parameters'!$B$2:$B$61, MATCH(AJ10, 'Fuel Conversion Parameters'!$A$2:$A$61, 0))), "MISSING VALUE")) | AM11: State of matter | AN11: =IF(OR(AN10="", AN10="-"), "-", IFERROR(IF(INDEX('Fuel Conversion Parameters'!$B$2:$B$61, MATCH(AN10, 'Fuel Conversion Parameters'!$A$2:$A$61, 0))="", "MISSING VALUE", INDEX('Fuel Conversion Parameters'!$B$2:$B$61, MATCH(AN10, 'Fuel Conversion Parameters'!$A$2:$A$61, 0))), "MISSING VALUE")) | AQ11: State of matter | AR11: =IF(OR(AR10="", AR10="-"), "-", IFERROR(IF(INDEX('Fuel Conversion Parameters'!$B$2:$B$61, MATCH(AR10, 'Fuel Conversion Parameters'!$A$2:$A$61, 0))="", "MISSING VALUE", INDEX('Fuel Conversion Parameters'!$B$2:$B$61, MATCH(AR10, 'Fuel Conversion Parameters'!$A$2:$A$61, 0))), "MISSING VALUE")) | AU11: State of matter | AV11: =IF(OR(AV10="", AV10="-"), "-", IFERROR(IF(INDEX('Fuel Conversion Parameters'!$B$2:$B$61, MATCH(AV10, 'Fuel Conversion Parameters'!$A$2:$A$61, 0))="", "MISSING VALUE", INDEX('Fuel Conversion Parameters'!$B$2:$B$61, MATCH(AV10, 'Fuel Conversion Parameters'!$A$2:$A$61, 0))), "MISSING VALUE")) | AY11: State of matter | AZ11: =IF(OR(AZ10="", AZ10="-"), "-", IFERROR(IF(INDEX('Fuel Conversion Parameters'!$B$2:$B$61, MATCH(AZ10, 'Fuel Conversion Parameters'!$A$2:$A$61, 0))="", "MISSING VALUE", INDEX('Fuel Conversion Parameters'!$B$2:$B$61, MATCH(AZ10, 'Fuel Conversion Parameters'!$A$2:$A$61, 0))), "MISSING VALUE"))
D12: =X11 | E12: =X12 | F12: =IF(C12="","-",W23) | G12: =IF(AND(B12="",D12="Liquid"), template_label_liquid_warning, IF(AND(A12<>"",B12<>"",C12<>"",D12<>"",E12<>"",F12<>"",OR(AND(OR(B12="L - Liter",B12="m³ - cubic meters"),OR(D12="Liquid",D12="Gaseous")),AND(OR(B12="Kg - Kilogram",B12="t - tonne",B12="g - gram"),D12="Solid"))),"OK", IF(AND(OR(B12="m³ - cubic meters",B12="L - Liter"),D12="Liquid",C12=""), "", IF(AND(OR(B12="Gg - Gigagram",B12="t - tonne",B12="Kg - Kilogram",B12="g - gram"),D12="Liquid"), template_label_liquid_warning, IF(AND(B12="",D12="Gaseous"), template_label_gaseous_warning, IF(AND(A12<>"",B12<>"",C12<>"",D12<>"",E12<>"",F12<>"",OR(AND(OR(B12="L - Liter",B12="m³ - cubic meters"),OR(D12="Liquid",D12="Gaseous")),AND(OR(B12="Kg - Kilogram",B12="t - tonne",B12="g - gram"),D12="Solid"))),"OK",IF(AND(OR(B12="m³ - cubic meters",B12="L - Liter"),D12="Gaseous",C12=""), "", IF(AND(OR(B12="Gg - Gigagram",B12="t - tonne",B12="Kg - Kilogram",B12="g - gram"),D12="Gaseous"), template_label_gaseous_warning, IF(AND(B12="",D12="Solid"), template_label_solid_warning, IF(AND(A12<>"",B12<>"",C12<>"",D12<>"",E12<>"",F12<>"",OR(AND(OR(B12="L - Liter",B12="m³ - cubic meters"),OR(D12="Liquid",D12="Gaseous")),AND(OR(B12="Kg - Kilogram",B12="t - tonne",B12="g - gram"),D12="Solid"))),"OK",IF(AND(OR(B12="Gg - Gigagram",B12="t - tonne",B12="Kg - Kilogram",B12="g - gram"),D12="Solid"), "", IF(AND(OR(B12="m³ - cubic meters",B12="L - Liter"),D12="Solid"), template_label_solid_warning, "")))))))))))) | J12: =template_label_3_in_cell_c9_select_the_amount_of_fuel_used | O12: Typical renewability state | P12: =IF(OR(P10="", P10="-"), "-", IFERROR(IF(INDEX('Fuel Conversion Parameters'!$F$2:$F$61, MATCH(P10, 'Fuel Conversion Parameters'!$A$2:$A$61, 0))="", "MISSING VALUE", INDEX('Fuel Conversion Parameters'!$F$2:$F$61, MATCH(P10, 'Fuel Conversion Parameters'!$A$2:$A$61, 0))), "MISSING VALUE")) | S12: Typical renewability state | T12: =IF(OR(T10="", T10="-"), "-", IFERROR(IF(INDEX('Fuel Conversion Parameters'!$F$2:$F$61, MATCH(T10, 'Fuel Conversion Parameters'!$A$2:$A$61, 0))="", "MISSING VALUE", INDEX('Fuel Conversion Parameters'!$F$2:$F$61, MATCH(T10, 'Fuel Conversion Parameters'!$A$2:$A$61, 0))), "MISSING VALUE")) | W12: Typical renewability state | X12: =IF(OR(X10="", X10="-"), "-", IFERROR(IF(INDEX('Fuel Conversion Parameters'!$F$2:$F$61, MATCH(X10, 'Fuel Conversion Parameters'!$A$2:$A$61, 0))="", "MISSING VALUE", INDEX('Fuel Conversion Parameters'!$F$2:$F$61, MATCH(X10, 'Fuel Conversion Parameters'!$A$2:$A$61, 0))), "MISSING VALUE")) | AA12: Typical renewability state | AB12: =IF(OR(AB10="", AB10="-"), "-", IFERROR(IF(INDEX('Fuel Conversion Parameters'!$F$2:$F$61, MATCH(AB10, 'Fuel Conversion Parameters'!$A$2:$A$61, 0))="", "MISSING VALUE", INDEX('Fuel Conversion Parameters'!$F$2:$F$61, MATCH(AB10, 'Fuel Conversion Parameters'!$A$2:$A$61, 0))), "MISSING VALUE")) | AE12: Typical renewability state | AF12: =IF(OR(AF10="", AF10="-"), "-", IFERROR(IF(INDEX('Fuel Conversion Parameters'!$F$2:$F$61, MATCH(AF10, 'Fuel Conversion Parameters'!$A$2:$A$61, 0))="", "MISSING VALUE", INDEX('Fuel Conversion Parameters'!$F$2:$F$61, MATCH(AF10, 'Fuel Conversion Parameters'!$A$2:$A$61, 0))), "MISSING VALUE")) | AI12: Typical renewability state | AJ12: =IF(OR(AJ10="", AJ10="-"), "-", IFERROR(IF(INDEX('Fuel Conversion Parameters'!$F$2:$F$61, MATCH(AJ10, 'Fuel Conversion Parameters'!$A$2:$A$61, 0))="", "MISSING VALUE", INDEX('Fuel Conversion Parameters'!$F$2:$F$61, MATCH(AJ10, 'Fuel Conversion Parameters'!$A$2:$A$61, 0))), "MISSING VALUE")) | AM12: Typical renewability state | AN12: =IF(OR(AN10="", AN10="-"), "-", IFERROR(IF(INDEX('Fuel Conversion Parameters'!$F$2:$F$61, MATCH(AN10, 'Fuel Conversion Parameters'!$A$2:$A$61, 0))="", "MISSING VALUE", INDEX('Fuel Conversion Parameters'!$F$2:$F$61, MATCH(AN10, 'Fuel Conversion Parameters'!$A$2:$A$61, 0))), "MISSING VALUE")) | AQ12: Typical renewability state | AR12: =IF(OR(AR10="", AR10="-"), "-", IFERROR(IF(INDEX('Fuel Conversion Parameters'!$F$2:$F$61, MATCH(AR10, 'Fuel Conversion Parameters'!$A$2:$A$61, 0))="", "MISSING VALUE", INDEX('Fuel Conversion Parameters'!$F$2:$F$61, MATCH(AR10, 'Fuel Conversion Parameters'!$A$2:$A$61, 0))), "MISSING VALUE")) | AU12: Typical renewability state | AV12: =IF(OR(AV10="", AV10="-"), "-", IFERROR(IF(INDEX('Fuel Conversion Parameters'!$F$2:$F$61, MATCH(AV10, 'Fuel Conversion Parameters'!$A$2:$A$61, 0))="", "MISSING VALUE", INDEX('Fuel Conversion Parameters'!$F$2:$F$61, MATCH(AV10, 'Fuel Conversion Parameters'!$A$2:$A$61, 0))), "MISSING VALUE")) | AY12: Typical renewability state | AZ12: =IF(OR(AZ10="", AZ10="-"), "-", IFERROR(IF(INDEX('Fuel Conversion Parameters'!$F$2:$F$61, MATCH(AZ10, 'Fuel Conversion Parameters'!$A$2:$A$61, 0))="", "MISSING VALUE", INDEX('Fuel Conversion Parameters'!$F$2:$F$61, MATCH(AZ10, 'Fuel Conversion Parameters'!$A$2:$A$61, 0))), "MISSING VALUE"))
D13: =AB11 | E13: =AB12 | F13: =IF(C13="","-",AA23) | G13: =IF(AND(B13="",D13="Liquid"), template_label_liquid_warning, IF(AND(A13<>"",B13<>"",C13<>"",D13<>"",E13<>"",F13<>"",OR(AND(OR(B13="L - Liter",B13="m³ - cubic meters"),OR(D13="Liquid",D13="Gaseous")),AND(OR(B13="Kg - Kilogram",B13="t - tonne",B13="g - gram"),D13="Solid"))),"OK", IF(AND(OR(B13="m³ - cubic meters",B13="L - Liter"),D13="Liquid",C13=""), "", IF(AND(OR(B13="Gg - Gigagram",B13="t - tonne",B13="Kg - Kilogram",B13="g - gram"),D13="Liquid"), template_label_liquid_warning, IF(AND(B13="",D13="Gaseous"), template_label_gaseous_warning, IF(AND(A13<>"",B13<>"",C13<>"",D13<>"",E13<>"",F13<>"",OR(AND(OR(B13="L - Liter",B13="m³ - cubic meters"),OR(D13="Liquid",D13="Gaseous")),AND(OR(B13="Kg - Kilogram",B13="t - tonne",B13="g - gram"),D13="Solid"))),"OK",IF(AND(OR(B13="m³ - cubic meters",B13="L - Liter"),D13="Gaseous",C13=""), "", IF(AND(OR(B13="Gg - Gigagram",B13="t - tonne",B13="Kg - Kilogram",B13="g - gram"),D13="Gaseous"), template_label_gaseous_warning, IF(AND(B13="",D13="Solid"), template_label_solid_warning, IF(AND(A13<>"",B13<>"",C13<>"",D13<>"",E13<>"",F13<>"",OR(AND(OR(B13="L - Liter",B13="m³ - cubic meters"),OR(D13="Liquid",D13="Gaseous")),AND(OR(B13="Kg - Kilogram",B13="t - tonne",B13="g - gram"),D13="Solid"))),"OK",IF(AND(OR(B13="Gg - Gigagram",B13="t - tonne",B13="Kg - Kilogram",B13="g - gram"),D13="Solid"), "", IF(AND(OR(B13="m³ - cubic meters",B13="L - Liter"),D13="Solid"), template_label_solid_warning, "")))))))))))) | J13: =template_label_4_in_cell_d9_it_is_displayed_the_state_of_matter_for_the_fuel_selected
D14: =AF11 | E14: =AF12 | F14: =IF(C14="","-",AE23) | G14: =IF(AND(B14="",D14="Liquid"), template_label_liquid_warning, IF(AND(A14<>"",B14<>"",C14<>"",D14<>"",E14<>"",F14<>"",OR(AND(OR(B14="L - Liter",B14="m³ - cubic meters"),OR(D14="Liquid",D14="Gaseous")),AND(OR(B14="Kg - Kilogram",B14="t - tonne",B14="g - gram"),D14="Solid"))),"OK", IF(AND(OR(B14="m³ - cubic meters",B14="L - Liter"),D14="Liquid",C14=""), "", IF(AND(OR(B14="Gg - Gigagram",B14="t - tonne",B14="Kg - Kilogram",B14="g - gram"),D14="Liquid"), template_label_liquid_warning, IF(AND(B14="",D14="Gaseous"), template_label_gaseous_warning, IF(AND(A14<>"",B14<>"",C14<>"",D14<>"",E14<>"",F14<>"",OR(AND(OR(B14="L - Liter",B14="m³ - cubic meters"),OR(D14="Liquid",D14="Gaseous")),AND(OR(B14="Kg - Kilogram",B14="t - tonne",B14="g - gram"),D14="Solid"))),"OK",IF(AND(OR(B14="m³ - cubic meters",B14="L - Liter"),D14="Gaseous",C14=""), "", IF(AND(OR(B14="Gg - Gigagram",B14="t - tonne",B14="Kg - Kilogram",B14="g - gram"),D14="Gaseous"), template_label_gaseous_warning, IF(AND(B14="",D14="Solid"), template_label_solid_warning, IF(AND(A14<>"",B14<>"",C14<>"",D14<>"",E14<>"",F14<>"",OR(AND(OR(B14="L - Liter",B14="m³ - cubic meters"),OR(D14="Liquid",D14="Gaseous")),AND(OR(B14="Kg - Kilogram",B14="t - tonne",B14="g - gram"),D14="Solid"))),"OK",IF(AND(OR(B14="Gg - Gigagram",B14="t - tonne",B14="Kg - Kilogram",B14="g - gram"),D14="Solid"), "", IF(AND(OR(B14="m³ - cubic meters",B14="L - Liter"),D14="Solid"), template_label_solid_warning, "")))))))))))) | J14: =template_label_5_in_cell_e9_it_is_displayed_the_typical_renewability_state_for_the_fuel_selected
D15: =AJ11 | E15: =AJ12 | F15: =IF(C15="","-",AI23) | G15: =IF(AND(B15="",D15="Liquid"), template_label_liquid_warning, IF(AND(A15<>"",B15<>"",C15<>"",D15<>"",E15<>"",F15<>"",OR(AND(OR(B15="L - Liter",B15="m³ - cubic meters"),OR(D15="Liquid",D15="Gaseous")),AND(OR(B15="Kg - Kilogram",B15="t - tonne",B15="g - gram"),D15="Solid"))),"OK", IF(AND(OR(B15="m³ - cubic meters",B15="L - Liter"),D15="Liquid",C15=""), "", IF(AND(OR(B15="Gg - Gigagram",B15="t - tonne",B15="Kg - Kilogram",B15="g - gram"),D15="Liquid"), template_label_liquid_warning, IF(AND(B15="",D15="Gaseous"), template_label_gaseous_warning, IF(AND(A15<>"",B15<>"",C15<>"",D15<>"",E15<>"",F15<>"",OR(AND(OR(B15="L - Liter",B15="m³ - cubic meters"),OR(D15="Liquid",D15="Gaseous")),AND(OR(B15="Kg - Kilogram",B15="t - tonne",B15="g - gram"),D15="Solid"))),"OK",IF(AND(OR(B15="m³ - cubic meters",B15="L - Liter"),D15="Gaseous",C15=""), "", IF(AND(OR(B15="Gg - Gigagram",B15="t - tonne",B15="Kg - Kilogram",B15="g - gram"),D15="Gaseous"), template_label_gaseous_warning, IF(AND(B15="",D15="Solid"), template_label_solid_warning, IF(AND(A15<>"",B15<>"",C15<>"",D15<>"",E15<>"",F15<>"",OR(AND(OR(B15="L - Liter",B15="m³ - cubic meters"),OR(D15="Liquid",D15="Gaseous")),AND(OR(B15="Kg - Kilogram",B15="t - tonne",B15="g - gram"),D15="Solid"))),"OK",IF(AND(OR(B15="Gg - Gigagram",B15="t - tonne",B15="Kg - Kilogram",B15="g - gram"),D15="Solid"), "", IF(AND(OR(B15="m³ - cubic meters",B15="L - Liter"),D15="Solid"), template_label_solid_warning, "")))))))))))) | J15: =template_label_6_in_cell_f9_is_displayed_the_energy_produced_in_mega_watt_hours_by_the_amount_of_fuel_specified
D16: =AN11 | E16: =AN12 | F16: =IF(C16="","-",AM23) | G16: =IF(AND(B16="",D16="Liquid"), template_label_liquid_warning, IF(AND(A16<>"",B16<>"",C16<>"",D16<>"",E16<>"",F16<>"",OR(AND(OR(B16="L - Liter",B16="m³ - cubic meters"),OR(D16="Liquid",D16="Gaseous")),AND(OR(B16="Kg - Kilogram",B16="t - tonne",B16="g - gram"),D16="Solid"))),"OK", IF(AND(OR(B16="m³ - cubic meters",B16="L - Liter"),D16="Liquid",C16=""), "", IF(AND(OR(B16="Gg - Gigagram",B16="t - tonne",B16="Kg - Kilogram",B16="g - gram"),D16="Liquid"), template_label_liquid_warning, IF(AND(B16="",D16="Gaseous"), template_label_gaseous_warning, IF(AND(A16<>"",B16<>"",C16<>"",D16<>"",E16<>"",F16<>"",OR(AND(OR(B16="L - Liter",B16="m³ - cubic meters"),OR(D16="Liquid",D16="Gaseous")),AND(OR(B16="Kg - Kilogram",B16="t - tonne",B16="g - gram"),D16="Solid"))),"OK",IF(AND(OR(B16="m³ - cubic meters",B16="L - Liter"),D16="Gaseous",C16=""), "", IF(AND(OR(B16="Gg - Gigagram",B16="t - tonne",B16="Kg - Kilogram",B16="g - gram"),D16="Gaseous"), template_label_gaseous_warning, IF(AND(B16="",D16="Solid"), template_label_solid_warning, IF(AND(A16<>"",B16<>"",C16<>"",D16<>"",E16<>"",F16<>"",OR(AND(OR(B16="L - Liter",B16="m³ - cubic meters"),OR(D16="Liquid",D16="Gaseous")),AND(OR(B16="Kg - Kilogram",B16="t - tonne",B16="g - gram"),D16="Solid"))),"OK",IF(AND(OR(B16="Gg - Gigagram",B16="t - tonne",B16="Kg - Kilogram",B16="g - gram"),D16="Solid"), "", IF(AND(OR(B16="m³ - cubic meters",B16="L - Liter"),D16="Solid"), template_label_solid_warning, "")))))))))))) | J16: =template_label_7_in_cell_a28_is_displayed_the_total_energy_in_mega_watt_hours | O16: Unit of measurement | P16: =B10 | Q16: =IF(AND(P16="", P11="Liquid"), "Liquid fuel: please select one unit of measurement among m³ and L", IF(AND(OR(P16="m³ - cubic meters", P16="L - Liter"), P11="Liquid"), "", IF(AND(OR(P16="Gg - Gigagram", P16="t - tonne", P16="Kg - Kilogram", P16="g - gram"), P11="Liquid"), "Liquid fuel: please change unit of measurement, select one among m³ and L", IF(AND(P16="", P11="Gaseous"), "Gaseous fuel: please select one unit of measurement among m³ and L", IF(AND(OR(P16="m³ - cubic meters", P16="L - Liter"), P11="Gaseous"), "", IF(AND(OR(P16="Gg - Gigagram", P16="t - tonne", P16="Kg - Kilogram", P16="g - gram"), P11="Gaseous"), "Gaseous fuel: please change unit of measurement, select one among m³ and L", IF(AND(P16="", P11="Solid"), "Solid fuel: please select one unit of measurement among Gg, t, Kg and g", IF(AND(OR(P16="Gg - Gigagram", P16="t - tonne", P16="Kg - Kilogram", P16="g - gram"), P11="Solid"), "", IF(AND(OR(P16="m³ - cubic meters", P16="L - Liter"), P11="Solid"), "Solid fuel: please change unit of measurement, select one among Gg, t, Kg and g", ""))))))))) | S16: Unit of measurement | T16: =B11 | U16: =IF(AND(T16="", T11="Liquid"), "Liquid fuel: please select one unit of measurement among m³ and L", IF(AND(OR(T16="m³ - cubic meters", T16="L - Liter"), T11="Liquid"), "", IF(AND(OR(T16="Gg - Gigagram", T16="t - tonne", T16="Kg - Kilogram", T16="g - gram"), T11="Liquid"), "Liquid fuel: please change unit of measurement, select one among m³ and L", IF(AND(T16="", T11="Gaseous"), "Gaseous fuel: please select one unit of measurement among m³ and L", IF(AND(OR(T16="m³ - cubic meters", T16="L - Liter"), T11="Gaseous"), "", IF(AND(OR(T16="Gg - Gigagram", T16="t - tonne", T16="Kg - Kilogram", T16="g - gram"), T11="Gaseous"), "Gaseous fuel: please change unit of measurement, select one among m³ and L", IF(AND(T16="", T11="Solid"), "Solid fuel: please select one unit of measurement among Gg, t, Kg and g", IF(AND(OR(T16="Gg - Gigagram", T16="t - tonne", T16="Kg - Kilogram", T16="g - gram"), T11="Solid"), "", IF(AND(OR(T16="m³ - cubic meters", T16="L - Liter"), T11="Solid"), "Solid fuel: please change unit of measurement, select one among Gg, t, Kg and g", ""))))))))) | W16: Unit of measurement | X16: =B12 | Y16: =IF(AND(X16="", X11="Liquid"), "Liquid fuel: please select one unit of measurement among m³ and L", IF(AND(OR(X16="m³ - cubic meters", X16="L - Liter"), X11="Liquid"), "", IF(AND(OR(X16="Gg - Gigagram", X16="t - tonne", X16="Kg - Kilogram", X16="g - gram"), X11="Liquid"), "Liquid fuel: please change unit of measurement, select one among m³ and L", IF(AND(X16="", X11="Gaseous"), "Gaseous fuel: please select one unit of measurement among m³ and L", IF(AND(OR(X16="m³ - cubic meters", X16="L - Liter"), X11="Gaseous"), "", IF(AND(OR(X16="Gg - Gigagram", X16="t - tonne", X16="Kg - Kilogram", X16="g - gram"), X11="Gaseous"), "Gaseous fuel: please change unit of measurement, select one among m³ and L", IF(AND(X16="", X11="Solid"), "Solid fuel: please select one unit of measurement among Gg, t, Kg and g", IF(AND(OR(X16="Gg - Gigagram", X16="t - tonne", X16="Kg - Kilogram", X16="g - gram"), X11="Solid"), "", IF(AND(OR(X16="m³ - cubic meters", X16="L - Liter"), X11="Solid"), "Solid fuel: please change unit of measurement, select one among Gg, t, Kg and g", ""))))))))) | AA16: Unit of measurement | AB16: =B13 | AC16: =IF(AND(AB16="", AB11="Liquid"), "Liquid fuel: please select one unit of measurement among m³ and L", IF(AND(OR(AB16="m³ - cubic meters", AB16="L - Liter"), AB11="Liquid"), "", IF(AND(OR(AB16="Gg - Gigagram", AB16="t - tonne", AB16="Kg - Kilogram", AB16="g - gram"), AB11="Liquid"), "Liquid fuel: please change unit of measurement, select one among m³ and L", IF(AND(AB16="", AB11="Gaseous"), "Gaseous fuel: please select one unit of measurement among m³ and L", IF(AND(OR(AB16="m³ - cubic meters", AB16="L - Liter"), AB11="Gaseous"), "", IF(AND(OR(AB16="Gg - Gigagram", AB16="t - tonne", AB16="Kg - Kilogram", AB16="g - gram"), AB11="Gaseous"), "Gaseous fuel: please change unit of measurement, select one among m³ and L", IF(AND(AB16="", AB11="Solid"), "Solid fuel: please select one unit of measurement among Gg, t, Kg and g", IF(AND(OR(AB16="Gg - Gigagram", AB16="t - tonne", AB16="Kg - Kilogram", AB16="g - gram"), AB11="Solid"), "", IF(AND(OR(AB16="m³ - cubic meters", AB16="L - Liter"), AB11="Solid"), "Solid fuel: please change unit of measurement, select one among Gg, t, Kg and g", ""))))))))) | AE16: Unit of measurement | AF16: =B14 | AG16: =IF(AND(AF16="", AF11="Liquid"), "Liquid fuel: please select one unit of measurement among m³ and L", IF(AND(OR(AF16="m³ - cubic meters", AF16="L - Liter"), AF11="Liquid"), "", IF(AND(OR(AF16="Gg - Gigagram", AF16="t - tonne", AF16="Kg - Kilogram", AF16="g - gram"), AF11="Liquid"), "Liquid fuel: please change unit of measurement, select one among m³ and L", IF(AND(AF16="", AF11="Gaseous"), "Gaseous fuel: please select one unit of measurement among m³ and L", IF(AND(OR(AF16="m³ - cubic meters", AF16="L - Liter"), AF11="Gaseous"), "", IF(AND(OR(AF16="Gg - Gigagram", AF16="t - tonne", AF16="Kg - Kilogram", AF16="g - gram"), AF11="Gaseous"), "Gaseous fuel: please change unit of measurement, select one among m³ and L", IF(AND(AF16="", AF11="Solid"), "Solid fuel: please select one unit of measurement among Gg, t, Kg and g", IF(AND(OR(AF16="Gg - Gigagram", AF16="t - tonne", AF16="Kg - Kilogram", AF16="g - gram"), AF11="Solid"), "", IF(AND(OR(AF16="m³ - cubic meters", AF16="L - Liter"), AF11="Solid"), "Solid fuel: please change unit of measurement, select one among Gg, t, Kg and g", ""))))))))) | AI16: Unit of measurement | AJ16: =B15 | AK16: =IF(AND(AJ16="", AJ11="Liquid"), "Liquid fuel: please select one unit of measurement among m³ and L", IF(AND(OR(AJ16="m³ - cubic meters", AJ16="L - Liter"), AJ11="Liquid"), "", IF(AND(OR(AJ16="Gg - Gigagram", AJ16="t - tonne", AJ16="Kg - Kilogram", AJ16="g - gram"), AJ11="Liquid"), "Liquid fuel: please change unit of measurement, select one among m³ and L", IF(AND(AJ16="", AJ11="Gaseous"), "Gaseous fuel: please select one unit of measurement among m³ and L", IF(AND(OR(AJ16="m³ - cubic meters", AJ16="L - Liter"), AJ11="Gaseous"), "", IF(AND(OR(AJ16="Gg - Gigagram", AJ16="t - tonne", AJ16="Kg - Kilogram", AJ16="g - gram"), AJ11="Gaseous"), "Gaseous fuel: please change unit of measurement, select one among m³ and L", IF(AND(AJ16="", AJ11="Solid"), "Solid fuel: please select one unit of measurement among Gg, t, Kg and g", IF(AND(OR(AJ16="Gg - Gigagram", AJ16="t - tonne", AJ16="Kg - Kilogram", AJ16="g - gram"), AJ11="Solid"), "", IF(AND(OR(AJ16="m³ - cubic meters", AJ16="L - Liter"), AJ11="Solid"), "Solid fuel: please change unit of measurement, select one among Gg, t, Kg and g", ""))))))))) | AM16: Unit of measurement | AN16: =B16 | AO16: =IF(AND(AN16="", AN11="Liquid"), "Liquid fuel: please select one unit of measurement among m³ and L", IF(AND(OR(AN16="m³ - cubic meters", AN16="L - Liter"), AN11="Liquid"), "", IF(AND(OR(AN16="Gg - Gigagram", AN16="t - tonne", AN16="Kg - Kilogram", AN16="g - gram"), AN11="Liquid"), "Liquid fuel: please change unit of measurement, select one among m³ and L", IF(AND(AN16="", AN11="Gaseous"), "Gaseous fuel: please select one unit of measurement among m³ and L", IF(AND(OR(AN16="m³ - cubic meters", AN16="L - Liter"), AN11="Gaseous"), "", IF(AND(OR(AN16="Gg - Gigagram", AN16="t - tonne", AN16="Kg - Kilogram", AN16="g - gram"), AN11="Gaseous"), "Gaseous fuel: please change unit of measurement, select one among m³ and L", IF(AND(AN16="", AN11="Solid"), "Solid fuel: please select one unit of measurement among Gg, t, Kg and g", IF(AND(OR(AN16="Gg - Gigagram", AN16="t - tonne", AN16="Kg - Kilogram", AN16="g - gram"), AN11="Solid"), "", IF(AND(OR(AN16="m³ - cubic meters", AN16="L - Liter"), AN11="Solid"), "Solid fuel: please change unit of measurement, select one among Gg, t, Kg and g", ""))))))))) | AQ16: Unit of measurement | AR16: =B17 | AS16: =IF(AND(AR16="", AR11="Liquid"), "Liquid fuel: please select one unit of measurement among m³ and L", IF(AND(OR(AR16="m³ - cubic meters", AR16="L - Liter"), AR11="Liquid"), "", IF(AND(OR(AR16="Gg - Gigagram", AR16="t - tonne", AR16="Kg - Kilogram", AR16="g - gram"), AR11="Liquid"), "Liquid fuel: please change unit of measurement, select one among m³ and L", IF(AND(AR16="", AR11="Gaseous"), "Gaseous fuel: please select one unit of measurement among m³ and L", IF(AND(OR(AR16="m³ - cubic meters", AR16="L - Liter"), AR11="Gaseous"), "", IF(AND(OR(AR16="Gg - Gigagram", AR16="t - tonne", AR16="Kg - Kilogram", AR16="g - gram"), AR11="Gaseous"), "Gaseous fuel: please change unit of measurement, select one among m³ and L", IF(AND(AR16="", AR11="Solid"), "Solid fuel: please select one unit of measurement among Gg, t, Kg and g", IF(AND(OR(AR16="Gg - Gigagram", AR16="t - tonne", AR16="Kg - Kilogram", AR16="g - gram"), AR11="Solid"), "", IF(AND(OR(AR16="m³ - cubic meters", AR16="L - Liter"), AR11="Solid"), "Solid fuel: please change unit of measurement, select one among Gg, t, Kg and g", ""))))))))) | AU16: Unit of measurement | AV16: =B18 | AW16: =IF(AND(AV16="", AV11="Liquid"), "Liquid fuel: please select one unit of measurement among m³ and L", IF(AND(OR(AV16="m³ - cubic meters", AV16="L - Liter"), AV11="Liquid"), "", IF(AND(OR(AV16="Gg - Gigagram", AV16="t - tonne", AV16="Kg - Kilogram", AV16="g - gram"), AV11="Liquid"), "Liquid fuel: please change unit of measurement, select one among m³ and L", IF(AND(AV16="", AV11="Gaseous"), "Gaseous fuel: please select one unit of measurement among m³ and L", IF(AND(OR(AV16="m³ - cubic meters", AV16="L - Liter"), AV11="Gaseous"), "", IF(AND(OR(AV16="Gg - Gigagram", AV16="t - tonne", AV16="Kg - Kilogram", AV16="g - gram"), AV11="Gaseous"), "Gaseous fuel: please change unit of measurement, select one among m³ and L", IF(AND(AV16="", AV11="Solid"), "Solid fuel: please select one unit of measurement among Gg, t, Kg and g", IF(AND(OR(AV16="Gg - Gigagram", AV16="t - tonne", AV16="Kg - Kilogram", AV16="g - gram"), AV11="Solid"), "", IF(AND(OR(AV16="m³ - cubic meters", AV16="L - Liter"), AV11="Solid"), "Solid fuel: please change unit of measurement, select one among Gg, t, Kg and g", ""))))))))) | AY16: Unit of measurement | AZ16: =B19 | BA16: =IF(AND(AZ16="", AZ11="Liquid"), "Liquid fuel: please select one unit of measurement among m³ and L", IF(AND(OR(AZ16="m³ - cubic meters", AZ16="L - Liter"), AZ11="Liquid"), "", IF(AND(OR(AZ16="Gg - Gigagram", AZ16="t - tonne", AZ16="Kg - Kilogram", AZ16="g - gram"), AZ11="Liquid"), "Liquid fuel: please change unit of measurement, select one among m³ and L", IF(AND(AZ16="", AZ11="Gaseous"), "Gaseous fuel: please select one unit of measurement among m³ and L", IF(AND(OR(AZ16="m³ - cubic meters", AZ16="L - Liter"), AZ11="Gaseous"), "", IF(AND(OR(AZ16="Gg - Gigagram", AZ16="t - tonne", AZ16="Kg - Kilogram", AZ16="g - gram"), AZ11="Gaseous"), "Gaseous fuel: please change unit of measurement, select one among m³ and L", IF(AND(AZ16="", AZ11="Solid"), "Solid fuel: please select one unit of measurement among Gg, t, Kg and g", IF(AND(OR(AZ16="Gg - Gigagram", AZ16="t - tonne", AZ16="Kg - Kilogram", AZ16="g - gram"), AZ11="Solid"), "", IF(AND(OR(AZ16="m³ - cubic meters", AZ16="L - Liter"), AZ11="Solid"), "Solid fuel: please change unit of measurement, select one among Gg, t, Kg and g", "")))))))))
D17: =AR11 | E17: =AR12 | F17: =IF(C17="","-",AQ23) | G17: =IF(AND(B17="",D17="Liquid"), template_label_liquid_warning, IF(AND(A17<>"",B17<>"",C17<>"",D17<>"",E17<>"",F17<>"",OR(AND(OR(B17="L - Liter",B17="m³ - cubic meters"),OR(D17="Liquid",D17="Gaseous")),AND(OR(B17="Kg - Kilogram",B17="t - tonne",B17="g - gram"),D17="Solid"))),"OK", IF(AND(OR(B17="m³ - cubic meters",B17="L - Liter"),D17="Liquid",C17=""), "", IF(AND(OR(B17="Gg - Gigagram",B17="t - tonne",B17="Kg - Kilogram",B17="g - gram"),D17="Liquid"), template_label_liquid_warning, IF(AND(B17="",D17="Gaseous"), template_label_gaseous_warning, IF(AND(A17<>"",B17<>"",C17<>"",D17<>"",E17<>"",F17<>"",OR(AND(OR(B17="L - Liter",B17="m³ - cubic meters"),OR(D17="Liquid",D17="Gaseous")),AND(OR(B17="Kg - Kilogram",B17="t - tonne",B17="g - gram"),D17="Solid"))),"OK",IF(AND(OR(B17="m³ - cubic meters",B17="L - Liter"),D17="Gaseous",C17=""), "", IF(AND(OR(B17="Gg - Gigagram",B17="t - tonne",B17="Kg - Kilogram",B17="g - gram"),D17="Gaseous"), template_label_gaseous_warning, IF(AND(B17="",D17="Solid"), template_label_solid_warning, IF(AND(A17<>"",B17<>"",C17<>"",D17<>"",E17<>"",F17<>"",OR(AND(OR(B17="L - Liter",B17="m³ - cubic meters"),OR(D17="Liquid",D17="Gaseous")),AND(OR(B17="Kg - Kilogram",B17="t - tonne",B17="g - gram"),D17="Solid"))),"OK",IF(AND(OR(B17="Gg - Gigagram",B17="t - tonne",B17="Kg - Kilogram",B17="g - gram"),D17="Solid"), "", IF(AND(OR(B17="m³ - cubic meters",B17="L - Liter"),D17="Solid"), template_label_solid_warning, "")))))))))))) | J17: =template_label_8_in_cell_a31_is_displayed_the_total_renewable_energy_in_mega_watt_hours | O17: Amount | P17: =C10 | S17: Amount | T17: =C11 | W17: Amount | X17: =C12 | AA17: Amount | AB17: =C13 | AE17: Amount | AF17: =C14 | AI17: Amount | AJ17: =C15 | AM17: Amount | AN17: =C16 | AQ17: Amount | AR17: =C17 | AU17: Amount | AV17: =C18 | AY17: Amount | AZ17: =C19
D18: =AV11 | E18: =AV12 | F18: =IF(C18="","-",AU23) | G18: =IF(AND(B18="",D18="Liquid"), template_label_liquid_warning, IF(AND(A18<>"",B18<>"",C18<>"",D18<>"",E18<>"",F18<>"",OR(AND(OR(B18="L - Liter",B18="m³ - cubic meters"),OR(D18="Liquid",D18="Gaseous")),AND(OR(B18="Kg - Kilogram",B18="t - tonne",B18="g - gram"),D18="Solid"))),"OK", IF(AND(OR(B18="m³ - cubic meters",B18="L - Liter"),D18="Liquid",C18=""), "", IF(AND(OR(B18="Gg - Gigagram",B18="t - tonne",B18="Kg - Kilogram",B18="g - gram"),D18="Liquid"), template_label_liquid_warning, IF(AND(B18="",D18="Gaseous"), template_label_gaseous_warning, IF(AND(A18<>"",B18<>"",C18<>"",D18<>"",E18<>"",F18<>"",OR(AND(OR(B18="L - Liter",B18="m³ - cubic meters"),OR(D18="Liquid",D18="Gaseous")),AND(OR(B18="Kg - Kilogram",B18="t - tonne",B18="g - gram"),D18="Solid"))),"OK",IF(AND(OR(B18="m³ - cubic meters",B18="L - Liter"),D18="Gaseous",C18=""), "", IF(AND(OR(B18="Gg - Gigagram",B18="t - tonne",B18="Kg - Kilogram",B18="g - gram"),D18="Gaseous"), template_label_gaseous_warning, IF(AND(B18="",D18="Solid"), template_label_solid_warning, IF(AND(A18<>"",B18<>"",C18<>"",D18<>"",E18<>"",F18<>"",OR(AND(OR(B18="L - Liter",B18="m³ - cubic meters"),OR(D18="Liquid",D18="Gaseous")),AND(OR(B18="Kg - Kilogram",B18="t - tonne",B18="g - gram"),D18="Solid"))),"OK",IF(AND(OR(B18="Gg - Gigagram",B18="t - tonne",B18="Kg - Kilogram",B18="g - gram"),D18="Solid"), "", IF(AND(OR(B18="m³ - cubic meters",B18="L - Liter"),D18="Solid"), template_label_solid_warning, "")))))))))))) | J18: =template_label_9_in_cell_b31_is_displayed_the_total_nonrenewable_energy_in_mega_watt_hours | O18: =IFERROR(VLOOKUP(P10, 'Fuel Conversion Parameters'!$A:$C, 3, FALSE), "") | P18: =IF(P16="g - gram",P17*0.000000001, IF(P16="Kg - Kilogram",P17*0.000001, IF(P16="t - tonne",P17*0.001, IF(P16="Gg - Gigagram",P17*1, IF(P16="m³ - cubic meters",P17*1000, IF(P16="L - Liter",P17*1, "")))))) | S18: =IFERROR(VLOOKUP(T10, 'Fuel Conversion Parameters'!$A:$C, 3, FALSE), "") | T18: =IF(T16="g - gram",T17*0.000000001, IF(T16="Kg - Kilogram",T17*0.000001, IF(T16="t - tonne",T17*0.001, IF(T16="Gg - Gigagram",T17*1, IF(T16="m³ - cubic meters",T17*1000, IF(T16="L - Liter",T17*1, "")))))) | W18: =IFERROR(VLOOKUP(X10, 'Fuel Conversion Parameters'!$A:$C, 3, FALSE), "") | X18: =IF(X16="g - gram",X17*0.000000001, IF(X16="Kg - Kilogram",X17*0.000001, IF(X16="t - tonne",X17*0.001, IF(X16="Gg - Gigagram",X17*1, IF(X16="m³ - cubic meters",X17*1000, IF(X16="L - Liter",X17*1, "")))))) | AA18: =IFERROR(VLOOKUP(AB10, 'Fuel Conversion Parameters'!$A:$C, 3, FALSE), "") | AB18: =IF(AB16="g - gram",AB17*0.000000001, IF(AB16="Kg - Kilogram",AB17*0.000001, IF(AB16="t - tonne",AB17*0.001, IF(AB16="Gg - Gigagram",AB17*1, IF(AB16="m³ - cubic meters",AB17*1000, IF(AB16="L - Liter",AB17*1, "")))))) | AE18: =IFERROR(VLOOKUP(AF10, 'Fuel Conversion Parameters'!$A:$C, 3, FALSE), "") | AF18: =IF(AF16="g - gram",AF17*0.000000001, IF(AF16="Kg - Kilogram",AF17*0.000001, IF(AF16="t - tonne",AF17*0.001, IF(AF16="Gg - Gigagram",AF17*1, IF(AF16="m³ - cubic meters",AF17*1000, IF(AF16="L - Liter",AF17*1, "")))))) | AI18: =IFERROR(VLOOKUP(AJ10, 'Fuel Conversion Parameters'!$A:$C, 3, FALSE), "") | AJ18: =IF(AJ16="g - gram",AJ17*0.000000001, IF(AJ16="Kg - Kilogram",AJ17*0.000001, IF(AJ16="t - tonne",AJ17*0.001, IF(AJ16="Gg - Gigagram",AJ17*1, IF(AJ16="m³ - cubic meters",AJ17*1000, IF(AJ16="L - Liter",AJ17*1, "")))))) | AM18: =IFERROR(VLOOKUP(AN10, 'Fuel Conversion Parameters'!$A:$C, 3, FALSE), "") | AN18: =IF(AN16="g - gram",AN17*0.000000001, IF(AN16="Kg - Kilogram",AN17*0.000001, IF(AN16="t - tonne",AN17*0.001, IF(AN16="Gg - Gigagram",AN17*1, IF(AN16="m³ - cubic meters",AN17*1000, IF(AN16="L - Liter",AN17*1, "")))))) | AQ18: =IFERROR(VLOOKUP(AR10, 'Fuel Conversion Parameters'!$A:$C, 3, FALSE), "") | AR18: =IF(AR16="g - gram",AR17*0.000000001, IF(AR16="Kg - Kilogram",AR17*0.000001, IF(AR16="t - tonne",AR17*0.001, IF(AR16="Gg - Gigagram",AR17*1, IF(AR16="m³ - cubic meters",AR17*1000, IF(AR16="L - Liter",AR17*1, "")))))) | AU18: =IFERROR(VLOOKUP(AV10, 'Fuel Conversion Parameters'!$A:$C, 3, FALSE), "") | AV18: =IF(AV16="g - gram",AV17*0.000000001, IF(AV16="Kg - Kilogram",AV17*0.000001, IF(AV16="t - tonne",AV17*0.001, IF(AV16="Gg - Gigagram",AV17*1, IF(AV16="m³ - cubic meters",AV17*1000, IF(AV16="L - Liter",AV17*1, "")))))) | AY18: =IFERROR(VLOOKUP(AZ10, 'Fuel Conversion Parameters'!$A:$C, 3, FALSE), "") | AZ18: =IF(AZ16="g - gram",AZ17*0.000000001, IF(AZ16="Kg - Kilogram",AZ17*0.000001, IF(AZ16="t - tonne",AZ17*0.001, IF(AZ16="Gg - Gigagram",AZ17*1, IF(AZ16="m³ - cubic meters",AZ17*1000, IF(AZ16="L - Liter",AZ17*1, ""))))))
D19: =AZ11 | E19: =AZ12 | F19: =IF(C19="","-",AY23) | G19: =IF(AND(B19="",D19="Liquid"), template_label_liquid_warning, IF(AND(A19<>"",B19<>"",C19<>"",D19<>"",E19<>"",F19<>"",OR(AND(OR(B19="L - Liter",B19="m³ - cubic meters"),OR(D19="Liquid",D19="Gaseous")),AND(OR(B19="Kg - Kilogram",B19="t - tonne",B19="g - gram"),D19="Solid"))),"OK", IF(AND(OR(B19="m³ - cubic meters",B19="L - Liter"),D19="Liquid",C19=""), "", IF(AND(OR(B19="Gg - Gigagram",B19="t - tonne",B19="Kg - Kilogram",B19="g - gram"),D19="Liquid"), template_label_liquid_warning, IF(AND(B19="",D19="Gaseous"), template_label_gaseous_warning, IF(AND(A19<>"",B19<>"",C19<>"",D19<>"",E19<>"",F19<>"",OR(AND(OR(B19="L - Liter",B19="m³ - cubic meters"),OR(D19="Liquid",D19="Gaseous")),AND(OR(B19="Kg - Kilogram",B19="t - tonne",B19="g - gram"),D19="Solid"))),"OK",IF(AND(OR(B19="m³ - cubic meters",B19="L - Liter"),D19="Gaseous",C19=""), "", IF(AND(OR(B19="Gg - Gigagram",B19="t - tonne",B19="Kg - Kilogram",B19="g - gram"),D19="Gaseous"), template_label_gaseous_warning, IF(AND(B19="",D19="Solid"), template_label_solid_warning, IF(AND(A19<>"",B19<>"",C19<>"",D19<>"",E19<>"",F19<>"",OR(AND(OR(B19="L - Liter",B19="m³ - cubic meters"),OR(D19="Liquid",D19="Gaseous")),AND(OR(B19="Kg - Kilogram",B19="t - tonne",B19="g - gram"),D19="Solid"))),"OK",IF(AND(OR(B19="Gg - Gigagram",B19="t - tonne",B19="Kg - Kilogram",B19="g - gram"),D19="Solid"), "", IF(AND(OR(B19="m³ - cubic meters",B19="L - Liter"),D19="Solid"), template_label_solid_warning, "")))))))))))) | J19: =template_label_10_further_notes_can_be_found_below | O19: =IFERROR( IF(AND(P11="Solid"),P18, IF(AND(P11="Liquid"),P18*_xlfn.XLOOKUP(P10,'Fuel Conversion Parameters'!$A$2:$A$51,'Fuel Conversion Parameters'!$D$2:$D$51)*10^(-6), IF(AND(P11="Gaseous"),P18*_xlfn.XLOOKUP(P10,'Fuel Conversion Parameters'!$A$2:$A$51,'Fuel Conversion Parameters'!$E$2:$E$51)*10^(-3)*10^(-6),"") ) ), "" ) | S19: =IFERROR( IF(AND(T11="Solid"),T18, IF(AND(T11="Liquid"),T18*_xlfn.XLOOKUP(T10,'Fuel Conversion Parameters'!$A$2:$A$61,'Fuel Conversion Parameters'!$D$2:$D$61)*10^(-6), IF(AND(T11="Gaseous"),T18*_xlfn.XLOOKUP(T10,'Fuel Conversion Parameters'!$A$2:$A$61,'Fuel Conversion Parameters'!$E$2:$E$61)*10^(-3)*10^(-6),"") ) ), "" ) | W19: =IFERROR( IF(AND(X11="Solid"),X18, IF(AND(X11="Liquid"),X18*_xlfn.XLOOKUP(X10,'Fuel Conversion Parameters'!$A$2:$A$61,'Fuel Conversion Parameters'!$D$2:$D$61)*10^(-6), IF(AND(X11="Gaseous"),X18*_xlfn.XLOOKUP(X10,'Fuel Conversion Parameters'!$A$2:$A$61,'Fuel Conversion Parameters'!$E$2:$E$61)*10^(-3)*10^(-6),"") ) ), "" ) | AA19: =IFERROR( IF(AND(AB11="Solid"),AB18, IF(AND(AB11="Liquid"),AB18*_xlfn.XLOOKUP(AB10,'Fuel Conversion Parameters'!$A$2:$A$61,'Fuel Conversion Parameters'!$D$2:$D$61)*10^(-6), IF(AND(AB11="Gaseous"),AB18*_xlfn.XLOOKUP(AB10,'Fuel Conversion Parameters'!$A$2:$A$61,'Fuel Conversion Parameters'!$E$2:$E$61)*10^(-3)*10^(-6),"") ) ), "" ) | AE19: =IFERROR( IF(AND(AF11="Solid"),AF18, IF(AND(AF11="Liquid"),AF18*_xlfn.XLOOKUP(AF10,'Fuel Conversion Parameters'!$A$2:$A$61,'Fuel Conversion Parameters'!$D$2:$D$61)*10^(-6), IF(AND(AF11="Gaseous"),AF18*_xlfn.XLOOKUP(AF10,'Fuel Conversion Parameters'!$A$2:$A$61,'Fuel Conversion Parameters'!$E$2:$E$61)*10^(-3)*10^(-6),"") ) ), "" ) | AI19: =IFERROR( IF(AND(AJ11="Solid"),AJ18, IF(AND(AJ11="Liquid"),AJ18*_xlfn.XLOOKUP(AJ10,'Fuel Conversion Parameters'!$A$2:$A$61,'Fuel Conversion Parameters'!$D$2:$D$61)*10^(-6), IF(AND(AJ11="Gaseous"),AJ18*_xlfn.XLOOKUP(AJ10,'Fuel Conversion Parameters'!$A$2:$A$61,'Fuel Conversion Parameters'!$E$2:$E$61)*10^(-3)*10^(-6),"") ) ), "" ) | AM19: =IFERROR( IF(AND(AN11="Solid"),AN18, IF(AND(AN11="Liquid"),AN18*_xlfn.XLOOKUP(AN10,'Fuel Conversion Parameters'!$A$2:$A$61,'Fuel Conversion Parameters'!$D$2:$D$61)*10^(-6), IF(AND(AN11="Gaseous"),AN18*_xlfn.XLOOKUP(AN10,'Fuel Conversion Parameters'!$A$2:$A$61,'Fuel Conversion Parameters'!$E$2:$E$61)*10^(-3)*10^(-6),"") ) ), "" ) | AQ19: =IFERROR( IF(AND(AR11="Solid"),AR18, IF(AND(AR11="Liquid"),AR18*_xlfn.XLOOKUP(AR10,'Fuel Conversion Parameters'!$A$2:$A$61,'Fuel Conversion Parameters'!$D$2:$D$61)*10^(-6), IF(AND(AR11="Gaseous"),AR18*_xlfn.XLOOKUP(AR10,'Fuel Conversion Parameters'!$A$2:$A$61,'Fuel Conversion Parameters'!$E$2:$E$61)*10^(-3)*10^(-6),"") ) ), "" ) | AU19: =IFERROR( IF(AND(AV11="Solid"),AV18, IF(AND(AV11="Liquid"),AV18*_xlfn.XLOOKUP(AV10,'Fuel Conversion Parameters'!$A$2:$A$61,'Fuel Conversion Parameters'!$D$2:$D$61)*10^(-6), IF(AND(AV11="Gaseous"),AV18*_xlfn.XLOOKUP(AV10,'Fuel Conversion Parameters'!$A$2:$A$61,'Fuel Conversion Parameters'!$E$2:$E$61)*10^(-3)*10^(-6),"") ) ), "" ) | AY19: =IFERROR( IF(AND(AZ11="Solid"),AZ18, IF(AND(AZ11="Liquid"),AZ18*_xlfn.XLOOKUP(AZ10,'Fuel Conversion Parameters'!$A$2:$A$61,'Fuel Conversion Parameters'!$D$2:$D$61)*10^(-6), IF(AND(AZ11="Gaseous"),AZ18*_xlfn.XLOOKUP(AZ10,'Fuel Conversion Parameters'!$A$2:$A$61,'Fuel Conversion Parameters'!$E$2:$E$61)*10^(-3)*10^(-6),"") ) ), "" )
O20: =IFERROR(IF(OR(O19="", O18=""), "", O19*O18), "") | S20: =IFERROR(IF(OR(S19="", S18=""), "", S19*S18), "") | W20: =IFERROR(IF(OR(W19="", W18=""), "", W19*W18), "") | AA20: =IFERROR(IF(OR(AA19="", AA18=""), "", AA19*AA18), "") | AE20: =IFERROR(IF(OR(AE19="", AE18=""), "", AE19*AE18), "") | AI20: =IFERROR(IF(OR(AI19="", AI18=""), "", AI19*AI18), "") | AM20: =IFERROR(IF(OR(AM19="", AM18=""), "", AM19*AM18), "") | AQ20: =IFERROR(IF(OR(AQ19="", AQ18=""), "", AQ19*AQ18), "") | AU20: =IFERROR(IF(OR(AU19="", AU18=""), "", AU19*AU18), "") | AY20: =IFERROR(IF(OR(AY19="", AY18=""), "", AY19*AY18), "")
O21: =IFERROR(O20, "") | S21: =IFERROR(S20, "") | W21: =IFERROR(W20, "") | AA21: =IFERROR(AA20, "") | AE21: =IFERROR(AE20, "") | AI21: =IFERROR(AI20, "") | AM21: =IFERROR(AM20, "") | AQ21: =IFERROR(AQ20, "") | AU21: =IFERROR(AU20, "") | AY21: =IFERROR(AY20, "")
O22: Energy [MWh] | P22: =IFERROR(IF(AND(P17<>0,O23=0),"ERROR",""),"") | S22: Energy [MWh] | T22: =IFERROR(IF(AND(T17<>0,S23=0),"ERROR",""),"") | W22: Energy [MWh] | X22: =IFERROR(IF(AND(X17<>0,W23=0),"ERROR",""),"") | AA22: Energy [MWh] | AB22: =IFERROR(IF(AND(AB17<>0,AA23=0),"ERROR",""),"") | AE22: Energy [MWh] | AF22: =IFERROR(IF(AND(AF17<>0,AE23=0),"ERROR",""),"") | AI22: Energy [MWh] | AJ22: =IFERROR(IF(AND(AJ17<>0,AI23=0),"ERROR",""),"") | AM22: Energy [MWh] | AN22: =IFERROR(IF(AND(AN17<>0,AM23=0),"ERROR",""),"") | AQ22: Energy [MWh] | AR22: =IFERROR(IF(AND(AR17<>0,AQ23=0),"ERROR",""),"") | AU22: Energy [MWh] | AV22: =IFERROR(IF(AND(AV17<>0,AU23=0),"ERROR",""),"") | AY22: Energy [MWh] | AZ22: =IFERROR(IF(AND(AZ17<>0,AY23=0),"ERROR",""),"")
A23: =template_label_transfer_the_total_results_to_the_b3_fuel_energy_consumption_reporting_cell | D23: FALSE | O23: =IF(OR( O21="", P17="", Q16="Liquid fuel: please change unit of measurement, select one among m³ and L", Q16="Gaseous fuel: please change unit of measurement, select one among m³ and L", Q16="Solid fuel: please change unit of measurement, select one among Gg, t, Kg and g" ), "-", IFERROR(O21*277.778, "") ) | S23: =IF(OR( S21="", T17="", U16="Liquid fuel: please change unit of measurement, select one among m³ and L", U16="Gaseous fuel: please change unit of measurement, select one among m³ and L", U16="Solid fuel: please change unit of measurement, select one among Gg, t, Kg and g" ), "-", IFERROR(S21*277.778, "") ) | W23: =IF(OR( W21="", X17="", Y16="Liquid fuel: please change unit of measurement, select one among m³ and L", Y16="Gaseous fuel: please change unit of measurement, select one among m³ and L", Y16="Solid fuel: please change unit of measurement, select one among Gg, t, Kg and g" ), "-", IFERROR(W21*277.778, "") ) | AA23: =IF(OR( AA21="", AB17="", AC16="Liquid fuel: please change unit of measurement, select one among m³ and L", AC16="Gaseous fuel: please change unit of measurement, select one among m³ and L", AC16="Solid fuel: please change unit of measurement, select one among Gg, t, Kg and g" ), "-", IFERROR(AA21*277.778, "") ) | AE23: =IF(OR( AE21="", AF17="", AG16="Liquid fuel: please change unit of measurement, select one among m³ and L", AG16="Gaseous fuel: please change unit of measurement, select one among m³ and L", AG16="Solid fuel: please change unit of measurement, select one among Gg, t, Kg and g" ), "-", IFERROR(AE21*277.778, "") ) | AI23: =IF(OR( AI21="", AJ17="", AK16="Liquid fuel: please change unit of measurement, select one among m³ and L", AK16="Gaseous fuel: please change unit of measurement, select one among m³ and L", AK16="Solid fuel: please change unit of measurement, select one among Gg, t, Kg and g" ), "-", IFERROR(AI21*277.778, "") ) | AM23: =IF(OR( AM21="", AN17="", AO16="Liquid fuel: please change unit of measurement, select one among m³ and L", AO16="Gaseous fuel: please change unit of measurement, select one among m³ and L", AO16="Solid fuel: please change unit of measurement, select one among Gg, t, Kg and g" ), "-", IFERROR(AM21*277.778, "") ) | AQ23: =IF(OR( AQ21="", AR17="", AS16="Liquid fuel: please change unit of measurement, select one among m³ and L", AS16="Gaseous fuel: please change unit of measurement, select one among m³ and L", AS16="Solid fuel: please change unit of measurement, select one among Gg, t, Kg and g" ), "-", IFERROR(AQ21*277.778, "") ) | AU23: =IF(OR( AU21="", AV17="", AW16="Liquid fuel: please change unit of measurement, select one among m³ and L", AW16="Gaseous fuel: please change unit of measurement, select one among m³ and L", AW16="Solid fuel: please change unit of measurement, select one among Gg, t, Kg and g" ), "-", IFERROR(AU21*277.778, "") ) | AY23: =IF(OR( AY21="", AZ17="", BA16="Liquid fuel: please change unit of measurement, select one among m³ and L", BA16="Gaseous fuel: please change unit of measurement, select one among m³ and L", BA16="Solid fuel: please change unit of measurement, select one among Gg, t, Kg and g" ), "-", IFERROR(AY21*277.778, "") )
M26: =IF(P24="m³ - cubic meters",M25*1000, IF(P24="L - Liter",M25*1, "")) | Q26: =IF(T24="m³ - cubic meters",Q25*1000, IF(T24="L - Liter",Q25*1, "")) | U26: =IF(X24="m³ - cubic meters",U25*1000, IF(X24="L - Liter",U25*1, "")) | Y26: =IF(AB24="m³ - cubic meters",Y25*1000, IF(AB24="L - Liter",Y25*1, "")) | AC26: =IF(AF24="m³ - cubic meters",AC25*1000, IF(AF24="L - Liter",AC25*1, "")) | AG26: =IF(AJ24="m³ - cubic meters",AG25*1000, IF(AJ24="L - Liter",AG25*1, "")) | AK26: =IF(AN24="m³ - cubic meters",AK25*1000, IF(AN24="L - Liter",AK25*1, "")) | AO26: =IF(AR24="m³ - cubic meters",AO25*1000, IF(AR24="L - Liter",AO25*1, "")) | AS26: =IF(AV24="m³ - cubic meters",AS25*1000, IF(AV24="L - Liter",AS25*1, ""))
A28: =template_label_total_energy
A29: {=_xlfn.IFS(AND(A32="-",B32="-"),"-",AND(A32="-",B32<>"-"),B32,AND(A32<>"-",B32="-"),A32,AND(A32<>"-",B32<>"-"),A32+B32)}
A31: =template_label_total_renewable_energy | B31: =template_label_total_nonrenewable_energy
A32: {=_xlfn.IFS(AND(H9=template_label_complete, COUNTIF(E10:E19, "Renewable") = 0), "-", AND(H9=template_label_complete, COUNTIF(E10:E19, "Renewable") > 0), SUMIF(E10:E19,"Renewable",F10:F19), H9=template_label_incomplete, "-", H9="-", "-")} | B32: {=_xlfn.IFS(AND(H9=template_label_complete, COUNTIF(E10:E19, "Non-renewable") = 0), "-", AND(H9=template_label_complete, COUNTIF(E10:E19, "Non-renewable") > 0), SUMIF(E10:E19,"Non-renewable",F10:F19), H9=template_label_incomplete, "-", H9="-", "-")}
A36: =template_label_further_notes
A37: =template_label_the_converter_offers_the_possibility_of_calculating_simultaneously_up_to_10_different_types_of_fuel
A39: =template_label_energy_consumption_per_hour_in_mwh_for_solid_fuels
A40: =template_label_energy_solid_fuels
A42: =template_label_energy_consumption_per_hour_in_mwh_for_liquid_fuels
A43: =template_label_mass_liquid_fuels
A44: =template_label_energy_liquid_fuels
A46: =template_label_energy_consumption_per_hour_in_mwh_for_gaseous_fuels
A47: =template_label_mass_gaseous_fuels
A48: =template_label_energy_gaseous_fuels

Sheet Fuel Conversion Parameters
A1: Fuels | B1: State of matter | C1: Typical NCV [TJ/Gg] | D1: Typical Density [kg/L] | E1: Typical Density [kg/m³] | F1: Typical renewability state | G1: Mass | H1: Volume | I1: Energy | J1: Mass and Volume | K1: From → To | L1: g/L | M1: Kg/L | N1: t/L | O1: Gg/L | P1: g/m³ | Q1: Kg/m³ | R1: t/m³ | S1: Gg/m³ | U1: From → To | V1: J/g | W1: J/Kg | X1: J/t | Y1: J/Gg | Z1: KJ/g | AA1: KJ/Kg | AB1: KJ/t | AC1: KJ/Gg | AD1: TJ/g | AE1: TJ/Kg | AF1: TJ/t | AG1: TJ/Gg | AH1: MWh/g | AI1: MWh/Kg | AJ1: MWh/t | AK1: MWh/Gg | AM1: From → To | AN1: g | AO1: dag | AP1: hg | AQ1: Kg | AR1: t | AS1: Mg | AT1: Gg | AU1: Tg | AW1: State of matter | AX1: Typical renewability state | AY1: Source
A2: Anthracite | B2: Solid | C2: 26.7 | F2: Non-renewable | G2: Gg - Gigagram | H2: m³ - cubic meters | I2: TJ - Terajoule | J2: Gg - Gigagram | K2: g/L | L2: 1 | M2: 0.001 | N2: 1e-06 | O2: 1e-09 | P2: 1000 | Q2: 1 | R2: 0.001 | S2: 1e-06 | U2: J/g | V2: 1 | W2: 1000 | X2: 1000000 | Y2: 1000000000 | Z2: 0.001 | AA2: 1 | AB2: 1000 | AC2: 1000000 | AD2: 1e-12 | AE2: 1e-09 | AF2: 1e-06 | AG2: 0.001 | AH2: 2.78e-13 | AI2: 2.78e-10 | AJ2: 2.78e-07 | AK2: 0.000278 | AM2: g | AN2: 1 | AO2: 0.1 | AP2: 0.01 | AQ2: 0.001 | AR2: 1e-06 | AS2: 1e-06 | AT2: 1e-09 | AU2: 1e-12 | AW2: Solid | AX2: Renewable
A3: Aviation gasoline | B3: Liquid | C3: 44.3 | D3: 0.71 | F3: Non-renewable | G3: t - tonne | H3: L - Liter | I3: MWh - Megawatt hours | J3: t - tonne | K3: Kg/L | L3: 1000 | M3: 1 | N3: 0.001 | O3: 1e-06 | P3: 1000000 | Q3: 1000 | R3: 1 | S3: 0.001 | U3: J/Kg | V3: 0.001 | W3: 1 | X3: 1000 | Y3: 1000000 | Z3: 1e-06 | AA3: 0.001 | AB3: 1 | AC3: 1000 | AD3: 1e-15 | AE3: 1e-12 | AF3: 1e-09 | AG3: 1e-06 | AH3: 2.78e-16 | AI3: 2.78e-10 | AJ3: 2.78e-07 | AK3: 0.000278 | AM3: dag | AN3: 10 | AO3: 1 | AP3: 0.1 | AQ3: 0.01 | AR3: 1e-05 | AS3: 1e-05 | AT3: 1e-08 | AU3: 1e-11 | AW3: Liquid | AX3: Non-renewable
A4: Biodiesel | B4: Liquid | C4: 27 | D4: 0.85 | F4: Renewable | G4: Kg - Kilogram | J4: Kg - Kilogram | K4: t/L | L4: 1000000 | M4: 1000 | N4: 1 | O4: 0.001 | P4: 1000000000 | Q4: 1000000 | R4: 1000 | S4: 1 | U4: J/t | V4: 1e-06 | W4: 0.001 | X4: 1 | Y4: 1000 | Z4: 1e-09 | AA4: 1e-06 | AB4: 1 | AC4: 1000 | AD4: 1e-18 | AE4: 1e-15 | AF4: 1e-12 | AG4: 1e-09 | AH4: 2.78e-19 | AI4: 2.78e-13 | AJ4: 2.78e-10 | AK4: 2.78e-07 | AM4: hg | AN4: 100 | AO4: 10 | AP4: 1 | AQ4: 0.1 | AR4: 0.0001 | AS4: 0.0001 | AT4: 1e-07 | AU4: 1e-10 | AW4: Gaseous
A5: Biogasoline | B5: Liquid | C5: 27 | D5: 0.75 | F5: Renewable | G5: g - gram | J5: g - gram | K5: Gg/L | L5: 1000000000 | M5: 1000000 | N5: 1000 | O5: 1 | P5: 1000000000000 | Q5: 1000000000 | R5: 1000000 | S5: 1000 | U5: J/Gg | V5: 1e-09 | W5: 1e-06 | X5: 0.001 | Y5: 1 | Z5: 1e-12 | AA5: 1e-06 | AB5: 0.001 | AC5: 1 | AD5: 1e-21 | AE5: 1e-18 | AF5: 1e-15 | AG5: 1e-12 | AH5: 2.78e-22 | AI5: 2.78e-16 | AJ5: 2.78e-13 | AK5: 2.78e-10 | AM5: Kg | AN5: 1000 | AO5: 100 | AP5: 10 | AQ5: 1 | AR5: 0.001 | AS5: 0.001 | AT5: 1e-06 | AU5: 1e-09 | AY5: a.
A6: Bitumen | B6: Liquid | C6: 40.2 | D6: 1.035 | F6: Non-renewable | J6: m³ - cubic meters | K6: g/m³ | L6: 0.001 | M6: 1e-06 | N6: 1e-09 | O6: 1e-12 | P6: 1 | Q6: 0.001 | R6: 1e-06 | S6: 1e-09 | U6: KJ/g | V6: 1000 | W6: 1000000 | X6: 1000000000 | Y6: 1000000000000 | Z6: 1 | AA6: 1000 | AB6: 1000000 | AC6: 1000000000 | AD6: 1e-09 | AE6: 1e-06 | AF6: 0.001 | AG6: 1 | AH6: 2.78e-10 | AI6: 2.78e-07 | AJ6: 0.000278 | AK6: 0.278 | AM6: t | AN6: 1000000 | AO6: 100000 | AP6: 10000 | AQ6: 1000 | AR6: 1 | AS6: 1 | AT6: 0.001 | AU6: 1e-06 | AY6: b.
A7: Blast furnace gas | B7: Gaseous | C7: 2.47 | E7: 1.25 | F7: Non-renewable | J7: L - Liter | K7: Kg/m³ | L7: 1 | M7: 0.001 | N7: 1e-06 | O7: 1e-09 | P7: 1000 | Q7: 1 | R7: 0.001 | S7: 1e-06 | U7: KJ/Kg | V7: 1 | W7: 1000 | X7: 1000000 | Y7: 1000000000 | Z7: 0.001 | AA7: 1 | AB7: 1000 | AC7: 1000000 | AD7: 1e-12 | AE7: 1e-09 | AF7: 1e-06 | AG7: 0.001 | AH7: 2.78e-13 | AI7: 2.78e-10 | AJ7: 2.78e-07 | AK7: 0.000278 | AM7: Mg | AN7: 1000000 | AO7: 100000 | AP7: 10000 | AQ7: 1000 | AR7: 1 | AS7: 1 | AT7: 0.001 | AU7: 1e-06 | AY7: c.
A8: Brown coal briquettes | B8: Solid | C8: 20.7 | F8: Non-renewable | K8: t/m³ | L8: 1000 | M8: 1 | N8: 0.001 | O8: 0.001 | P8: 1000000 | Q8: 1000 | R8: 1 | S8: 0.001 | U8: KJ/t | V8: 0.001 | W8: 1 | X8: 1000 | Y8: 1000000 | Z8: 1e-06 | AA8: 0.001 | AB8: 1 | AC8: 1000 | AD8: 1e-15 | AE8: 1e-12 | AF8: 1e-09 | AG8: 1e-06 | AH8: 2.78e-16 | AI8: 2.78e-10 | AJ8: 2.78e-07 | AK8: 0.000278 | AM8: Gg | AN8: 1000000000 | AO8: 100000000 | AP8: 10000000 | AQ8: 1000000 | AR8: 1000 | AS8: 1000 | AT8: 1 | AU8: 0.001
A9: Butane and isomers | B9: Gaseous | C9: 45.57 | E9: 2.5 | F9: Non-renewable | K9: Gg/m³ | L9: 1000000 | M9: 1000 | N9: 1 | O9: 0.001 | P9: 1000000000 | Q9: 1000000 | R9: 1000 | S9: 1 | U9: KJ/Gg | V9: 1e-06 | W9: 0.001 | X9: 1 | Y9: 1000 | Z9: 1e-09 | AA9: 1e-06 | AB9: 1 | AC9: 1000 | AD9: 1e-18 | AE9: 1e-15 | AF9: 1e-12 | AG9: 1e-09 | AH9: 2.78e-19 | AI9: 2.78e-13 | AJ9: 2.78e-10 | AK9: 2.78e-07 | AM9: Tg | AN9: 1000000000000 | AO9: 100000000000 | AP9: 10000000000 | AQ9: 1000000000 | AR9: 1000000 | AS9: 1000000 | AT9: 1000 | AU9: 1 | AY9: d.
A10: Coke oven coke & lignite coke | B10: Solid | C10: 28.2 | F10: Non-renewable | U10: TJ/t | V10: 1000000 | W10: 1000000000 | X10: 1000000000000 | Y10: 1e+15 | Z10: 1000 | AA10: 1000000 | AB10: 1000000000 | AC10: 1000000000000 | AD10: 1e-06 | AE10: 0.001 | AF10: 1 | AG10: 1000 | AH10: 2.778e-07 | AI10: 0.0002777778 | AJ10: 0.27777778 | AK10: 277.77778
A11: Coke oven gas | B11: Gaseous | C11: 38.7 | E11: 0.475 | F11: Non-renewable | U11: TJ/Gg | V11: 1000 | W11: 1000000 | X11: 1000000000 | Y11: 1000000000000 | Z11: 1 | AA11: 1000 | AB11: 1000000 | AC11: 1000000000 | AD11: 1e-09 | AE11: 1e-06 | AF11: 0.001 | AG11: 1 | AH11: 2.78e-10 | AI11: 2.778e-07 | AJ11: 0.0002777778 | AK11: 0.27777778 | AY11: e.
A12: Coking coal | B12: Solid | C12: 28.2 | F12: Non-renewable | U12: MWh/g | V12: 3600000000000 | W12: 3.6e+15 | X12: 3.6e+18 | Y12: 3.6e+21 | Z12: 3600000000 | AA12: 3600000000000 | AB12: 3.6e+15 | AC12: 3.6e+18 | AD12: 3.6 | AE12: 3600 | AF12: 3600000 | AG12: 3600000000 | AH12: 1 | AI12: 1000 | AJ12: 1000000 | AK12: 1000000000
A13: Crude oil and distillates | B13: Liquid | C13: 42.3 | D13: 0.8 | F13: Non-renewable | U13: MWh/Kg | V13: 3600000000 | W13: 3600000000000 | X13: 3.6e+15 | Y13: 3.6e+18 | Z13: 3600000 | AA13: 3600000000 | AB13: 3600000000000 | AC13: 3.6e+15 | AD13: 0.0036 | AE13: 3.6 | AF13: 3600 | AG13: 3600000 | AH13: 0.001 | AI13: 1 | AJ13: 1000 | AK13: 1000000
A14: Ethane | B14: Gaseous | C14: 46.4 | E14: 1.3 | F14: Non-renewable
A15: Gas coke | B15: Gaseous | C15: 28.2 | E15: 0.54 | F15: Non-renewable | AY15: f.
A16: Gas/Diesel oil | B16: Liquid | C16: 43 | D16: 0.84 | F16: Non-renewable
A17: Jet gasoline | B17: Liquid | C17: 44.3 | D17: 0.81 | F17: Non-renewable | AY17: g.
A18: Jet kerosene | B18: Liquid | C18: 44.1 | D18: 0.79 | F18: Non-renewable
A19: Kerosene | B19: Liquid | C19: 43.8 | D19: 0.8 | F19: Non-renewable
A20: Landfill gas | B20: Gaseous | C20: 50.4 | E20: 0.9 | F20: Renewable
A21: Lignite | B21: Solid | C21: 11.9 | F21: Non-renewable
A22: Liquefied Petroleum Gases (LPG) | B22: Liquid | C22: 47.3 | D22: 0.54 | F22: Non-renewable
A23: Lubricants | B23: Liquid | C23: 40.2 | D23: 1 | F23: Non-renewable
A24: Methane | B24: Gaseous | C24: 50 | E24: 0.67 | F24: Non-renewable | AY24: h.
A25: Motor gasoline/Petrol | B25: Liquid | C25: 44.3 | D25: 0.74 | F25: Non-renewable
A26: Municipal wastes (biomass fraction) | B26: Solid | C26: 11.6 | F26: Renewable
A27: Municipal wastes (non-biomass fraction) | B27: Solid | C27: 10 | F27: Non-renewable
A28: Naphtha | B28: Liquid | C28: 44.5 | D28: 0.77 | F28: Non-renewable
A29: Natural gas | B29: Gaseous | C29: 48 | E29: 0.7 | F29: Non-renewable
A30: Natural gas liquids (NGL) | B30: Liquid | C30: 44.2 | D30: 0.47 | F30: Non-renewable
A31: Oil shale and tar sands | B31: Liquid | C31: 8.9 | D31: 0.95 | F31: Non-renewable | AY31: i.
A32: Orimulsion | B32: Liquid | C32: 27.5 | D32: 1.13 | F32: Non-renewable | AY32: j.
A33: Oxygen steel furnace gas | B33: Gaseous | C33: 7.06 | E33: 1.33 | F33: Non-renewable | AY33: k.
A34: Paraffin waxes | B34: Solid | C34: 40.2 | F34: Non-renewable
A35: Patent fuel | B35: Solid | C35: 20.7 | F35: Non-renewable
A36: Peat | B36: Solid | C36: 9.76 | F36: Non-renewable
A37: Petroleum coke | B37: Solid | C37: 32.5 | F37: Non-renewable
A38: Propane | B38: Gaseous | C38: 46.32 | E38: 1.9 | F38: Non-renewable | AY38: l.
A39: Refinery feedstocks | B39: Liquid | C39: 43 | D39: 0.825 | F39: Non-renewable | AY39: m.
A40: Refinery Gas | B40: Gaseous | C40: 49.5 | E40: 0.88 | F40: Non-renewable | AY40: n.
A41: Residual fuel oil | B41: Liquid | C41: 40.4 | D41: 0.94 | F41: Non-renewable
A42: Shale oil (liquid) | B42: Liquid | C42: 38.1 | D42: 1 | F42: Non-renewable
