Workbook
Name AddressOfSite: 'General Information'!$D$404:$D$503
Name AmountOfEmissionsTable: 'Environmental Disclosures'!$D$80:$K$179
Name AmountOfEmissionToAir: 'Environmental Disclosures'!$G$80:$I$179
Name AmountOfEmissionToAir_unit: 'Environmental Disclosures'!$C$78
Name AmountOfEmissionToSoil: 'Environmental Disclosures'!$K$80:$K$179
Name AmountOfEmissionToSoil_unit: 'Environmental Disclosures'!$C$78
Name AmountOfEmissionToWater: 'Environmental Disclosures'!$J$80:$J$179
Name AmountOfEmissionToWater_unit: 'Environmental Disclosures'!$C$78
Name AmountOfWaterWithdrawnAtSitesLocatedInAreasOfHighWaterStress: 'Environmental Disclosures'!$D$304
Name AreaOfSiteInBiodiversitySensitiveArea: 'Environmental Disclosures'!$G$188:$I$287
Name AreaOfSiteInBiodiversitySensitiveArea_unit: 'Environmental Disclosures'!$C$186
Name Assets: 'General Information'!$E$280
Name AverageNumberOfAnnualTrainingHoursPerFemaleEmployee: 'Social Disclosures'!$D$158
Name AverageNumberOfAnnualTrainingHoursPerMaleEmployee: 'Social Disclosures'!$D$157
Name AverageNumberOfAnnualTrainingHoursPerNonReportedGenderEmployee: 'Social Disclosures'!$D$160
Name AverageNumberOfAnnualTrainingHoursPerOtherGenderEmployee: 'Social Disclosures'!$D$159
Name BaselineYearMember: 'Environmental Disclosures'!$G$21
Name BasisForPreparation: 'General Information'!$E$122
Name BasisForReporting: 'General Information'!$E$177
Name BreakdownOfAnnualMassFlowOfRelevantMaterialsUsedByTheUndertakingHypercube: 'Environmental Disclosures'!$C$435:$I$534
Name BreakdownOfEnergyConsumptionAxis: 'Environmental Disclosures'!$C$12:$F$14
Name BreakdownOfEnergyConsumptionTable: 'Environmental Disclosures'!$G$12:$K$14
Name CityOfSite: 'General Information'!$F$404:$F$503
Name CountryOfEmploymentContractAxis: 'Social Disclosures'!$C$29:$D$128
Name CountryOfPrimaryOperationsAndLocationOfSignificantAssets: 'General Information'!$E$285
Name CountryOfSite: 'General Information'!$G$404:$G$503
Name DateOfAdoptionOfTransitionPlanForUndertakingNotHavingAdoptedTransitionPlanYet: 'Environmental Disclosures'!$D$62
Name DescriptionOfActionsTakeToAddressTheConfirmedIncidents: 'Social Disclosures'!$D$192
Name DescriptionOfATargetRelatedToAPolicy: 'General Information'!$E$520
Name DescriptionOfATransitionPlanForClimateChangeMitigationIncludingAnExplanationOfHowItIsContributingToReduceGhgEmissions: 'Environmental Disclosures'!$D$58
Name DescriptionOfClimateRelatedHazardsAndClimateRelatedTransitionEvents: 'Environmental Disclosures'!$E$540
Name DescriptionOfHowCircularEconomyPrinciplesAreApplied: 'Environmental Disclosures'!$D$317
Name DescriptionOfKeyElementsOfStrategyThatRelatesToOrAffectsSustainabilityIssues: 'General Information'!$E$529
Name DescriptionOfLimitsToTheDistributionOfProfitsConnectedToTheMutualisticNatureOrToTheNatureOfTheActivitiesConsistingInServicesOfGeneralEconomicInterestSGEI: 'General Information'!$D$516
Name DescriptionOfMainBusinessRelationships: 'General Information'!$E$527
Name DescriptionOfPracticesPoliciesAndOrFutureInitiatives: 'General Information'!$E$519
Name DescriptionOfSignificantGroupsOfProductsAndOrServicesOffered: 'General Information'!$E$525
Name DescriptionOfSignificantMarketsTheUndertakingOperatesIn: 'General Information'!$E$526
Name DescriptionOfSustainabilityRelatedCertificationsOrLabels: 'General Information'!$E$395
Name DescriptionOfTheEffectiveParticipationOfWorkersUsersOrOtherInterestedPartiesOrCommunitiesInGovernance: 'General Information'!$D$514
Name DisclosureOfAnyOtherEnvironmentalAndOrEntitySpecificEnvironmentalDisclosures: 'Environmental Disclosures'!$C$548
Name DisclosureOfAnyOtherGeneralAndOrEntitySpecificInformation: 'General Information'!$C$533
Name DisclosureOfAnyOtherGovernanceAndOrEntitySpecificGovernanceDisclosures: 'Governance Disclosures'!$C$38
Name DisclosureOfAnyOtherSocialAndOrEntitySpecificSocialDisclosures: 'Social Disclosures'!$C$200
Name DisclosureOfHowItHasAssessedTheExposureAndSensitivityOfItsAssetsActivitiesAndValueChainToTheseHazardsAndTransitionEvents: 'Environmental Disclosures'!$E$541
Name DisclosureOfListOfMainActionsTheEntitySeeksInOrderToAchieveItsTargets: 'Environmental Disclosures'!$C$52
Name DisclosureOfWhetherItHasUndertakenClimateChangeAdaptationActionsForAnyClimateRelatedHazardsAndTransitionEvents: 'Environmental Disclosures'!$E$543
Name EmployeeCountingMethodology: 'General Information'!$E$283
Name EmployeesReceivePayEqualOrAboveMinimumWageDeterminedByNationalLawOrCollectiveAgreement: 'Social Disclosures'!$D$147
Name EmployeeTurnoverRate: 'Social Disclosures'!$D$137
Name EnergyConsumptionFromElectricity_NonRenewableEnergyMember: 'Environmental Disclosures'!$J$12
Name EnergyConsumptionFromElectricity_RenewableEnergyMember: 'Environmental Disclosures'!$G$12
Name EnergyConsumptionFromElectricity_TotalRenewableAndNonRenewableEnergyMember: 'Environmental Disclosures'!$K$12
Name EnergyConsumptionFromFuels_NonRenewableEnergyMember: 'Environmental Disclosures'!$J$14
Name EnergyConsumptionFromFuels_RenewableEnergyMember: 'Environmental Disclosures'!$G$14
Name EnergyConsumptionFromFuels_TotalRenewableAndNonRenewableEnergyMember: 'Environmental Disclosures'!$K$14
Name EnergyConsumptionFromSelfGeneratedElectricity_NonRenewableEnergyMember: 'Environmental Disclosures'!$J$13
Name EnergyConsumptionFromSelfGeneratedElectricity_RenewableEnergyMember: 'Environmental Disclosures'!$G$13
Name EnergyConsumptionFromSelfGeneratedElectricity_TotalRenewableAndNonRenewableEnergyMember: 'Environmental Disclosures'!$K$13
Name enum_B2: 'Enumeration Lists'!$P$2:$P$4

Sheet Language Selection
G5: =template_language_selection -> Language selection
G6: =template_label_select_template_display_language -> VSME Digital Template enable translations into different EU languages. Please select the language from the dropdown below.
G7: English - Official [en] | Q7: ¬

Sheet Introduction
B1: =template_label_version -> Version: | C1: 1.2.0
B2: =template_label_publication_date -> Publication date: | C2: 46080
B3: {=IF(ISERROR(CELL("filename",A1)),template_label_warning_microsoft_excel,"")}
B10: =template_label_taxonomy_entry_point -> Taxonomy entry point: | C10: https://xbrl.efrag.org/taxonomy/vsme/2026-02-01/vsme-all.xsd
B11: =template_label_title_of_report -> Main title of the report | C11: =template_label_main_title_of_report_text -> Sustainability Report
B12: =template_label_subtitle_of_report -> Subtitle of the report | C12: =template_label_subtitle_of_report_text -> Prepared in accordance with the Voluntary Sustainability Reporting Standard for small and medium-sized undertakings (VSME), released by the European Commission on 30 July 2025.
B13: =template_label_vsme_digital_template -> VSME Digital Template
B14: =template_label_the_purpose_of_this_digital_template_is_to_illustrate_how_vsme_reporting_can_be_implemented_in_a_digital_template -> The purpose of this digital template is to illustrate how VSME reporting can be implemented in a digital template. The template reflects the VSME Recommendation as published by the European Commission on 30 July 2025. The template is accompanied by a digital VSME XBRL taxonomy, which represents the digital data model of the disclosures and is available on EFRAG's website. The VSME requires disclosure of comparative information on metrics (paragraph 12). This template enables reporting for one reporting period only. Therefore, it might be used for reporting in the first year only. It is expected that reporting solutions will enable the roll-forward of reporting periods, which would automatically provide the necessary comparative information. This template can be used for data entry and validation. By using an XBRL Converter on EFRAG's website, it can be saved as an XBRL report, in a free and open data format. Excel-named ranges are used to extract the disclosures. Value cells that are empty and do not have any value (neither text nor a number) will not be considered as reported and will not be included in the XBRL report when using the Excel-to-XBRL converter. A few drop-down selection menus in the VSME have more than 100 entries (e.g. the NACE codes under B1, the list of pollutants under B4, the list of wastes under B7). In order to search in the list, users can simply start typing search keywords in the cell. If a security warning is shown, please "Enable Content" in order to allow automatic calculation of GPS coordinates for the list of sites under B1. No content other than the address entered will be sent to the internet and the contents shared with the provider can be found in the Nominatim Usage Policy (Geocoding Policy) and Privacy Policy. All materials developed by the EFRAG Secretariat are released for free and as open source (MIT license), which will enable any stakeholder to further enhance them and integrate them into commercial solutions. However, respecting the license conditions, the reference to EFRAG must be mentioned by the providers of those commercial solutions. It's possible to consult the MIT License in the specific sheet. If you wish to raise an issue with the VSME Digital Template or the Digital Template to XBRL Converter, please do so by creating an issue in the GitHub project.
B17: =template_label_how_to_use_it -> How to use it:
B18: =template_label_0_provide_information_that_is_mandatory_in_order_to_generate_the_vsme_and_xbrl_report -> 0. Provide information that is mandatory in order to generate the VSME and XBRL Report.
B19: =template_label_1_fill_in_the_disclosures_on_the_four_worksheets -> 1. Fill in the disclosures on the four worksheets (General Information, Environmental Disclosures, Social Disclosures, Governance Disclosures) in the white cells framed by a black border. Do not enter information outside of those cells. Searching in drop-downs can be done by typing into the cell. Hints (input messages) are shown in several cells when selecting them.
B20: =template_label_2_find_more_information_on_the_actual_disclosure_requirements_in_the_vsme_standard -> 2. Find more information on the actual disclosure requirements in the VSME Standard and the related guidance linked to each cell. Additional or entity-specific disclosures can be provided in each text box at the end of each worksheet.
B21: =template_label_3_for_open_tables_like_the_list_of_subsidizers_sites_please_expand_the_groups_by_clicking_the_plus -> 3. For open tables like the List of subsidiaries/sites, please expand the groups by clicking the plus [+] icon on the left side. If more rows are needed, they can be added by inserting them between the first and last row. The row IDs in open tables must remain unique per table.
B22: =template_label_4_validate_the_data_entered_by_checking_the_validation_status -> 4. Validate the data entered by checking the validation status. The report is considered incomplete or erroneous if the validation fails, which might result in an invalid XBRL report.
B23: =template_label_5_convert_this_template_to_an_inline_xbrl_report -> 5. Convert this template to an Inline XBRL report (or XBRL-JSON, XBRL-CSV), using the online converter: https://xbrl.efrag.org/convert/. Pay attention to the XBRL validation performed by the validator.
B24: =template_label_6_the_undertaking_may_also_upload_the_report_to_public_repositories_or_a_webpage -> 6. The undertaking may also upload the report to public repositories or a webpage.
B26: =template_label_cell_background_color_index -> Cell background color index:
B27: =template_label_general_principles -> General Principles | C27: =template_label_indicates_that_the_disclosure_is_from_the_general_principles_of_the_vsme -> Indicates that the disclosure is from the general principles of the VSME.
B28: =template_label_basic_module -> Basic Module | C28: =template_label_indicates_that_the_disclosure_is_from_the_vsme_basic_module -> Indicates that the disclosure is from the VSME Basic Module.
B29: =template_label_comprehensive_module -> Comprehensive Module | C29: =template_label_indicates_that_the_disclosure_is_from_the_vsme_comprehensive_module -> Indicates that the disclosure is from the VSME Comprehensive Module.
C30: =template_label_indicates_that_the_cell_is_automatically_calculated_and_that_no_data_entry_is_required -> Indicates that the cell is automatically calculated and that no data entry is required.
C31: =template_label_indicates_that_the_datapoint_often_a_condition_will_not_be_included_in_the_vsme_and_digital_xbrl_report -> Indicates that the datapoint (often a condition) will not be included in the VSME and digital XBRL report. These cells are provided to facilitate the completion of the disclosure as they either trigger the applicability of the disclosure or they enable the automatic calculation of the disclosure. If the yellow cells are not being used to calculate a value, the total that is to be reported can be entered manually overwriting by the formula.
C32: =template_label_indicates_that_no_data_entry_is_required_unless_certain_logics_are_selected_in_the_disclosure_itself -> Indicates that no data entry is required unless certain logics are selected in the disclosure itself. When one of these logics is selected, then this cell will turn white.
B33: =template_label_validation_missing_value_error_velue_inconsistency_invalid_url -> Validation MISSING VALUE/ERROR/VALUE INCONSISTENCY/INVALID URL | C33: =template_label_indicates_that_either_data_entry_is_incorrect_in_terms_of_format_or_that_certain_information -> Indicates that either data entry is incorrect in terms of format or that certain information is missing in order to correctly report on the disclosure.
B34: Validation OK | C34: =template_label_indicates_that_data_entry_is_ok_and_the_undertaking_can_proceed_to_the_next_disclosure -> Indicates that data entry is OK and the undertaking can proceed to the next disclosure.
B35: =template_label_validation_classified_or_sensitive_information -> Validation CLASSIFIED OR SENSITIVE INFORMATION | C35: =template_label_indicates_that_the_undertaking_has_omitted_the_data_entry_as_it_is_deemed_to_be_classified_or_sensitive_information -> Indicates that the undertaking has omitted the data entry as it is deemed to be classified or sensitive information.
C36: =template_label_no_value_can_be_entered_in_the_cell -> No value can be entered in the cell.
B37: [+] | C37: =template_label_lists_can_be_expanded_using_the_plus_button_on_the_left -> Lists can be expanded using the plus [+] button on the left. If the number of rows is not sufficient, additional rows can be added by right clicking the second row and selecting "Insert row".
B43: =template_label_efrag_is_funded_by_the_european_union_through_the_single_market_programme -> EFRAG is funded by the European Union through the Single Market Programme in which the EEA-EFTA countries (Norway, Iceland and Liechtenstein), as well as Kosovo participate. Any views and opinions expressed are however those of the author(s) only and do not necessarily reflect those of the European Union, the European Commission or of countries that participate in the Single Market Programme. Neither the European Union, the European Commission nor countries participating in the Single market Programme can be held responsible for them. © 2025 EFRAG All rights reserved.
B44: =template_label_reproduction_and_use_rights_are_strictly_limited -> Reproduction and use rights are strictly limited. For further details please contact efragsecretariat@efrag.org

Sheet Table of Contents & Validation
B2: =template_label_table_of_contents_validation -> Table of Contents | C2: =template_label_overall_validation_status_validation -> Overall Validation Status | D2: =template_classified_or_sensitive_information -> Classified or sensitive information
B3: =template_label_contents_grouping_follows_templates_framework -> Contents grouping follows template's framework | C3: {=IF(SUMPRODUCT(--((C5:C70<>template_label_ok)*(C5:C70<>"-")*(C5:C70<>"")*(C5:C70<>template_label_classified_or_sensitive_information))) > 0, template_label_incomplete, template_label_complete)} -> INCOMPLETE | D3: =template_filling_sensitive_checkboxes -> Filling the checkboxes below will fill automatically the list of omitted disclosures in B1 (from row 123 to 172 within General Information sheet)
C4: =template_label_specific_content_validation_status_validation -> Specific Content Validation Status
B5: =template_label_general_information_validation -> General Information
B6: =template_label_information_on_the_report_necessary_for_xbrl_validation -> Information on the report necessary for XBRL | C6: =IF( AND( COUNTIF('General Information'!F3:F12, template_label_missing_value) > 0, COUNTIF('General Information'!F3:F12, template_label_error) = 0 ), template_label_missing_value, IF( AND( COUNTIF('General Information'!F3:F12, template_label_error) > 0, COUNTIF('General Information'!F3:F12, template_label_missing_value) = 0 ), template_label_value_inconsistency, IF( AND( COUNTIF('General Information'!F3:F12, template_label_error) > 0, COUNTIF('General Information'!F3:F12, template_label_missing_value) > 0 ), template_label_error_plus_value_inconsistency, template_label_ok ) ) ) -> MISSING VALUE
B7: =template_label_information_on_previous_reporting_period_validation -> Information on previous reporting period | C7: =IF(COUNTIF('General Information'!F18:F119, template_label_missing_value) > 0, template_label_missing_value, IF(COUNTIF('General Information'!F18:F119, template_label_invalid_url ) > 0, template_label_invalid_url, IF(COUNTIF('General Information'!F18:F119, template_label_value_inconsistency ) > 0, template_label_value_inconsistency, IF(COUNTIF('General Information'!F18:F119, template_label_ok) > 0, template_label_ok, "-")))) -> -
B8: =template_label_basic_module_validation -> Basic Module
B9: =template_label_general_information_validation -> General Information
B10: =template_label_b1_basis_for_preparation_validation -> B1 - Basis for Preparation | C10: =IF(D10=TRUE,template_label_classified_or_sensitive_information, IF(COUNTIF(C11:C15,template_label_error_plus_missing_value_plus_value_inconsistency)>0,template_label_error_plus_missing_value_plus_value_inconsistency, IF(COUNTIF(C11:C15,template_label_error_plus_value_inconsistency)>0,template_label_error_plus_value_inconsistency, IF(COUNTIF(C11:C15,template_label_error_plus_missing_value)>0,template_label_error_plus_missing_value, IF(COUNTIF(C11:C15,template_label_error)>0,template_label_error, IF(COUNTIF(C11:C15,template_label_missing_value_plus_value_inconsistency)>0,template_label_missing_value_plus_value_inconsistency, IF(COUNTIF(C11:C15,template_label_value_inconsistency)>0,template_label_value_inconsistency, IF(COUNTIF(C11:C15,template_label_missing_value)>0,template_label_missing_value, IF(COUNTIF(C11:C15,template_label_ok)=ROWS(C11:C15),template_label_ok, IF(COUNTIF(C11:C15,"-")=ROWS(C11:C15),"-", IF(AND(COUNTIF(C11:C15,template_label_ok)>0, COUNTIF(C11:C15,template_label_error_plus_missing_value_plus_value_inconsistency)=0, COUNTIF(C11:C15,template_label_error_plus_value_inconsistency)=0, COUNTIF(C11:C15,template_label_error_plus_missing_value)=0, COUNTIF(C11:C15,template_label_error)=0, COUNTIF(C11:C15,template_label_missing_value_plus_value_inconsistency)=0, COUNTIF(C11:C15,template_label_value_inconsistency)=0, COUNTIF(C11:C15,template_label_missing_value)=0, OR(COUNTIF(C11:C15,template_label_missing_value)=0, COUNTIF(C11:C15,template_label_missing_value)>0)), template_label_ok, "-"))))))))) )) -> MISSING VALUE | D10: =IF(COUNTIF(D12:D15,TRUE)=ROWS(D12:D15),TRUE,FALSE) -> FALSE
B11: =template_label_b1_basis_for_preparation -> B1 - Basis for Preparation & Module | C11: =IF(COUNTIF('General Information'!F122,template_label_missing_value)>0,template_label_missing_value, IF(COUNTIF('General Information'!F122,template_label_ok)>0,template_label_ok,"-")) -> MISSING VALUE
B12: =template_label_b1_other_undertakings_general_information -> B1 - Other undertaking's general information | C12: =IF(D12=TRUE, template_label_classified_or_sensitive_information,IF( AND( COUNTIF('General Information'!F177:F285,template_label_missing_value)>0, COUNTIF('General Information'!F177:F285,template_label_value_inconsistency)=0, COUNTIF('General Information'!F177:F285,template_label_error)=0 ), template_label_missing_value, IF( AND( COUNTIF('General Information'!F177:F285,template_label_value_inconsistency)>0, COUNTIF('General Information'!F177:F285,template_label_missing_value)=0, COUNTIF('General Information'!F177:F285,template_label_error)=0 ), template_label_value_inconsistency, IF( AND( COUNTIF('General Information'!F177:F285,template_label_value_inconsistency)=0, COUNTIF('General Information'!F177:F285,template_label_missing_value)=0, COUNTIF('General Information'!F177:F285,template_label_error)>0 ), template_label_error, IF( AND( COUNTIF('General Information'!F177:F285,template_label_value_inconsistency)>0, COUNTIF('General Information'!F177:F285,template_label_missing_value)>0, COUNTIF('General Information'!F177:F285,template_label_error)=0 ), template_label_missing_value_plus_value_inconsistency, IF( AND( COUNTIF('General Information'!F177:F285,template_label_value_inconsistency)=0, COUNTIF('General Information'!F177:F285,template_label_missing_value)>0, COUNTIF('General Information'!F177:F285,template_label_error)>0 ), template_label_error_plus_missing_value, IF( AND( COUNTIF('General Information'!F177:F285,template_label_value_inconsistency)>0, COUNTIF('General Information'!F177:F285,template_label_missing_value)=0, COUNTIF('General Information'!F177:F285,template_label_error)>0 ), template_label_error_plus_value_inconsistency, IF( AND( COUNTIF('General Information'!F177:F285,template_label_value_inconsistency)>0, COUNTIF('General Information'!F177:F285,template_label_missing_value)>0, COUNTIF('General Information'!F177:F285,template_label_error)>0 ), template_label_error_plus_missing_value_plus_value_inconsistency, IF( AND( COUNTIF('General Information'!F177:F285,template_label_value_inconsistency)=0, COUNTIF('General Information'!F177:F285,template_label_missing_value)=0, COUNTIF('General Information'!F177:F285,template_label_error)=0, COUNTIF('General Information'!F177:F285,template_label_ok)>0 ), template_label_ok, "-" ))))))))) -> - | D12: FALSE | E12: =IF(AND(C12=template_label_classified_or_sensitive_information,COUNTIF('General Information'!E177:E285,"<>")>0),template_label_information_on_sensitive_information_before_converting,"")
B13: =template_label_b1_list_of_subsidiaries -> B1 - List of subsidiaries | C13: =IF(D13=TRUE, template_label_classified_or_sensitive_information, IF( COUNTIF('General Information'!F290:F389, template_label_missing_value) > 0, template_label_missing_value, IF( COUNTIF('General Information'!F290:F389, template_label_ok) > 0, template_label_ok, "-" ) ) ) -> - | D13: FALSE | E13: =IF(AND(C13=template_label_classified_or_sensitive_information,COUNTIF('General Information'!D404:G503,"<>")>0),template_label_information_on_sensitive_information_before_converting,"")
B14: =template_label_b1_disclosure_of_sustainability_related_certification_or_label -> B1 - Disclosure of sustainability-related certification(s) or label(s) | C14: =IF(D14=TRUE, template_label_classified_or_sensitive_information, IF( COUNTIF('General Information'!I395, template_label_missing_value) > 0, template_label_missing_value, IF( COUNTIF('General Information'!I395, template_label_ok) > 0, template_label_ok, "-" ) ) ) -> - | D14: FALSE | E14: =IF(AND(C14=template_label_classified_or_sensitive_information,'General Information'!E394=TRUE),template_label_information_on_sensitive_information_before_converting,"")
B15: =template_label_b1_list_of_site -> B1 - List of site(s) | C15: =IF(D15=TRUE, template_label_classified_or_sensitive_information, IF( COUNTIF('General Information'!I404:I503, template_label_missing_value) > 0, template_label_missing_value, IF( COUNTIF('General Information'!I404:I503, template_label_ok) > 0, template_label_ok, "-" ) ) ) -> - | D15: FALSE | E15: =IF(AND(C15=template_label_classified_or_sensitive_information,COUNTIF('General Information'!D404:G503,"<>")>0),template_label_information_on_sensitive_information_before_converting,"")
B16: =template_label_b2_practices_policies_and_future_initiatives_for_transitioning_towards_a_more_sustainable_economy -> B2 - Practices, policies and future initiatives for transitioning towards a more sustainable economy | C16: =IF(D16=TRUE, template_label_classified_or_sensitive_information, IF( COUNTIF('General Information'!P510, template_label_missing_value) > 0, template_label_missing_value, IF( COUNTIF('General Information'!P510, template_label_ok) > 0, template_label_ok, "-" ) ) ) -> - | D16: FALSE | E16: =IF(AND(C16=template_label_classified_or_sensitive_information,'General Information'!C510=TRUE),template_label_information_on_sensitive_information_before_converting,"")
B17: =template_label_b2_cooperative_specific_disclosures -> B2 - Cooperative specific disclosures | C17: {=IF(D17=TRUE, template_label_classified_or_sensitive_information, IF(OR('General Information'!E514:E516=template_label_ok),template_label_ok,"-") )} -> - | D17: FALSE | E17: =IF(AND(C17=template_label_classified_or_sensitive_information,COUNTIF('General Information'!D514:D516,"<>")>0),template_label_information_on_sensitive_information_before_converting,"")
B18: =template_label_environmental_disclosures_validation -> Environmental Disclosures
B19: =template_label_b3_energy_and_greenhouse_gas_emissions_validation -> B3 - Energy and greenhouse gas emissions | C19: =IF(D19=TRUE,template_label_classified_or_sensitive_information, IF(COUNTIF(C20:C23,template_label_error_plus_missing_value_plus_value_inconsistency)>0,template_label_error_plus_missing_value_plus_value_inconsistency, IF(COUNTIF(C20:C23,template_label_error_plus_value_inconsistency)>0,template_label_error_plus_value_inconsistency, IF(COUNTIF(C20:C23,template_label_error_plus_missing_value)>0,template_label_error_plus_missing_value, IF(COUNTIF(C20:C23,template_label_error)>0,template_label_error, IF(COUNTIF(C20:C23,template_label_missing_value_plus_value_inconsistency)>0,template_label_missing_value_plus_value_inconsistency, IF(COUNTIF(C20:C23,template_label_value_inconsistency)>0,template_label_value_inconsistency, IF(COUNTIF(C20:C23,template_label_missing_value)>0,template_label_missing_value, IF(COUNTIF(C20:C23,template_label_ok)=ROWS(C20:C23),template_label_ok, IF(COUNTIF(C20:C23,"-")=ROWS(C20:C23),"-", IF(AND(COUNTIF(C20:C23,template_label_ok)>0, COUNTIF(C20:C23,template_label_error_plus_missing_value_plus_value_inconsistency)=0, COUNTIF(C20:C23,template_label_error_plus_value_inconsistency)=0, COUNTIF(C20:C23,template_label_error_plus_missing_value)=0, COUNTIF(C20:C23,template_label_error)=0, COUNTIF(C20:C23,template_label_missing_value_plus_value_inconsistency)=0, COUNTIF(C20:C23,template_label_value_inconsistency)=0, COUNTIF(C20:C23,template_label_missing_value)=0,OR(COUNTIF(C20:C23,template_label_missing_value)=0, COUNTIF(C20:C23,template_label_missing_value)>0)), template_label_ok, "-"))))))))) )) -> - | D19: =IF(COUNTIF(D20:D23,TRUE)=ROWS(D20:D23),TRUE,FALSE) -> FALSE
B20: =template_label_b3_total_energy_consumption -> B3 - Total Energy Consumption (in MWh) | C20: =IF(D20=TRUE, template_label_classified_or_sensitive_information, IF(COUNTIF('Environmental Disclosures'!L5,template_label_missing_value)>0,template_label_missing_value, IF(COUNTIF('Environmental Disclosures'!L5,template_label_ok)>0,template_label_ok,"-")) ) -> - | D20: FALSE | E20: =IF(AND(C20=template_label_classified_or_sensitive_information,COUNTIF(TotalEnergyConsumption,"<>")>0),template_label_information_on_sensitive_information_before_converting,"")
B21: =template_label_b3_breakdown_of_energy_consumption -> B3 - Breakdown of energy consumption (in MWh) | C21: =IF(D21=TRUE,template_label_classified_or_sensitive_information, IF( AND( COUNTIF('Environmental Disclosures'!L12:L14,template_label_missing_value)>0, COUNTIF('Environmental Disclosures'!L12:L14,template_label_value_inconsistency)=0 ), template_label_missing_value, IF( AND( COUNTIF('Environmental Disclosures'!L12:L14,template_label_value_inconsistency)>0, COUNTIF('Environmental Disclosures'!L12:L14,template_label_missing_value)=0 ), template_label_value_inconsistency, IF( AND( COUNTIF('Environmental Disclosures'!L12:L14,template_label_value_inconsistency)>0, COUNTIF('Environmental Disclosures'!L12:L14,template_label_missing_value)>0 ), template_label_error_plus_value_inconsistency, IF( COUNTIF('Environmental Disclosures'!L12:L14,"-")=3, "-", IF( COUNTIF('Environmental Disclosures'!L12:L14,template_label_ok)>0, template_label_ok, "-" ) )) )) ) -> - | D21: FALSE | E21: =IF(AND(C21=template_label_classified_or_sensitive_information,'Environmental Disclosures'!G10=TRUE),template_label_information_on_sensitive_information_before_converting,"")
B22: =template_label_b3_estimated_greenhouse_gas_emissions -> B3 - Estimated Greenhouse Gas Emissions considering the GHG Protocol Version 2004 (in tCO2e) | C22: =IF(D22=TRUE, template_label_classified_or_sensitive_information, IF(COUNTIF('Environmental Disclosures'!L21:L44,template_label_missing_value)>0,template_label_missing_value, IF(COUNTIF('Environmental Disclosures'!L21:L44,template_label_ok)>0,template_label_ok,"-")) ) -> - | D22: FALSE | E22: =IF(AND(C22=template_label_classified_or_sensitive_information,COUNTIF('Environmental Disclosures'!D22:F24,"<>")>0),template_label_information_on_sensitive_information_before_converting,"")
B23: =template_label_b3_greenhouse_gas_emission_intensity_per_turnover -> B3 - Greenhouse gas emission intensity per turnover (in tCO2e) | C23: =IF(D23=TRUE, template_label_classified_or_sensitive_information, IF(C22=template_label_ok,template_label_ok,"-") ) -> - | D23: FALSE | E23: =IF(AND(C23=template_label_classified_or_sensitive_information,COUNTIF('Environmental Disclosures'!D22:F24,"<>")>0,COUNTIF(Turnover,"<>")>0),template_label_information_on_sensitive_information_before_converting,"")
B24: =template_label_b4_pollution_of_air_water_and_soil_validation -> B4 - Pollution of air, water and soil | C24: =IF(D24=TRUE, template_label_classified_or_sensitive_information, IF(COUNTIF('Environmental Disclosures'!L75:L179,template_label_invalid_url)>0, template_label_invalid_url, IF(AND(COUNTIF('Environmental Disclosures'!L75:L179,template_label_missing_value)>0, COUNTIF('Environmental Disclosures'!L75:L179,template_label_value_inconsistency)>0), template_label_missing_value_plus_value_inconsistency, IF(COUNTIF('Environmental Disclosures'!L75:L179,template_label_missing_value)>0, template_label_missing_value, IF(COUNTIF('Environmental Disclosures'!L75:L179,template_label_value_inconsistency)>0, template_label_value_inconsistency, IF(COUNTIF('Environmental Disclosures'!L75:L179,template_label_ok)>0, template_label_ok, "-"))))) ) -> - | D24: FALSE | E24: =IF(AND(C24=template_label_classified_or_sensitive_information,'Environmental Disclosures'!G74=TRUE),template_label_information_on_sensitive_information_before_converting,"")
B25: =template_label_b5_biodiversity_validation -> B5 - Biodiversity | C25: =IF(D25=TRUE, template_label_classified_or_sensitive_information, IF(COUNTIF(C26:C27,template_label_error_plus_missing_value_plus_value_inconsistency)>0,template_label_error_plus_missing_value_plus_value_inconsistency, IF(COUNTIF(C26:C27,template_label_error_plus_value_inconsistency)>0,template_label_error_plus_value_inconsistency, IF(COUNTIF(C26:C27,template_label_error_plus_missing_value)>0,template_label_error_plus_missing_value, IF(COUNTIF(C26:C27,template_label_error)>0,template_label_error, IF(COUNTIF(C26:C27,template_label_missing_value_plus_value_inconsistency)>0,template_label_missing_value_plus_value_inconsistency, IF(COUNTIF(C26:C27,template_label_value_inconsistency)>0,template_label_value_inconsistency, IF(COUNTIF(C26:C27,template_label_missing_value)>0,template_label_missing_value, IF(COUNTIF(C26:C27,template_label_ok)=ROWS(C26:C27),template_label_ok, IF(COUNTIF(C26:C27,"-")=ROWS(C26:C27),"-", IF(AND(COUNTIF(C26:C27,template_label_ok)>0, COUNTIF(C26:C27,template_label_error_plus_missing_value_plus_value_inconsistency)=0, COUNTIF(C26:C27,template_label_error_plus_value_inconsistency)=0, COUNTIF(C26:C27,template_label_error_plus_missing_value)=0, COUNTIF(C26:C27,template_label_error)=0, COUNTIF(C26:C27,template_label_missing_value_plus_value_inconsistency)=0, COUNTIF(C26:C27,template_label_value_inconsistency)=0, COUNTIF(C26:C27,template_label_missing_value)=0,OR(COUNTIF(C26:C27,template_label_missing_value)=0, COUNTIF(C26:C27,template_label_missing_value)>0)), template_label_ok, "-"))))))))) )) -> - | D25: =IF(COUNTIF(D26:D27,TRUE)=ROWS(D26:D27),TRUE,FALSE) -> FALSE
B26: =template_label_b5_sites_in_biodiversity_sensitive_areas -> B5 - Sites in biodiversity sensitive areas | C26: =IF(D26=TRUE, template_label_classified_or_sensitive_information, IF(AND( COUNTIF('Environmental Disclosures'!D188:D287,template_label_ok) + COUNTIF('Environmental Disclosures'!L186:L287,template_label_ok) > 0, COUNTIF('Environmental Disclosures'!D188:D287,template_label_missing_value) + COUNTIF('Environmental Disclosures'!L186:L287,template_label_missing_value) = 0, COUNTIF('Environmental Disclosures'!D188:D287,template_label_value_inconsistency) + COUNTIF('Environmental Disclosures'!L186:L287,template_label_value_inconsistency) = 0), template_label_ok, IF(AND( COUNTIF('Environmental Disclosures'!D188:D287,template_label_missing_value) + COUNTIF('Environmental Disclosures'!L186:L287,template_label_missing_value) > 0, COUNTIF('Environmental Disclosures'!D188:D287,template_label_value_inconsistency) + COUNTIF('Environmental Disclosures'!L186:L287,template_label_value_inconsistency) = 0), template_label_missing_value, IF(AND( COUNTIF('Environmental Disclosures'!D188:D287,template_label_value_inconsistency) + COUNTIF('Environmental Disclosures'!L186:L287,template_label_value_inconsistency) > 0, COUNTIF('Environmental Disclosures'!D188:D287,template_label_missing_value) + COUNTIF('Environmental Disclosures'!L186:L287,template_label_missing_value) = 0), template_label_value_inconsistency, IF(AND( COUNTIF('Environmental Disclosures'!D188:D287,template_label_value_inconsistency) + COUNTIF('Environmental Disclosures'!L186:L287,template_label_value_inconsistency) > 0, COUNTIF('Environmental Disclosures'!D188:D287,template_label_missing_value) + COUNTIF('Environmental Disclosures'!L186:L287,template_label_missing_value) > 0), template_label_missing_value_plus_value_inconsistency, "-" ) ) ) ) ) -> - | D26: FALSE | E26: =IF(AND(C26=template_label_classified_or_sensitive_information,'Environmental Disclosures'!G184=TRUE),template_label_information_on_sensitive_information_before_converting,"")
B27: =template_label_b5_biodiversity_land_use -> B5 - Biodiversity - Land-use | C27: =IF(D27=TRUE, template_label_classified_or_sensitive_information, IF( AND( COUNTIF('Environmental Disclosures'!G293:G298,template_label_missing_value)>0, COUNTIF('Environmental Disclosures'!G293:G298,template_label_value_inconsistency)=0, COUNTIF('Environmental Disclosures'!G293:G298,template_label_ok)>=0 ), template_label_missing_value, IF( AND( COUNTIF('Environmental Disclosures'!G293:G298,template_label_value_inconsistency)>0, COUNTIF('Environmental Disclosures'!G293:G298,template_label_missing_value)=0, COUNTIF('Environmental Disclosures'!G293:G298,template_label_ok)>=0 ), template_label_value_inconsistency, IF( AND( COUNTIF('Environmental Disclosures'!G293:G298,template_label_value_inconsistency)>0, COUNTIF('Environmental Disclosures'!G293:G298,template_label_missing_value)>0, COUNTIF('Environmental Disclosures'!G293:G298,template_label_ok)>=0 ), template_label_missing_value_plus_value_inconsistency, IF( AND( COUNTIF('Environmental Disclosures'!G293:G298,template_label_value_inconsistency)=0, COUNTIF('Environmental Disclosures'!G293:G298,template_label_missing_value)=0, COUNTIF('Environmental Disclosures'!G293:G298,template_label_ok)>0 ), template_label_ok, "-" ) ) )) ) -> - | D27: FALSE | E27: =IF(AND(C27=template_label_classified_or_sensitive_information,COUNTIF('Environmental Disclosures'!D295:F298,"<>")>0),template_label_information_on_sensitive_information_before_converting,"")
B28: =template_label_b6_water_validation -> B6 - Water | C28: =IF(D28=TRUE, template_label_classified_or_sensitive_information, IF(COUNTIF(C29:C30,template_label_error_plus_missing_value_plus_value_inconsistency)>0,template_label_error_plus_missing_value_plus_value_inconsistency, IF(COUNTIF(C29:C30,template_label_error_plus_value_inconsistency)>0,template_label_error_plus_value_inconsistency, IF(COUNTIF(C29:C30,template_label_error_plus_missing_value)>0,template_label_error_plus_missing_value, IF(COUNTIF(C29:C30,template_label_error)>0,template_label_error, IF(COUNTIF(C29:C30,template_label_missing_value_plus_value_inconsistency)>0,template_label_missing_value_plus_value_inconsistency, IF(COUNTIF(C29:C30,template_label_value_inconsistency)>0,template_label_value_inconsistency, IF(COUNTIF(C29:C30,template_label_missing_value)>0,template_label_missing_value, IF(COUNTIF(C29:C30,template_label_ok)=ROWS(C29:C30),template_label_ok, IF(COUNTIF(C29:C30,"-")=ROWS(C29:C30),"-", IF(AND(COUNTIF(C29:C30,template_label_ok)>0, COUNTIF(C26:C27,template_label_error_plus_missing_value_plus_value_inconsistency)=0, COUNTIF(C29:C30,template_label_error_plus_value_inconsistency)=0, COUNTIF(C29:C30,template_label_error_plus_missing_value)=0, COUNTIF(C29:C30,template_label_error)=0, COUNTIF(C29:C30,template_label_missing_value_plus_value_inconsistency)=0, COUNTIF(C29:C30,template_label_value_inconsistency)=0, COUNTIF(C29:C30,template_label_missing_value)=0,OR(COUNTIF(C29:C30,template_label_missing_value)=0, COUNTIF(C29:C30,template_label_missing_value)>0)), template_label_ok, "-"))))))))) )) -> - | D28: =IF(COUNTIF(D29:D30,TRUE)=ROWS(D29:D30),TRUE,FALSE) -> FALSE
B29: =template_label_b6_water_withdrawal -> B6 - Water Withdrawal | C29: =IF(D29=TRUE, template_label_classified_or_sensitive_information, IF(COUNTIF('Environmental Disclosures'!E303:F304, template_label_missing_value) > 0, template_label_missing_value, IF(COUNTIF('Environmental Disclosures'!E303:F304, template_label_ok) > 0, template_label_ok, "-")) ) -> - | D29: FALSE | E29: =IF(AND(C29=template_label_classified_or_sensitive_information,COUNTIF('Environmental Disclosures'!D303:D304,"<>")>0),template_label_information_on_sensitive_information_before_converting,"")
B30: =template_label_b6_water_consumption -> B6 - Water Consumption | C30: =IF(D30=TRUE, template_label_classified_or_sensitive_information, IF(COUNTIF('Environmental Disclosures'!E310:F310, template_label_missing_value) > 0, template_label_missing_value, IF(COUNTIF('Environmental Disclosures'!E310:F310, template_label_ok) > 0, template_label_ok, "-")) ) -> - | D30: FALSE | E30: =IF(AND(C30=template_label_classified_or_sensitive_information,'Environmental Disclosures'!D309=TRUE),template_label_information_on_sensitive_information_before_converting,"")
B31: =template_label_b7_resource_use_circular_economy_and_waste_management_validation -> B7 - Resource use, circular economy and waste management | C31: =IF(D31=TRUE, template_label_classified_or_sensitive_information, IF(COUNTIF(C32:C34, template_label_error_plus_missing_value_plus_value_inconsistency) > 0, template_label_error_plus_missing_value_plus_value_inconsistency, IF(COUNTIF(C32:C34, template_label_error_plus_value_inconsistency) > 0, template_label_error_plus_value_inconsistency, IF(COUNTIF(C32:C34, template_label_error_plus_missing_value) > 0, template_label_error_plus_missing_value, IF(COUNTIF(C32:C34, template_label_error) > 0, template_label_error, IF(COUNTIF(C32:C34, template_label_missing_value_plus_value_inconsistency) > 0, template_label_missing_value_plus_value_inconsistency, IF(COUNTIF(C32:C34, template_label_value_inconsistency) > 0, template_label_value_inconsistency, IF(COUNTIF(C32:C34, template_label_missing_value) > 0, template_label_missing_value, IF(COUNTIF(C32:C34, template_label_ok) = ROWS(C32:C34), template_label_ok, IF(COUNTIF(C32:C34, "-") = ROWS(C32:C34), "-", IF(AND(COUNTIF(C32:C34,template_label_ok)>0, COUNTIF(C32:C34,template_label_error_plus_missing_value_plus_value_inconsistency)=0, COUNTIF(C32:C34,template_label_error_plus_value_inconsistency)=0, COUNTIF(C32:C34,template_label_error_plus_missing_value)=0, COUNTIF(C32:C34,template_label_error)=0, COUNTIF(C32:C34,template_label_missing_value_plus_value_inconsistency)=0, COUNTIF(C32:C34,template_label_value_inconsistency)=0, COUNTIF(C32:C34,template_label_missing_value)=0,OR(COUNTIF(C32:C34,template_label_missing_value)=0, COUNTIF(C32:C34,template_label_missing_value)>0)), template_label_ok, "-"))))))))) )) -> - | D31: =IF(COUNTIF(D33:D34,TRUE)=ROWS(D33:D34),TRUE,FALSE) -> FALSE
B32: =template_label_b7_description_of_circular_economy_principles -> B7 - Description of circular economy principles | C32: =IF(D32=TRUE, template_label_classified_or_sensitive_information, IF( AND( COUNTIF('Environmental Disclosures'!H316:I317, template_label_missing_value) > 0, COUNTIF('Environmental Disclosures'!H316:I317, template_label_value_inconsistency) = 0, COUNTIF('Environmental Disclosures'!H316:I317, template_label_ok) >= 0 ), template_label_missing_value, IF( AND( COUNTIF('Environmental Disclosures'!H316:I317, template_label_value_inconsistency) > 0, COUNTIF('Environmental Disclosures'!H316:I317, template_label_missing_value) = 0, COUNTIF('Environmental Disclosures'!H316:I317, template_label_ok) >= 0 ), template_label_value_inconsistency, IF( AND( COUNTIF('Environmental Disclosures'!H316:I317, template_label_value_inconsistency) > 0, COUNTIF('Environmental Disclosures'!H316:I317, template_label_missing_value) > 0, COUNTIF('Environmental Disclosures'!H316:I317, template_label_ok) >= 0 ), template_label_missing_value_plus_value_inconsistency, IF( AND( COUNTIF('Environmental Disclosures'!H316:I317, template_label_value_inconsistency) = 0, COUNTIF('Environmental Disclosures'!H316:I317, template_label_missing_value) = 0, COUNTIF('Environmental Disclosures'!H316:I317, template_label_ok) > 0 ), template_label_ok, "-" ) ) )) ) -> - | D32: FALSE | E32: =IF(AND(C32=template_label_classified_or_sensitive_information,COUNTIF('Environmental Disclosures'!D316:G317,"<>")>0),template_label_information_on_sensitive_information_before_converting,"")
B33: =template_label_b7_waste_generated -> B7 - Waste generated | C33: =IF(D33=TRUE, template_label_classified_or_sensitive_information, IF( AND( COUNTIF('Environmental Disclosures'!M323:M423, template_label_error) > 0, COUNTIF('Environmental Disclosures'!M323:M423, template_label_missing_value) > 0, COUNTIF('Environmental Disclosures'!M323:M423, template_label_value_inconsistency) > 0 ), template_label_error_plus_missing_value_plus_value_inconsistency, IF( AND( COUNTIF('Environmental Disclosures'!M323:M423, template_label_error) > 0, COUNTIF('Environmental Disclosures'!M323:M423, template_label_value_inconsistency) > 0, COUNTIF('Environmental Disclosures'!M323:M423, template_label_missing_value) = 0 ), template_label_error_plus_value_inconsistency, IF( AND( COUNTIF('Environmental Disclosures'!M323:M423, template_label_error) > 0, COUNTIF('Environmental Disclosures'!M323:M423, template_label_missing_value) > 0, COUNTIF('Environmental Disclosures'!M323:M423, template_label_value_inconsistency) = 0 ), template_label_error_plus_missing_value, IF( AND( COUNTIF('Environmental Disclosures'!M323:M423, template_label_missing_value) > 0, COUNTIF('Environmental Disclosures'!M323:M423, template_label_value_inconsistency) > 0, COUNTIF('Environmental Disclosures'!M323:M423, template_label_error) = 0 ), template_label_missing_value_plus_value_inconsistency, IF( AND( COUNTIF('Environmental Disclosures'!M323:M423, template_label_error) > 0, COUNTIF('Environmental Disclosures'!M323:M423, template_label_missing_value) = 0, COUNTIF('Environmental Disclosures'!M323:M423, template_label_value_inconsistency) = 0 ), template_label_error, IF( AND( COUNTIF('Environmental Disclosures'!M323:M423, template_label_missing_value) > 0, COUNTIF('Environmental Disclosures'!M323:M423, template_label_error) = 0, COUNTIF('Environmental Disclosures'!M323:M423, template_label_value_inconsistency) = 0 ), template_label_missing_value, IF( AND( COUNTIF('Environmental Disclosures'!M323:M423, template_label_value_inconsistency) > 0, COUNTIF('Environmental Disclosures'!M323:M423, template_label_error) = 0, COUNTIF('Environmental Disclosures'!M323:M423, template_label_missing_value) = 0 ), template_label_value_inconsistency, IF( AND( COUNTIF('Environmental Disclosures'!M323:M423, template_label_error) = 0, COUNTIF('Environmental Disclosures'!M323:M423, template_label_missing_value) = 0, COUNTIF('Environmental Disclosures'!M323:M423, template_label_value_inconsistency) = 0, COUNTIF('Environmental Disclosures'!M323:M423, template_label_ok) > 0 ), template_label_ok, "-" )))))))) ) -> - | D33: FALSE | E33: =IF(AND(C33=template_label_classified_or_sensitive_information,COUNTIF('Environmental Disclosures'!D323:K422,"<>")>0),template_label_information_on_sensitive_information_before_converting,"")
B34: =template_label_b7_annual_mass_flow_of_relevant_materials_used -> B7 - Annual mass-flow of relevant materials used | C34: =IF(D34=TRUE, template_label_classified_or_sensitive_information, IF(COUNTIF('Environmental Disclosures'!K435:K534, template_label_missing_value) > 0, template_label_missing_value, IF(COUNTIF('Environmental Disclosures'!K435:K534, template_label_ok) > 0, template_label_ok, "-")) ) -> - | D34: FALSE | E34: =IF(AND(C34=template_label_classified_or_sensitive_information,'Environmental Disclosures'!G433=TRUE),template_label_information_on_sensitive_information_before_converting,"")
B35: =template_label_social_disclosures_validation -> Social Disclosures
B36: =template_label_b8_workforce_general_characteristics_validation -> B8 - Workforce - General characteristics | C36: =IF(D36=TRUE, template_label_classified_or_sensitive_information, IF(COUNTIF(C37:C40, template_label_error_plus_missing_value_plus_value_inconsistency) > 0, template_label_error_plus_missing_value_plus_value_inconsistency, IF(COUNTIF(C37:C40, template_label_error_plus_value_inconsistency) > 0, template_label_error_plus_value_inconsistency, IF(COUNTIF(C37:C40, template_label_error_plus_missing_value) > 0, template_label_error_plus_missing_value, IF(COUNTIF(C37:C40, template_label_error) > 0, template_label_error, IF(COUNTIF(C37:C40, template_label_missing_value_plus_value_inconsistency) > 0, template_label_missing_value_plus_value_inconsistency, IF(COUNTIF(C37:C40, template_label_value_inconsistency) > 0, template_label_value_inconsistency, IF(COUNTIF(C37:C40, template_label_missing_value) > 0, template_label_missing_value, IF(COUNTIF(C37:C40, template_label_ok) = ROWS(C37:C40), template_label_ok, IF(COUNTIF(C37:C40, "-") = ROWS(C37:C40), "-", IF(AND(COUNTIF(C37:C40,template_label_ok)>0, COUNTIF(C37:C40,template_label_error_plus_missing_value_plus_value_inconsistency)=0, COUNTIF(C37:C40,template_label_error_plus_value_inconsistency)=0, COUNTIF(C37:C40,template_label_error_plus_missing_value)=0, COUNTIF(C37:C40,template_label_error)=0, COUNTIF(C37:C40,template_label_missing_value_plus_value_inconsistency)=0, COUNTIF(C37:C40,template_label_value_inconsistency)=0, COUNTIF(C37:C40,template_label_missing_value)=0,OR(COUNTIF(C37:C40,template_label_missing_value)=0, COUNTIF(C37:C40,template_label_missing_value)>0)), template_label_ok, "-"))))))))) )) -> - | D36: =IF(COUNTIF(D37:D40,TRUE)=ROWS(D37:D40),TRUE,FALSE) -> FALSE
B37: =template_label_b8_workforce_general_characteristics_type_of_contract -> B8 - Workforce - General characteristics - Type of contract | C37: =IF(D37=TRUE, template_label_classified_or_sensitive_information, IF(COUNTIF('Social Disclosures'!H10, template_label_missing_value) > 0, template_label_missing_value, IF(COUNTIF('Social Disclosures'!H10, template_label_ok) > 0, template_label_ok, "-")) ) -> - | D37: FALSE | E37: =IF(AND(C37=template_label_classified_or_sensitive_information,COUNTIF([0]!NumberOfPermanentContractEmployees,"<>")>0),template_label_information_on_sensitive_information_before_converting,"")
B38: =template_label_b8_workforce_general_characteristics_gender -> B8 - Workforce - General characteristics - Gender | C38: =IF(D38=TRUE,template_label_classified_or_sensitive_information, IF(COUNTIF('Social Disclosures'!H18,template_label_missing_value)>0, template_label_missing_value,IF(COUNTIF('Social Disclosures'!H18,template_label_value_inconsistency)>0, template_label_value_inconsistency, IF(COUNTIF('Social Disclosures'!H18,template_label_ok)>0, template_label_ok, "-")) )) -> - | D38: FALSE | E38: =IF(AND(C38=template_label_classified_or_sensitive_information,COUNTIF('Social Disclosures'!D18:G21,"<>")>0),template_label_information_on_sensitive_information_before_converting,"")
B39: =template_label_b8_workforce_general_characteristics_country_of_employment -> B8 - Workforce - General characteristics - Country of employment | C39: =IF(D39=TRUE, template_label_classified_or_sensitive_information, IF(COUNTIF('Social Disclosures'!I29:I128, template_label_missing_value) > 0, template_label_missing_value, IF(COUNTIF('Social Disclosures'!I29:I128, template_label_ok) > 0, template_label_ok, "-")) ) -> - | D39: FALSE | E39: =IF(AND(C39=template_label_classified_or_sensitive_information,'Social Disclosures'!E27=TRUE),template_label_information_on_sensitive_information_before_converting,"")
B40: =template_label_b8_workforce_general_characteristics_turnover_rate -> B8 - Workforce - General characteristics - Turnover rate | C40: =IF(D40=TRUE, template_label_classified_or_sensitive_information, IF(COUNTIF('Social Disclosures'!I134:I136, template_label_missing_value) > 0, template_label_missing_value, IF(COUNTIF('Social Disclosures'!I134:I136, template_label_ok) > 0, template_label_ok, "-")) ) -> - | D40: FALSE | E40: =IF(AND(C40=template_label_classified_or_sensitive_information,COUNTIF('Social Disclosures'!D134:H136,"<>")>0),template_label_information_on_sensitive_information_before_converting,"")
B41: =template_label_b9_workforce_health_and_safety_validation -> B9 - Workforce - Health and safety | C41: =IF(D41=TRUE, template_label_classified_or_sensitive_information, IF(COUNTIF('Social Disclosures'!I140:I144, template_label_missing_value) > 0, template_label_missing_value, IF(COUNTIF('Social Disclosures'!I140:I144, template_label_ok) > 0, template_label_ok, "-")) ) -> - | D41: FALSE | E41: =IF(AND(C41=template_label_classified_or_sensitive_information,COUNTIF('Social Disclosures'!D140:H142,"<>")>0),template_label_information_on_sensitive_information_before_converting,"")
B42: =template_label_b10_workforce_remuneration_collective_bargaining_and_training_validation -> B10 - Workforce - Remuneration, collective bargaining and training | C42: =IF(D42=TRUE,template_label_classified_or_sensitive_information, IF(COUNTIF(C43:C44,template_label_error_plus_missing_value_plus_value_inconsistency)>0,template_label_error_plus_missing_value_plus_value_inconsistency, IF(COUNTIF(C43:C44,template_label_error_plus_value_inconsistency)>0,template_label_error_plus_value_inconsistency, IF(COUNTIF(C43:C44,template_label_error_plus_missing_value)>0,template_label_error_plus_missing_value, IF(COUNTIF(C43:C44,template_label_error)>0,template_label_error, IF(COUNTIF(C43:C44,template_label_missing_value_plus_value_inconsistency)>0,template_label_missing_value_plus_value_inconsistency, IF(COUNTIF(C43:C44,template_label_value_inconsistency)>0,template_label_value_inconsistency, IF(COUNTIF(C43:C44,template_label_missing_value)>0,template_label_missing_value, IF(COUNTIF(C43:C44,template_label_ok)=ROWS(C43:C44),template_label_ok, IF(COUNTIF(C43:C44,"-")=ROWS(C43:C44),"-", IF(AND(COUNTIF(C43:C44,template_label_ok)>0,COUNTIF(C43:C44,template_label_error_plus_missing_value_plus_value_inconsistency)=0,COUNTIF(C43:C44,template_label_error_plus_value_inconsistency)=0,COUNTIF(C43:C44,template_label_error_plus_missing_value)=0,COUNTIF(C43:C44,template_label_error)=0,COUNTIF(C43:C44,template_label_missing_value_plus_value_inconsistency)=0,COUNTIF(C43:C44,template_label_value_inconsistency)=0,COUNTIF(C43:C44,template_label_missing_value)=0,OR(COUNTIF(C43:C44,template_label_missing_value)=0, COUNTIF(C43:C44,template_label_missing_value)>0)),template_label_ok, "-"))))))))))) -> - | D42: =IF(COUNTIF(D43:D44,TRUE)=ROWS(D43:D44),TRUE,FALSE) -> FALSE
B43: =template_label_b10_workforce_remuneration_collective_bargaining -> B10 - Workforce - Remuneration and collective bargaining | C43: =IF(D43=TRUE, template_label_classified_or_sensitive_information, IF(COUNTIF('Social Disclosures'!I147:I151, template_label_missing_value) > 0, template_label_missing_value, IF(COUNTIF('Social Disclosures'!I147:I151, template_label_ok) > 0, template_label_ok, "-")) ) -> - | D43: FALSE | E43: =IF(AND(C43=template_label_classified_or_sensitive_information,OR(COUNTIF('Social Disclosures'!D147:H149,"<>")>0,COUNTIF('Social Disclosures'!D151,"<>")>0)),template_label_information_on_sensitive_information_before_converting,"")
B44: =template_label_number_of_annual_training_hours_per_employee_during_the_reporting_period -> B10 - Workforce - Number of annual training hours per employee during the reporting period | C44: =IF(D44=TRUE, template_label_classified_or_sensitive_information, IF(COUNTIF('Social Disclosures'!I157:I160, template_label_missing_value) > 0, template_label_missing_value, IF(COUNTIF('Social Disclosures'!I157:I160, template_label_ok) > 0, template_label_ok, "-")) ) -> - | D44: FALSE | E44: =IF(AND(C44=template_label_classified_or_sensitive_information,COUNTIF('Social Disclosures'!D157:H160,"<>")>0),template_label_information_on_sensitive_information_before_converting,"")
B45: =template_label_governance_disclosures_validation -> Governance Disclosures
B46: =template_label_b11_convictions_and_fines_for_corruption_and_bribery_validation -> B11 - Convictions and fines for corruption and bribery | C46: =IF(D46=TRUE, template_label_classified_or_sensitive_information, IF(COUNTIF('Governance Disclosures'!I6:I7, template_label_missing_value) > 0, template_label_missing_value, IF(COUNTIF('Governance Disclosures'!I6:I7, template_label_ok) > 0, template_label_ok, "-")) ) -> - | D46: FALSE | E46: =IF(AND(C46=template_label_classified_or_sensitive_information,'Governance Disclosures'!H5=TRUE),template_label_information_on_sensitive_information_before_converting,"")
B47: =template_label_comprehensive_module_validation -> Comprehensive Module
B48: =template_label_general_information_validation -> General Information
B49: =template_label_c1_strategy_business_model_and_sustainability_related_initiatives_validation -> C1 - Strategy: Business Model and Sustainability - Related Initiatives | C49: =IF(D49=TRUE, template_label_classified_or_sensitive_information, IF(COUNTIF('General Information'!H525:H529, template_label_missing_value) > 0, template_label_missing_value, IF(COUNTIF('General Information'!H525:H529, template_label_ok) > 0, template_label_ok, "-")) ) -> - | D49: FALSE | E49: =IF(AND(C49=template_label_classified_or_sensitive_information,OR(COUNTIF('General Information'!E525:G527,"<>")>0,'General Information'!E528=TRUE)),template_label_information_on_sensitive_information_before_converting,"")
B50: =template_label_c2_description_of_practices_policies_and_future_initiatives_for_transitioning_towards_a_more_sustainable_economy_validation -> C2 - Description of practices, policies and future initiatives for transitioning towards a more sustainable economy | C50: =IF(D50=TRUE, template_label_classified_or_sensitive_information, IF(COUNTIF('General Information'!H519:H521, template_label_missing_value) > 0, template_label_missing_value, IF(COUNTIF('General Information'!H519:H521, template_label_ok) > 0, template_label_ok, "-")) ) -> - | D50: FALSE | E50: =IF(AND(C50=template_label_classified_or_sensitive_information,COUNTIF('General Information'!E216:E324,"<>")>0),template_label_information_on_sensitive_information_before_converting,"")
B51: =template_label_environmental_disclosures_validation -> Environmental Disclosures
B52: =template_label_c3_ghg_reduction_targets_and_climate_transition_validation -> C3 - GHG reduction targets and climate transition | C52: =IF(D52=TRUE,template_label_classified_or_sensitive_information, IF(COUNTIF(C53:C55,template_label_error_plus_missing_value_plus_value_inconsistency)>0,template_label_error_plus_missing_value_plus_value_inconsistency, IF(COUNTIF(C53:C55,template_label_error_plus_value_inconsistency)>0,template_label_error_plus_value_inconsistency, IF(COUNTIF(C53:C55,template_label_error_plus_missing_value)>0,template_label_error_plus_missing_value, IF(COUNTIF(C53:C55,template_label_error)>0,template_label_error, IF(COUNTIF(C53:C55,template_label_missing_value_plus_value_inconsistency)>0,template_label_missing_value_plus_value_inconsistency, IF(COUNTIF(C53:C55,template_label_value_inconsistency)>0,template_label_value_inconsistency, IF(COUNTIF(C53:C55,template_label_missing_value)>0,template_label_missing_value, IF(COUNTIF(C53:C55,template_label_ok)=ROWS(C53:C55),template_label_ok, IF(COUNTIF(C53:C55,"-")=ROWS(C53:C55),"-", IF(AND(COUNTIF(C53:C55,template_label_ok)>0, COUNTIF(C53:C55,template_label_error_plus_missing_value_plus_value_inconsistency)=0, COUNTIF(C53:C55,template_label_error_plus_value_inconsistency)=0, COUNTIF(C53:C55,template_label_error_plus_missing_value)=0, COUNTIF(C53:C55,template_label_error)=0, COUNTIF(C53:C55,template_label_missing_value_plus_value_inconsistency)=0, COUNTIF(C53:C55,template_label_value_inconsistency)=0, COUNTIF(C53:C55,template_label_missing_value)=0), template_label_ok, "-"))))))))))) -> - | D52: =IF(COUNTIF(D53:D55,TRUE)=ROWS(D53:D55),TRUE,FALSE) -> FALSE
B53: =template_label_c3_ghg_reduction_targets -> C3 - GHG reduction targets (in tC02e) | C53: =IF(D53=TRUE, template_label_classified_or_sensitive_information, IF(AND('General Information'!E122 = "Option A (Basic Module only)", COUNTA('Environmental Disclosures'!G21:G24) = 0), "-", IF(COUNTIF('Environmental Disclosures'!L52, template_label_missing_value) > 0, template_label_missing_value, IF(COUNTIF('Environmental Disclosures'!L52, template_label_ok) > 0, template_label_ok, "-"))) ) -> - | D53: FALSE | E53: =IF(AND(C53=template_label_classified_or_sensitive_information,'Environmental Disclosures'!J19=TRUE),template_label_information_on_sensitive_information_before_converting,"")
B54: =template_label_c3_disclosure_of_list_of_main_actions_the_entity_seeks_in_order_to_achieve_its_targets -> C3 - Disclosure of list of main actions the entity seeks in order to achieve its targets | C54: =IF(D54=TRUE, template_label_classified_or_sensitive_information, IF(COUNTIF('Environmental Disclosures'!L52, template_label_missing_value) > 0, template_label_missing_value, IF(COUNTIF('Environmental Disclosures'!L52, template_label_ok) > 0, template_label_ok, "-")) ) -> - | D54: FALSE | E54: =IF(AND(C54=template_label_classified_or_sensitive_information,COUNTIF(DisclosureOfListOfMainActionsTheEntitySeeksInOrderToAchieveItsTargets,"<>")>0),template_label_information_on_sensitive_information_before_converting,"")
B55: =template_label_c3_transition_plan_for_undertakings_operating_in_high_climate_impact_sectors -> C3 - Transition plan for undertakings operating in high climate impact sectors | C55: =IF(D55=TRUE, template_label_classified_or_sensitive_information, IF( AND( COUNTIF('Environmental Disclosures'!L57:L59, template_label_missing_value) > 0, COUNTIF('Environmental Disclosures'!L57:L59, template_label_error) = 0, COUNTIF('Environmental Disclosures'!L57:L59, template_label_ok) >= 0 ), template_label_missing_value, IF( AND( COUNTIF('Environmental Disclosures'!L57:L59, template_label_error) > 0, COUNTIF('Environmental Disclosures'!L57:L59, template_label_missing_value) = 0, COUNTIF('Environmental Disclosures'!L57:L59, template_label_ok) >= 0 ), template_label_error, IF( AND( COUNTIF('Environmental Disclosures'!L57:L59, template_label_error) > 0, COUNTIF('Environmental Disclosures'!L57:L59, template_label_missing_value) > 0, COUNTIF('Environmental Disclosures'!L57:L59, template_label_ok) >= 0 ), template_label_error_plus_missing_value, IF( AND( COUNTIF('Environmental Disclosures'!L57:L59, template_label_error) = 0, COUNTIF('Environmental Disclosures'!L57:L59, template_label_missing_value) = 0, COUNTIF('Environmental Disclosures'!L57:L59, template_label_ok) > 0 ), template_label_ok, "-" ) ) )) ) -> - | D55: FALSE | E55: =IF(AND(C55=template_label_classified_or_sensitive_information,COUNTIF('Environmental Disclosures'!D57,"<>")>0),template_label_information_on_sensitive_information_before_converting,"")
B56: =template_label_c4_climate_risks_validation -> C4 - Climate risks | C56: =IF(D56=TRUE, template_label_classified_or_sensitive_information, IF(COUNTIF('Environmental Disclosures'!L540:L544, template_label_missing_value) > 0, template_label_missing_value, IF(COUNTIF('Environmental Disclosures'!L540:L544, template_label_ok) > 0, template_label_ok, "-")) ) -> - | D56: FALSE | E56: {=IF(AND(C56=template_label_classified_or_sensitive_information,'Environmental Disclosures'!E539:K539=TRUE),template_label_information_on_sensitive_information_before_converting,"")}
B57: =template_label_social_disclosures_validation -> Social Disclosures
B58: =template_label_c5_additional_general_workforce_characteristics_validation -> C5 - Additional (general) workforce characteristics | C58: =IF(D58=TRUE, template_label_classified_or_sensitive_information, IF(COUNTIF('Social Disclosures'!I165:I169, template_label_ok) > 0, template_label_ok, "-") ) -> - | D58: FALSE | E58: =IF(AND(C58=template_label_classified_or_sensitive_information,OR(COUNTIF('Social Disclosures'!D165:H166,"<>")>0,COUNTIF('Social Disclosures'!D168:H169,"<>")>0)),template_label_information_on_sensitive_information_before_converting,"")
B59: =template_label_c6_additional_own_workforce_information_human_rights_policies_and_processes_validation -> C6 - Additional own workforce information - Human rights policies and processes | C59: =IF(D59=TRUE, template_label_classified_or_sensitive_information, IF( AND( COUNTIF('Social Disclosures'!I172:I181, template_label_missing_value) > 0, COUNTIF('Social Disclosures'!I172:I181, template_label_value_inconsistency) = 0, COUNTIF('Social Disclosures'!I172:I181, template_label_ok) >= 0 ), template_label_missing_value, IF( AND( COUNTIF('Social Disclosures'!I172:I181, template_label_value_inconsistency) > 0, COUNTIF('Social Disclosures'!I172:I181, template_label_missing_value) = 0, COUNTIF('Social Disclosures'!I172:I181, template_label_ok) >= 0 ), template_label_value_inconsistency, IF( AND( COUNTIF('Social Disclosures'!I172:I181, template_label_value_inconsistency) > 0, COUNTIF('Social Disclosures'!I172:I181, template_label_missing_value) > 0, COUNTIF('Social Disclosures'!I172:I181, template_label_ok) >= 0 ), template_label_missing_value_plus_value_inconsistency, IF( AND( COUNTIF('Social Disclosures'!I172:I181, template_label_value_inconsistency) = 0, COUNTIF('Social Disclosures'!I172:I181, template_label_missing_value) = 0, COUNTIF('Social Disclosures'!I172:I181, template_label_ok) > 0 ), template_label_ok, "-" ) ) )) ) -> - | D59: FALSE | E59: =IF(AND(C59=template_label_classified_or_sensitive_information,OR(COUNTIF(UndertakingHasACodeOfConductOrHumanRightsPolicyForItsOwnWorkforce,"<>")>0,COUNTIF('Social Disclosures'!D180:H181,"<>")>0,COUNTIF(TypeOfContentCoveredByTheCodeOfConductOrHumanRightsPolicyForItsOwnWorkforce,TRUE)>0)),template_label_information_on_sensitive_information_before_converting,"")
B60: =template_label_c7_severe_negative_human_rights_incidents_validation -> C7 - Severe negative human rights incidents | C60: =IF(D60=TRUE, template_label_classified_or_sensitive_information, IF( AND( COUNTIF('Social Disclosures'!I184:I194, template_label_missing_value) > 0, COUNTIF('Social Disclosures'!I184:I194, template_label_value_inconsistency) = 0, COUNTIF('Social Disclosures'!I184:I194, template_label_ok) >= 0 ), template_label_missing_value, IF( AND( COUNTIF('Social Disclosures'!I184:I194, template_label_value_inconsistency) > 0, COUNTIF('Social Disclosures'!I184:I194, template_label_missing_value) = 0, COUNTIF('Social Disclosures'!I184:I194, template_label_ok) >= 0 ), template_label_value_inconsistency, IF( AND( COUNTIF('Social Disclosures'!I184:I194, template_label_value_inconsistency) > 0, COUNTIF('Social Disclosures'!I184:I194, template_label_missing_value) > 0, COUNTIF('Social Disclosures'!I184:I194, template_label_ok) >= 0 ), template_label_missing_value_plus_value_inconsistency, IF( AND( COUNTIF('Social Disclosures'!I184:I194, template_label_value_inconsistency) = 0, COUNTIF('Social Disclosures'!I184:I194, template_label_missing_value) = 0, COUNTIF('Social Disclosures'!I184:I194, template_label_ok) > 0 ), template_label_ok, "-" ) ) )) ) -> - | D60: FALSE | E60: =IF(AND(C60=template_label_classified_or_sensitive_information,OR(COUNTIF(UndertakingHasConfirmedHumanRightsIncidentsInItsOwnWorkforce,"<>")>0,COUNTIF(TypeOfHumanRightRelatedToTheConfirmedIncident,TRUE)>0,COUNTIF('Social Disclosures'!D191:H194,"<>"))),template_label_information_on_sensitive_information_before_converting,"")
B61: =template_label_governance_disclosures_validation -> Governance Disclosures
B62: =template_label_c8_revenues_from_certain_sectors_and_exclusion_from_eu_reference_benchmarks_validation -> C8 - Revenues from certain activities and exclusion from EU reference benchmarks | C62: =IF(D62=TRUE,template_label_classified_or_sensitive_information, IF(COUNTIF(C63:C64,template_label_error_plus_missing_value_plus_value_inconsistency)>0,template_label_error_plus_missing_value_plus_value_inconsistency, IF(COUNTIF(C63:C64,template_label_error_plus_value_inconsistency)>0,template_label_error_plus_value_inconsistency, IF(COUNTIF(C63:C64,template_label_error_plus_missing_value)>0,template_label_error_plus_missing_value, IF(COUNTIF(C63:C64,template_label_error)>0,template_label_error, IF(COUNTIF(C63:C64,template_label_missing_value_plus_value_inconsistency)>0,template_label_missing_value_plus_value_inconsistency, IF(COUNTIF(C63:C64,template_label_value_inconsistency)>0,template_label_value_inconsistency, IF(COUNTIF(C63:C64,template_label_missing_value)>0,template_label_missing_value, IF(COUNTIF(C63:C64,template_label_ok)=ROWS(C63:C64),template_label_ok, IF(COUNTIF(C63:C64,"-")=ROWS(C63:C64),"-", IF(AND(COUNTIF(C63:C64,template_label_ok)>0, COUNTIF(C63:C64,template_label_error_plus_missing_value_plus_value_inconsistency)=0, COUNTIF(C63:C64,template_label_error_plus_value_inconsistency)=0, COUNTIF(C63:C64,template_label_error_plus_missing_value)=0, COUNTIF(C63:C64,template_label_error)=0, COUNTIF(C63:C64,template_label_missing_value_plus_value_inconsistency)=0, COUNTIF(C63:C64,template_label_value_inconsistency)=0, COUNTIF(C63:C64,template_label_missing_value)=0), template_label_ok, "-"))))))))))) -> - | D62: =IF(COUNTIF(D63:D64,TRUE)=ROWS(D63:D64),TRUE,FALSE) -> FALSE
B63: =template_label_c8_revenues_from_certain_sectors -> C8 - Revenues from certain activities | C63: =IF(D63=TRUE, template_label_classified_or_sensitive_information, IF(COUNTIF('Governance Disclosures'!I12:I18, template_label_value_inconsistency) > 0, template_label_value_inconsistency, IF(COUNTIF('Governance Disclosures'!I12:I18, template_label_ok) > 0, template_label_ok, "-")) ) -> - | D63: FALSE | E63: =IF(AND(C63=template_label_classified_or_sensitive_information,COUNTIF('Governance Disclosures'!H10,TRUE)>0),template_label_information_on_sensitive_information_before_converting,"")
B64: =template_label_c8_exclusion_from_eu_reference_benchmarks -> C8 - Exclusion from EU reference benchmarks | C64: =IF(D64=TRUE, template_label_classified_or_sensitive_information, IF(COUNTIF('Governance Disclosures'!I22:I26, template_label_missing_value) > 0, template_label_missing_value, IF(COUNTIF('Governance Disclosures'!I22:I26, template_label_ok) > 0, template_label_ok, "-")) ) -> - | D64: FALSE | E64: =IF(AND(C64=template_label_classified_or_sensitive_information,COUNTIF('Governance Disclosures'!H22:H26,TRUE)>0),template_label_information_on_sensitive_information_before_converting,"")
B65: =template_label_c9_gender_diversity_ratio_in_the_governance_body_validation -> C9 - Gender diversity ratio in the governance body | C65: =IF(D65=TRUE, template_label_classified_or_sensitive_information, IF(COUNTIF('Governance Disclosures'!I31:I32, template_label_missing_value) > 0, template_label_missing_value, IF(COUNTIF('Governance Disclosures'!I31:I32, template_label_ok) > 0, template_label_ok, "-")) ) -> - | D65: FALSE | E65: =IF(AND(C65=template_label_classified_or_sensitive_information,COUNTIF('Governance Disclosures'!H30,"<>")>0),template_label_information_on_sensitive_information_before_converting,"")
B66: =template_label_additional_disclosures_validation -> Additional Disclosures
B67: =template_label_disclosure_of_any_other_general_and_or_entity_specific_information_on_the_reporting_period -> Disclosure of any other general and/or entity specific information on the reporting period | C67: =IF(D67=TRUE, template_label_classified_or_sensitive_information, IF('General Information'!I533 = template_label_ok, template_label_ok, "-") ) -> - | D67: FALSE | E67: =IF(AND(C67=template_label_classified_or_sensitive_information,COUNTIF(DisclosureOfAnyOtherGeneralAndOrEntitySpecificInformation,"<>")>0),template_label_information_on_sensitive_information_before_converting,"")
B68: =template_label_disclosure_of_any_other_environmental_and_or_entity_specific_environmental_disclosures -> Disclosure of any other environmental and/or entity specific environmental disclosures | C68: =IF(D68=TRUE, template_label_classified_or_sensitive_information, IF('Environmental Disclosures'!M548 = template_label_ok, template_label_ok, "-") ) -> - | D68: FALSE | E68: =IF(AND(C68=template_label_classified_or_sensitive_information,COUNTIF(DisclosureOfAnyOtherEnvironmentalAndOrEntitySpecificEnvironmentalDisclosures,"<>")>0),template_label_information_on_sensitive_information_before_converting,"")
B69: =template_label_disclosure_of_any_other_social_and_or_entity_specific_social_disclosures -> Disclosure of any other social and/or entity specific social disclosures | C69: =IF(D69=TRUE, template_label_classified_or_sensitive_information, IF('Social Disclosures'!I200 = template_label_ok, template_label_ok, "-") ) -> - | D69: FALSE | E69: =IF(AND(C69=template_label_classified_or_sensitive_information,COUNTIF(DisclosureOfAnyOtherSocialAndOrEntitySpecificSocialDisclosures,"<>")>0),template_label_information_on_sensitive_information_before_converting,"")
B70: =template_label_disclosure_of_any_other_governance_and_or_entity_specific_governance_disclosures -> Disclosure of any other governance and/or entity specific governance disclosures | C70: =IF(D70=TRUE, template_label_classified_or_sensitive_information, IF('Governance Disclosures'!I38 = template_label_ok, template_label_ok, "-") ) -> - | D70: FALSE | E70: =IF(AND(C70=template_label_classified_or_sensitive_information,COUNTIF(DisclosureOfAnyOtherGovernanceAndOrEntitySpecificGovernanceDisclosures,"<>")>0),template_label_information_on_sensitive_information_before_converting,"")

Sheet General Information
A1: =template_label_paragraph_reference -> Paragraph Reference | B1: =template_label_paragraph_guidance_reference -> Paragraph Guidance Reference
C2: =template_label_information_on_the_report_necessary_for_xbrl & " " & template_label_always_to_be_reported -> Information on the report necessary for XBRL [Always to be reported]
C3: =template_label_name_of_the_reporting_entity -> Name of the reporting entity | F3: =IF(D3 = "", template_label_missing_value, template_label_ok) -> MISSING VALUE
C4: =template_label_identifier_of_the_reporting_entity -> Identifier of the reporting entity (select and specify on the right) | F4: =IF(OR(D4 = "", E4 = ""), template_label_missing_value, template_label_ok) -> MISSING VALUE | G4: =template_label_identifier_warning -> ℹ️ The entity identifier is a unique ID, that will enable identifying the company that has reported the information. The VSME Standard does not require any specific identifier. An entity identifier is required for the digital reporting.
C5: =template_label_currency_of_the_monetary_values_in_the_report -> Currency of the monetary values in the report | F5: =IF(D5 = "", template_label_missing_value, template_label_ok) -> MISSING VALUE
C6: =template_label_starting_year -> Starting year | F6: =IF(OR(D6 = "", D7 = "", D8 = ""), template_label_missing_value, IF(OR( AND(D7 = 2, D8 > 29), AND(D7 = 2, D8 = 29, NOT(AND(MOD(D6, 4) = 0, OR(MOD(D6, 100) <> 0, MOD(D6, 400) = 0)))), AND(OR(D7 = 4, D7 = 6, D7 = 9, D7 = 11), D8 = 31) ), template_label_error, IF(F10 = template_label_value_inconsistency, template_label_value_inconsistency, template_label_ok) ) ) -> MISSING VALUE | G6: =template_label_date_warning -> ℹ️ If VALUE INCONSISTENCY message appears on the right, please ensure that the reporting period end date is greater than the reporting period start date.
C7: =template_label_starting_month -> Starting month
C8: =template_label_starting_day -> Starting day
C9: =template_label_reporting_period_start_date -> Reporting period start date (yyyy-mm-dd) | D9: =IF(OR(ISBLANK(D6), ISBLANK(D7), ISBLANK(D8)), "-", D6 & "-" & TEXT(D7, "00") & "-" & TEXT(D8, "00")) -> -
C10: =template_label_ending_year -> Ending year | F10: =IF(OR(D10 = "", D11 = "", D12 = ""), template_label_missing_value, IF(OR( AND(D11 = 2, D12 > 29), AND(D11 = 2, D12 = 29, NOT(AND(MOD(D10, 4) = 0, OR(MOD(D10, 100) <> 0, MOD(D10, 400) = 0)))), AND(OR(D11 = 4, D11 = 6, D11 = 9, D11 = 11), D12 = 31) ), template_label_error, IF(D10 < D6, template_label_value_inconsistency, IF(D10 > D6, template_label_ok, IF(AND(D10 = D6, MATCH(D11, {1;2;3;4;5;6;7;8;9;10;11;12}, 0) < MATCH(D7, {1;2;3;4;5;6;7;8;9;10;11;12}, 0)), template_label_value_inconsistency, IF(AND(D10 = D6, MATCH(D11, {1;2;3;4;5;6;7;8;9;10;11;12}, 0) > MATCH(D7, {1;2;3;4;5;6;7;8;9;10;11;12}, 0)), template_label_ok, IF(AND(D10 = D6, MATCH(D11, {1;2;3;4;5;6;7;8;9;10;11;12}, 0) = MATCH(D7, {1;2;3;4;5;6;7;8;9;10;11;12}, 0), D12 < D8), template_label_value_inconsistency, template_label_ok ))))))) -> MISSING VALUE | G10: =template_label_date_warning -> ℹ️ If VALUE INCONSISTENCY message appears on the right, please ensure that the reporting period end date is greater than the reporting period start date.
C11: =template_label_ending_month -> Ending month
C12: Ending day
C13: =template_label_reporting_period_end_date -> Reporting period end date (yyyy-mm-dd) | D13: =IF(OR(ISBLANK(D10), ISBLANK(D11), ISBLANK(D12)), "-", D10 & "-" & TEXT(D11, "00") & "-" & TEXT(D12, "00")) -> -
C16: =template_label_information_on_previous_reporting_period -> Information on previous reporting period
C17: 16
C18: =template_label_disclosures_from_the_previous_reporting_period_that_remain_unchanged -> This report contains disclosures from the previous reporting period that remain unchanged | E18: FALSE | F18: =IF(E18 = FALSE, "", template_label_ok)
C19: =template_label_disclosures_for_which_no_changes_are_reported_compared_to_the_previous_period_reporting -> List of disclosures for which no changes are reported compared to the previous period reporting | F19: =IF(AND(E18 = FALSE, E19 = ""), "", IF(AND(E18 = FALSE, E19 <> ""), "", IF(AND(E18 = TRUE, E19 = ""), template_label_missing_value, IF(AND(E18 = TRUE, E19 <> "", COUNTIF(E19:E118, E19) = COUNTA(E19:E118), COUNTA(E19:E118) > 1), template_label_value_inconsistency, template_label_ok)))) | G19: =template_label_additional_rows_warning -> ℹ️ Lists can be expanded using the little [+] button on the left. If the number of rows is not sufficient, those can be added by right clicking the second row and selecting "Insert row".
F20: =IF($E$18 = FALSE, "", IF(E20 = "", "", IF(COUNTIF($E$19:$E$118, E20) > 1, template_label_value_inconsistency, template_label_ok)))
F21: =IF($E$18 = FALSE, "", IF(E21 = "", "", IF(COUNTIF($E$19:$E$118, E21) > 1, template_label_value_inconsistency, template_label_ok)))
F22: =IF($E$18 = FALSE, "", IF(E22 = "", "", IF(COUNTIF($E$19:$E$118, E22) > 1, template_label_value_inconsistency, template_label_ok)))
F23: =IF($E$18 = FALSE, "", IF(E23 = "", "", IF(COUNTIF($E$19:$E$118, E23) > 1, template_label_value_inconsistency, template_label_ok)))
F24: =IF($E$18 = FALSE, "", IF(E24 = "", "", IF(COUNTIF($E$19:$E$118, E24) > 1, template_label_value_inconsistency, template_label_ok)))
F25: =IF($E$18 = FALSE, "", IF(E25 = "", "", IF(COUNTIF($E$19:$E$118, E25) > 1, template_label_value_inconsistency, template_label_ok)))
F26: =IF($E$18 = FALSE, "", IF(E26 = "", "", IF(COUNTIF($E$19:$E$118, E26) > 1, template_label_value_inconsistency, template_label_ok)))
F27: =IF($E$18 = FALSE, "", IF(E27 = "", "", IF(COUNTIF($E$19:$E$118, E27) > 1, template_label_value_inconsistency, template_label_ok)))
C119: =template_label_link_to_previous_report_containing_disclosures_that_remain_unchanged -> Link to previous report containing disclosures that remain unchanged | F119: =IF(AND(E18 = FALSE, E119 = ""), "", IF(AND(E18 = TRUE, E119 = ""), template_label_missing_value, IF(AND(E18 = FALSE, E119 <> ""), "", IF(AND(E18 = TRUE, E119 <> "", OR(LEFT(E119, 7) = "http://", LEFT(E119, 8) = "https://", LEFT(E119, 4) = "www.")), template_label_ok, IF(E18 = TRUE, template_label_invalid_url, template_label_missing_value)))))
C121: =template_label_b1_basis_for_preparation & " " & template_label_from & " " & template_starting_date_display & " " & template_label_to & " " & template_ending_date_display & " " & template_label_always_to_be_reported -> B1 - Basis for Preparation & Module from - to - [Always to be reported]
A122: 24(a) | B122: N/A | C122: =template_label_basis_for_preparation -> Basis for preparation (Basic Module Only or Basic & Comprehensive Module) | F122: =IF( 'Table of Contents & Validation'!D11=TRUE, IF(E122 = "", "", template_label_ok), IF(E122 = "", template_label_missing_value, template_label_ok) ) -> MISSING VALUE
A123: 24(b) | B123: N/A | C123: =template_label_list_of_omitted_disclosures_deemed_to_be_classified_or_sensitive_information -> List of omitted disclosures deemed to be classified or sensitive information | E123: =IF('Technical Sheet'!E167=0,template_label_none,_xlfn.XLOOKUP('Technical Sheet'!A28, 'Technical Sheet'!E106:E166, 'Table of Contents & Validation'!B10:B70, "")) -> None | G123: =template_label_bold_omitted_information -> ℹ️ Whenever a disclosure is fully omitted because sensitive or classfied, it will be highligted in bold
E124: =_xlfn.XLOOKUP('Technical Sheet'!A29, 'Technical Sheet'!E107:E167, 'Table of Contents & Validation'!B11:B71, "")
E125: =_xlfn.XLOOKUP('Technical Sheet'!A30, 'Technical Sheet'!E108:E168, 'Table of Contents & Validation'!B12:B72, "")
E126: =_xlfn.XLOOKUP('Technical Sheet'!A31, 'Technical Sheet'!E109:E169, 'Table of Contents & Validation'!B13:B73, "")
E127: =_xlfn.XLOOKUP('Technical Sheet'!A32, 'Technical Sheet'!E110:E170, 'Table of Contents & Validation'!B14:B74, "")
E128: =_xlfn.XLOOKUP('Technical Sheet'!A33, 'Technical Sheet'!E111:E171, 'Table of Contents & Validation'!B15:B75, "")
E129: =_xlfn.XLOOKUP('Technical Sheet'!A34, 'Technical Sheet'!E112:E172, 'Table of Contents & Validation'!B16:B76, "")
E130: =_xlfn.XLOOKUP('Technical Sheet'!A35, 'Technical Sheet'!E112:E173, 'Table of Contents & Validation'!B16:B77, "")
E131: =_xlfn.XLOOKUP('Technical Sheet'!A36, 'Technical Sheet'!E113:E174, 'Table of Contents & Validation'!B17:B78, "")
E132: =_xlfn.XLOOKUP('Technical Sheet'!A37, 'Technical Sheet'!E114:E175, 'Table of Contents & Validation'!B18:B79, "")
E133: =_xlfn.XLOOKUP('Technical Sheet'!A38, 'Technical Sheet'!E115:E176, 'Table of Contents & Validation'!B19:B80, "")
E134: =_xlfn.XLOOKUP('Technical Sheet'!A39, 'Technical Sheet'!E116:E177, 'Table of Contents & Validation'!B20:B81, "")
E135: =_xlfn.XLOOKUP('Technical Sheet'!A40, 'Technical Sheet'!E117:E178, 'Table of Contents & Validation'!B21:B82, "")
E136: =_xlfn.XLOOKUP('Technical Sheet'!A41, 'Technical Sheet'!E118:E179, 'Table of Contents & Validation'!B22:B83, "")
E137: =_xlfn.XLOOKUP('Technical Sheet'!A42, 'Technical Sheet'!E119:E180, 'Table of Contents & Validation'!B23:B84, "")
E138: =_xlfn.XLOOKUP('Technical Sheet'!A43, 'Technical Sheet'!E120:E181, 'Table of Contents & Validation'!B24:B85, "")
E139: =_xlfn.XLOOKUP('Technical Sheet'!A44, 'Technical Sheet'!E121:E182, 'Table of Contents & Validation'!B25:B86, "")
E140: =_xlfn.XLOOKUP('Technical Sheet'!A45, 'Technical Sheet'!E122:E183, 'Table of Contents & Validation'!B26:B87, "")
E141: =_xlfn.XLOOKUP('Technical Sheet'!A46, 'Technical Sheet'!E123:E184, 'Table of Contents & Validation'!B27:B88, "")
... E174: =_xlfn.XLOOKUP('Technical Sheet'!A79, 'Technical Sheet'!E156:E217, 'Table of Contents & Validation'!B60:B121, "")
C176: =template_label_b1_other_undertakings_general_information & " " & template_label_from & " " & template_starting_date_display & " " & template_label_to & " " & template_ending_date_display & " " & template_label_always_to_be_reported -> B1 - Other undertaking's general information from - to - [Always to be reported]
A177: 24(c) | B177: N/A | C177: =template_label_basis_for_reporting -> Basis for reporting (consolidated or individual basis) | F177: =IF( OR( 'Table of Contents & Validation'!D12=TRUE, 'Table of Contents & Validation'!D10=TRUE ), IF( AND( OR( E122="Option A (Basic Module only)", E122="Option B (Basic Module and Comprehensive Module)" ), E177="" ), "", IF( AND(E122<>"", E177<>""), template_label_ok, "" ) ), IF( AND( OR( E122="Option A (Basic Module only)", E122="Option B (Basic Module and Comprehensive Module)" ), E177="" ), template_label_missing_value, IF( AND(E122<>"", E177<>""), template_label_ok, "" ) ) )
A178: 24(e)(i) | B178: 4 | C178: =template_label_undertakings_legal_form -> Undertakings legal form | F178: =IF(OR( 'Table of Contents & Validation'!D12=TRUE, 'Table of Contents & Validation'!D10=TRUE),IF(AND(OR(E122="Option A (Basic Module only)",E122="Option B (Basic Module and Comprehensive Module)"),E178=""), "", IF(E122="","",template_label_ok)), IF(AND(OR(E122="Option A (Basic Module only)",E122="Option B (Basic Module and Comprehensive Module)"),E178=""), template_label_missing_value, IF(E122="","",template_label_ok)) ) | G178: =template_label_other_warning -> ℹ️ When "other" is chosen as undertaking legal form please fill the row below
C179: =template_label_other_undertakings_legal_form_specification -> Other undertaking's legal form specification | F179: =IF( 'Table of Contents & Validation'!D11=TRUE, IF(AND(E178 = "other (please specify the legal form in the row below)", E179 <> ""), template_label_ok, IF(AND(E178 = "other (please specify the legal form in the row below)", E179 = ""), template_label_missing_value, IF(AND(E178 = "", E179 = ""), "", IF(AND(E178 <> "other (please specify the legal form in the row below)", E179 = ""), "", "")))), IF(AND(E178 = "other (please specify the legal form in the row below)", E179 <> ""), template_label_ok, IF(AND(E178 = "other (please specify the legal form in the row below)", E179 = ""), template_label_missing_value, IF(AND(E178 = "", E179 = ""), "", IF(AND(E178 <> "other (please specify the legal form in the row below)", E179 = ""), "", "")))) )
A180: 24(e)(ii) | B180: 5-6 | C180: =template_label_nace_sector_classification_code -> NACE sector classification code(s) | F180: =IF(OR( 'Table of Contents & Validation'!D12=TRUE,'Table of Contents & Validation'!D10=TRUE),IF(OR(E122="Option A (Basic Module only)",E122="Option B (Basic Module and Comprehensive Module)"), IF(COUNTIF(enum_ListNACECategories,E180)>0,template_label_error, IF(E180="","", IF(COUNTIF($E$180:$E$279,E180)>1,template_label_value_inconsistency,template_label_ok) ) ), "" ), IF(OR(E122="Option A (Basic Module only)",E122="Option B (Basic Module and Comprehensive Module)"), IF(COUNTIF(enum_ListNACECategories,E180)>0,template_label_error, IF(E180="",template_label_missing_value, IF(COUNTIF($E$180:$E$279,E180)>1,template_label_value_inconsistency,template_label_ok) ) ), "" ) ) | G180: =template_label_NACE_warning -> ℹ️ Please select a NACE code rather than a category else an ERROR message will appear.
F181: =IF(COUNTIF(enum_ListNACECategories, E181) > 0, template_label_error, IF(E181 = "", "", IF(COUNTIF($E$180:$E$279, E181) > 1, template_label_value_inconsistency, template_label_ok)))
F182: =IF(COUNTIF(enum_ListNACECategories, E182) > 0, template_label_error, IF(E182 = "", "", IF(COUNTIF($E$180:$E$279, E182) > 1, template_label_value_inconsistency, template_label_ok)))
F183: =IF(COUNTIF(enum_ListNACECategories, E183) > 0, template_label_error, IF(E183 = "", "", IF(COUNTIF($E$180:$E$279, E183) > 1, template_label_value_inconsistency, template_label_ok)))
F184: =IF(COUNTIF(enum_ListNACECategories, E184) > 0, template_label_error, IF(E184 = "", "", IF(COUNTIF($E$180:$E$279, E184) > 1, template_label_value_inconsistency, template_label_ok)))
F185: =IF(COUNTIF(enum_ListNACECategories, E185) > 0, template_label_error, IF(E185 = "", "", IF(COUNTIF($E$180:$E$279, E185) > 1, template_label_value_inconsistency, template_label_ok)))
F186: =IF(COUNTIF(enum_ListNACECategories, E186) > 0, template_label_error, IF(E186 = "", "", IF(COUNTIF($E$180:$E$279, E186) > 1, template_label_value_inconsistency, template_label_ok)))
F187: =IF(COUNTIF(enum_ListNACECategories, E187) > 0, template_label_error, IF(E187 = "", "", IF(COUNTIF($E$180:$E$279, E187) > 1, template_label_value_inconsistency, template_label_ok)))
F188: =IF(COUNTIF(enum_ListNACECategories, E188) > 0, template_label_error, IF(E188 = "", "", IF(COUNTIF($E$180:$E$279, E188) > 1, template_label_value_inconsistency, template_label_ok)))
F189: =IF(COUNTIF(enum_ListNACECategories, E189) > 0, template_label_error, IF(E189 = "", "", IF(COUNTIF($E$180:$E$279, E189) > 1, template_label_value_inconsistency, template_label_ok)))
F190: =IF(COUNTIF(enum_ListNACECategories, E190) > 0, template_label_error, IF(E190 = "", "", IF(COUNTIF($E$180:$E$279, E190) > 1, template_label_value_inconsistency, template_label_ok)))
F191: =IF(COUNTIF(enum_ListNACECategories, E191) > 0, template_label_error, IF(E191 = "", "", IF(COUNTIF($E$180:$E$279, E191) > 1, template_label_value_inconsistency, template_label_ok)))
F192: =IF(COUNTIF(enum_ListNACECategories, E192) > 0, template_label_error, IF(E192 = "", "", IF(COUNTIF($E$180:$E$279, E192) > 1, template_label_value_inconsistency, template_label_ok)))
... F279: =IF(COUNTIF(enum_ListNACECategories, E279) > 0, template_label_error, IF(E279 = "", "", IF(COUNTIF($E$180:$E$279, E279) > 1, template_label_value_inconsistency, template_label_ok)))
A280: 24(e)(iii) | B280: N/A | C280: =template_label_size_of_balance_sheet_in & " " & template_currency -> Size of balance sheet (total assets) in | F280: =IF(OR( 'Table of Contents & Validation'!D12=TRUE,'Table of Contents & Validation'!D10=TRUE),IF(AND(OR(E122="Option A (Basic Module only)",E122="Option B (Basic Module and Comprehensive Module)"),E280=""), "", IF(E122="","",template_label_ok)), IF(AND(OR(E122="Option A (Basic Module only)",E122="Option B (Basic Module and Comprehensive Module)"),E280=""), template_label_missing_value, IF(E122="","",template_label_ok)) )
A281: 24(e)(iv) | B281: N/A | C281: =template_label_turnover_in & " " & template_currency -> Turnover in | F281: =IF(OR( 'Table of Contents & Validation'!D12=TRUE,'Table of Contents & Validation'!D10=TRUE), IF(AND(OR(E122 = "Option A (Basic Module only)", E122 = "Option B (Basic Module and Comprehensive Module)"), E281 = ""), "", IF(E122 = "", "", template_label_ok)), IF(AND(OR(E122 = "Option A (Basic Module only)", E122 = "Option B (Basic Module and Comprehensive Module)"), E281 = ""), template_label_missing_value, IF(E122 = "", "", template_label_ok)) )
A282: 24(e)(v) | B282: 7-8 | C282: =+template_label_number_of_employees -> Number of employees | F282: =IF(OR( 'Table of Contents & Validation'!D12=TRUE, 'Table of Contents & Validation'!D10=TRUE), IF(AND(OR(E122 = "Option A (Basic Module only)", E122 = "Option B (Basic Module and Comprehensive Module)"), E282 = ""), "", IF(E122 = "", "", template_label_ok)), IF(AND(OR(E122 = "Option A (Basic Module only)", E122 = "Option B (Basic Module and Comprehensive Module)"), E282 = ""), template_label_missing_value, IF(E122 = "", "", template_label_ok)) )
A283: 24(e)(v) | B283: 7-8 | C283: =template_label_employee_counting_methodology_end_of_reporting_period_or_average_during_the_reporting_period -> Employee counting methodology (At the end of reporting period or as an average during the reporting period) | F283: =IF(OR( 'Table of Contents & Validation'!D12=TRUE, 'Table of Contents & Validation'!D10=TRUE), IF(AND(OR(E122 = "Option A (Basic Module only)", E122 = "Option B (Basic Module and Comprehensive Module)"), E283 = ""), "", IF(E122 = "", "", template_label_ok)), IF(AND(OR(E122 = "Option A (Basic Module only)", E122 = "Option B (Basic Module and Comprehensive Module)"), E283 = ""), template_label_missing_value, IF(E122 = "", "", template_label_ok)) )
A284: 24(e)(v) | B284: 7-8 | C284: =template_label_employee_counting_methodology_headcount_or_fulltime_equivalent -> Employee counting methodology (Headcount or Full-time equivalent) | F284: =IF(OR( 'Table of Contents & Validation'!D12=TRUE, 'Table of Contents & Validation'!D10=TRUE), IF(AND(OR(E122 = "Option A (Basic Module only)", E122 = "Option B (Basic Module and Comprehensive Module)"), E284 = ""), "", IF(E122 = "", "", template_label_ok)), IF(AND(OR(E122 = "Option A (Basic Module only)", E122 = "Option B (Basic Module and Comprehensive Module)"), E284 = ""), template_label_missing_value, IF(E122 = "", "", template_label_ok)) )
A285: 24(e)(vi) | B285: 9-12 | C285: =template_label_country_of_primary_operations_and_location_of_significant_asset -> Country of primary operations and location of significant asset(s) | F285: =IF(OR( 'Table of Contents & Validation'!D12=TRUE, 'Table of Contents & Validation'!D10=TRUE), IF(AND(OR(E122 = "Option A (Basic Module only)", E122 = "Option B (Basic Module and Comprehensive Module)"), E285 = ""), "", IF(E122 = "", "", template_label_ok)), IF(AND(OR(E122 = "Option A (Basic Module only)", E122 = "Option B (Basic Module and Comprehensive Module)"), E285 = ""), template_label_missing_value, IF(E122 = "", "", template_label_ok)) )
C287: =template_label_b1_list_of_subsidiaries & " " & template_label_from & " " & template_starting_date_display & " " & template_label_to & " " & template_ending_date_display & " " & template_label_if_applicable -> B1 - List of subsidiaries from - to - [If applicable]
C288: 24(d)
C289: =template_label_id -> ID | D289: =template_label_name -> Name | E289: =template_label_registered_address -> Registered Address
C290: 1 | F290: =IF(AND(BasisForReporting="Sustainability report prepared on a consolidated basis", D290<>"", E290=""), template_label_missing_value, IF(AND(BasisForReporting="Sustainability report prepared on a consolidated basis", D290<>"", E290<>""), template_label_ok, IF(AND(BasisForReporting="Sustainability report prepared on a consolidated basis", D290="", E290=""), template_label_missing_value, ""))) | G290: =template_label_additional_rows_warning -> ℹ️ Lists can be expanded using the little [+] button on the left. If the number of rows is not sufficient, those can be added by right clicking the second row and selecting "Insert row".
C291: 2 | F291: =IF(AND(D291<>"",E291=""), template_label_missing_value, IF(AND(D291<>"",E291<>""), template_label_ok, IF(AND(D291="",E291=""), "", template_label_missing_value)))
C292: 3 | F292: =IF(AND(D292<>"",E292=""), template_label_missing_value, IF(AND(D292<>"",E292<>""), template_label_ok, IF(AND(D292="",E292=""), "", template_label_missing_value)))
C293: 4 | F293: =IF(AND(D293<>"",E293=""), template_label_missing_value, IF(AND(D293<>"",E293<>""), template_label_ok, IF(AND(D293="",E293=""), "", template_label_missing_value)))
C294: 5 | F294: =IF(AND(D294<>"",E294=""), template_label_missing_value, IF(AND(D294<>"",E294<>""), template_label_ok, IF(AND(D294="",E294=""), "", template_label_missing_value)))
C295: 6 | F295: =IF(AND(D295<>"",E295=""), template_label_missing_value, IF(AND(D295<>"",E295<>""), template_label_ok, IF(AND(D295="",E295=""), "", template_label_missing_value)))
C296: 7 | F296: =IF(AND(D296<>"",E296=""), template_label_missing_value, IF(AND(D296<>"",E296<>""), template_label_ok, IF(AND(D296="",E296=""), "", template_label_missing_value)))
C297: 8 | F297: =IF(AND(D297<>"",E297=""), template_label_missing_value, IF(AND(D297<>"",E297<>""), template_label_ok, IF(AND(D297="",E297=""), "", template_label_missing_value)))
C298: 9 | F298: =IF(AND(D298<>"",E298=""), template_label_missing_value, IF(AND(D298<>"",E298<>""), template_label_ok, IF(AND(D298="",E298=""), "", template_label_missing_value)))
C299: 10 | F299: =IF(AND(D299<>"",E299=""), template_label_missing_value, IF(AND(D299<>"",E299<>""), template_label_ok, IF(AND(D299="",E299=""), "", template_label_missing_value)))
C300: 11 | F300: =IF(AND(D300<>"",E300=""), template_label_missing_value, IF(AND(D300<>"",E300<>""), template_label_ok, IF(AND(D300="",E300=""), "", template_label_missing_value)))
C301: 12 | F301: =IF(AND(D301<>"",E301=""), template_label_missing_value, IF(AND(D301<>"",E301<>""), template_label_ok, IF(AND(D301="",E301=""), "", template_label_missing_value)))
C302: 13 | F302: =IF(AND(D302<>"",E302=""), template_label_missing_value, IF(AND(D302<>"",E302<>""), template_label_ok, IF(AND(D302="",E302=""), "", template_label_missing_value)))
... C389: 100 | F389: =IF(AND(D389<>"",E389=""), template_label_missing_value, IF(AND(D389<>"",E389<>""), template_label_ok, IF(AND(D389="",E389=""), "", template_label_missing_value)))
C391: =template_label_b1_disclosure_of_sustainability_related_certification_or_label & " " & template_label_from & " " & template_starting_date_display & " " & template_label_to & " " & template_ending_date_display & " " & template_label_if_applicable -> B1 - Disclosure of sustainability-related certification(s) or label(s) from - to - [If applicable]
C392: 25
C393: 13
C394: =template_label_has_the_undertaking_obtained_any_sustainability_related_certification_or_label -> Has the undertaking obtained any sustainability-related certification(s) or label(s) ? | E394: FALSE
C395: =template_label_description_of_sustainability_related_certification_or_label -> Description of sustainability-related certification(s) or label(s) including where relevant the issuers of the certification or label date and rating score | I395: =IF(AND(E394=TRUE,E395=""), template_label_missing_value, IF(AND(E394=TRUE,E395<>""), template_label_ok, ""))
C397: =template_label_b1_list_of_site& " " & template_label_from & " " & template_starting_date_display & " " & template_label_to & " " & template_ending_date_display & " " & template_label_always_to_be_reported -> B1 - List of site(s) from - to - [Always to be reported]
C398: 24(e)(vii)
C399: 9-12
C400: =template_label_id -> ID | D400: =template_label_address -> Address | E400: =template_label_postal_code -> Postal code | F400: =template_label_city -> City | G400: =template_label_country -> Country | H400: =template_label_gps_coordinates -> GPS Coordinates (geolocation)
H401: =template_label_automatic_geolocation -> Automatic geolocation: enabling the OpenStreetMaps's automatic geolocation with the checkbox below the undertaking is declaring to be fully aware and in acceptance of Nominatim Usage Policy and Privacy Policy. OpenStreetMap® is open data licensed under the Open Data Commons Open Database License (ODbL) by the OpenStreetMap Foundation (OSMF). All data belong and are owned by OpenStreetMap®.
H402: Nominatim Usage Policy (Geocoding Policy) Privacy Policy
...

Sheet Environmental Disclosures
A1: =template_label_paragraph_reference -> Paragraph Reference | B1: =template_label_paragraph_guidance_reference -> Paragraph Guidance Reference
C2: =template_label_b3_total_energy_consumption&" "&template_label_from&" "&template_starting_date_display&" "&template_label_to&" "&template_ending_date_display&" "&template_label_always_to_be_reported -> B3 - Total Energy Consumption (in MWh) from - to - [Always to be reported]
C3: 29
C4: 18-25
C5: =template_label_total_energy_consumption -> Total Energy Consumption | L5: =IF(OR( 'Table of Contents & Validation'!D20=TRUE, 'Table of Contents & Validation'!D19=TRUE), IF(AND(OR('General Information'!E122="Option A (Basic Module only)", 'General Information'!E122="Option B (Basic Module and Comprehensive Module)"), G5=""), "", IF('General Information'!E122="", "", template_label_ok)), IF(AND(OR('General Information'!E122="Option A (Basic Module only)", 'General Information'!E122="Option B (Basic Module and Comprehensive Module)"), G5=""), template_label_missing_value, IF('General Information'!E122="", "", template_label_ok)) )
C7: =template_label_b3_breakdown_of_energy_consumption&" "&template_label_from&" "&template_starting_date_display&" "&template_label_to&" "&template_ending_date_display&" "&template_label_if_applicable -> B3 - Breakdown of energy consumption (in MWh) from - to - [If applicable]
C8: 29
C9: 18-25
C10: =template_label_has_the_undertaking_obtained_the_necessary_information_to_provide_an_energy_consumption_breakdown -> Has the undertaking obtained the necessary information to provide an energy consumption breakdown? | G10: FALSE
G11: =template_label_renewable -> Renewable | J11: =template_label_non_renewable -> Non-renewable | K11: =template_label_total_renewable_and_nonrenewable -> Total renewable and non-renewable
C12: =template_label_electricity -> Electricity (as reflected in utility billings) | K12: =IF(AND(G12="",J12=""),"-",SUM(G12:J12)) -> - | L12: {=IF(G10=TRUE, IF(SUMPRODUCT(--(G12:J14<>"-"), --(G12:J14<>""))>0, IF(SUM(G12:J14) > TotalEnergyConsumption, template_label_value_inconsistency, template_label_ok), template_label_missing_value), "")}
C13: =template_label_selfgenerated_electricity -> Self-generated electricity | K13: =IF(AND(G13="",J13=""),"-",SUM(G13:J13)) -> -
C14: =template_label_fuels -> Fuels (see Fuel Converter on Fuels worksheet) | G14: =IF('Fuel Converter'!D23=TRUE, 'Fuel Converter'!A32, "-") -> - | J14: =IF('Fuel Converter'!D23=TRUE, 'Fuel Converter'!B32, "-") -> - | K14: =IF(AND(G14="-",J14="-"),"-",SUM(G14:J14)) -> - | M14: =template_label_energy_consumption_warning -> ℹ️ Please note that the formula present in this cell may be overwritten in case the undertaking wants to directly provide the value.
C16: =template_label_b3_estimated_greenhouse_gas_emissions& " "&template_label_always_to_be_reported -> B3 - Estimated Greenhouse Gas Emissions considering the GHG Protocol Version 2004 (in tCO2e) [Always to be reported] | G16: =template_label_c3_ghg_reduction_targets&" "&template_label_if_applicable -> C3 - GHG reduction targets (in tC02e) [If applicable]
C17: 30 | G17: 54(b) | J17: 54(a) | K17: 54(d)
C18: N/A | D18: 26-45 | G18: 152-158 | J18: 152-158 | K18: 152-158
G19: =template_label_has_the_undertaking_has_established_ghg_emission_reduction_targets -> Has the undertaking has established GHG emission reduction targets? | J19: FALSE
D20: =template_label_current_reporting_period -> Current Reporting Period | G20: =template_label_base_year -> Base Year | J20: =template_label_target_year -> Target Year | K20: =template_label_percentage_reduction_from_base_year -> Percentage reduction from base year
A21: =template_label_GHG_calculator -> ℹ️ Check EFRAG website for a non-exhaustive list of GHG calculators. | C21: =template_label_year_date -> Year (date) | D21: =IF('General Information'!$D$9="", "-", 'General Information'!$D$9) & " - " & IF('General Information'!$D$13="", "-", 'General Information'!$D$13) -> - - - | L21: =IF(AND(J19=TRUE, G21<>"", J21<>""), template_label_ok, IF(AND(J19=TRUE, G21="", J21=""), template_label_missing_value, IF(AND(J19=FALSE, G21="", J21=""), "", IF(AND(J19=TRUE, OR(G21="", J21="")), template_label_missing_value, ""))))
C22: =template_label_gross_scope_1_ghg_emissions -> Gross Scope 1 GHG Emissions | K22: =IF(AND(G22="", J22=""), "-", IFERROR(-(1 - (J22 / G22)), "-")) -> - | L22: =IF(OR( 'Table of Contents & Validation'!D22=TRUE,'Table of Contents & Validation'!D19=TRUE), IF(AND(OR(BasisForPreparation="Option A (Basic Module Only)", BasisForPreparation="Option B (Basic Module and Comprehensive Module)"), D22="", J19=FALSE), "", IF(AND(OR(BasisForPreparation="Option A (Basic Module Only)", BasisForPreparation="Option B (Basic Module and Comprehensive Module)"), D22<>"", G22<>"", J22<>"", J19=TRUE), template_label_ok, IF(AND(BasisForPreparation="Option A (Basic Module Only)", D22<>"", OR(G22="", J22=""), J19=FALSE), template_label_ok, IF(AND(BasisForPreparation="Option A (Basic Module Only)", D22<>"", OR(G22="", J22=""), J19=TRUE), template_label_missing_value, IF(AND(BasisForPreparation="Option B (Basic Module and Comprehensive Module)", D22<>"", OR(G22="", J22=""), J19=TRUE), template_label_missing_value, IF(AND(BasisForPreparation="Option B (Basic Module and Comprehensive Module)", D22="", OR(G22="", J22=""), J19=TRUE), template_label_missing_value, IF(AND(BasisForPreparation="Option A (Basic Module Only)", D22<>"", G22="", J22="", J19=FALSE), template_label_ok, IF(AND(BasisForPreparation="Option B (Basic Module and Comprehensive Module)", D22<>"", G22="", J22="", J19=FALSE), template_label_ok, IF(OR(BasisForPreparation="", D22="", G22="", J22="", J19=FALSE), "", template_label_missing_value))))))))), IF(AND(OR(BasisForPreparation="Option A (Basic Module Only)", BasisForPreparation="Option B (Basic Module and Comprehensive Module)"), D22="", J19=FALSE), template_label_missing_value, IF(AND(OR(BasisForPreparation="Option A (Basic Module Only)", BasisForPreparation="Option B (Basic Module and Comprehensive Module)"), D22<>"", G22<>"", J22<>"", J19=TRUE), template_label_ok, IF(AND(BasisForPreparation="Option A (Basic Module Only)", D22<>"", OR(G22="", J22=""), J19=FALSE), template_label_ok, IF(AND(BasisForPreparation="Option A (Basic Module Only)", D22<>"", OR(G22="", J22=""), J19=TRUE), template_label_missing_value, IF(AND(BasisForPreparation="Option B (Basic Module and Comprehensive Module)", D22<>"", OR(G22="", J22=""), J19=TRUE), template_label_missing_value, IF(AND(BasisForPreparation="Option B (Basic Module and Comprehensive Module)", D22="", OR(G22="", J22=""), J19=TRUE), template_label_missing_value, IF(AND(BasisForPreparation="Option A (Basic Module Only)", D22<>"", G22="", J22="", J19=FALSE), template_label_ok, IF(AND(BasisForPreparation="Option B (Basic Module and Comprehensive Module)", D22<>"", G22="", J22="", J19=FALSE), template_label_ok, IF(OR(BasisForPreparation="", D22="", G22="", J22="", J19=FALSE), "", template_label_missing_value))))))))) )
C23: =template_label_gross_scope_2_location_based_ghg_emissions -> Gross Scope 2 location-based GHG Emissions | K23: =IF(AND(G23="", J23=""), "-", IFERROR(-(1 - (J23 / G23)), "-")) -> - | L23: =IF(OR( 'Table of Contents & Validation'!D22=TRUE,'Table of Contents & Validation'!D19=TRUE), IF(AND(OR(BasisForPreparation="Option A (Basic Module Only)", BasisForPreparation="Option B (Basic Module and Comprehensive Module)"), D23="", J19=FALSE), "", IF(AND(OR(BasisForPreparation="Option A (Basic Module Only)", BasisForPreparation="Option B (Basic Module and Comprehensive Module)"), D23<>"", G23<>"", J23<>"", J19=TRUE), template_label_ok, IF(AND(BasisForPreparation="Option A (Basic Module Only)", D23<>"", OR(G23="", J23=""), J19=FALSE), template_label_ok, IF(AND(BasisForPreparation="Option A (Basic Module Only)", D23<>"", OR(G23="", J23=""), J19=TRUE), template_label_missing_value, IF(AND(BasisForPreparation="Option B (Basic Module and Comprehensive Module)", D23<>"", OR(G23="", J23=""), J19=TRUE), template_label_missing_value, IF(AND(BasisForPreparation="Option B (Basic Module and Comprehensive Module)", D23="", OR(G23="", J23=""), J19=TRUE), template_label_missing_value, IF(AND(BasisForPreparation="Option A (Basic Module Only)", D23<>"", G23="", J23="", J19=FALSE), template_label_ok, IF(AND(BasisForPreparation="Option B (Basic Module and Comprehensive Module)", D23<>"", G23="", J23="", J19=FALSE), template_label_ok, IF(OR(BasisForPreparation="", D23="", G23="", J23="", J19=FALSE), "", template_label_missing_value))))))))), IF(AND(OR(BasisForPreparation="Option A (Basic Module Only)", BasisForPreparation="Option B (Basic Module and Comprehensive Module)"), D23="", J19=FALSE), template_label_missing_value, IF(AND(OR(BasisForPreparation="Option A (Basic Module Only)", BasisForPreparation="Option B (Basic Module and Comprehensive Module)"), D23<>"", G23<>"", J23<>"", J19=TRUE), template_label_ok, IF(AND(BasisForPreparation="Option A (Basic Module Only)", D23<>"", OR(G23="", J23=""), J19=FALSE), template_label_ok, IF(AND(BasisForPreparation="Option A (Basic Module Only)", D23<>"", OR(G23="", J23=""), J19=TRUE), template_label_missing_value, IF(AND(BasisForPreparation="Option B (Basic Module and Comprehensive Module)", D23<>"", OR(G23="", J23=""), J19=TRUE), template_label_missing_value, IF(AND(BasisForPreparation="Option B (Basic Module and Comprehensive Module)", D23="", OR(G23="", J23=""), J19=TRUE), template_label_missing_value, IF(AND(BasisForPreparation="Option A (Basic Module Only)", D23<>"", G23="", J23="", J19=FALSE), template_label_ok, IF(AND(BasisForPreparation="Option B (Basic Module and Comprehensive Module)", D23<>"", G23="", J23="", J19=FALSE), template_label_ok, IF(OR(BasisForPreparation="", D23="", G23="", J23="", J19=FALSE), "", template_label_missing_value))))))))) )
C24: =template_label_gross_scope_2_market_based_ghg_emissions & " - " & template_label_may_not_headline -> Gross scope 2 market-based GHG Emissions - May (optional) | K24: =IF(AND(G24="", J24=""), "-", IFERROR(-(1 - (J24 / G24)), "-")) -> - | L24: =IF(D24<>"", IF(AND(G24="", J24=""), template_label_ok, IF(AND(G24<>"", J24=""), template_label_missing_value, template_label_ok) ), "")
C25: =template_label_total_scope_1_and_scope_2_ghg_emissions_location_based -> Total Scope 1 and Scope 2 GHG Emissions (location-based) | D25: =IF(AND(D22="",D23=""),"-",SUM(D22,D23)) -> - | G25: =IF(AND(G22="",G23=""),"-",SUM(G22,G23)) -> - | J25: =IF(AND(J22="",J23=""),"-",SUM(J22,J23)) -> - | K25: =IF(AND(G25="", J25=""), "-", IFERROR(-(1 - (J25 / G25)), "-")) -> -
C26: =template_label_total_scope_1_and_scope_2_ghg_emissions_market_based & " - " & template_label_may_not_headline -> Total Scope 1 and Scope 2 GHG emissions (market-based) - May (optional) | D26: =IF(OR(D22="",D24=""),"-",SUM(D22,D24)) -> - | G26: =IF(OR(G22="",G24=""),"-",SUM(G22,G24)) -> - | J26: =IF(OR(J22="",J24=""),"-",SUM(J22,J24)) -> - | K26: =IF(AND(G26="", J26=""), "-", IFERROR(-(1 - (J26 / G26)), "-")) -> -
C27: 50-53 | G27: 54
C28: N/A | D28: 150-151 | G28: N/A | J28: N/A
C29: =template_label_is_the_undertaking_disclosing_entity_specific_information_on_scope_3_emissions -> Is the undertaking disclosing entity-specific information on Scope 3 emissions (in tCO2e)? | G29: FALSE
C30: =template_label_1_purchased_goods_and_services -> 1. Purchased Goods and Services | K30: =IF(OR(G30="", J30=""), "-", IFERROR(-(1 - (J30 / G30)), "-")) -> - | L30: {=IF( OR( SUMPRODUCT((G30:G44<>"")*(J30:J44="")) > 0, SUMPRODUCT((J30:J44<>"")*(G30:G44="")) > 0 ), template_label_missing_value, IF( AND(G29=TRUE, COUNTA(D30:F44)=0), template_label_missing_value, IF(G29=FALSE, "", template_label_ok) ) )} | M30: =template_label_scope_3_categories_warning -> ℹ️ Scope 3 categories according to the GHG protocol might help to calculate the total Scope 3 GHG emissions. In case the undertaking wants to, it can directly provide the Total Scope 3 GHG emissions in the respective cell.
C31: =template_label_2_capital_goods -> 2. Capital Goods | K31: =IF(OR(G31="", J31=""), "-", IFERROR(-(1 - (J31 / G31)), "-")) -> -
C32: =template_label_3_fuel__and_energy_related_activities -> 3. Fuel- and Energy-Related Activities (Not Included in Scope 1 or Scope 2) | K32: =IF(OR(G32="", J32=""), "-", IFERROR(-(1 - (J32 / G32)), "-")) -> -
C33: =template_label_4_upstream_transportation_and_distribution -> 4. Upstream Transportation and Distribution | K33: =IF(OR(G33="", J33=""), "-", IFERROR(-(1 - (J33 / G33)), "-")) -> -
C34: =template_label_5_waste_generated_in_operations -> 5. Waste Generated in Operations | K34: =IF(OR(G34="", J34=""), "-", IFERROR(-(1 - (J34 / G34)), "-")) -> -
C35: =template_label_6_business_travel -> 6. Business Travel | K35: =IF(OR(G35="", J35=""), "-", IFERROR(-(1 - (J35 / G35)), "-")) -> -
C36: =template_label_7_employee_commuting -> 7. Employee Commuting | K36: =IF(OR(G36="", J36=""), "-", IFERROR(-(1 - (J36 / G36)), "-")) -> -
C37: =template_label_8_upstream_leased_assets -> 8. Upstream Leased Assets | K37: =IF(OR(G37="", J37=""), "-", IFERROR(-(1 - (J37 / G37)), "-")) -> -
C38: =template_label_9_downstream_transportation_and_distribution -> 9. Downstream Transportation and Distribution | K38: =IF(OR(G38="", J38=""), "-", IFERROR(-(1 - (J38 / G38)), "-")) -> -
C39: =template_label_10_processing_of_sold_products -> 10. Processing of Sold Products | K39: =IF(OR(G39="", J39=""), "-", IFERROR(-(1 - (J39 / G39)), "-")) -> -
C40: =template_label_11_use_of_sold_products -> 11. Use of Sold Products | K40: =IF(OR(G40="", J40=""), "-", IFERROR(-(1 - (J40 / G40)), "-")) -> -
C41: =template_label_12_end_of_life_treatment_of_sold_products -> 12. End-of-Life Treatment of Sold Products | K41: =IF(OR(G41="", J41=""), "-", IFERROR(-(1 - (J41 / G41)), "-")) -> -
C42: =template_label_13_downstream_leased_assets -> 13. Downstream Leased Assets | K42: =IF(OR(G42="", J42=""), "-", IFERROR(-(1 - (J42 / G42)), "-")) -> -
C43: =template_label_14_franchises -> 14. Franchises | K43: =IF(OR(G43="", J43=""), "-", IFERROR(-(1 - (J43 / G43)), "-")) -> -
C44: =template_label_15_investments -> 15. Investments | K44: =IF(OR(G44="", J44=""), "-", IFERROR(-(1 - (J44 / G44)), "-")) -> -
C45: =template_label_total_scope_3_ghg_emissions -> Total Scope 3 GHG emissions | D45: =IF(AND(G29=FALSE, COUNTA(D30:F44)=0), "-", IF(G29=TRUE, IF(SUM(D30:F44)=0, "-", SUM(D30:F44)), "-")) -> - | G45: =IF(AND(G29=FALSE, COUNTA(G30:I44)=0), "-", IF(G29=TRUE, IF(SUM(G30:I44)=0, "-", SUM(G30:I44)), "-")) -> - | J45: =IF(AND(G29=FALSE, COUNTA(J30:J44)=0), "-", IF(G29=TRUE, IF(SUM(J30:J44)=0, "-", SUM(J30:J44)), "-")) -> - | K45: =IF(AND(G45="", J45=""), "-", IFERROR(-(1 - (J45 / G45)), "-")) -> -
C46: =template_label_total_scope_1_scope_2_and_scope_3_ghg_emissions_location_based -> Total Scope 1 Scope 2 and Scope 3 GHG Emissions (location-based) | D46: =IF(G29=FALSE, "-", IF(AND(D22="", D23="", D45=""), "-", IF(SUM(D22, D23, D45)=0, "-", SUM(D22, D23, D45)))) -> - | G46: =IF(G29=FALSE, "-", IF(AND(G22="", G23="", G45=""), "-", IF(SUM(G22, G23, G45)=0, "-", SUM(G22, G23, G45)))) -> - | J46: =IF(G29=FALSE, "-", IF(AND(J22="", J23="", J45=""), "-", IF(SUM(J22, J23, J45)=0, "-", SUM(J22, J23, J45)))) -> - | K46: =IF(AND(G46="", J46=""), "-", IFERROR(-(1 - (J46 / G46)), "-")) -> -
C47: =template_label_total_scope_1_scope_2_and_scope_3_ghg_emissions_market_based & " - " & template_label_may_not_headline -> Total Scope 1 Scope 2 and Scope 3 GHG Emissions (market-based) - May (optional) | D47: =IF(G29=FALSE,"-",IF(OR(D22="",D24="",D45=""),"-",SUM(D22,D24,D45))) -> - | G47: =IF(G29=FALSE, "-", IF(OR(G22="", G24="", G45=""), "-", IF(SUM(G22, G24, G45)=0, "-", SUM(G22, G24, G45)))) -> - | J47: =IF(G29=FALSE, "-", IF(OR(J22="", J24="", J45=""), "-", IF(SUM(J22, J24, J45)=0, "-", SUM(J22, J24, J45)))) -> - | K47: =IF(AND(G47="", J47=""), "-", IFERROR(-(1 - (J47 / G47)), "-")) -> -
C49: =template_label_c3_disclosure_of_list_of_main_actions_the_entity_seeks_in_order_to_achieve_its_targets&" "&template_label_from&" "&template_starting_date_display&" "&template_label_to&" "&template_ending_date_display&" "&template_label_if_applicable -> C3 - Disclosure of list of main actions the entity seeks in order to achieve its targets from - to - [If applicable]
C50: 54(e)
C51: 159
L52: =IF(AND(J19=TRUE, C52<>""), template_label_ok, IF(AND(J19=TRUE, C52=""), template_label_missing_value, ""))
A55: =template_label_supporting_guidance_c3 -> ℹ️ VSME Supporting guide on Disclosure C3 - Comprehensive Module (GHG reduction targets and climate transition) | C55: =template_label_c3_transition_plan_for_undertakings_operating_in_high_climate_impact_sectors&" "&template_label_from&" "&template_starting_date_display&" "&template_label_to&" "&template_ending_date_display&" "& template_label_if_applicable -> C3 - Transition plan for undertakings operating in high climate impact sectors from - to - [If applicable]
A56: 55 | B56: 160-163 | C56: =template_label_is_the_undertaking_operating_in_high_impact_sectors -> Is the undertaking operating in high impact sectors? | D56: =OR( ISNUMBER(MATCH('General Information'!E180, 'Enumeration Lists'!A3:A677, 0)), ISNUMBER(MATCH('General Information'!E181, 'Enumeration Lists'!A3:A677, 0)), ISNUMBER(MATCH('General Information'!E182, 'Enumeration Lists'!A3:A677, 0)), ISNUMBER(MATCH('General Information'!E183, 'Enumeration Lists'!A3:A677, 0)), ISNUMBER(MATCH('General Information'!E184, 'Enumeration Lists'!A3:A677, 0)), ISNUMBER(MATCH('General Information'!E180, 'Enumeration Lists'!A782:A791, 0)), ISNUMBER(MATCH('General Information'!E181, 'Enumeration Lists'!A782:A791, 0)), ISNUMBER(MATCH('General Information'!E182, 'Enumeration Lists'!A782:A791, 0)), ISNUMBER(MATCH('General Information'!E183, 'Enumeration Lists'!A782:A791, 0)), ISNUMBER(MATCH('General Information'!E184, 'Enumeration Lists'!A782:A791, 0)) ) -> FALSE
A57: 55 | B57: 160-163 | C57: =template_label_status_of_implementation_of_a_transition_plan_in_relation_to_climate_change_mitigation -> Status of implementation of a transition plan in relation to climate change mitigation | L57: =IF(AND(OR(D57="A transition plan has already been adopted", D57="Adoption of a transition plan is planned in the future"), D56=TRUE), template_label_ok, IF(AND(BasisForPreparation="Option B (Basic Module and Comprehensive Module)", D57="", D56=TRUE), template_label_missing_value, "" ) )
A58: 55 | B58: 160-163 | C58: =template_label_description_of_a_transition_plan_for_climate_change_mitigation & " - " & template_label_may_not_headline -> Description of a transition plan for climate change mitigation including an explanation of how it is contributing to reduce GHG emissions - May (optional) | L58: =IF(AND(D57="A transition plan has already been adopted", DescriptionOfATransitionPlanForClimateChangeMitigationIncludingAnExplanationOfHowItIsContributingToReduceGhgEmissions<>""), template_label_ok, "")
A59: 56 | B59: 160-163 | C59: =template_label_date_of_foreseen_adoption_of_transition_plan_for_undertaking_not_having_adopted_transition_plan_yet -> Date of foreseen adoption of transition plan for undertaking not having adopted transition plan yet | D59: =template_label_year -> Year | L59: =IF(AND(D57="A transition plan has already been adopted", OR(I59="", I60="", I61="")), "", IF(AND(D57="Adoption of a transition plan is planned in the future", OR(I59="", I60="", I61="")), template_label_missing_value, IF(AND(D57="", OR(I59="", I60="", I61="")), "", IF(OR( AND(I60=2, I61>29), AND(I60=2, I61=29, NOT(AND(MOD(I59,4)=0, OR(MOD(I59,100)<>0, MOD(I59,400)=0)))), AND(OR(I60=4, I60=6, I60=9, I60=11), I61=31) ), template_label_error, template_label_ok ) ) ) )
D60: =template_label_month -> Month
D61: =template_label_day -> Day
D62: =IF(OR(ISBLANK(I59), ISBLANK(I60), ISBLANK(I61)), "-", I59 & "-" & TEXT(I60, "00") & "-" & TEXT(I61, "00")) -> -
C64: =template_label_b3_greenhouse_gas_emission_intensity_per_turnover&" "&template_label_from&" "&template_starting_date_display&" "&template_label_to&" "&template_ending_date_display&" "&template_label_always_to_be_reported -> B3 - Greenhouse gas emission intensity per turnover (in tCO2e) from - to - [Always to be reported]
C65: 31
C66: =template_label_scope_1_and_scope_2_ghg_emissions_intensity_location_based -> Scope 1 and Scope 2 GHG Emissions intensity (location-based) | G66: =IF(G29=TRUE, "-", IFERROR( IF(OR(D25="", Turnover=""), "-", D25/Turnover), "-" ) ) -> -
C67: =template_label_scope_1_and_scope_2_ghg_emissions_intensity_market_based & " - " & template_label_may_not_headline -> Scope 1 and Scope 2 GHG Emissions intensity (market-based) - May (optional) | G67: =IF(G29=TRUE, "-", IFERROR( IF(OR(D26="", Turnover=""), "-", D26/Turnover), "-" ) ) -> -
C68: =template_label_total_scope_1_scope_2_and_scope_3_ghg_emissions_intensity_location_based -> Total Scope 1 Scope 2 and Scope 3 GHG Emissions intensity (location-based) | G68: =IF(G29=FALSE, "-", IFERROR( IF(OR(D46="", Turnover=""), "-", D46/Turnover), "-" ) ) -> -
C69: =template_label_total_scope_1_scope_2_and_scope_3_ghg_emissions_intensity_market_based & " - " & template_label_may_not_headline -> Total Scope 1 Scope 2 and Scope 3 GHG Emissions intensity (market-based) - May (optional) | G69: =IF(G29=FALSE, "-", IFERROR( IF(OR(D47="", Turnover=""), "-", D47/Turnover), "-" ) ) -> -
C71: =template_label_b4_pollution_of_air_water_and_soil&" "&template_label_from&" "&template_starting_date_display&" "&template_label_to&" "&template_ending_date_display&" "&template_label_if_applicable -> B4 - Pollution of air water and soil from - to - [If applicable]
C72: 32
C73: 46-69
C74: =template_label_required_by_law_or_other_national_regulations_to_report_to_competent_authorities_its_emissions_of_pollutants -> Is the undertaking already required by law or other national regulations to report to competent authorities its emissions of pollutants or does it already voluntarily report on them according to an Environmental Management System? | G74: FALSE
C75: =template_label_is_this_disclosure_already_publicly_available -> Is this disclosure already publicly available? | L75: {=IF(AND(G75=TRUE,D80:K179=""), template_label_ok,IF(AND(G74=TRUE,G75=""),template_label_missing_value,IF(AND(G74=TRUE,PubliclyAvailableDisclosure=FALSE),template_label_ok, IF(AND(OR(D80:K179<>""),G75=TRUE), template_label_value_inconsistency, "" ) )))}
C76: =template_label_please_provide_the_relevant_url_link_or_hyperlink_of_where_this_information_is_reported -> Please provide the relevant URL link or hyperlink of where this information is reported | L76: =IF(G75=TRUE, IF(G76="", template_label_missing_value, IF(OR(LEFT(G76,7)="http://", LEFT(G76,8)="https://", LEFT(G76,4)="www."), template_label_ok, template_label_invalid_url ) ), "")
C77: =template_label_please_select_the_unit_used_for_reporting_the_amount -> Please select the unit used for reporting the amount (i.e. either kg or tonne)
L78: {=IF(PubliclyAvailableDisclosure="","",IF(AND(OR(D80:F179<>"",G80:I179<>"",J80:J179<>"",G296<>"",K80:K179<>""),C78<>"",G74=TRUE,G75=FALSE), template_label_ok, IF(AND(OR(D80:F179<>"",G80:I179<>"",J80:J179<>"",G296<>"",K80:K179<>""),C78<>"",G74=TRUE,G75=TRUE), template_label_value_inconsistency, IF(AND(OR(D80:D179="",G80:G179="",J80:J179="",K80:K179=""),C78<>"",G74=TRUE,G75=FALSE), template_label_ok, IF(AND(OR(D80:D179="",G80:G179="",J80:J179="",K80:K179=""),C78<>"",G74=TRUE,G75=TRUE), template_label_value_inconsistency, IF(AND(C78="",G74=TRUE,G75=FALSE), template_label_missing_value, "" ) ) ) ) ))}
C79: =template_label_row_id -> Row ID | D79: =template_label_pollutant -> Pollutant | G79: =template_label_emission_to_air -> Emission to air | J79: =template_label_emission_to_water -> Emission to water | K79: =template_label_emission_to_soil -> Emission to soil
C80: 1 | L80: =IF(PubliclyAvailableDisclosure="","",IF(AND($G$74=TRUE,$G$75=TRUE,OR(D80<>"",G80<>"",J80<>"",K80<>"")), template_label_value_inconsistency, IF($G$74<>TRUE,"", IF(AND(D80="",G80="",J80="",K80="",G74=TRUE,G75=FALSE),template_label_missing_value, IF(AND(D80="",G80="",J80="",K80="",G74=TRUE,G75=TRUE),"", IF(AND(D80="",G80="",J80="",K80="",G74=FALSE),"", IF(AND(D80<>"",G80="",J80="",K80=""),template_label_missing_value, IF(AND(D80<>"",OR(G80<>"",J80<>"",K80<>"")), IF(COUNTIF($D$80:$D$179,D80)>1,template_label_value_inconsistency,template_label_ok), template_label_missing_value))))))))
C81: 2 | L81: =IF(AND($G$74=TRUE,$G$75=TRUE,OR(D81<>"",G81<>"",J81<>"",K81<>"")), template_label_value_inconsistency, IF($G$74<>TRUE, "", IF(AND(D81="", G81="", J81="", K81=""), "", IF(AND(D81<>"", G81="", J81="", K81=""), template_label_missing_value, IF(AND(D81<>"", OR(G81<>"", J81<>"", K81<>"")), IF(COUNTIF($D$80:$D$179, D81)>1, template_label_value_inconsistency, template_label_ok), template_label_missing_value)))))
C82: 3 | L82: =IF(AND($G$74=TRUE,$G$75=TRUE,OR(D82<>"",G82<>"",J82<>"",K82<>"")), template_label_value_inconsistency, IF($G$74<>TRUE, "", IF(AND(D82="", G82="", J82="", K82=""), "", IF(AND(D82<>"", G82="", J82="", K82=""), template_label_missing_value, IF(AND(D82<>"", OR(G82<>"", J82<>"", K82<>"")), IF(COUNTIF($D$80:$D$179, D82)>1, template_label_value_inconsistency, template_label_ok), template_label_missing_value))))) | M82: =template_label_additional_rows_warning -> ℹ️ Lists can be expanded using the little [+] button on the left. If the number of rows is not sufficient, those can be added by right clicking the second row and selecting "Insert row".
C83: 4 | L83: =IF(AND($G$74=TRUE,$G$75=TRUE,OR(D83<>"",G83<>"",J83<>"",K83<>"")), template_label_value_inconsistency, IF($G$74<>TRUE, "", IF(AND(D83="", G83="", J83="", K83=""), "", IF(AND(D83<>"", G83="", J83="", K83=""), template_label_missing_value, IF(AND(D83<>"", OR(G83<>"", J83<>"", K83<>"")), IF(COUNTIF($D$80:$D$179, D83)>1, template_label_value_inconsistency, template_label_ok), template_label_missing_value)))))
C84: 5 | L84: =IF(AND($G$74=TRUE,$G$75=TRUE,OR(D84<>"",G84<>"",J84<>"",K84<>"")), template_label_value_inconsistency, IF($G$74<>TRUE, "", IF(AND(D84="", G84="", J84="", K84=""), "", IF(AND(D84<>"", G84="", J84="", K84=""), template_label_missing_value, IF(AND(D84<>"", OR(G84<>"", J84<>"", K84<>"")), IF(COUNTIF($D$80:$D$179, D84)>1, template_label_value_inconsistency, template_label_ok), template_label_missing_value)))))
C85: 6 | L85: =IF(AND($G$74=TRUE,$G$75=TRUE,OR(D85<>"",G85<>"",J85<>"",K85<>"")), template_label_value_inconsistency, IF($G$74<>TRUE, "", IF(AND(D85="", G85="", J85="", K85=""), "", IF(AND(D85<>"", G85="", J85="", K85=""), template_label_missing_value, IF(AND(D85<>"", OR(G85<>"", J85<>"", K85<>"")), IF(COUNTIF($D$80:$D$179, D85)>1, template_label_value_inconsistency, template_label_ok), template_label_missing_value)))))
C86: 7 | L86: =IF(AND($G$74=TRUE,$G$75=TRUE,OR(D86<>"",G86<>"",J86<>"",K86<>"")), template_label_value_inconsistency, IF($G$74<>TRUE, "", IF(AND(D86="", G86="", J86="", K86=""), "", IF(AND(D86<>"", G86="", J86="", K86=""), template_label_missing_value, IF(AND(D86<>"", OR(G86<>"", J86<>"", K86<>"")), IF(COUNTIF($D$80:$D$179, D86)>1, template_label_value_inconsistency, template_label_ok), template_label_missing_value)))))
C87: 8 | L87: =IF(AND($G$74=TRUE,$G$75=TRUE,OR(D87<>"",G87<>"",J87<>"",K87<>"")), template_label_value_inconsistency, IF($G$74<>TRUE, "", IF(AND(D87="", G87="", J87="", K87=""), "", IF(AND(D87<>"", G87="", J87="", K87=""), template_label_missing_value, IF(AND(D87<>"", OR(G87<>"", J87<>"", K87<>"")), IF(COUNTIF($D$80:$D$179, D87)>1, template_label_value_inconsistency, template_label_ok), template_label_missing_value)))))
C88: 9 | L88: =IF(AND($G$74=TRUE,$G$75=TRUE,OR(D88<>"",G88<>"",J88<>"",K88<>"")), template_label_value_inconsistency, IF($G$74<>TRUE, "", IF(AND(D88="", G88="", J88="", K88=""), "", IF(AND(D88<>"", G88="", J88="", K88=""), template_label_missing_value, IF(AND(D88<>"", OR(G88<>"", J88<>"", K88<>"")), IF(COUNTIF($D$80:$D$179, D88)>1, template_label_value_inconsistency, template_label_ok), template_label_missing_value)))))
C89: 10 | L89: =IF(AND($G$74=TRUE,$G$75=TRUE,OR(D89<>"",G89<>"",J89<>"",K89<>"")), template_label_value_inconsistency, IF($G$74<>TRUE, "", IF(AND(D89="", G89="", J89="", K89=""), "", IF(AND(D89<>"", G89="", J89="", K89=""), template_label_missing_value, IF(AND(D89<>"", OR(G89<>"", J89<>"", K89<>"")), IF(COUNTIF($D$80:$D$179, D89)>1, template_label_value_inconsistency, template_label_ok), template_label_missing_value)))))
C90: 11 | L90: =IF(AND($G$74=TRUE,$G$75=TRUE,OR(D90<>"",G90<>"",J90<>"",K90<>"")), template_label_value_inconsistency, IF($G$74<>TRUE, "", IF(AND(D90="", G90="", J90="", K90=""), "", IF(AND(D90<>"", G90="", J90="", K90=""), template_label_missing_value, IF(AND(D90<>"", OR(G90<>"", J90<>"", K90<>"")), IF(COUNTIF($D$80:$D$179, D90)>1, template_label_value_inconsistency, template_label_ok), template_label_missing_value)))))
C91: 12 | L91: =IF(AND($G$74=TRUE,$G$75=TRUE,OR(D91<>"",G91<>"",J91<>"",K91<>"")), template_label_value_inconsistency, IF($G$74<>TRUE, "", IF(AND(D91="", G91="", J91="", K91=""), "", IF(AND(D91<>"", G91="", J91="", K91=""), template_label_missing_value, IF(AND(D91<>"", OR(G91<>"", J91<>"", K91<>"")), IF(COUNTIF($D$80:$D$179, D91)>1, template_label_value_inconsistency, template_label_ok), template_label_missing_value)))))
C92: 13 | L92: =IF(AND($G$74=TRUE,$G$75=TRUE,OR(D92<>"",G92<>"",J92<>"",K92<>"")), template_label_value_inconsistency, IF($G$74<>TRUE, "", IF(AND(D92="", G92="", J92="", K92=""), "", IF(AND(D92<>"", G92="", J92="", K92=""), template_label_missing_value, IF(AND(D92<>"", OR(G92<>"", J92<>"", K92<>"")), IF(COUNTIF($D$80:$D$179, D92)>1, template_label_value_inconsistency, template_label_ok), template_label_missing_value)))))
C93: 14 | L93: =IF(AND($G$74=TRUE,$G$75=TRUE,OR(D93<>"",G93<>"",J93<>"",K93<>"")), template_label_value_inconsistency, IF($G$74<>TRUE, "", IF(AND(D93="", G93="", J93="", K93=""), "", IF(AND(D93<>"", G93="", J93="", K93=""), template_label_missing_value, IF(AND(D93<>"", OR(G93<>"", J93<>"", K93<>"")), IF(COUNTIF($D$80:$D$179, D93)>1, template_label_value_inconsistency, template_label_ok), template_label_missing_value)))))
C94: 15 | L94: =IF(AND($G$74=TRUE,$G$75=TRUE,OR(D94<>"",G94<>"",J94<>"",K94<>"")), template_label_value_inconsistency, IF($G$74<>TRUE, "", IF(AND(D94="", G94="", J94="", K94=""), "", IF(AND(D94<>"", G94="", J94="", K94=""), template_label_missing_value, IF(AND(D94<>"", OR(G94<>"", J94<>"", K94<>"")), IF(COUNTIF($D$80:$D$179, D94)>1, template_label_value_inconsistency, template_label_ok), template_label_missing_value)))))
... C179: 100 | L179: =IF(AND($G$74=TRUE,$G$75=TRUE,OR(D179<>"",G179<>"",J179<>"",K179<>"")), template_label_value_inconsistency, IF($G$74<>TRUE, "", IF(AND(D179="", G179="", J179="", K179=""), "", IF(AND(D179<>"", G179="", J179="", K179=""), template_label_missing_value, IF(AND(D179<>"", OR(G179<>"", J179<>"", K179<>"")), IF(COUNTIF($D$80:$D$179, D179)>1, template_label_value_inconsistency, template_label_ok), template_label_missing_value)))))
C181: =template_label_b5_sites_in_biodiversity_sensitive_areas&" "&template_label_from&" "&template_starting_date_display&" "&template_label_to&" "&template_ending_date_display&" "&template_label_if_applicable -> B5 - Sites in biodiversity sensitive areas from - to - [If applicable]
C182: 33
C183: 70-73
C184: =template_label_does_the_undertaking_have_sites_that_are_located_in_or_near_biodiversity_sensitive_areas -> Does the undertaking have sites that are located in or near biodiversity sensitive areas? | G184: FALSE
C185: =template_label_please_select_the_unit_used_for_the_area -> Please select the unit used for the area (i.e. either hectares or m²):
L186: =IF(AND(G184=TRUE,C186=""), template_label_missing_value, IF(AND(G184=TRUE,C186<>""), template_label_ok, ""))
C187: =template_label_related_site_id -> Related Site ID (select an ID from a site location reported in B1) | D187: =template_label_site_location_in_near_a_biodiversity_area -> Site Location in near a biodiversity area - auto filled from B1 | G187: =template_label_area_hectares_or_m2 -> Area (hectares or m² based on the selection above) | J187: =template_label_site_located_in_a_biodiversity_sensitive_area -> Site located in a biodiversity sensitive area | K187: =template_label_site_located_near_a_biodiversity_sensitive_area -> Site located near a biodiversity sensitive area
D188: =IF(C188 = "", "", IF(AND(COUNTIF('General Information'!C404:C503, C188), INDEX('General Information'!D404:D503, MATCH(C188, 'General Information'!C404:C503, 0)) = ""), "VALUE INCONSISTENCY", IFERROR(VLOOKUP(C188, ListOfSitesTable, 5, FALSE),"") & " " & IFERROR(VLOOKUP(C188, ListOfSitesTable, 4, FALSE),"") & " " & IFERROR(VLOOKUP(C188, ListOfSitesTable, 2, FALSE),""))) | J188: FALSE | K188: FALSE | L188: =IF($G$184=FALSE, "", IF(AND($G$184=TRUE, TRIM(D188)<>"", TRIM(G188)<>"", OR(J188=TRUE, K188=TRUE)), template_label_ok, IF(AND($G$184=TRUE, TRIM(D188)<>"", TRIM(G188)<>"", J188=FALSE, K188=FALSE), template_label_missing_value, IF(AND($G$184=TRUE, TRIM(D188)<>"", TRIM(G188)="", J188=FALSE, K188=FALSE), template_label_missing_value, IF(AND($G$184=TRUE, TRIM(D188)<>"", TRIM(G188)="", OR(J188=TRUE, K188=TRUE)), template_label_missing_value, IF(AND($G$184=TRUE, TRIM(D188)="", TRIM(G188)<>"", J188=FALSE, K188=FALSE), template_label_missing_value, IF(AND($G$184=TRUE, TRIM(D188)="", TRIM(G188)="", OR(J188=TRUE, K188=TRUE)), template_label_missing_value, IF(AND($G$184=TRUE, TRIM(D188)="", TRIM(G188)<>"", OR(J188=TRUE, K188=TRUE)), template_label_missing_value, "" ) ) ) ) ) ) ) ) | M188: =template_label_site_ID_value_inconsistency_warning -> ℹ️ If a validation related to value inconsistency is displayed, please select a site ID that is different from one of those previously selected.
D189: =IF(C189 = "", "", IF(COUNTIF($C$188:C188, C189), "VALUE INCONSISTENCY", IF(AND(COUNTIF('General Information'!$C$404:$C$503, C189), INDEX('General Information'!$D$404:$D$503, MATCH(C189, 'General Information'!$C$404:$C$503, 0)) = ""), "VALUE INCONSISTENCY", IFERROR(VLOOKUP(C189, ListOfSitesTable, 5, FALSE), "") & " " & IFERROR(VLOOKUP(C189, ListOfSitesTable, 4, FALSE), "") & " " & IFERROR(VLOOKUP(C189, ListOfSitesTable, 2, FALSE), "")))) | J189: FALSE | K189: FALSE | L189: =IF($G$184=FALSE, "", IF(AND($G$184=TRUE, TRIM(D189)<>"", TRIM(G189)<>"", OR(J189=TRUE, K189=TRUE)), template_label_ok, IF(AND($G$184=TRUE, TRIM(D189)<>"", TRIM(G189)<>"", J189=FALSE, K189=FALSE), template_label_missing_value, IF(AND($G$184=TRUE, TRIM(D189)<>"", TRIM(G189)="", J189=FALSE, K189=FALSE), template_label_missing_value, IF(AND($G$184=TRUE, TRIM(D189)<>"", TRIM(G189)="", OR(J189=TRUE, K189=TRUE)), template_label_missing_value, IF(AND($G$184=TRUE, TRIM(D189)="", TRIM(G189)<>"", J189=FALSE, K189=FALSE), template_label_missing_value, IF(AND($G$184=TRUE, TRIM(D189)="", TRIM(G189)="", OR(J189=TRUE, K189=TRUE)), template_label_missing_value, IF(AND($G$184=TRUE, TRIM(D189)="", TRIM(G189)<>"", OR(J189=TRUE, K189=TRUE)), template_label_missing_value, "" ) ) ) ) ) ) ) )
D190: =IF(C190 = "", "", IF(COUNTIF($C$188:C189, C190), "VALUE INCONSISTENCY", IF(AND(COUNTIF('General Information'!$C$404:$C$503, C190), INDEX('General Information'!$D$404:$D$503, MATCH(C190, 'General Information'!$C$404:$C$503, 0)) = ""), "VALUE INCONSISTENCY", IFERROR(VLOOKUP(C190, ListOfSitesTable, 5, FALSE), "") & " " & IFERROR(VLOOKUP(C190, ListOfSitesTable, 4, FALSE), "") & " " & IFERROR(VLOOKUP(C190, ListOfSitesTable, 2, FALSE), "")))) | J190: FALSE | K190: FALSE | L190: =IF($G$184=FALSE, "", IF(AND($G$184=TRUE, TRIM(D190)<>"", TRIM(G190)<>"", OR(J190=TRUE, K190=TRUE)), template_label_ok, IF(AND($G$184=TRUE, TRIM(D190)<>"", TRIM(G190)<>"", J190=FALSE, K190=FALSE), template_label_missing_value, IF(AND($G$184=TRUE, TRIM(D190)<>"", TRIM(G190)="", J190=FALSE, K190=FALSE), template_label_missing_value, IF(AND($G$184=TRUE, TRIM(D190)<>"", TRIM(G190)="", OR(J190=TRUE, K190=TRUE)), template_label_missing_value, IF(AND($G$184=TRUE, TRIM(D190)="", TRIM(G190)<>"", J190=FALSE, K190=FALSE), template_label_missing_value, IF(AND($G$184=TRUE, TRIM(D190)="", TRIM(G190)="", OR(J190=TRUE, K190=TRUE)), template_label_missing_value, IF(AND($G$184=TRUE, TRIM(D190)="", TRIM(G190)<>"", OR(J190=TRUE, K190=TRUE)), template_label_missing_value, "" ) ) ) ) ) ) ) ) | M190: =template_label_additional_rows_warning -> ℹ️ Lists can be expanded using the little [+] button on the left. If the number of rows is not sufficient, those can be added by right clicking the second row and selecting "Insert row".
D191: =IF(C191 = "", "", IF(COUNTIF($C$188:C190, C191), "VALUE INCONSISTENCY", IF(AND(COUNTIF('General Information'!$C$404:$C$503, C191), INDEX('General Information'!$D$404:$D$503, MATCH(C191, 'General Information'!$C$404:$C$503, 0)) = ""), "VALUE INCONSISTENCY", IFERROR(VLOOKUP(C191, ListOfSitesTable, 5, FALSE), "") & " " & IFERROR(VLOOKUP(C191, ListOfSitesTable, 4, FALSE), "") & " " & IFERROR(VLOOKUP(C191, ListOfSitesTable, 2, FALSE), "")))) | J191: FALSE | K191: FALSE | L191: =IF($G$184=FALSE, "", IF(AND($G$184=TRUE, TRIM(D191)<>"", TRIM(G191)<>"", OR(J191=TRUE, K191=TRUE)), template_label_ok, IF(AND($G$184=TRUE, TRIM(D191)<>"", TRIM(G191)<>"", J191=FALSE, K191=FALSE), template_label_missing_value, IF(AND($G$184=TRUE, TRIM(D191)<>"", TRIM(G191)="", J191=FALSE, K191=FALSE), template_label_missing_value, IF(AND($G$184=TRUE, TRIM(D191)<>"", TRIM(G191)="", OR(J191=TRUE, K191=TRUE)), template_label_missing_value, IF(AND($G$184=TRUE, TRIM(D191)="", TRIM(G191)<>"", J191=FALSE, K191=FALSE), template_label_missing_value, IF(AND($G$184=TRUE, TRIM(D191)="", TRIM(G191)="", OR(J191=TRUE, K191=TRUE)), template_label_missing_value, IF(AND($G$184=TRUE, TRIM(D191)="", TRIM(G191)<>"", OR(J191=TRUE, K191=TRUE)), template_label_missing_value, "" ) ) ) ) ) ) ) )
D192: =IF(C192 = "", "", IF(COUNTIF($C$188:C191, C192), "VALUE INCONSISTENCY", IF(AND(COUNTIF('General Information'!$C$404:$C$503, C192), INDEX('General Information'!$D$404:$D$503, MATCH(C192, 'General Information'!$C$404:$C$503, 0)) = ""), "VALUE INCONSISTENCY", IFERROR(VLOOKUP(C192, ListOfSitesTable, 5, FALSE), "") & " " & IFERROR(VLOOKUP(C192, ListOfSitesTable, 4, FALSE), "") & " " & IFERROR(VLOOKUP(C192, ListOfSitesTable, 2, FALSE), "")))) | J192: FALSE | K192: FALSE | L192: =IF($G$184=FALSE, "", IF(AND($G$184=TRUE, TRIM(D192)<>"", TRIM(G192)<>"", OR(J192=TRUE, K192=TRUE)), template_label_ok, IF(AND($G$184=TRUE, TRIM(D192)<>"", TRIM(G192)<>"", J192=FALSE, K192=FALSE), template_label_missing_value, IF(AND($G$184=TRUE, TRIM(D192)<>"", TRIM(G192)="", J192=FALSE, K192=FALSE), template_label_missing_value, IF(AND($G$184=TRUE, TRIM(D192)<>"", TRIM(G192)="", OR(J192=TRUE, K192=TRUE)), template_label_missing_value, IF(AND($G$184=TRUE, TRIM(D192)="", TRIM(G192)<>"", J192=FALSE, K192=FALSE), template_label_missing_value, IF(AND($G$184=TRUE, TRIM(D192)="", TRIM(G192)="", OR(J192=TRUE, K192=TRUE)), template_label_missing_value, IF(AND($G$184=TRUE, TRIM(D192)="", TRIM(G192)<>"", OR(J192=TRUE, K192=TRUE)), template_label_missing_value, "" ) ) ) ) ) ) ) )
...

Sheet Social Disclosures
A1: =template_label_paragraph_reference -> Paragraph Reference | B1: =template_label_paragraph_guidance_reference -> Paragraph Guidance Reference
C2: =template_label_employee_counting_methodology_for_the_disclosures_below_headcount_full_time_equivalent -> Employee counting methodology for the disclosures below (Headcount or Full time Equivalent linked from B1 | F2: =IF('General Information'!$E$284="","-",'General Information'!$E$284) -> -
C3: =template_label_employee_counting_methodology_for_the_disclosures_below_period -> Employee counting methodology for the disclosures below (At the end of the reporting period or as an average across the reporting period linked from B1) | F3: =IF('General Information'!$E$283="","-",'General Information'!$E$283) -> -
C6: =template_label_b8_workforce_general_characteristics_type_of_contract&" "&template_label_always_to_be_reported -> B8 - Workforce - General characteristics - Type of contract [Always to be reported]
C7: 39(a)
C8: 110-117
C9: =template_label_type_of_contract -> Type of contract | D9: =template_label_number_of_employees -> Number of employees
C10: =template_label_permanent_contract -> Permanent contract | H10: =IF(OR( 'Table of Contents & Validation'!D37=TRUE,'Table of Contents & Validation'!D36=TRUE), IF( AND( OR( 'General Information'!E122="Option A (Basic Module only)", 'General Information'!E122="Option B (Basic Module and Comprehensive Module)" ), D10="" ), "", IF('General Information'!E122="", "", template_label_ok ) ), IF( AND( OR( 'General Information'!E122="Option A (Basic Module only)", 'General Information'!E122="Option B (Basic Module and Comprehensive Module)" ), D10="" ), template_label_missing_value, IF('General Information'!E122="", "", template_label_ok ) ) )
C11: =template_label_temporary_contract -> Temporary contract | D11: =IFERROR(IF(D10="", "-", $D$12 - $D$10), "-") -> -
C12: =template_label_total_employees -> Total employees (linked to B1) | D12: =IF('General Information'!$E$282="", "-", VALUE(SUBSTITUTE('General Information'!$E$282, "-", "0"))) -> -
C14: =template_label_b8_workforce_general_characteristics_gender&" "&template_label_always_to_be_reported -> B8 - Workforce - General characteristics - Gender [Always to be reported]
C15: 39(b)
C16: 110-117
C17: =template_label_gender -> Gender | D17: =template_label_number_of_employees -> Number of employees
C18: =template_label_male -> Male | H18: =IF(OR( 'Table of Contents & Validation'!D38=TRUE,'Table of Contents & Validation'!D36=TRUE), IF( 'General Information'!E282="", IF( OR( 'General Information'!E122="Option A (Basic Module only)", 'General Information'!E122="Option B (Basic Module and Comprehensive Module)" ), IF( NumberOfMaleEmployees +NumberOfFemaleEmployees +NumberOfOtherGenderEmployees +NumberOfNonReportedGenderEmployees =D22, template_label_ok, "" ), "" ), IF( OR( 'General Information'!E122="Option A (Basic Module only)", 'General Information'!E122="Option B (Basic Module and Comprehensive Module)" ), IF( NumberOfMaleEmployees +NumberOfFemaleEmployees +NumberOfOtherGenderEmployees +NumberOfNonReportedGenderEmployees =D22, template_label_ok, "" ), "" ) ), IF( 'General Information'!E282="", IF( OR( 'General Information'!E122="Option A (Basic Module only)", 'General Information'!E122="Option B (Basic Module and Comprehensive Module)" ), IF( NumberOfMaleEmployees +NumberOfFemaleEmployees +NumberOfOtherGenderEmployees +NumberOfNonReportedGenderEmployees =D22, template_label_ok, template_label_missing_value ), "" ), IF( OR( 'General Information'!E122="Option A (Basic Module only)", 'General Information'!E122="Option B (Basic Module and Comprehensive Module)" ), IF( NumberOfMaleEmployees +NumberOfFemaleEmployees +NumberOfOtherGenderEmployees +NumberOfNonReportedGenderEmployees =D22, template_label_ok, template_label_value_inconsistency ), "" ) ) ) | I18: =template_label_number_of_employees_warning -> ℹ️ Please make sure that the total number of employees is the same as the one provided in the "General Information" sheet cell E55
C19: =template_label_female -> Female
C20: =template_label_other -> Other
C21: =template_label_not_reported -> Not reported
C22: =template_label_total_employees -> Total employees (linked to B1) | D22: =IF('General Information'!$E$282="","-",'General Information'!$E$282) -> -
C24: =template_label_b8_workforce_general_characteristics_country_of_employment&" "&template_label_if_applicable -> B8 - Workforce - General characteristics - Country of employment [If applicable]
C25: 39(c)
C26: 110-117
C27: =template_label_undertaking_operating_in_more_than_one_country -> Does the undertaking operate in more than one country? | E27: FALSE
C28: =template_label_country_of_employment_contract -> Country of employment contract | E28: =template_label_number_of_employees -> Number of employees
I29: =IF( AND(C29="", E29=""), "", IF( AND(C29<>"", E29=""), template_label_missing_value, IF( AND(C29<>"", E29<>""), IF( SUM($E$29:$E$128)<$E$129, template_label_missing_value, IF( COUNTIF($C$29:$C$128, C29) > 1, template_label_value_inconsistency, template_label_ok ) ), template_label_missing_value ) ) ) | J29: =template_label_number_of_employees_warning -> ℹ️ Please make sure that the total number of employees is the same as the one provided in the "General Information" sheet cell E55
I30: =IF( AND(C30="", E30=""), "", IF( AND(C30<>"", E30=""), template_label_missing_value, IF( AND(C30<>"", E30<>""), IF( SUM($E$29:$E$128)<$E$129, template_label_missing_value, IF( COUNTIF($C$29:$C$128, C30) > 1, template_label_value_inconsistency, template_label_ok ) ), template_label_missing_value ) ) )
I31: =IF( AND(C31="", E31=""), "", IF( AND(C31<>"", E31=""), template_label_missing_value, IF( AND(C31<>"", E31<>""), IF( SUM($E$29:$E$128)<$E$129, template_label_missing_value, IF( COUNTIF($C$29:$C$128, C31) > 1, template_label_value_inconsistency, template_label_ok ) ), template_label_missing_value ) ) ) | J31: =template_label_additional_rows_warning -> ℹ️ Lists can be expanded using the little [+] button on the left. If the number of rows is not sufficient, those can be added by right clicking the second row and selecting "Insert row".
I32: =IF( AND(C32="", E32=""), "", IF( AND(C32<>"", E32=""), template_label_missing_value, IF( AND(C32<>"", E32<>""), IF( SUM($E$29:$E$128)<$E$129, template_label_missing_value, IF( COUNTIF($C$29:$C$128, C32) > 1, template_label_value_inconsistency, template_label_ok ) ), template_label_missing_value ) ) )
I33: =IF( AND(C33="", E33=""), "", IF( AND(C33<>"", E33=""), template_label_missing_value, IF( AND(C33<>"", E33<>""), IF( SUM($E$29:$E$128)<$E$129, template_label_missing_value, IF( COUNTIF($C$29:$C$128, C33) > 1, template_label_value_inconsistency, template_label_ok ) ), template_label_missing_value ) ) )
I34: =IF( AND(C34="", E34=""), "", IF( AND(C34<>"", E34=""), template_label_missing_value, IF( AND(C34<>"", E34<>""), IF( SUM($E$29:$E$128)<$E$129, template_label_missing_value, IF( COUNTIF($C$29:$C$128, C34) > 1, template_label_value_inconsistency, template_label_ok ) ), template_label_missing_value ) ) )
I35: =IF( AND(C35="", E35=""), "", IF( AND(C35<>"", E35=""), template_label_missing_value, IF( AND(C35<>"", E35<>""), IF( SUM($E$29:$E$128)<$E$129, template_label_missing_value, IF( COUNTIF($C$29:$C$128, C35) > 1, template_label_value_inconsistency, template_label_ok ) ), template_label_missing_value ) ) )
I36: =IF( AND(C36="", E36=""), "", IF( AND(C36<>"", E36=""), template_label_missing_value, IF( AND(C36<>"", E36<>""), IF( SUM($E$29:$E$128)<$E$129, template_label_missing_value, IF( COUNTIF($C$29:$C$128, C36) > 1, template_label_value_inconsistency, template_label_ok ) ), template_label_missing_value ) ) )
I37: =IF( AND(C37="", E37=""), "", IF( AND(C37<>"", E37=""), template_label_missing_value, IF( AND(C37<>"", E37<>""), IF( SUM($E$29:$E$128)<$E$129, template_label_missing_value, IF( COUNTIF($C$29:$C$128, C37) > 1, template_label_value_inconsistency, template_label_ok ) ), template_label_missing_value ) ) )
I38: =IF( AND(C38="", E38=""), "", IF( AND(C38<>"", E38=""), template_label_missing_value, IF( AND(C38<>"", E38<>""), IF( SUM($E$29:$E$128)<$E$129, template_label_missing_value, IF( COUNTIF($C$29:$C$128, C38) > 1, template_label_value_inconsistency, template_label_ok ) ), template_label_missing_value ) ) )
I39: =IF( AND(C39="", E39=""), "", IF( AND(C39<>"", E39=""), template_label_missing_value, IF( AND(C39<>"", E39<>""), IF( SUM($E$29:$E$128)<$E$129, template_label_missing_value, IF( COUNTIF($C$29:$C$128, C39) > 1, template_label_value_inconsistency, template_label_ok ) ), template_label_missing_value ) ) )
I40: =IF( AND(C40="", E40=""), "", IF( AND(C40<>"", E40=""), template_label_missing_value, IF( AND(C40<>"", E40<>""), IF( SUM($E$29:$E$128)<$E$129, template_label_missing_value, IF( COUNTIF($C$29:$C$128, C40) > 1, template_label_value_inconsistency, template_label_ok ) ), template_label_missing_value ) ) )
I41: =IF( AND(C41="", E41=""), "", IF( AND(C41<>"", E41=""), template_label_missing_value, IF( AND(C41<>"", E41<>""), IF( SUM($E$29:$E$128)<$E$129, template_label_missing_value, IF( COUNTIF($C$29:$C$128, C41) > 1, template_label_value_inconsistency, template_label_ok ) ), template_label_missing_value ) ) )
I42: =IF( AND(C42="", E42=""), "", IF( AND(C42<>"", E42=""), template_label_missing_value, IF( AND(C42<>"", E42<>""), IF( SUM($E$29:$E$128)<$E$129, template_label_missing_value, IF( COUNTIF($C$29:$C$128, C42) > 1, template_label_value_inconsistency, template_label_ok ) ), template_label_missing_value ) ) )
I43: =IF( AND(C43="", E43=""), "", IF( AND(C43<>"", E43=""), template_label_missing_value, IF( AND(C43<>"", E43<>""), IF( SUM($E$29:$E$128)<$E$129, template_label_missing_value, IF( COUNTIF($C$29:$C$128, C43) > 1, template_label_value_inconsistency, template_label_ok ) ), template_label_missing_value ) ) )
... I128: =IF( AND(C128="", E128=""), "", IF( AND(C128<>"", E128=""), template_label_missing_value, IF( AND(C128<>"", E128<>""), IF( SUM($E$29:$E$128)<$E$129, template_label_missing_value, IF( COUNTIF($C$29:$C$128, C128) > 1, template_label_value_inconsistency, template_label_ok ) ), template_label_missing_value ) ) )
C129: =template_label_total_employees -> Total employees (linked to B1) | E129: =IF('General Information'!$E$282="","-",'General Information'!$E$282) -> -
C131: =template_label_b8_workforce_general_characteristics_turnover_rate&" "&template_label_from&" "&template_starting_date_display&" "&template_label_to&" "&template_ending_date_display&" "&template_label_if_applicable -> B8 - Workforce - General characteristics - Turnover rate from - to - [If applicable]
C132: 40
C133: 118
C134: =template_label_number_of_employees_who_left_during_the_reporting_period -> Number of employees who left during the reporting period | I134: =IF( AND('General Information'!$E$282<50, D134=""), "", IF( AND('General Information'!$E$282<50, D134<>""), template_label_ok, IF( AND('General Information'!$E$282>=50, D134<>""), template_label_ok, template_label_missing_value ) ) )
C135: =template_label_number_of_employees_at_the_beginning_of_the_reporting_period -> Number of employees at the beginning of the reporting period | I135: =IF( AND('General Information'!$E$282<50, D135=""), "", IF( AND('General Information'!$E$282<50, D135<>""), template_label_ok, IF( AND('General Information'!$E$282>=50, D135<>""), template_label_ok, template_label_missing_value ) ) )
C136: =template_label_number_of_employees_at_the_end_of_the_reporting_period -> Number of employees at the end of the reporting period | I136: =IF( AND('General Information'!$E$282<50, D136=""), "", IF( AND('General Information'!$E$282<50, D136<>""), template_label_ok, IF( AND('General Information'!$E$282>=50, D136<>""), template_label_ok, template_label_missing_value ) ) )
C137: =template_label_employee_turnover_rate_in_the_reporting_period -> Employee turnover rate [%] in the reporting period | D137: =IF(AND(D134<>"",D135<>"",D136<>""),(D134/((D135+D136)/2)),"-") -> -
C139: =template_label_b9_workforce_health_and_safety&" "&template_label_from&" "&template_starting_date_display&" "&template_label_to&" "&template_ending_date_display&" "&template_label_always_to_be_reported -> B9 - Workforce - Health and safety from - to - [Always to be reported]
A140: 41(a) | B140: 119-126 | C140: =template_label_number_of_recordable_work_related_accidents_in_the_reporting_period -> Number of recordable work-related accidents in the reporting period | I140: =IF( 'Table of Contents & Validation'!D41=TRUE, IF( AND( OR('General Information'!E122="Option A (Basic Module only)", 'General Information'!E122="Option B (Basic Module and Comprehensive Module)"), NumberOfRecordableWorkRelatedAccidentsInTheReportingPeriod="" ), "", IF('General Information'!E122="", "", template_label_ok) ), IF( AND( OR('General Information'!E122="Option A (Basic Module only)", 'General Information'!E122="Option B (Basic Module and Comprehensive Module)"), NumberOfRecordableWorkRelatedAccidentsInTheReportingPeriod="" ), template_label_missing_value, IF('General Information'!E122="", "", template_label_ok) ) )
A141: 41(a) | B141: 119-126 | C141: =template_label_number_of_hours_worked_by_one_fulltime_employee_in_the_reporting_period -> Number of hours worked by one full-time employee in the reporting period | D141: 2000 | I141: =IF(D141="", "MISSING VALUE", IF(D141<>2000, "OK", "")) | J141: =template_label_health_and_safety_formula_warning -> ℹ️ The undertaking can modify the value in this cell as 2,000 hours is based on the assumption that one full-time worker works 2,000 hours per year. This figure may vary by country or sector, depending on national rules or collective bargaining agreements.
A142: 41(a) | B142: 119-126 | C142: =template_label_total_number_of_hours_worked_in_a_year_by_all_employees_in_the_reporting_period -> Total number of hours worked in a year by all employees in the reporting period | D142: =IF('General Information'!E282="","-",D141*'General Information'!E282) -> -
A143: 41(a) | B143: 119-126 | C143: =template_label_rate_of_recordable_work_related_accidents_in_the_reporting_period -> Rate of recordable work-related accidents in the reporting period | D143: =IFERROR(IF(AND(D140<>"", D142<>""), ($D$140/$D$142)*200000, "-"), "-") -> -
A144: 41(b) | B144: 119-126 | C144: =template_label_number_of_fatalities_as_a_result_of_work_related_injuries_and_work_related_ill_health -> Number of fatalities as a result of work-related injuries and work-related ill health | I144: =IF( 'Table of Contents & Validation'!D41=TRUE, IF( AND( OR('General Information'!E122="Option A (Basic Module only)", 'General Information'!E122="Option B (Basic Module and Comprehensive Module)"), NumberOfFatalitiesAsAResultOfWorkRelatedInjuriesAndWorkRelatedIllHealth="" ), "", IF('General Information'!E122="", "", template_label_ok) ), IF( AND( OR('General Information'!E122="Option A (Basic Module only)", 'General Information'!E122="Option B (Basic Module and Comprehensive Module)"), NumberOfFatalitiesAsAResultOfWorkRelatedInjuriesAndWorkRelatedIllHealth="" ), template_label_missing_value, IF('General Information'!E122="", "", template_label_ok) ) )
C146: =template_label_b10_workforce_remuneration_collective_bargaining&" "&template_label_from&" "&template_starting_date_display&" "&template_label_to&" "&template_ending_date_display&" "&template_label_always_to_be_reported_if_applicable -> B10 - Workforce - Remuneration and collective bargaining from - to - [Always to be reported + If applicable]
A147: 42(a) | B147: 127-128 | C147: =template_label_employees_receive_pay_that_is_equal_or_above_applicable_minimum_wage -> Employees receive pay that is equal or above applicable minimum wage determined directly by the national minimum wage law or through a collective bargaining agreement | I147: =IF(OR( 'Table of Contents & Validation'!D43=TRUE,'Table of Contents & Validation'!D42=TRUE), IF( AND( OR('General Information'!E122="Option A (Basic Module only)", 'General Information'!E122="Option B (Basic Module and Comprehensive Module)"), EmployeesReceivePayEqualOrAboveMinimumWageDeterminedByNationalLawOrCollectiveAgreement="" ), "", IF('General Information'!E122="", "", template_label_ok) ), IF( AND( OR('General Information'!E122="Option A (Basic Module only)", 'General Information'!E122="Option B (Basic Module and Comprehensive Module)"), EmployeesReceivePayEqualOrAboveMinimumWageDeterminedByNationalLawOrCollectiveAgreement="" ), template_label_missing_value, IF('General Information'!E122="", "", template_label_ok) ) )
A148: 42(b) | B148: 129-136 | C148: =template_label_average_gross_hourly_pay_level_of_male_employees & " " & "(" & template_label_amount_in & " " & template_currency & ")" -> Average gross hourly pay level of male employees (amount in ) | I148: =IF( AND('General Information'!$E$282<150, D148=""), "", IF( AND('General Information'!$E$282<150, D148<>""), template_label_ok, IF( AND('General Information'!$E$282>=150, D148<>""), template_label_ok, template_label_missing_value ) ) )
A149: 42(b) | B149: 129-136 | C149: =template_label_average_gross_hourly_pay_level_of_female_employees & " " & "(" & template_label_amount_in & " " & template_currency & ")" -> Average gross hourly pay level of female employees (amount in ) | I149: =IF( AND('General Information'!$E$282<150, D149=""), "", IF( AND('General Information'!$E$282<150, D149<>""), template_label_ok, IF( AND('General Information'!$E$282>=150, D149<>""), template_label_ok, template_label_missing_value ) ) )
A150: 42(b) | B150: 129-136 | C150: =template_label_percentage_gap_in_pay_between_the__undertakings_female_and_male_employees -> Percentage gap in pay between the undertaking's female and male employees [%] | D150: =IF(AND(D148<>"",D149<>""),((D148-D149)/D148),"-") -> -
A151: 42(c) | B151: 137-140 | C151: =template_label_number_of_employees_covered_by_collective_bargaining_agreements -> Number of employees covered by collective bargaining agreements | I151: =IF(OR( 'Table of Contents & Validation'!D43=TRUE,'Table of Contents & Validation'!D42=TRUE), IF( AND( OR('General Information'!E122="Option A (Basic Module only)",'General Information'!E122="Option B (Basic Module and Comprehensive Module)"), D151="" ), "", IF('General Information'!E122="","",template_label_ok) ), IF( AND( OR('General Information'!E122="Option A (Basic Module only)",'General Information'!E122="Option B (Basic Module and Comprehensive Module)"), D151="" ), template_label_missing_value, IF('General Information'!E122="","",template_label_ok) ) )
C152: =template_label_percentage_of_employees_covered_by_collective_bargaining_agreements -> Percentage of employees covered by collective bargaining agreements [%] | D152: =IF(D151<>"", IF('General Information'!E282=0, "-", D151/'General Information'!E282), "-") -> -
C154: =template_label_number_of_annual_training_hours_per_employee_during_the_reporting_period&" "&template_label_from&" "&template_starting_date_display&" "&template_label_to&" "&template_ending_date_display&" "&template_label_always_to_be_reported -> B10 - Workforce - Number of annual training hours per employee during the reporting period from - to - [Always to be reported]
C155: 42(d)
C156: =template_label_gender -> Gender | D156: =template_label_number_of_annual_training_hours_per_employee_during_the_reporting_period -> B10 - Workforce - Number of annual training hours per employee during the reporting period
C157: =template_label_male -> Male | I157: =IF(OR( 'Table of Contents & Validation'!D44=TRUE,'Table of Contents & Validation'!D42=TRUE), IF( OR('General Information'!E122="Option A (Basic Module only)", 'General Information'!E122="Option B (Basic Module and Comprehensive Module)"), IF(OR(D157<>"", D158<>"", D159<>"", D160<>""), template_label_ok, ""), "" ), IF( OR('General Information'!E122="Option A (Basic Module only)", 'General Information'!E122="Option B (Basic Module and Comprehensive Module)"), IF(OR(D157<>"", D158<>"", D159<>"", D160<>""), template_label_ok, template_label_missing_value), "" ) )
C158: =template_label_female -> Female
C159: =template_label_other -> Other
C160: =template_label_not_reported -> Not reported
C161: =template_label_average_number_of_annual_training_hours_per_employee -> Average number of annual training hours per employee
C162: =IFERROR( IF( AND(D18<>"",D18<>0,D19<>"",D19<>0,D20<>"",D20<>0,D21<>"",D21<>0), AVERAGE(D157:D160), IF(OR(D18="", D18=0), AVERAGE(D158:D160), IF(OR(D19="", D19=0), AVERAGE(D157,D159,D160), IF(OR(D20="", D20=0), AVERAGE(D157,D158,D160), IF(OR(D21="", D21=0), AVERAGE(D157,D158,D159), "-")))) ), "-") -> -
C164: =template_label_c5_additional_workforce_characteristics&" "&template_label_from&" "&template_starting_date_display&" "&template_label_to&" "&template_ending_date_display&" " & template_label_may -> C5 - Additional (general) workforce characteristics from - to - [May (optional)]
A165: 59 | B165: 167-169 | C165: =template_label_number_of_male_employees_at_management_level -> Number of male employees at management level | I165: =IF(D165<>"", template_label_ok, "")
A166: 59 | B166: 167-169 | C166: =template_label_number_of_female_employees_at_management_level -> Number of female employees at management level | I166: =IF(D166<>"", template_label_ok, "")
A167: 59 | B167: 167-169 | C167: =template_label_female_to_male_ratio_at_management_level_for_the_reporting_period -> Female-to-male ratio at management level for the reporting period | D167: =IF(AND(D165<>"",D166<>""),$D$166/$D$165,"-") -> -
A168: 60 | B168: 170-172 | C168: =template_label_total_self_employed_workers_without_personnel_that_are_working_exclusively_for_the_undertaking -> Total self-employed workers without personnel that are working exclusively for the undertaking | I168: =IF(D168<>"", template_label_ok, "")
A169: 60 | B169: 170-172 | C169: =template_label_total_temporary_workers_provided_by_undertakings_primarily_engaged_in_employment_activities -> Total temporary workers provided by undertakings primarily engaged in employment activities | I169: =IF(D169<>"", template_label_ok, "")
C171: =template_label_c6_additional_own_workforce_information_human_rights_policies_and_processes&" "&template_label_from&" "&template_starting_date_display&" "&template_label_to&" "&template_ending_date_display&" "&template_label_always_to_be_reported -> C6 - Additional own workforce information - Human rights policies and processes from - to - [Always to be reported]
A172: 61(a) | B172: 173 | C172: =template_label_does_the_undertaking_have_a_code_of_conduct_or_human_rights_policy_for_its_own_workforce -> Does the undertaking have a code of conduct or human rights policy for its own workforce? | I172: =IF( 'Table of Contents & Validation'!D59=TRUE, IF( AND('General Information'!$E$122="Option B (Basic Module and Comprehensive Module)", D172<>""), template_label_ok, IF( AND('General Information'!$E$122="Option B (Basic Module and Comprehensive Module)", D172=""), "", IF( AND('General Information'!$E$122="Option A (Basic Module only)", D172<>""), template_label_ok, "" ) ) ), IF( AND('General Information'!$E$122="Option B (Basic Module and Comprehensive Module)", D172<>""), template_label_ok, IF( AND('General Information'!$E$122="Option B (Basic Module and Comprehensive Module)", D172=""), template_label_missing_value, IF( AND('General Information'!$E$122="Option A (Basic Module only)", D172<>""), template_label_ok, "" ) ) ) )
A173: 61(b) | B173: 173 | C173: =template_label_if_yes_does_this_cover -> If yes does this cover:
A174: 61(b) | B174: 173 | C174: =template_label_child_labour -> child labour | D174: FALSE | I174: =IF( AND(OR(D174=TRUE,D175=TRUE,D176=TRUE,D177=TRUE,D178=TRUE,D179=TRUE), D172="YES"), template_label_ok, IF( AND(D174=FALSE,D175=FALSE,D176=FALSE,D177=FALSE,D178=FALSE,D179=FALSE, D172="YES"), template_label_missing_value, IF( AND(D174=FALSE,D175=FALSE,D176=FALSE,D177=FALSE,D178=FALSE,D179=FALSE, D172="NO"), "", IF( AND(D174=FALSE,D175=FALSE,D176=FALSE,D177=FALSE,D178=FALSE,D179=FALSE, D172=""), "", IF( AND(OR(D174=TRUE,D175=TRUE,D176=TRUE,D177=TRUE,D178=TRUE,D179=TRUE), D172=""), "", template_label_value_inconsistency ) ) ) ) )
A175: 61(b) | B175: 173 | C175: =template_label_forced_labour -> forced labour | D175: FALSE
A176: 61(b) | B176: 173 | C176: =template_label_human_trafficking -> human trafficking | D176: FALSE
A177: 61(b) | B177: 173 | C177: =template_label_discrimination -> discrimination | D177: FALSE
A178: 61(b) | B178: 173 | C178: =template_label_accident_prevention -> accident prevention | D178: FALSE
A179: 61(b) | B179: 173 | C179: =template_label_other_if_yes_specify -> other? ( if yes specify) | D179: FALSE | J179: =template_label_other_warning -> ℹ️ When "other" is chosen as undertaking legal form please fill the row below
A180: 61(b) | B180: 173 | C180: =template_label_specify_other_types_of_content_covered_by_the_code_of_conduct_or_human_rights_policy -> Specify other types of content covered by the code of conduct or human rights policy | I180: =IF(AND(D179=TRUE,D180<>""), template_label_ok, IF(AND(D179=TRUE,D180=""), template_label_missing_value, IF(AND(D179=FALSE,D180<>""), template_label_missing_value, "")))
A181: 61(c) | B181: 173 | C181: =template_label_does_the_undertaking_have_a_complaint_handling_mechanism_for_its_own_workforce -> Does the undertaking have a complaint-handling mechanism for its own workforce? | I181: =IF( 'Table of Contents & Validation'!D59=TRUE, IF(AND('General Information'!$E$122="Option B (Basic Module and Comprehensive Module)",D181<>""), template_label_ok, IF(AND('General Information'!$E$122="Option B (Basic Module and Comprehensive Module)",D181=""), "", IF(AND('General Information'!$E$122="Option A (Basic Module only)",D181<>""), template_label_ok, ""))), IF(AND('General Information'!$E$122="Option B (Basic Module and Comprehensive Module)",D181<>""), template_label_ok, IF(AND('General Information'!$E$122="Option B (Basic Module and Comprehensive Module)",D181=""), template_label_missing_value, IF(AND('General Information'!$E$122="Option A (Basic Module only)",D181<>""), template_label_ok, ""))) )
A183: =template_label_supporting_guidance_c7 -> ℹ️ VSME Supporting Guide to Disclosure C7 - Comprehensive Module (Severe negative human rights incidents (paragraph 62(c)) | C183: =template_label_c7_severe_negative_human_rights_incidents&" "&template_label_from&" "&template_starting_date_display&" "&template_label_to&" "&template_ending_date_display&" "&template_label_always_to_be_reported -> C7 - Severe negative human rights incidents from - to - [Always to be reported]
A184: 62 | B184: 174 | C184: =template_label_does_the_undertaking_have_confirmed_incidents_in_its_own_workforce -> Does the undertaking have confirmed incidents in its own workforce? | I184: =IF( 'Table of Contents & Validation'!D60=TRUE, IF(AND('General Information'!$E$122="Option B (Basic Module and Comprehensive Module)",D184<>""), template_label_ok, IF(AND('General Information'!$E$122="Option B (Basic Module and Comprehensive Module)",D184=""), "", IF(AND('General Information'!$E$122="Option A (Basic Module only)",D184<>""), template_label_ok, ""))), IF(AND('General Information'!$E$122="Option B (Basic Module and Comprehensive Module)",D184<>""), template_label_ok, IF(AND('General Information'!$E$122="Option B (Basic Module and Comprehensive Module)",D184=""), template_label_missing_value, IF(AND('General Information'!$E$122="Option A (Basic Module only)",D184<>""), template_label_ok, ""))) )
A185: 62(a) | B185: 174 | C185: =template_label_if_yes_are_incidents_related_to -> If yes are incidents related to:
A186: 62(a) | B186: 174 | C186: =template_label_child_labour -> child labour | D186: FALSE | I186: {=IF(AND(OR(D186=TRUE,D187=TRUE,D188=TRUE,D189=TRUE,D190=TRUE),D184="YES"), template_label_ok, IF(AND(D186=FALSE,D187=FALSE,D188=FALSE,D189=FALSE,D190=FALSE,D184="YES"), template_label_missing_value, IF(AND(D186=FALSE,D187=FALSE,D188=FALSE,D189=FALSE,D190=FALSE,D184=""), "", IF(AND(D186=FALSE,D187=FALSE,D188=FALSE,D189=FALSE,D190=FALSE,D184="NO"), "", IF(AND(OR(D186:D190=TRUE),D184=""), "", template_label_value_inconsistency)))))}
A187: 62(a) | B187: 174 | C187: =template_label_forced_labour -> forced labour | D187: FALSE
A188: 62(a) | B188: 174 | C188: =template_label_human_trafficking -> human trafficking | D188: FALSE
A189: 62(a) | B189: 174 | C189: =template_label_discrimination -> discrimination | D189: FALSE
A190: 62(a) | B190: 174 | C190: =template_label_other_if_yes_specify -> other? ( if yes specify) | D190: FALSE | J190: =template_label_other_warning -> ℹ️ When "other" is chosen as undertaking legal form please fill the row below
A191: 62(a) | B191: 174 | C191: =template_label_specify_other_human_rights_related_to_the_confirmed_incidents -> Specify other human rights related to the confirmed incidents | I191: =IF(AND(D190=TRUE,D191<>""), template_label_ok, IF(AND(D190=TRUE,D191=""), template_label_missing_value, IF(AND(D190=FALSE,D191<>""), template_label_missing_value, "")))
A192: 62(b) | B192: 174 | C192: =template_label_description_of_actions_taken_to_address_the_confirmed_incidents -> Description of actions taken to address the confirmed incidents | I192: =IF(D192<>"",template_label_ok,"")
A193: 62(c) | B193: 174 | C193: =template_label_is_the_undertaking_aware_of_any_confirmed_incidents_involving_workers -> Is the undertaking aware of any confirmed incidents involving workers in the value chain affected communities consumers and end-users? | I193: =IF( 'Table of Contents & Validation'!D60=TRUE, IF(AND('General Information'!$E$122="Option B (Basic Module and Comprehensive Module)",D193<>""), template_label_ok, IF(AND('General Information'!$E$122="Option B (Basic Module and Comprehensive Module)",D193=""), "", IF(AND('General Information'!$E$122="Option A (Basic Module only)",D193<>""), template_label_ok, ""))), IF(AND('General Information'!$E$122="Option B (Basic Module and Comprehensive Module)",D193<>""), template_label_ok, IF(AND('General Information'!$E$122="Option B (Basic Module and Comprehensive Module)",D193=""), template_label_missing_value, IF(AND('General Information'!$E$122="Option A (Basic Module only)",D193<>""), template_label_ok, ""))) )
A194: 62(c) | B194: 174 | C194: =template_label_specification_of_any_confirmed_incident_involving_workers -> Specification of any confirmed incident involving workers in the value chain affected communities consumers and end-users | I194: =IF(AND(D193="YES",D194<>""), template_label_ok, IF(AND(D193="YES",D194=""), template_label_missing_value, IF(AND(D193="NO",D194<>""), template_label_missing_value, "")))
C198: =template_label_disclosure_of_any_other_social_and_or_entity_specific_social_disclosures&" "&template_label_from&" "&template_starting_date_display&" "&template_label_to&" "&template_ending_date_display&" " & template_label_may -> Disclosure of any other social and/or entity specific social disclosures from - to - [May (optional)]
...

Sheet Governance Disclosures
A1: Paragraph Reference | B1: Paragraph Guidance Reference
C2: =template_label_b11_convictions_and_fines_for_corruption_and_bribery&" "&template_label_from&" "&template_starting_date_display&" "&template_label_to&" "&template_ending_date_display&" "&template_label_if_applicable -> B11 - Convictions and fines for corruption and bribery from - to - [If applicable]
C3: 43
C4: 141-144
C5: =template_label_has_the_undertaking_incurred_in_convictions_and_fines_in_the_reporting_period -> Has the undertaking incurred in convictions and fines in the reporting period? | H5: FALSE
C6: =template_label_total_number_of_convictions_for_the_violation_of_anti_corruption_and_anti_bribery_laws -> Total number of convictions for the violation of anti-corruption and anti-bribery laws | I6: =IF(AND($H$5=TRUE,H6<>""), template_label_ok, IF(AND($H$5=TRUE,H6=""), template_label_missing_value, ""))
C7: =template_label_total_amount_of_fines_for_the_violation_of_anti_corruption_and_anti_bribery_laws & " " & "(" & template_label_amount_in & " " & template_currency & ")" -> Total amount of fines for the violation of anti-corruption and anti-bribery laws (amount in ) | I7: =IF(AND($H$5=TRUE,H7<>""), template_label_ok, IF(AND($H$5=TRUE,H7=""), template_label_missing_value, ""))
C9: =template_label_c8_revenues_from_certain_sectors&" "&template_label_from&" "&template_starting_date_display&" "&template_label_to&" "&template_ending_date_display&" "&template_label_if_applicable -> C8 - Revenues from certain activities from - to - [If applicable]
C10: =template_label_is_the_undertaking_deriving_revenues_from_one_of_the_activities_listed_below -> Is the undertaking deriving revenues from one of the activities listed below? | H10: FALSE
H11: =template_label_monetary_amount_in & " " & template_currency -> Monetary amount in
A12: 63(a) | B12: 175-176 | C12: =template_label_revenue_derived_from_controversial_weapons -> Revenue derived from controversial weapons (anti-personnel mines cluster munitions chemical weapons and biological weapons) | I12: =IF(AND(H10=FALSE,COUNTA(H12:H16)=0, H18=""), "", IF(AND(OR(COUNTA(H12:H16)>0, H18<>""), SUM(H12:H16, H18)<='General Information'!E281), template_label_ok, IF(AND(H10=TRUE, COUNTA(H12:H16)=0, H18=""), template_label_missing_value, template_label_value_inconsistency ) ) )
A13: 63(b) | B13: 175-176 | C13: =template_label_revenue_derived_from_cultivation_and_production_of_tobacco -> Revenue derived from cultivation and production of tobacco
A14: 63(c) | B14: 175-176 | C14: =template_label_revenue_derived_from_coal -> Revenue derived from coal
A15: 63(c) | B15: 175-176 | C15: =template_label_revenue_derived_from_oil -> Revenue derived from oil
A16: 63(c) | B16: 175-176 | C16: =template_label_revenue_derived_from_gas -> Revenue derived from gas
A17: 63(c) | B17: 175-176 | C17: =template_label_total_revenues_derived_from_fossil_fuel_sector -> Total revenues derived from fossil fuel (coal oil and gas) sector (i.e. the undertaking derives revenues from exploration mining extraction production processing storage refining or distribution including transportation storage and trade of fossil fuels as defined in Article 2 point (62) of Regulation (EU) 2018 1999 of the European Parliament and the Council) | H17: =IF(COUNTA(H14:H16)=0, "-", SUM(H14:H16)) -> -
A18: 63(d) | B18: 175-176 | C18: =template_label_revenue_derived_from_chemicals_production -> Revenue derived from chemicals production
C20: =template_label_c8_exclusion_from_eu_reference_benchmarks&" "&template_label_from&" "&template_starting_date_display&" "&template_label_to&" "&template_ending_date_display&" "&template_label_always_to_be_reported -> C8 - Exclusion from EU reference benchmarks from - to - [Always to be reported]
C21: =template_label_undertakings_are_excluded_from_the_eu_paris_aligned_benchmarks_if_they_derive -> Undertakings are excluded from the EU Paris-aligned Benchmarks if they derive:
A22: 64 | B22: 177(a) | C22: =template_label_1_percent_or_more_of_their_revenues_from_exploration_mining_extraction_distribution_or_refining_of_hard_coal_and_lignite -> 1% or more of their revenues from exploration mining extraction distribution or refining of hard coal and lignite | H22: FALSE | I22: =IF(OR( 'Table of Contents & Validation'!D64=TRUE,'Table of Contents & Validation'!D62=TRUE), IF(AND(OR(H22=TRUE, H23=TRUE, H24=TRUE, H25=TRUE), 'General Information'!E122="Option B (Basic Module and Comprehensive Module)"), template_label_ok, IF(AND(H22=FALSE, H23=FALSE, H24=FALSE, H25=FALSE, H26=FALSE, 'General Information'!E122="Option B (Basic Module and Comprehensive Module)"), "", IF('General Information'!E122="Option A (Basic Module only)", "", IF(AND('General Information'!E122="Option B (Basic Module and Comprehensive Module)", H26=TRUE), template_label_ok, "")))), IF(AND(OR(H22=TRUE, H23=TRUE, H24=TRUE, H25=TRUE), 'General Information'!E122="Option B (Basic Module and Comprehensive Module)"), template_label_ok, IF(AND(H22=FALSE, H23=FALSE, H24=FALSE, H25=FALSE, H26=FALSE, 'General Information'!E122="Option B (Basic Module and Comprehensive Module)"), template_label_missing_value, IF('General Information'!E122="Option A (Basic Module only)", "", IF(AND('General Information'!E122="Option B (Basic Module and Comprehensive Module)", H26=TRUE), template_label_ok, "")))) )
A23: 64 | B23: 177(b) | C23: =template_label_10_percent_or_more_of_their_revenues_from_the_exploration_extraction_distribution_or_refining_of_oil_fuels -> 10% or more of their revenues from the exploration extraction distribution or refining of oil fuels | H23: FALSE
A24: 64 | B24: 177(c) | C24: =template_label_50_percent_or_more_of_their_revenues_from_the_exploration_extraction_manufacturing_or_distribution_of_gaseous_fuels -> 50% or more of their revenues from the exploration extraction manufacturing or distribution of gaseous fuels | H24: FALSE
A25: 64 | B25: 177(d) | C25: =template_label_50_percent_or_more_of_their_revenues_from_electricity_generation -> 50% or more of their revenues from electricity generation with a GHG intensity of more than 100g CO2 e kWh | H25: FALSE
C26: =template_label_none_of_the_above -> None of the above | H26: FALSE
A27: 64 | B27: 177 | C27: =template_label_undertakings_are_excluded_from_any_eu_reference_benchmarks_that_are_aligned_with_the_paris_agreement -> Undertakings are excluded from any EU reference benchmarks that are aligned with the Paris Agreement | H27: =IF(AND(OR(H22=TRUE, H23=TRUE, H24=TRUE, H25=TRUE), H26=FALSE), "YES", IF(AND(OR(H22=TRUE, H23=TRUE, H24=TRUE, H25=TRUE), H26=TRUE), "NA", IF(AND(H22=FALSE, H23=FALSE, H24=FALSE, H25=FALSE, H26=TRUE), "NO", IF(AND(H22=FALSE, H23=FALSE, H24=FALSE, H25=FALSE, H26=FALSE), "-", "")))) -> - | I27: =IF(H27=TRUE, template_label_ok, "")
C29: =template_label_c9_gender_diversity_ratio_in_the_governance_body&" "&template_label_at&" "&template_ending_date_display&" "&template_label_if_applicable -> C9 - Gender diversity ratio in the governance body at - [If applicable]
C30: =template_label_does_the_undertaking_have_a_governance_body_in_place -> Does the undertaking have a governance body in place? | H30: FALSE
A31: 65 | B31: 178-180 | C31: =template_label_number_of_female_board_members_at_the_end_of_the_reporting_period -> Number of female board members at the end of the reporting period | I31: =IF(AND($H$30=TRUE, H31<>""), template_label_ok, IF(AND($H$30=TRUE, H31=""), template_label_missing_value, ""))
C32: =template_label_number_of_male_board_members_at_the_end_of_the_reporting_period -> Number of male board members at the end of the reporting period | I32: =IF(AND($H$30=TRUE, H32<>""), template_label_ok, IF(AND($H$30=TRUE, H32=""), template_label_missing_value, ""))
C33: =template_label_gender_diversity_ratio_in_governance_body -> Gender diversity ratio in governance body | H33: =IF(AND(H31<>"",H32<>""),IF(OR(H31=0,H32=0),0,H31/H32),"-") -> -
C36: =template_label_disclosure_of_any_other_governance_and_or_entity_specific_governance_disclosures&" "&template_label_from&" "&template_starting_date_display&" "&template_label_to&" "&template_ending_date_display&" " & template_label_may -> Disclosure of any other governance and/or entity specific governance disclosures from - to - [May (optional)]
C37: 10
I38: =IF(C38<>"",template_label_ok, "")

Sheet Footnotes
B1: =template_label_footnote_instructions -> If you need to add footnotes for the converted VSME Digital Template, please select the disclosures in column A and write the related footnote in column B.
B2: =template_label_footnote_id -> Footnote ID | C2: =template_label_disclosure_selection -> Disclosure selection | D2: =template_label_footnote_text -> Footnote text
B3: 1
B4: 2
B5: 3
B6: 4
B7: 5
B8: 6
B9: 7
B10: 8
B11: 9
B12: 10
B13: 11
B14: 12
... B155: 153

Sheet Fuel Converter
A1: =template_label_fuel_converter -> FUEL CONVERTER
A2: =template_label_disclaimer -> DISCLAIMER:
A3: =template_label_this_converter_is_intended_solely_to_illustrate_how_energy_consumption_in_mwh -> This converter is intended solely to illustrate how energy consumption (in MWh) can be calculated from various fuel types. EFRAG assumes no responsibility or liability for the content or for any direct, indirect, or incidental consequences or damages resulting from the use of this fuel converter.
A4: =template_label_please_note_that_the_typical_values_for_net_calorific_value_and_density_are_provided_for_each_fuel_type -> Please note that the typical values for Net Calorific Value (NCV) and Density are provided for each fuel type. However, these parameters may vary depending on factors such as national regulations, specific characteristics of fuel providers, or other circumstances. Therefore, users are expected to manually enter or adjust the NCV and Density values to reflect their specific situation.
A5: =template_label_additionally_users_are_encouraged_to_determine_the_renewability_status_of_each_fuel_based_on_guarantees_of_origin -> Additionally, users are encouraged to determine the renewability status of each fuel based on Guarantees of Origin, as outlined in Article 19 of the European Directive 2018/2001/EC on the promotion of the use of energy from renewable sources. The default renewability status provided for each fuel is a typical assumption and should be adjusted if necessary, based on geographical or individual circumstances.
B6: =template_label_indicates_that_the_cell_should_be_filled_either_by_selecting_a_value_from_the_dropdown -> Indicates that the cell should be filled either by selecting a value from the dropdown (e.g. Type of fuel or Unit of Measurement) or by entering an amount.
A7: - | B7: =template_label_indicates_that_the_cell_is_automatically_calculated_and_that_no_data_entry_is_required -> Indicates that the cell is automatically calculated and that no data entry is required.
A9: =template_label_fuel_type -> Fuel type | B9: =template_label_unit_of_measurement -> Unit of measurement | C9: =template_label_amount -> Amount | D9: =template_label_state_of_matter -> State of matter | E9: =template_label_typical_renewable_state -> Typical renewable state | F9: =template_label_calculated_energy_in_mwh -> Calculated Energy in MWh | G9: =template_label_overall_validation_status_validation&":" -> Overall Validation Status: | H9: {=_xlfn.IFS( OR( COUNTIF(G10:G19,template_label_liquid_warning)>0, COUNTIF(G10:G19,template_label_gaseous_warning)>0, COUNTIF(G10:G19,template_label_solid_warning)>0 ), template_label_incomplete, COUNTBLANK(A10:A19)=10, "-", AND( COUNTIF(G10:G19,template_label_liquid_warning)=0, COUNTIF(G10:G19,template_label_gaseous_warning)=0, COUNTIF(G10:G19,template_label_solid_warning)=0, COUNTBLANK(A10:A19)<>10, COUNTIF(F10:F19,"-")=10 ), "-", AND( COUNTIF(G10:G19,template_label_liquid_warning)=0, COUNTIF(G10:G19,template_label_gaseous_warning)=0, COUNTIF(G10:G19,template_label_solid_warning)=0, COUNTIF(F10:F19,"-")<>10 ), template_label_complete )} -> - | J9: =template_label_usage_of_fuel_converter -> Usage of Fuel Converter:
D10: =P11 -> - | E10: =P12 -> - | F10: =IF(C10="","-",O23) -> - | G10: =IF(AND(B10="",D10="Liquid"), template_label_liquid_warning, IF(AND(A10<>"",B10<>"",C10<>"",D10<>"",E10<>"",F10<>"",OR(AND(OR(B10="L - Liter",B10="m³ - cubic meters"),OR(D10="Liquid",D10="Gaseous")),AND(OR(B10="Kg - Kilogram",B10="t - tonne",B10="g - gram"),D10="Solid"))),"OK", IF(AND(OR(B10="m³ - cubic meters",B10="L - Liter"),D10="Liquid",C10=""), "", IF(AND(OR(B10="Gg - Gigagram",B10="t - tonne",B10="Kg - Kilogram",B10="g - gram"),D10="Liquid"), template_label_liquid_warning, IF(AND(B10="",D10="Gaseous"), template_label_gaseous_warning, IF(AND(A10<>"",B10<>"",C10<>"",D10<>"",E10<>"",F10<>"",OR(AND(OR(B10="L - Liter",B10="m³ - cubic meters"),OR(D10="Liquid",D10="Gaseous")),AND(OR(B10="Kg - Kilogram",B10="t - tonne",B10="g - gram"),D10="Solid"))),"OK",IF(AND(OR(B10="m³ - cubic meters",B10="L - Liter"),D10="Gaseous",C10=""), "", IF(AND(OR(B10="Gg - Gigagram",B10="t - tonne",B10="Kg - Kilogram",B10="g - gram"),D10="Gaseous"), template_label_gaseous_warning, IF(AND(B10="",D10="Solid"), template_label_solid_warning, IF(AND(A10<>"",B10<>"",C10<>"",D10<>"",E10<>"",F10<>"",OR(AND(OR(B10="L - Liter",B10="m³ - cubic meters"),OR(D10="Liquid",D10="Gaseous")),AND(OR(B10="Kg - Kilogram",B10="t - tonne",B10="g - gram"),D10="Solid"))),"OK",IF(AND(OR(B10="Gg - Gigagram",B10="t - tonne",B10="Kg - Kilogram",B10="g - gram"),D10="Solid"), "", IF(AND(OR(B10="m³ - cubic meters",B10="L - Liter"),D10="Solid"), template_label_solid_warning, "")))))))))))) | J10: =template_label_1_in_cell_a9_select_the_fuel_used_searching_for_it_or_scrolling_down_the_list_displayed_clicking_the_cell -> 1. In cell A10 select the Fuel used, searching for it or scrolling down the list displayed clicking the cell | O10: What is your fuel? | P10: =IF(A10="","-",A10) -> - | S10: What is your fuel? | T10: =IF(A11="","-",A11) -> - | W10: What is your fuel? | X10: =IF(A12="","-",A12) -> - | AA10: What is your fuel? | AB10: =IF(A13="","-",A13) -> - | AE10: What is your fuel? | AF10: =IF(A14="","-",A14) -> - | AI10: What is your fuel? | AJ10: =IF(A15="","-",A15) -> - | AM10: What is your fuel? | AN10: =IF(A16="","-",A16) -> - | AQ10: What is your fuel? | AR10: =IF(A17="","-",A17) -> - | AU10: What is your fuel? | AV10: =IF(A18="","-",A18) -> - | AY10: What is your fuel? | AZ10: =IF(A19="","-",A19) -> -
D11: =T11 -> - | E11: =T12 -> - | F11: =IF(C11="","-",S23) -> - | G11: =IF(AND(B11="",D11="Liquid"), template_label_liquid_warning, IF(AND(A11<>"",B11<>"",C11<>"",D11<>"",E11<>"",F11<>"",OR(AND(OR(B11="L - Liter",B11="m³ - cubic meters"),OR(D11="Liquid",D11="Gaseous")),AND(OR(B11="Kg - Kilogram",B11="t - tonne",B11="g - gram"),D11="Solid"))),"OK", IF(AND(OR(B11="m³ - cubic meters",B11="L - Liter"),D11="Liquid",C11=""), "", IF(AND(OR(B11="Gg - Gigagram",B11="t - tonne",B11="Kg - Kilogram",B11="g - gram"),D11="Liquid"), template_label_liquid_warning, IF(AND(B11="",D11="Gaseous"), template_label_gaseous_warning, IF(AND(A11<>"",B11<>"",C11<>"",D11<>"",E11<>"",F11<>"",OR(AND(OR(B11="L - Liter",B11="m³ - cubic meters"),OR(D11="Liquid",D11="Gaseous")),AND(OR(B11="Kg - Kilogram",B11="t - tonne",B11="g - gram"),D11="Solid"))),"OK",IF(AND(OR(B11="m³ - cubic meters",B11="L - Liter"),D11="Gaseous",C11=""), "", IF(AND(OR(B11="Gg - Gigagram",B11="t - tonne",B11="Kg - Kilogram",B11="g - gram"),D11="Gaseous"), template_label_gaseous_warning, IF(AND(B11="",D11="Solid"), template_label_solid_warning, IF(AND(A11<>"",B11<>"",C11<>"",D11<>"",E11<>"",F11<>"",OR(AND(OR(B11="L - Liter",B11="m³ - cubic meters"),OR(D11="Liquid",D11="Gaseous")),AND(OR(B11="Kg - Kilogram",B11="t - tonne",B11="g - gram"),D11="Solid"))),"OK",IF(AND(OR(B11="Gg - Gigagram",B11="t - tonne",B11="Kg - Kilogram",B11="g - gram"),D11="Solid"), "", IF(AND(OR(B11="m³ - cubic meters",B11="L - Liter"),D11="Solid"), template_label_solid_warning, "")))))))))))) | J11: =template_label_2_in_cell_b9_select_the_unit_of_measurement_used -> 2. In cell B10 select the Unit of measurement used | O11: State of matter | P11: =IF(OR(P10="", P10="-"), "-", IFERROR(IF(INDEX('Fuel Conversion Parameters'!$B$2:$B$61, MATCH(P10, 'Fuel Conversion Parameters'!$A$2:$A$61, 0))="", "MISSING VALUE", INDEX('Fuel Conversion Parameters'!$B$2:$B$61, MATCH(P10, 'Fuel Conversion Parameters'!$A$2:$A$61, 0))), "MISSING VALUE")) -> - | S11: State of matter | T11: =IF(OR(T10="", T10="-"), "-", IFERROR(IF(INDEX('Fuel Conversion Parameters'!$B$2:$B$61, MATCH(T10, 'Fuel Conversion Parameters'!$A$2:$A$61, 0))="", "MISSING VALUE", INDEX('Fuel Conversion Parameters'!$B$2:$B$61, MATCH(T10, 'Fuel Conversion Parameters'!$A$2:$A$61, 0))), "MISSING VALUE")) -> - | W11: State of matter | X11: =IF(OR(X10="", X10="-"), "-", IFERROR(IF(INDEX('Fuel Conversion Parameters'!$B$2:$B$61, MATCH(X10, 'Fuel Conversion Parameters'!$A$2:$A$61, 0))="", "MISSING VALUE", INDEX('Fuel Conversion Parameters'!$B$2:$B$61, MATCH(X10, 'Fuel Conversion Parameters'!$A$2:$A$61, 0))), "MISSING VALUE")) -> - | AA11: State of matter | AB11: =IF(OR(AB10="", AB10="-"), "-", IFERROR(IF(INDEX('Fuel Conversion Parameters'!$B$2:$B$61, MATCH(AB10, 'Fuel Conversion Parameters'!$A$2:$A$61, 0))="", "MISSING VALUE", INDEX('Fuel Conversion Parameters'!$B$2:$B$61, MATCH(AB10, 'Fuel Conversion Parameters'!$A$2:$A$61, 0))), "MISSING VALUE")) -> - | AE11: State of matter | AF11: =IF(OR(AF10="", AF10="-"), "-", IFERROR(IF(INDEX('Fuel Conversion Parameters'!$B$2:$B$61, MATCH(AF10, 'Fuel Conversion Parameters'!$A$2:$A$61, 0))="", "MISSING VALUE", INDEX('Fuel Conversion Parameters'!$B$2:$B$61, MATCH(AF10, 'Fuel Conversion Parameters'!$A$2:$A$61, 0))), "MISSING VALUE")) -> - | AI11: State of matter | AJ11: =IF(OR(AJ10="", AJ10="-"), "-", IFERROR(IF(INDEX('Fuel Conversion Parameters'!$B$2:$B$61, MATCH(AJ10, 'Fuel Conversion Parameters'!$A$2:$A$61, 0))="", "MISSING VALUE", INDEX('Fuel Conversion Parameters'!$B$2:$B$61, MATCH(AJ10, 'Fuel Conversion Parameters'!$A$2:$A$61, 0))), "MISSING VALUE")) -> - | AM11: State of matter | AN11: =IF(OR(AN10="", AN10="-"), "-", IFERROR(IF(INDEX('Fuel Conversion Parameters'!$B$2:$B$61, MATCH(AN10, 'Fuel Conversion Parameters'!$A$2:$A$61, 0))="", "MISSING VALUE", INDEX('Fuel Conversion Parameters'!$B$2:$B$61, MATCH(AN10, 'Fuel Conversion Parameters'!$A$2:$A$61, 0))), "MISSING VALUE")) -> - | AQ11: State of matter | AR11: =IF(OR(AR10="", AR10="-"), "-", IFERROR(IF(INDEX('Fuel Conversion Parameters'!$B$2:$B$61, MATCH(AR10, 'Fuel Conversion Parameters'!$A$2:$A$61, 0))="", "MISSING VALUE", INDEX('Fuel Conversion Parameters'!$B$2:$B$61, MATCH(AR10, 'Fuel Conversion Parameters'!$A$2:$A$61, 0))), "MISSING VALUE")) -> - | AU11: State of matter | AV11: =IF(OR(AV10="", AV10="-"), "-", IFERROR(IF(INDEX('Fuel Conversion Parameters'!$B$2:$B$61, MATCH(AV10, 'Fuel Conversion Parameters'!$A$2:$A$61, 0))="", "MISSING VALUE", INDEX('Fuel Conversion Parameters'!$B$2:$B$61, MATCH(AV10, 'Fuel Conversion Parameters'!$A$2:$A$61, 0))), "MISSING VALUE")) -> - | AY11: State of matter | AZ11: =IF(OR(AZ10="", AZ10="-"), "-", IFERROR(IF(INDEX('Fuel Conversion Parameters'!$B$2:$B$61, MATCH(AZ10, 'Fuel Conversion Parameters'!$A$2:$A$61, 0))="", "MISSING VALUE", INDEX('Fuel Conversion Parameters'!$B$2:$B$61, MATCH(AZ10, 'Fuel Conversion Parameters'!$A$2:$A$61, 0))), "MISSING VALUE")) -> -
D12: =X11 -> - | E12: =X12 -> - | F12: =IF(C12="","-",W23) -> - | G12: =IF(AND(B12="",D12="Liquid"), template_label_liquid_warning, IF(AND(A12<>"",B12<>"",C12<>"",D12<>"",E12<>"",F12<>"",OR(AND(OR(B12="L - Liter",B12="m³ - cubic meters"),OR(D12="Liquid",D12="Gaseous")),AND(OR(B12="Kg - Kilogram",B12="t - tonne",B12="g - gram"),D12="Solid"))),"OK", IF(AND(OR(B12="m³ - cubic meters",B12="L - Liter"),D12="Liquid",C12=""), "", IF(AND(OR(B12="Gg - Gigagram",B12="t - tonne",B12="Kg - Kilogram",B12="g - gram"),D12="Liquid"), template_label_liquid_warning, IF(AND(B12="",D12="Gaseous"), template_label_gaseous_warning, IF(AND(A12<>"",B12<>"",C12<>"",D12<>"",E12<>"",F12<>"",OR(AND(OR(B12="L - Liter",B12="m³ - cubic meters"),OR(D12="Liquid",D12="Gaseous")),AND(OR(B12="Kg - Kilogram",B12="t - tonne",B12="g - gram"),D12="Solid"))),"OK",IF(AND(OR(B12="m³ - cubic meters",B12="L - Liter"),D12="Gaseous",C12=""), "", IF(AND(OR(B12="Gg - Gigagram",B12="t - tonne",B12="Kg - Kilogram",B12="g - gram"),D12="Gaseous"), template_label_gaseous_warning, IF(AND(B12="",D12="Solid"), template_label_solid_warning, IF(AND(A12<>"",B12<>"",C12<>"",D12<>"",E12<>"",F12<>"",OR(AND(OR(B12="L - Liter",B12="m³ - cubic meters"),OR(D12="Liquid",D12="Gaseous")),AND(OR(B12="Kg - Kilogram",B12="t - tonne",B12="g - gram"),D12="Solid"))),"OK",IF(AND(OR(B12="Gg - Gigagram",B12="t - tonne",B12="Kg - Kilogram",B12="g - gram"),D12="Solid"), "", IF(AND(OR(B12="m³ - cubic meters",B12="L - Liter"),D12="Solid"), template_label_solid_warning, "")))))))))))) | J12: =template_label_3_in_cell_c9_select_the_amount_of_fuel_used -> 3. In cell C10 select the Amount of fuel used | O12: Typical renewability state | P12: =IF(OR(P10="", P10="-"), "-", IFERROR(IF(INDEX('Fuel Conversion Parameters'!$F$2:$F$61, MATCH(P10, 'Fuel Conversion Parameters'!$A$2:$A$61, 0))="", "MISSING VALUE", INDEX('Fuel Conversion Parameters'!$F$2:$F$61, MATCH(P10, 'Fuel Conversion Parameters'!$A$2:$A$61, 0))), "MISSING VALUE")) -> - | S12: Typical renewability state | T12: =IF(OR(T10="", T10="-"), "-", IFERROR(IF(INDEX('Fuel Conversion Parameters'!$F$2:$F$61, MATCH(T10, 'Fuel Conversion Parameters'!$A$2:$A$61, 0))="", "MISSING VALUE", INDEX('Fuel Conversion Parameters'!$F$2:$F$61, MATCH(T10, 'Fuel Conversion Parameters'!$A$2:$A$61, 0))), "MISSING VALUE")) -> - | W12: Typical renewability state | X12: =IF(OR(X10="", X10="-"), "-", IFERROR(IF(INDEX('Fuel Conversion Parameters'!$F$2:$F$61, MATCH(X10, 'Fuel Conversion Parameters'!$A$2:$A$61, 0))="", "MISSING VALUE", INDEX('Fuel Conversion Parameters'!$F$2:$F$61, MATCH(X10, 'Fuel Conversion Parameters'!$A$2:$A$61, 0))), "MISSING VALUE")) -> - | AA12: Typical renewability state | AB12: =IF(OR(AB10="", AB10="-"), "-", IFERROR(IF(INDEX('Fuel Conversion Parameters'!$F$2:$F$61, MATCH(AB10, 'Fuel Conversion Parameters'!$A$2:$A$61, 0))="", "MISSING VALUE", INDEX('Fuel Conversion Parameters'!$F$2:$F$61, MATCH(AB10, 'Fuel Conversion Parameters'!$A$2:$A$61, 0))), "MISSING VALUE")) -> - | AE12: Typical renewability state | AF12: =IF(OR(AF10="", AF10="-"), "-", IFERROR(IF(INDEX('Fuel Conversion Parameters'!$F$2:$F$61, MATCH(AF10, 'Fuel Conversion Parameters'!$A$2:$A$61, 0))="", "MISSING VALUE", INDEX('Fuel Conversion Parameters'!$F$2:$F$61, MATCH(AF10, 'Fuel Conversion Parameters'!$A$2:$A$61, 0))), "MISSING VALUE")) -> - | AI12: Typical renewability state | AJ12: =IF(OR(AJ10="", AJ10="-"), "-", IFERROR(IF(INDEX('Fuel Conversion Parameters'!$F$2:$F$61, MATCH(AJ10, 'Fuel Conversion Parameters'!$A$2:$A$61, 0))="", "MISSING VALUE", INDEX('Fuel Conversion Parameters'!$F$2:$F$61, MATCH(AJ10, 'Fuel Conversion Parameters'!$A$2:$A$61, 0))), "MISSING VALUE")) -> - | AM12: Typical renewability state | AN12: =IF(OR(AN10="", AN10="-"), "-", IFERROR(IF(INDEX('Fuel Conversion Parameters'!$F$2:$F$61, MATCH(AN10, 'Fuel Conversion Parameters'!$A$2:$A$61, 0))="", "MISSING VALUE", INDEX('Fuel Conversion Parameters'!$F$2:$F$61, MATCH(AN10, 'Fuel Conversion Parameters'!$A$2:$A$61, 0))), "MISSING VALUE")) -> - | AQ12: Typical renewability state | AR12: =IF(OR(AR10="", AR10="-"), "-", IFERROR(IF(INDEX('Fuel Conversion Parameters'!$F$2:$F$61, MATCH(AR10, 'Fuel Conversion Parameters'!$A$2:$A$61, 0))="", "MISSING VALUE", INDEX('Fuel Conversion Parameters'!$F$2:$F$61, MATCH(AR10, 'Fuel Conversion Parameters'!$A$2:$A$61, 0))), "MISSING VALUE")) -> - | AU12: Typical renewability state | AV12: =IF(OR(AV10="", AV10="-"), "-", IFERROR(IF(INDEX('Fuel Conversion Parameters'!$F$2:$F$61, MATCH(AV10, 'Fuel Conversion Parameters'!$A$2:$A$61, 0))="", "MISSING VALUE", INDEX('Fuel Conversion Parameters'!$F$2:$F$61, MATCH(AV10, 'Fuel Conversion Parameters'!$A$2:$A$61, 0))), "MISSING VALUE")) -> - | AY12: Typical renewability state | AZ12: =IF(OR(AZ10="", AZ10="-"), "-", IFERROR(IF(INDEX('Fuel Conversion Parameters'!$F$2:$F$61, MATCH(AZ10, 'Fuel Conversion Parameters'!$A$2:$A$61, 0))="", "MISSING VALUE", INDEX('Fuel Conversion Parameters'!$F$2:$F$61, MATCH(AZ10, 'Fuel Conversion Parameters'!$A$2:$A$61, 0))), "MISSING VALUE")) -> -
D13: =AB11 -> - | E13: =AB12 -> - | F13: =IF(C13="","-",AA23) -> - | G13: =IF(AND(B13="",D13="Liquid"), template_label_liquid_warning, IF(AND(A13<>"",B13<>"",C13<>"",D13<>"",E13<>"",F13<>"",OR(AND(OR(B13="L - Liter",B13="m³ - cubic meters"),OR(D13="Liquid",D13="Gaseous")),AND(OR(B13="Kg - Kilogram",B13="t - tonne",B13="g - gram"),D13="Solid"))),"OK", IF(AND(OR(B13="m³ - cubic meters",B13="L - Liter"),D13="Liquid",C13=""), "", IF(AND(OR(B13="Gg - Gigagram",B13="t - tonne",B13="Kg - Kilogram",B13="g - gram"),D13="Liquid"), template_label_liquid_warning, IF(AND(B13="",D13="Gaseous"), template_label_gaseous_warning, IF(AND(A13<>"",B13<>"",C13<>"",D13<>"",E13<>"",F13<>"",OR(AND(OR(B13="L - Liter",B13="m³ - cubic meters"),OR(D13="Liquid",D13="Gaseous")),AND(OR(B13="Kg - Kilogram",B13="t - tonne",B13="g - gram"),D13="Solid"))),"OK",IF(AND(OR(B13="m³ - cubic meters",B13="L - Liter"),D13="Gaseous",C13=""), "", IF(AND(OR(B13="Gg - Gigagram",B13="t - tonne",B13="Kg - Kilogram",B13="g - gram"),D13="Gaseous"), template_label_gaseous_warning, IF(AND(B13="",D13="Solid"), template_label_solid_warning, IF(AND(A13<>"",B13<>"",C13<>"",D13<>"",E13<>"",F13<>"",OR(AND(OR(B13="L - Liter",B13="m³ - cubic meters"),OR(D13="Liquid",D13="Gaseous")),AND(OR(B13="Kg - Kilogram",B13="t - tonne",B13="g - gram"),D13="Solid"))),"OK",IF(AND(OR(B13="Gg - Gigagram",B13="t - tonne",B13="Kg - Kilogram",B13="g - gram"),D13="Solid"), "", IF(AND(OR(B13="m³ - cubic meters",B13="L - Liter"),D13="Solid"), template_label_solid_warning, "")))))))))))) | J13: =template_label_4_in_cell_d9_it_is_displayed_the_state_of_matter_for_the_fuel_selected -> 4. In cell D10 it is displayed the State of matter for the Fuel selected
D14: =AF11 -> - | E14: =AF12 -> - | F14: =IF(C14="","-",AE23) -> - | G14: =IF(AND(B14="",D14="Liquid"), template_label_liquid_warning, IF(AND(A14<>"",B14<>"",C14<>"",D14<>"",E14<>"",F14<>"",OR(AND(OR(B14="L - Liter",B14="m³ - cubic meters"),OR(D14="Liquid",D14="Gaseous")),AND(OR(B14="Kg - Kilogram",B14="t - tonne",B14="g - gram"),D14="Solid"))),"OK", IF(AND(OR(B14="m³ - cubic meters",B14="L - Liter"),D14="Liquid",C14=""), "", IF(AND(OR(B14="Gg - Gigagram",B14="t - tonne",B14="Kg - Kilogram",B14="g - gram"),D14="Liquid"), template_label_liquid_warning, IF(AND(B14="",D14="Gaseous"), template_label_gaseous_warning, IF(AND(A14<>"",B14<>"",C14<>"",D14<>"",E14<>"",F14<>"",OR(AND(OR(B14="L - Liter",B14="m³ - cubic meters"),OR(D14="Liquid",D14="Gaseous")),AND(OR(B14="Kg - Kilogram",B14="t - tonne",B14="g - gram"),D14="Solid"))),"OK",IF(AND(OR(B14="m³ - cubic meters",B14="L - Liter"),D14="Gaseous",C14=""), "", IF(AND(OR(B14="Gg - Gigagram",B14="t - tonne",B14="Kg - Kilogram",B14="g - gram"),D14="Gaseous"), template_label_gaseous_warning, IF(AND(B14="",D14="Solid"), template_label_solid_warning, IF(AND(A14<>"",B14<>"",C14<>"",D14<>"",E14<>"",F14<>"",OR(AND(OR(B14="L - Liter",B14="m³ - cubic meters"),OR(D14="Liquid",D14="Gaseous")),AND(OR(B14="Kg - Kilogram",B14="t - tonne",B14="g - gram"),D14="Solid"))),"OK",IF(AND(OR(B14="Gg - Gigagram",B14="t - tonne",B14="Kg - Kilogram",B14="g - gram"),D14="Solid"), "", IF(AND(OR(B14="m³ - cubic meters",B14="L - Liter"),D14="Solid"), template_label_solid_warning, "")))))))))))) | J14: =template_label_5_in_cell_e9_it_is_displayed_the_typical_renewability_state_for_the_fuel_selected -> 5. In cell E10 it is displayed the Typical renewability state for the Fuel selected
D15: =AJ11 -> - | E15: =AJ12 -> - | F15: =IF(C15="","-",AI23) -> - | G15: =IF(AND(B15="",D15="Liquid"), template_label_liquid_warning, IF(AND(A15<>"",B15<>"",C15<>"",D15<>"",E15<>"",F15<>"",OR(AND(OR(B15="L - Liter",B15="m³ - cubic meters"),OR(D15="Liquid",D15="Gaseous")),AND(OR(B15="Kg - Kilogram",B15="t - tonne",B15="g - gram"),D15="Solid"))),"OK", IF(AND(OR(B15="m³ - cubic meters",B15="L - Liter"),D15="Liquid",C15=""), "", IF(AND(OR(B15="Gg - Gigagram",B15="t - tonne",B15="Kg - Kilogram",B15="g - gram"),D15="Liquid"), template_label_liquid_warning, IF(AND(B15="",D15="Gaseous"), template_label_gaseous_warning, IF(AND(A15<>"",B15<>"",C15<>"",D15<>"",E15<>"",F15<>"",OR(AND(OR(B15="L - Liter",B15="m³ - cubic meters"),OR(D15="Liquid",D15="Gaseous")),AND(OR(B15="Kg - Kilogram",B15="t - tonne",B15="g - gram"),D15="Solid"))),"OK",IF(AND(OR(B15="m³ - cubic meters",B15="L - Liter"),D15="Gaseous",C15=""), "", IF(AND(OR(B15="Gg - Gigagram",B15="t - tonne",B15="Kg - Kilogram",B15="g - gram"),D15="Gaseous"), template_label_gaseous_warning, IF(AND(B15="",D15="Solid"), template_label_solid_warning, IF(AND(A15<>"",B15<>"",C15<>"",D15<>"",E15<>"",F15<>"",OR(AND(OR(B15="L - Liter",B15="m³ - cubic meters"),OR(D15="Liquid",D15="Gaseous")),AND(OR(B15="Kg - Kilogram",B15="t - tonne",B15="g - gram"),D15="Solid"))),"OK",IF(AND(OR(B15="Gg - Gigagram",B15="t - tonne",B15="Kg - Kilogram",B15="g - gram"),D15="Solid"), "", IF(AND(OR(B15="m³ - cubic meters",B15="L - Liter"),D15="Solid"), template_label_solid_warning, "")))))))))))) | J15: =template_label_6_in_cell_f9_is_displayed_the_energy_produced_in_mega_watt_hours_by_the_amount_of_fuel_specified -> 6. In cell F10 is displayed the Energy produced in Mega Watt hours by the Amount of Fuel specified
